Workbook

Sheet Summary
A1: USB DAC + Balanced Headphone Amplifier — Parts List v0.4
A2: Diego Yang · 24 Sep 2026 · after the fifth review round · companion to Design Specification v0.6 and Schematic Design Notes v0.5 · supersedes Parts List v0.3 (kept unchanged) · 80 MHz MCLK, OPA2210 I/V op-amps, break-before-make family oscillators, overload latch, VREF clamp
A4: 5-board sample run — cost gate
A5: Key figure | B5: Value | C5: Unit | D5: Basis
A6: Parts (LCSC tier matching the run quantity) | B6: =Cost!F43 -> 4401.228 | C6: NTD | D6: ="US$ "&TEXT(Cost!E43,"#,##0.00")&"; includes the US$"&TEXT(Cost!B8,"0.00")&" minimum per purchasing line for parts under US$"&TEXT(Cost!B9,"0.00") -> US$ 138.84; includes the US$0.10 minimum per purchasing line for parts under US$0.05
A7: Bare 4-layer PCBs (estimate) | B7: =Cost!F44 -> 317 | C7: NTD | D7: ="US$ "&TEXT(Cost!E44,"#,##0.00")&" for "&TEXT(Cost!B6,"0")&" boards" -> US$ 10.00 for 5 boards
A8: JLCPCB Economic PCBA fees | B8: =Cost!F45 -> 3517.5588 | C8: NTD | D8: ="US$ "&TEXT(Cost!E45,"#,##0.00")&"; itemised on the Cost sheet" -> US$ 110.96; itemised on the Cost sheet
A9: Total, 5-board run | B9: =Cost!F46 -> 8235.7868 | C9: NTD | D9: ="US$ "&TEXT(Cost!E46,"#,##0.00")&" at "&TEXT(Cost!B5,"0.0")&" NTD per US$" -> US$ 259.80 at 31.7 NTD per US$
A10: Per board | B10: =Cost!F47 -> 1647.1574 | C10: NTD | D10: ="US$ "&TEXT(Cost!E47,"#,##0.00")&" per board — the cost-gate figure" -> US$ 51.96 per board — the cost-gate figure
A11: Target per board | B11: =Cost!F48 -> 1500 | C11: NTD | D11: =TEXT(Cost!B10*Cost!B6,"#,##0")&" NTD for "&TEXT(Cost!B6,"0")&" boards; WARNING above; incl. bare PCBs and assembly fees; excl. shipping, import tax, programmers, enclosure, proof-of-concept hardware and a possible assembly-fixture fee" -> 7,500 NTD for 5 boards; WARNING above; incl. bare PCBs and assembly fees; excl. shipping, import tax, programmers, enclosure, proof-of-concept hardware and a possible assembly-fixture fee
A12: Ceiling per board (hard order gate) | B12: =Cost!F49 -> 1700 | C12: NTD | D12: ="Ceiling "&TEXT(Cost!B11,"#,##0")&" NTD per board, set when the third oscillator was added; on 24 Sep 2026 the owner confirmed the budget is flexible as long as it does not surge; the actual JLCPCB quote from the real BOM/CPL files must pass the ceiling before ordering; FAIL above" -> Ceiling 1,700 NTD per board, set when the third oscillator was added; on 24 Sep 2026 the owner confirmed the budget is flexible as long as it does not surge; the actual JLCPCB quote from the real BOM/CPL files must pass the ceiling before ordering; FAIL above
A13: Margin to the target | B13: =Cost!F50 -> -147.15736 | C13: NTD per board | D13: =Cost!G50 -> 147 NTD over the target (9.8%)
A14: Margin to the ceiling | B14: =Cost!F51 -> 52.84264 | C14: NTD per board | D14: =Cost!G51 -> 53 NTD under the ceiling
A15: Cost-gate status | B15: =Cost!F52 -> WARNING | D15: =Cost!G52 -> PASS ≤ 1,500 NTD per board (target); WARNING ≤ 1,700 (ceiling, hard order gate); FAIL > 1,700
A16: Without the conservative fee items | B16: =Cost!F58 -> 1549.7116 | C16: NTD per board | D16: ="through-hole Extended fee "&TEXT(Cost!F56,"+0.0;-0.0")&" NTD and X-ray of the "&TEXT(Cost!B23,"0")&" oscillators "&IF(Cost!B23=0,"+0.0",TEXT(Cost!F57/Cost!B23,"+0.0;-0.0"))&" NTD each, per board, all counted above; the JLCPCB quote after layout decides" -> through-hole Extended fee -19.5 NTD and X-ray of the 3 oscillators -26.0 NTD each, per board, all counted above; the JLCPCB quote after layout decides
A17: Self-checks | B17: =Checks!F32 -> ALL OK — target WARNING | D17: ="Checks sheet: counts, LCSC / class rule, cross-sheet totals, the "&TEXT(Checks!B23,"#,##0")&" NTD result and the gate rule" -> Checks sheet: counts, LCSC / class rule, cross-sheet totals, the 1,647 NTD result and the gate rule
A19: Counts
A20: Count | B20: Value | C20: Unit | D20: Basis
A21: BOM lines | B21: =COUNTA('Parts list'!$B$4:$B$133) -> 130 | C21: lines | D21: every component of every circuit, one part per line
A22: Fitted lines | B22: =Cost!B14 -> 122 | C22: lines | D22: ="Fit = Yes, including the bare-PCB row; DNF: "&TEXT(COUNTIF('Parts list'!$K$4:$K$133,"DNF"),"0")&" lines (U205, R215, R703, J703)" -> Fit = Yes, including the bare-PCB row; DNF: 4 lines (U205, R215, R703, J703)
A23: Purchase lines | B23: =COUNTA('Purchasing list'!$C$4:$C$51) -> 48 | C23: lines | D23: one per LCSC number
A24: SMT-placed parts per board | B24: =Cost!B15 -> 231 | C24: parts | D24: ="plus "&TEXT(Cost!B16,"0")&" through-hole part (4.4 mm jack J701)" -> plus 1 through-hole part (4.4 mm jack J701)
A25: Extended part types | B25: =Cost!B17 -> 19 | C25: types | D25: ="US$"&TEXT(Cost!C35,"0.00")&" each on the sample run; includes the through-hole jack and X202 (class assumed Extended)" -> US$3.07 each on the sample run; includes the through-hole jack and X202 (class assumed Extended)
A26: Basic part types | B26: =Cost!B18 -> 29 | C26: types | D26: no per-type fee; every class is taken from its JLCPCB part page or the JLCPCB basic-parts list, except X202, whose class is not shown on its JLCPCB page (assumed Extended)
A27: SMT joints per board | B27: =Cost!B20 -> 690 | C27: joints | D27: Qty × SMT joints per part, fitted lines
A28: Through-hole joints per board | B28: =Cost!B21 -> 7 | C28: joints | D28: 4.4 mm jack, hand-soldered
A29: Leadless (X-ray) parts per board | B29: =Cost!B22 -> 8 | C29: parts | D29: CPLD, ES9018K2M, 2 × OPA1622, LM27762, three oscillators (80 / 24.576 / 22.5792 MHz)
A31: Reference only — 100-unit build
A32: Key figure | B32: Value | C32: Unit | D32: Basis
A33: Total per board, 100-unit build | B33: =Cost!F79 -> 798.52934 | C33: NTD | D33: ="JLCPCB Standard PCBA, parts at the 100-board tier; US$ "&TEXT(Cost!E79,"#,##0.00")&" per board — not the budget basis" -> JLCPCB Standard PCBA, parts at the 100-board tier; US$ 25.19 per board — not the budget basis
A35: Parts cost per board by block (sample-run tier prices)
A36: Block | B36: US$ per board | C36: NTD per board | D36: Main cost items
A37: 1 USB-C input and sensing | B37: {=SUMPRODUCT(('Parts list'!$A$4:$A$133=$A37)*('Parts list'!$K$4:$K$133="Yes")*('Parts list'!$B$4:$B$133<>"PCB")*'Parts list'!$C$4:$C$133*'Parts list'!$O$4:$O$133)} -> 0.3064 | C37: =B37*Cost!$B$5 -> 9.71288 | D37: SHOU HAN USB-C receptacle, USBLC6-2SC6 ESD array, CC / VBUS sensing resistors
A38: 2 USB audio bridge (CH32V307 + CPLD) | B38: {=SUMPRODUCT(('Parts list'!$A$4:$A$133=$A38)*('Parts list'!$K$4:$K$133="Yes")*('Parts list'!$B$4:$B$133<>"PCB")*'Parts list'!$C$4:$C$133*'Parts list'!$O$4:$O$133)} -> 7.3751 | C38: =B38*Cost!$B$5 -> 233.79067 | D38: CH32V307RCT6, AGRV2KQ32 CPLD, three oscillators, 8 MHz 5032 crystal
A39: 3 DAC (ES9018K2M) and its supplies | B39: {=SUMPRODUCT(('Parts list'!$A$4:$A$133=$A39)*('Parts list'!$K$4:$K$133="Yes")*('Parts list'!$B$4:$B$133<>"PCB")*'Parts list'!$C$4:$C$133*'Parts list'!$O$4:$O$133)} -> 3.8169 | C39: =B39*Cost!$B$5 -> 120.99573 | D39: ES9018K2M, LP5907-3.3, ME6216A13M3G 1.3 V LDO
A40: 4 I/V converters and output legs | B40: {=SUMPRODUCT(('Parts list'!$A$4:$A$133=$A40)*('Parts list'!$K$4:$K$133="Yes")*('Parts list'!$B$4:$B$133<>"PCB")*'Parts list'!$C$4:$C$133*'Parts list'!$O$4:$O$133)} -> 6.3712 | C40: =B40*Cost!$B$5 -> 201.96704 | D40: 2 × OPA2210 I/V converters, 2 × OPA1622, 16 × 2.00 kΩ 0.1 % resistors
A41: 5 Power: domains, current limit and ±3.8 V rails | B41: {=SUMPRODUCT(('Parts list'!$A$4:$A$133=$A41)*('Parts list'!$K$4:$K$133="Yes")*('Parts list'!$B$4:$B$133<>"PCB")*'Parts list'!$C$4:$C$133*'Parts list'!$O$4:$O$133)} -> 2.0087 | C41: =B41*Cost!$B$5 -> 63.67579 | D41: TPS2553 current limit, LM27762 +3.78 V / −3.72 V, 2 × ME6211C33
A42: 6 Protection and control | B42: {=SUMPRODUCT(('Parts list'!$A$4:$A$133=$A42)*('Parts list'!$K$4:$K$133="Yes")*('Parts list'!$B$4:$B$133<>"PCB")*'Parts list'!$C$4:$C$133*'Parts list'!$O$4:$O$133)} -> 0.4444 | C42: =B42*Cost!$B$5 -> 14.08748 | D42: LM393 window comparator, ten 2N7002 fault latch (Q601–Q610), BAV99 diode-OR
A43: 7 Outputs, indicators, test, board | B43: {=SUMPRODUCT(('Parts list'!$A$4:$A$133=$A43)*('Parts list'!$K$4:$K$133="Yes")*('Parts list'!$B$4:$B$133<>"PCB")*'Parts list'!$C$4:$C$133*'Parts list'!$O$4:$O$133)} -> 7.2655 | C43: =B43*Cost!$B$5 -> 230.31635 | D43: ="4.4 mm jack J701 ("&TEXT(SUMIFS('Parts list'!$O$4:$O$133,'Parts list'!$B$4:$B$133,"J701")*Cost!$B$5,"#,##0")&" NTD), 3.5 mm jack, ESD diodes, LEDs" -> 4.4 mm jack J701 (218 NTD), 3.5 mm jack, ESD diodes, LEDs
A44: Minimum-spend allowance (purchasing lines under US$0.05) | B44: =Cost!B26/Cost!B6 -> 0.1798 | C44: =B44*Cost!$B$5 -> 5.69966 | D44: ="US$"&TEXT(Cost!B8,"0.00")&" minimum per purchasing line, spread over "&TEXT(Cost!B6,"0")&" boards" -> US$0.10 minimum per purchasing line, spread over 5 boards
A45: Parts per board | B45: =SUM(B37:B44) -> 27.768 | C45: =B45*Cost!$B$5 -> 880.2456 | D45: ="= Cost sheet parts ÷ "&TEXT(Cost!B6,"0")&" boards (bare PCB excluded)" -> = Cost sheet parts ÷ 5 boards (bare PCB excluded)
A47: What changed from v0.3
A48: Area | B48: Change
A49: MCLK oscillator | B49: 80 MHz SCTF SX3M80.000B20F30TNN (C5179978) replaces the 100 MHz YXC part at X201, which sat at the ES9018K2M limit: 12.5 ns cycle (≥ 10 ns), ≥ 5.6 ns pulse width at 45:55, 208 × 384 kHz; still the CPLD system clock (tri-state pin 1 tied to 3V3D).
A50: Family oscillators | B50: Break-before-make: R212, R213 are now both 2.2 kΩ enable pull-downs, so X202 and X203 are off at power-up and during CPLD configuration; R214 10 kΩ pull-down on the shared family-clock node; DNF fallback 2:1 mux U205 (Nexperia 74LVC1G157GW,125, C135822) with R215 33 Ω.
A51: I/V op-amp | B51: TI OPA2210IDR (C1849415) replaces the OPA2197IDR: single input pair, so VREF 1.703 V sits 0.47 V inside the common-mode range (no input-pair transition); Vos ±35 µV max, 2.2 nV/√Hz; priced at its JLCPCB part page.
A52: Overload latch | B52: Q610 (2N7002: PGOOD bad sets the latch) and D606 (1N4148WS: a sustained TPS2553 overcurrent sets the latch) added — lines "Q601–Q610" (10 × 2N7002) and "D605, D606".
A53: VREF and rails | B53: VREF clamp D401 (1N4148WS, VREF → 3V3A) added and C421 10 µF → 100 nF (VREF τ ≈ 1.5 ms with C422); R518 10 kΩ → 5.1 kΩ: −3.722 V nominal (3.618–3.828 V incl. VFB and 1 % resistors); +3.780 V unchanged.
A54: Test | B54: R703 1 kΩ (DNF, fitted with J703): the test-header MCLK pin is a monitor output only; test pads TP701–TP729 (29), incl. the shared family-clock node and both enables.
A55: Descriptions | B55: U202, X202, X203, R501/R515, R503/R517, R617 and J703 updated (80 MHz system clock and break-before-make enables, rail ranges incl. resistor tolerance, blanking 25–133 ms, MCLK monitor output).
A56: Cost | B56: ="Parts US$"&TEXT(Cost!E43,"#,##0.00")&" ("&TEXT(Cost!F43,"#,##0")&" NTD), "&TEXT(Cost!B6,"0")&" PCBs US$"&TEXT(Cost!E44,"#,##0")&", fees US$"&TEXT(Cost!E45,"#,##0.00")&" → US$"&TEXT(Cost!E46,"#,##0.00")&" = "&TEXT(Cost!F46,"#,##0")&" NTD = "&TEXT(Cost!F47,"#,##0")&" NTD per board (was 1,666): the 80 MHz part and the OPA2210 at the JLCPCB price are cheaper; the new protection parts add a little." -> Parts US$138.84 (4,401 NTD), 5 PCBs US$10, fees US$110.96 → US$259.80 = 8,236 NTD = 1,647 NTD per board (was 1,666): the 80 MHz part and the OPA2210 at the JLCPCB price are cheaper; the new protection parts add a little.
A57: Price risk | B57: ="OPA2210 at the LCSC price (US$"&TEXT(Cost!C61,"0.00")&" at 10+, if the JLCPCB stock of 76 is gone): "&TEXT(Cost!F61,"+#,##0;-#,##0")&" NTD per board → ≈ "&TEXT(Cost!F47+Cost!F61,"#,##0")&" NTD, "&IF(Cost!F47+Cost!F61>Cost!F49,"above","within")&" the ceiling → reserve the "&TEXT(Cost!B61,"0")&" pieces in the JLCPCB parts library." -> OPA2210 at the LCSC price (US$2.67 at 10+, if the JLCPCB stock of 76 is gone): +106 NTD per board → ≈ 1,753 NTD, above the ceiling → reserve the 10 pieces in the JLCPCB parts library.
A58: Ceiling | B58: ="Ceiling "&TEXT(Cost!B11,"#,##0")&" NTD per board, set when the third oscillator was added; on 24 Sep 2026 the owner confirmed the budget is flexible as long as it does not surge; the actual JLCPCB quote from the real BOM/CPL files must pass the ceiling before ordering. Target "&TEXT(Cost!B10,"#,##0")&" NTD per board (WARNING above)." -> Ceiling 1,700 NTD per board, set when the third oscillator was added; on 24 Sep 2026 the owner confirmed the budget is flexible as long as it does not surge; the actual JLCPCB quote from the real BOM/CPL files must pass the ceiling before ordering. Target 1,500 NTD per board (WARNING above).
A59: Parts list | B59: ="One part per line: "&TEXT(B21,"0")&" BOM lines ("&TEXT(B22,"0")&" fitted; DNF: U205, R215, R703, J703), "&TEXT(B23,"0")&" purchasing lines (one per LCSC number); every fitted part has an LCSC number; every class is taken from its JLCPCB part page or the basic-parts list, except X202, whose class is not shown on its JLCPCB page (assumed Extended)." -> One part per line: 130 BOM lines (122 fitted; DNF: U205, R215, R703, J703), 48 purchasing lines (one per LCSC number); every fitted part has an LCSC number; every class is taken from its JLCPCB part page or the basic-parts list, except X202, whose class is not shown on its JLCPCB page (assumed Extended).
A60: Cost model | B60: ="LCSC tier matching the run quantity (OPA2210: JLCPCB part-page price); US$"&TEXT(Cost!B8,"0.00")&" minimum per purchasing line for parts under US$"&TEXT(Cost!B9,"0.00")&"; "&TEXT(Cost!B17,"0")&" Extended types incl. the through-hole jack; estimate history 1,540 (one oscillator) → 1,602 (+24.576 MHz) → 1,666 (+22.5792 MHz) → "&TEXT(Cost!F47,"#,##0")&" NTD per board (80 MHz MCLK, OPA2210 at the JLCPCB price, protection parts)." -> LCSC tier matching the run quantity (OPA2210: JLCPCB part-page price); US$0.10 minimum per purchasing line for parts under US$0.05; 19 Extended types incl. the through-hole jack; estimate history 1,540 (one oscillator) → 1,602 (+24.576 MHz) → 1,666 (+22.5792 MHz) → 1,647 NTD per board (80 MHz MCLK, OPA2210 at the JLCPCB price, protection parts).

Sheet Parts list
A1: Parts list — every BOM line, grouped by block
A2: One part per line; every fitted part has an LCSC number; every line’s JLCPCB class is taken from its JLCPCB part page or the JLCPCB basic-parts list, except X202, whose class is not shown on its JLCPCB page (assumed Extended). Unit prices in US$ at the LCSC tier matching the sample-run quantity (the OPA2210 at its JLCPCB part-page price, see its note) and at the 100-board tier (reference). Line costs here are before the US$0.10 minimum, which is applied per purchasing line on the Purchasing list. Helper columns V–W count distinct part types by LCSC number.
A3: Block | B3: Designators | C3: Qty per board | D3: Description | E3: Value | F3: Package | G3: Rating / tolerance | H3: Part number (MPN) | I3: LCSC no. | J3: JLCPCB library type | K3: Fit | L3: Leadless (X-ray) | M3: SMT joints per part | N3: Through-hole joints per part | O3: Unit price US$ (sample-run tier) | P3: Unit price US$ (100-board tier) | Q3: Price basis | R3: Qty for 5-board run | S3: Line cost US$, 5-board run (before the minimum) | T3: Line cost US$, 100-board run (reference) | U3: Notes | V3: Part-type key (helper) | W3: New part type (helper)
A4: 1 USB-C input and sensing | B4: J101 | C4: 1 | D4: USB-C receptacle, 16-pin, USB 2.0 (data + 5 V), sink | E4: — | F4: SMD, right angle | G4: 5 V, 3 A | H4: SHOU HAN TYPE-C 16PIN 2MD(073) | I4: C2765186 | J4: Extended | K4: Yes | M4: 20 | N4: 0 | O4: 0.1 | P4: 0.0604 | Q4: Quote | R4: =IF($K4="Yes",$C4*Cost!$B$6,0) -> 5 | S4: =IF($K4="Yes",$C4*Cost!$B$6*$O4,0) -> 0.5 | T4: =IF($K4="Yes",$C4*Cost!$B$7*$P4,0) -> 6.04 | V4: =IF(AND($K4="Yes",$B4<>"PCB",LEFT($I4,1)="C"),$I4,"") -> C2765186 | W4: =IF($V4="",0,IF(COUNTIF($V$4:$V4,$V4)=1,1,0)) -> 1
A5: 1 USB-C input and sensing | B5: R101, R102 | C5: 2 | D5: CC1/CC2 pull-down Rd (USB-C sink) | E5: 5.1 kΩ | F5: 0402 | G5: 1 % | H5: UNI-ROYAL 0402WGF5101TCE | I5: C25905 | J5: Basic | K5: Yes | M5: 2 | N5: 0 | O5: 0.002 | P5: 0.0005 | Q5: Quote | R5: =IF($K5="Yes",$C5*Cost!$B$6,0) -> 10 | S5: =IF($K5="Yes",$C5*Cost!$B$6*$O5,0) -> 0.02 | T5: =IF($K5="Yes",$C5*Cost!$B$7*$P5,0) -> 0.1 | V5: =IF(AND($K5="Yes",$B5<>"PCB",LEFT($I5,1)="C"),$I5,"") -> C25905 | W5: =IF($V5="",0,IF(COUNTIF($V$4:$V5,$V5)=1,1,0)) -> 1
A6: 1 USB-C input and sensing | B6: R103, R104 | C6: 2 | D6: CC1/CC2 → MCU ADC series (reads the Type-C current advertisement; does not load CC) | E6: 10 kΩ | F6: 0402 | G6: 1 % | H6: UNI-ROYAL 0402WGF1002TCE | I6: C25744 | J6: Basic | K6: Yes | M6: 2 | N6: 0 | O6: 0.002 | P6: 0.0005 | Q6: Quote | R6: =IF($K6="Yes",$C6*Cost!$B$6,0) -> 10 | S6: =IF($K6="Yes",$C6*Cost!$B$6*$O6,0) -> 0.02 | T6: =IF($K6="Yes",$C6*Cost!$B$7*$P6,0) -> 0.1 | V6: =IF(AND($K6="Yes",$B6<>"PCB",LEFT($I6,1)="C"),$I6,"") -> C25744 | W6: =IF($V6="",0,IF(COUNTIF($V$4:$V6,$V6)=1,1,0)) -> 1
A7: 1 USB-C input and sensing | B7: R105 | C7: 1 | D7: VBUS sense divider, top (→ MCU ADC with analog watchdog) | E7: 100 kΩ | F7: 0402 | G7: 1 % | H7: UNI-ROYAL 0402WGF1003TCE | I7: C25741 | J7: Basic | K7: Yes | M7: 2 | N7: 0 | O7: 0.002 | P7: 0.0005 | Q7: Quote | R7: =IF($K7="Yes",$C7*Cost!$B$6,0) -> 5 | S7: =IF($K7="Yes",$C7*Cost!$B$6*$O7,0) -> 0.01 | T7: =IF($K7="Yes",$C7*Cost!$B$7*$P7,0) -> 0.05 | V7: =IF(AND($K7="Yes",$B7<>"PCB",LEFT($I7,1)="C"),$I7,"") -> C25741 | W7: =IF($V7="",0,IF(COUNTIF($V$4:$V7,$V7)=1,1,0)) -> 1
A8: 1 USB-C input and sensing | B8: R106 | C8: 1 | D8: VBUS sense divider, bottom (5.0 V → 1.60 V) | E8: 47 kΩ | F8: 0402 | G8: 1 % | H8: UNI-ROYAL 0402WGF4702TCE | I8: C25792 | J8: Basic | K8: Yes | M8: 2 | N8: 0 | O8: 0.002 | P8: 0.0005 | Q8: Quote | R8: =IF($K8="Yes",$C8*Cost!$B$6,0) -> 5 | S8: =IF($K8="Yes",$C8*Cost!$B$6*$O8,0) -> 0.01 | T8: =IF($K8="Yes",$C8*Cost!$B$7*$P8,0) -> 0.05 | V8: =IF(AND($K8="Yes",$B8<>"PCB",LEFT($I8,1)="C"),$I8,"") -> C25792 | W8: =IF($V8="",0,IF(COUNTIF($V$4:$V8,$V8)=1,1,0)) -> 1
A9: 1 USB-C input and sensing | B9: R107 | C9: 1 | D9: Shield to GND bleed | E9: 1 MΩ | F9: 0402 | G9: 1 % | H9: UNI-ROYAL 0402WGF1004TCE | I9: C26083 | J9: Basic | K9: Yes | M9: 2 | N9: 0 | O9: 0.002 | P9: 0.0005 | Q9: Quote | R9: =IF($K9="Yes",$C9*Cost!$B$6,0) -> 5 | S9: =IF($K9="Yes",$C9*Cost!$B$6*$O9,0) -> 0.01 | T9: =IF($K9="Yes",$C9*Cost!$B$7*$P9,0) -> 0.05 | V9: =IF(AND($K9="Yes",$B9<>"PCB",LEFT($I9,1)="C"),$I9,"") -> C26083 | W9: =IF($V9="",0,IF(COUNTIF($V$4:$V9,$V9)=1,1,0)) -> 1
A10: 1 USB-C input and sensing | B10: C101 | C10: 1 | D10: Shield to GND (RF) | E10: 4.7 nF | F10: 0402 | G10: 50 V X7R | H10: FH 0402B472K500NT | I10: C1538 | J10: Basic | K10: Yes | M10: 2 | N10: 0 | O10: 0.002 | P10: 0.0006 | Q10: Quote | R10: =IF($K10="Yes",$C10*Cost!$B$6,0) -> 5 | S10: =IF($K10="Yes",$C10*Cost!$B$6*$O10,0) -> 0.01 | T10: =IF($K10="Yes",$C10*Cost!$B$7*$P10,0) -> 0.06 | V10: =IF(AND($K10="Yes",$B10<>"PCB",LEFT($I10,1)="C"),$I10,"") -> C1538 | W10: =IF($V10="",0,IF(COUNTIF($V$4:$V10,$V10)=1,1,0)) -> 1
A11: 1 USB-C input and sensing | B11: U101 | C11: 1 | D11: ESD array, D+, D−, VBUS | E11: — | F11: SOT-23-6 | G11: 5.25 V, 3.5 pF | H11: ST USBLC6-2SC6 | I11: C7519 | J11: Extended | K11: Yes | M11: 6 | N11: 0 | O11: 0.1844 | P11: 0.1439 | Q11: Quote | R11: =IF($K11="Yes",$C11*Cost!$B$6,0) -> 5 | S11: =IF($K11="Yes",$C11*Cost!$B$6*$O11,0) -> 0.922 | T11: =IF($K11="Yes",$C11*Cost!$B$7*$P11,0) -> 14.39 | V11: =IF(AND($K11="Yes",$B11<>"PCB",LEFT($I11,1)="C"),$I11,"") -> C7519 | W11: =IF($V11="",0,IF(COUNTIF($V$4:$V11,$V11)=1,1,0)) -> 1
A12: 1 USB-C input and sensing | B12: C102 | C12: 1 | D12: VBUS at the connector (VBUS capacitance before any switch: 5 × 1 µF) | E12: 1 µF | F12: 0603 | G12: 25 V X5R | H12: Samsung CL10A105KB8NNNC | I12: C15849 | J12: Basic | K12: Yes | M12: 2 | N12: 0 | O12: 0.006 | P12: 0.0022 | Q12: Quote | R12: =IF($K12="Yes",$C12*Cost!$B$6,0) -> 5 | S12: =IF($K12="Yes",$C12*Cost!$B$6*$O12,0) -> 0.03 | T12: =IF($K12="Yes",$C12*Cost!$B$7*$P12,0) -> 0.22 | V12: =IF(AND($K12="Yes",$B12<>"PCB",LEFT($I12,1)="C"),$I12,"") -> C15849 | W12: =IF($V12="",0,IF(COUNTIF($V$4:$V12,$V12)=1,1,0)) -> 1
A13: 2 USB audio bridge (CH32V307 + CPLD) | B13: U201 | C13: 1 | D13: MCU, RISC-V, USB 2.0 High-Speed with built-in PHY; own USB Audio Class 2.0 firmware | E13: — | F13: LQFP-64 10 × 10 mm | G13: 144 MHz, 3.3 V | H13: WCH CH32V307RCT6 | I13: C2988083 | J13: Extended | K13: Yes | M13: 64 | N13: 0 | O13: 3.45 | P13: 2.33 | Q13: Quote | R13: =IF($K13="Yes",$C13*Cost!$B$6,0) -> 5 | S13: =IF($K13="Yes",$C13*Cost!$B$6*$O13,0) -> 17.25 | T13: =IF($K13="Yes",$C13*Cost!$B$7*$P13,0) -> 233 | U13: LCSC stock 119: reserve before ordering | V13: =IF(AND($K13="Yes",$B13<>"PCB",LEFT($I13,1)="C"),$I13,"") -> C2988083 | W13: =IF($V13="",0,IF(COUNTIF($V$4:$V13,$V13)=1,1,0)) -> 1
A14: 2 USB audio bridge (CH32V307 + CPLD) | B14: Y201 | C14: 1 | D14: Crystal, CH32V307 HSE 8 MHz (firmware: HSE ÷ 2 = 4 MHz USB HS PLL reference) | E14: 8 MHz | F14: 5.0 × 3.2 mm, 2-pad | G14: ±10 ppm, CL 20 pF | H14: YXC X50328MSB2GI | I14: C115962 | J14: Basic | K14: Yes | M14: 2 | N14: 0 | O14: 0.2452 | P14: 0.2 | Q14: Quote | R14: =IF($K14="Yes",$C14*Cost!$B$6,0) -> 5 | S14: =IF($K14="Yes",$C14*Cost!$B$6*$O14,0) -> 1.226 | T14: =IF($K14="Yes",$C14*Cost!$B$7*$P14,0) -> 20 | U14: No Basic 3.2 × 2.5 mm 8 MHz crystal exists; 5032 used | V14: =IF(AND($K14="Yes",$B14<>"PCB",LEFT($I14,1)="C"),$I14,"") -> C115962 | W14: =IF($V14="",0,IF(COUNTIF($V$4:$V14,$V14)=1,1,0)) -> 1
A15: 2 USB audio bridge (CH32V307 + CPLD) | B15: C201, C202 | C15: 2 | D15: Crystal load capacitors (CL 20 pF crystal: 2 × (20 − ≈3.5 pF stray) ≈ 33 pF) | E15: 33 pF | F15: 0402 | G15: 50 V C0G | H15: FH 0402CG330J500NT | I15: C1562 | J15: Basic | K15: Yes | M15: 2 | N15: 0 | O15: 0.002 | P15: 0.0006 | Q15: Quote | R15: =IF($K15="Yes",$C15*Cost!$B$6,0) -> 10 | S15: =IF($K15="Yes",$C15*Cost!$B$6*$O15,0) -> 0.02 | T15: =IF($K15="Yes",$C15*Cost!$B$7*$P15,0) -> 0.12 | V15: =IF(AND($K15="Yes",$B15<>"PCB",LEFT($I15,1)="C"),$I15,"") -> C1562 | W15: =IF($V15="",0,IF(COUNTIF($V$4:$V15,$V15)=1,1,0)) -> 1
A16: 2 USB audio bridge (CH32V307 + CPLD) | B16: C203–C210 | C16: 8 | D16: CH32V307 VDD/VDDA/VIO decoupling, one per supply pin | E16: 100 nF | F16: 0402 | G16: 16 V X7R | H16: Samsung CL05B104KO5NNNC | I16: C1525 | J16: Basic | K16: Yes | M16: 2 | N16: 0 | O16: 0.003 | P16: 0.0011 | Q16: Quote | R16: =IF($K16="Yes",$C16*Cost!$B$6,0) -> 40 | S16: =IF($K16="Yes",$C16*Cost!$B$6*$O16,0) -> 0.12 | T16: =IF($K16="Yes",$C16*Cost!$B$7*$P16,0) -> 0.88 | V16: =IF(AND($K16="Yes",$B16<>"PCB",LEFT($I16,1)="C"),$I16,"") -> C1525 | W16: =IF($V16="",0,IF(COUNTIF($V$4:$V16,$V16)=1,1,0)) -> 1
A17: 2 USB audio bridge (CH32V307 + CPLD) | B17: C211 | C17: 1 | D17: CH32V307 3V3M bulk (2.2 µF keeps the attach inrush charge ≈ 38 µC) | E17: 2.2 µF | F17: 0402 | G17: 6.3 V X5R | H17: Samsung CL05A225MQ5NSNC | I17: C12530 | J17: Basic | K17: Yes | M17: 2 | N17: 0 | O17: 0.005 | P17: 0.0019 | Q17: Quote | R17: =IF($K17="Yes",$C17*Cost!$B$6,0) -> 5 | S17: =IF($K17="Yes",$C17*Cost!$B$6*$O17,0) -> 0.025 | T17: =IF($K17="Yes",$C17*Cost!$B$7*$P17,0) -> 0.19 | V17: =IF(AND($K17="Yes",$B17<>"PCB",LEFT($I17,1)="C"),$I17,"") -> C12530 | W17: =IF($V17="",0,IF(COUNTIF($V$4:$V17,$V17)=1,1,0)) -> 1
A18: 2 USB audio bridge (CH32V307 + CPLD) | B18: R201 | C18: 1 | D18: NRST pull-up | E18: 10 kΩ | F18: 0402 | G18: 1 % | H18: UNI-ROYAL 0402WGF1002TCE | I18: C25744 | J18: Basic | K18: Yes | M18: 2 | N18: 0 | O18: 0.002 | P18: 0.0005 | Q18: Quote | R18: =IF($K18="Yes",$C18*Cost!$B$6,0) -> 5 | S18: =IF($K18="Yes",$C18*Cost!$B$6*$O18,0) -> 0.01 | T18: =IF($K18="Yes",$C18*Cost!$B$7*$P18,0) -> 0.05 | V18: =IF(AND($K18="Yes",$B18<>"PCB",LEFT($I18,1)="C"),$I18,"") -> C25744 | W18: =IF($V18="",0,IF(COUNTIF($V$4:$V18,$V18)=1,1,0)) -> 0
A19: 2 USB audio bridge (CH32V307 + CPLD) | B19: C212 | C19: 1 | D19: NRST filter | E19: 100 nF | F19: 0402 | G19: 16 V X7R | H19: Samsung CL05B104KO5NNNC | I19: C1525 | J19: Basic | K19: Yes | M19: 2 | N19: 0 | O19: 0.003 | P19: 0.0011 | Q19: Quote | R19: =IF($K19="Yes",$C19*Cost!$B$6,0) -> 5 | S19: =IF($K19="Yes",$C19*Cost!$B$6*$O19,0) -> 0.015 | T19: =IF($K19="Yes",$C19*Cost!$B$7*$P19,0) -> 0.11 | V19: =IF(AND($K19="Yes",$B19<>"PCB",LEFT($I19,1)="C"),$I19,"") -> C1525 | W19: =IF($V19="",0,IF(COUNTIF($V$4:$V19,$V19)=1,1,0)) -> 0
A20: 2 USB audio bridge (CH32V307 + CPLD) | B20: R202 | C20: 1 | D20: BOOT0 pull-down | E20: 10 kΩ | F20: 0402 | G20: 1 % | H20: UNI-ROYAL 0402WGF1002TCE | I20: C25744 | J20: Basic | K20: Yes | M20: 2 | N20: 0 | O20: 0.002 | P20: 0.0005 | Q20: Quote | R20: =IF($K20="Yes",$C20*Cost!$B$6,0) -> 5 | S20: =IF($K20="Yes",$C20*Cost!$B$6*$O20,0) -> 0.01 | T20: =IF($K20="Yes",$C20*Cost!$B$7*$P20,0) -> 0.05 | V20: =IF(AND($K20="Yes",$B20<>"PCB",LEFT($I20,1)="C"),$I20,"") -> C25744 | W20: =IF($V20="",0,IF(COUNTIF($V$4:$V20,$V20)=1,1,0)) -> 0
A21: 2 USB audio bridge (CH32V307 + CPLD) | B21: U202 | C21: 1 | D21: CPLD, 2K LUT: FIFO and I²S master; 80 MHz system clock; PLL ×2 on the selected family oscillator (45.1584 / 49.152 MHz), exact integer division to BCLK/LRCLK for all 8 rates; drives the two oscillator enables (break-before-make) | E21: — | F21: QFN-32 4 × 4 mm | G21: 3.3 V | H21: AGM AGRV2KQ32 | I21: C18208899 | J21: Extended | K21: Yes | L21: Yes | M21: 33 | N21: 0 | O21: 1.6503 | P21: 1.11 | Q21: Quote | R21: =IF($K21="Yes",$C21*Cost!$B$6,0) -> 5 | S21: =IF($K21="Yes",$C21*Cost!$B$6*$O21,0) -> 8.2515 | T21: =IF($K21="Yes",$C21*Cost!$B$7*$P21,0) -> 111 | U21: LCSC stock 980 | V21: =IF(AND($K21="Yes",$B21<>"PCB",LEFT($I21,1)="C"),$I21,"") -> C18208899 | W21: =IF($V21="",0,IF(COUNTIF($V$4:$V21,$V21)=1,1,0)) -> 1
A22: 2 USB audio bridge (CH32V307 + CPLD) | B22: C213–C216 | C22: 4 | D22: CPLD decoupling | E22: 100 nF | F22: 0402 | G22: 16 V X7R | H22: Samsung CL05B104KO5NNNC | I22: C1525 | J22: Basic | K22: Yes | M22: 2 | N22: 0 | O22: 0.003 | P22: 0.0011 | Q22: Quote | R22: =IF($K22="Yes",$C22*Cost!$B$6,0) -> 20 | S22: =IF($K22="Yes",$C22*Cost!$B$6*$O22,0) -> 0.06 | T22: =IF($K22="Yes",$C22*Cost!$B$7*$P22,0) -> 0.44 | V22: =IF(AND($K22="Yes",$B22<>"PCB",LEFT($I22,1)="C"),$I22,"") -> C1525 | W22: =IF($V22="",0,IF(COUNTIF($V$4:$V22,$V22)=1,1,0)) -> 0
A23: 2 USB audio bridge (CH32V307 + CPLD) | B23: X201 | C23: 1 | D23: Oscillator, 80 MHz 3.3 V CMOS: DAC MCLK (asynchronous mode; 208 × 384 kHz > 192 × FSR; 12.5 ns cycle, ≥ 5.6 ns pulse width at 45:55) and the CPLD system clock; tri-state pin 1 tied to 3V3D | E23: 80 MHz | F23: 3.2 × 2.5 mm, 4-pad | G23: ±20 ppm tol., ±30 ppm stab., 40 mA max, duty 45–55 % | H23: SCTF SX3M80.000B20F30TNN | I23: C5179978 | J23: Extended | K23: Yes | L23: Yes | M23: 4 | N23: 0 | O23: 0.8916 | P23: 0.7211 | Q23: Quote | R23: =IF($K23="Yes",$C23*Cost!$B$6,0) -> 5 | S23: =IF($K23="Yes",$C23*Cost!$B$6*$O23,0) -> 4.458 | T23: =IF($K23="Yes",$C23*Cost!$B$7*$P23,0) -> 72.11 | U23: Replaces the 100 MHz part, which sat at the ES9018K2M 10 ns minimum MCLK cycle; LCSC stock 2,503 | V23: =IF(AND($K23="Yes",$B23<>"PCB",LEFT($I23,1)="C"),$I23,"") -> C5179978 | W23: =IF($V23="",0,IF(COUNTIF($V$4:$V23,$V23)=1,1,0)) -> 1
A24: 2 USB audio bridge (CH32V307 + CPLD) | B24: X202 | C24: 1 | D24: Oscillator, 24.576 MHz 3.3 V CMOS, tri-state enable on pin 1: 48 kHz rate family (OSC48_EN; off by default through R212; shared node into the CPLD PLL, ×2 = 49.152 MHz) | E24: 24.576 MHz | F24: 3.2 × 2.5 mm, 4-pad | G24: ±10 ppm tol., ±20 ppm stab., 1.8–3.3 V | H24: YXC OT322524.576MJBA4SL | I24: C2831388 | J24: Extended | K24: Yes | L24: Yes | M24: 4 | N24: 0 | O24: 0.5075 | P24: 0.2907 | Q24: Quote | R24: =IF($K24="Yes",$C24*Cost!$B$6,0) -> 5 | S24: =IF($K24="Yes",$C24*Cost!$B$6*$O24,0) -> 2.5375 | T24: =IF($K24="Yes",$C24*Cost!$B$7*$P24,0) -> 29.07 | U24: Class assumed Extended (not shown on the JLCPCB page); LCSC stock 1,755; JLCPCB page notes an assembly fixture may be needed (check the quote) | V24: =IF(AND($K24="Yes",$B24<>"PCB",LEFT($I24,1)="C"),$I24,"") -> C2831388 | W24: =IF($V24="",0,IF(COUNTIF($V$4:$V24,$V24)=1,1,0)) -> 1
A25: 2 USB audio bridge (CH32V307 + CPLD) | B25: X203 | C25: 1 | D25: Oscillator, 22.5792 MHz 1.62–3.63 V CMOS, tri-state pin 1 (SCTF 2CM datasheet: enabled when high or open, disabled when low; start-up ≤ 5 ms): 44.1 kHz rate family (OSC44_EN; off by default through R213; shared node into the CPLD PLL, ×2 = 45.1584 MHz) | E25: 22.5792 MHz | F25: 2.5 × 2.0 mm, 4-pad | G25: ±20 ppm tol., ±30 ppm stab., 10 mA max | H25: SCTF SX2M22.5792M20F30TNN | I25: C5452663 | J25: Extended | K25: Yes | L25: Yes | M25: 4 | N25: 0 | O25: 0.5455 | P25: 0.3085 | Q25: Quote | R25: =IF($K25="Yes",$C25*Cost!$B$6,0) -> 5 | S25: =IF($K25="Yes",$C25*Cost!$B$6*$O25,0) -> 2.7275 | T25: =IF($K25="Yes",$C25*Cost!$B$7*$P25,0) -> 30.85 | U25: JLCPCB class Extended (part page); LCSC stock 1,426; datasheet gives no disable time or disabled-output leakage: measured on the proof-of-concept board | V25: =IF(AND($K25="Yes",$B25<>"PCB",LEFT($I25,1)="C"),$I25,"") -> C5452663 | W25: =IF($V25="",0,IF(COUNTIF($V$4:$V25,$V25)=1,1,0)) -> 1
A26: 2 USB audio bridge (CH32V307 + CPLD) | B26: C217–C219 | C26: 3 | D26: Oscillator VDD decoupling (X201, X202, X203) | E26: 100 nF | F26: 0402 | G26: 16 V X7R | H26: Samsung CL05B104KO5NNNC | I26: C1525 | J26: Basic | K26: Yes | M26: 2 | N26: 0 | O26: 0.003 | P26: 0.0011 | Q26: Quote | R26: =IF($K26="Yes",$C26*Cost!$B$6,0) -> 15 | S26: =IF($K26="Yes",$C26*Cost!$B$6*$O26,0) -> 0.045 | T26: =IF($K26="Yes",$C26*Cost!$B$7*$P26,0) -> 0.33 | V26: =IF(AND($K26="Yes",$B26<>"PCB",LEFT($I26,1)="C"),$I26,"") -> C1525 | W26: =IF($V26="",0,IF(COUNTIF($V$4:$V26,$V26)=1,1,0)) -> 0
A27: 2 USB audio bridge (CH32V307 + CPLD) | B27: R212, R213 | C27: 2 | D27: Oscillator enable pull-downs, OSC48_EN (X202) and OSC44_EN (X203): both family oscillators stay off until the CPLD drives one enable (overrides the oscillators’ internal enable pull-ups and any CPLD weak pull-up ≥ 5.1 kΩ) | E27: 2.2 kΩ | F27: 0402 | G27: 1 % | H27: UNI-ROYAL 0402WGF2201TCE | I27: C25879 | J27: Basic | K27: Yes | M27: 2 | N27: 0 | O27: 0.002 | P27: 0.0005 | Q27: Quote | R27: =IF($K27="Yes",$C27*Cost!$B$6,0) -> 10 | S27: =IF($K27="Yes",$C27*Cost!$B$6*$O27,0) -> 0.02 | T27: =IF($K27="Yes",$C27*Cost!$B$7*$P27,0) -> 0.1 | V27: =IF(AND($K27="Yes",$B27<>"PCB",LEFT($I27,1)="C"),$I27,"") -> C25879 | W27: =IF($V27="",0,IF(COUNTIF($V$4:$V27,$V27)=1,1,0)) -> 1
A28: 2 USB audio bridge (CH32V307 + CPLD) | B28: R214 | C28: 1 | D28: Shared family-clock node pull-down (defined low while both family oscillators are off) | E28: 10 kΩ | F28: 0402 | G28: 1 % | H28: UNI-ROYAL 0402WGF1002TCE | I28: C25744 | J28: Basic | K28: Yes | M28: 2 | N28: 0 | O28: 0.002 | P28: 0.0005 | Q28: Quote | R28: =IF($K28="Yes",$C28*Cost!$B$6,0) -> 5 | S28: =IF($K28="Yes",$C28*Cost!$B$6*$O28,0) -> 0.01 | T28: =IF($K28="Yes",$C28*Cost!$B$7*$P28,0) -> 0.05 | V28: =IF(AND($K28="Yes",$B28<>"PCB",LEFT($I28,1)="C"),$I28,"") -> C25744 | W28: =IF($V28="",0,IF(COUNTIF($V$4:$V28,$V28)=1,1,0)) -> 0
A29: 2 USB audio bridge (CH32V307 + CPLD) | B29: U205 | C29: 1 | D29: DNF fallback: 2:1 logic mux in front of the CPLD PLL input (fit U205 + R215 and remove R210/R211); select = OSC44_EN | E29: — | F29: SOT-363 (SC-88) | G29: 1.65–5.5 V | H29: Nexperia 74LVC1G157GW,125 | I29: C135822 | J29: Extended | K29: DNF | M29: 6 | N29: 0 | O29: 0.2106 | P29: 0.1643 | Q29: Quote | R29: =IF($K29="Yes",$C29*Cost!$B$6,0) -> 0 | S29: =IF($K29="Yes",$C29*Cost!$B$6*$O29,0) -> 0 | T29: =IF($K29="Yes",$C29*Cost!$B$7*$P29,0) -> 0 | V29: =IF(AND($K29="Yes",$B29<>"PCB",LEFT($I29,1)="C"),$I29,"") | W29: =IF($V29="",0,IF(COUNTIF($V$4:$V29,$V29)=1,1,0)) -> 0
A30: 2 USB audio bridge (CH32V307 + CPLD) | B30: R215 | C30: 1 | D30: DNF: series termination, mux output to the CPLD PLL input (fitted with U205) | E30: 33 Ω | F30: 0402 | G30: 1 % | H30: UNI-ROYAL 0402WGF330JTCE | I30: C25105 | J30: Basic | K30: DNF | M30: 2 | N30: 0 | O30: 0.002 | P30: 0.0005 | Q30: Quote | R30: =IF($K30="Yes",$C30*Cost!$B$6,0) -> 0 | S30: =IF($K30="Yes",$C30*Cost!$B$6*$O30,0) -> 0 | T30: =IF($K30="Yes",$C30*Cost!$B$7*$P30,0) -> 0 | V30: =IF(AND($K30="Yes",$B30<>"PCB",LEFT($I30,1)="C"),$I30,"") | W30: =IF($V30="",0,IF(COUNTIF($V$4:$V30,$V30)=1,1,0)) -> 0
A31: 2 USB audio bridge (CH32V307 + CPLD) | B31: R203–R206 | C31: 4 | D31: Series termination: MCLK to the DAC, BCLK, LRCLK, SDATA toward the DAC | E31: 33 Ω | F31: 0402 | G31: 1 % | H31: UNI-ROYAL 0402WGF330JTCE | I31: C25105 | J31: Basic | K31: Yes | M31: 2 | N31: 0 | O31: 0.002 | P31: 0.0005 | Q31: Quote | R31: =IF($K31="Yes",$C31*Cost!$B$6,0) -> 20 | S31: =IF($K31="Yes",$C31*Cost!$B$6*$O31,0) -> 0.04 | T31: =IF($K31="Yes",$C31*Cost!$B$7*$P31,0) -> 0.2 | V31: =IF(AND($K31="Yes",$B31<>"PCB",LEFT($I31,1)="C"),$I31,"") -> C25105 | W31: =IF($V31="",0,IF(COUNTIF($V$4:$V31,$V31)=1,1,0)) -> 1
A32: 2 USB audio bridge (CH32V307 + CPLD) | B32: R209 | C32: 1 | D32: Series termination: MCLK branch to the CPLD clock input | E32: 33 Ω | F32: 0402 | G32: 1 % | H32: UNI-ROYAL 0402WGF330JTCE | I32: C25105 | J32: Basic | K32: Yes | M32: 2 | N32: 0 | O32: 0.002 | P32: 0.0005 | Q32: Quote | R32: =IF($K32="Yes",$C32*Cost!$B$6,0) -> 5 | S32: =IF($K32="Yes",$C32*Cost!$B$6*$O32,0) -> 0.01 | T32: =IF($K32="Yes",$C32*Cost!$B$7*$P32,0) -> 0.05 | V32: =IF(AND($K32="Yes",$B32<>"PCB",LEFT($I32,1)="C"),$I32,"") -> C25105 | W32: =IF($V32="",0,IF(COUNTIF($V$4:$V32,$V32)=1,1,0)) -> 0
A33: 2 USB audio bridge (CH32V307 + CPLD) | B33: R210, R211 | C33: 2 | D33: Series termination: X202 and X203 outputs into the shared node at the CPLD PLL clock input | E33: 33 Ω | F33: 0402 | G33: 1 % | H33: UNI-ROYAL 0402WGF330JTCE | I33: C25105 | J33: Basic | K33: Yes | M33: 2 | N33: 0 | O33: 0.002 | P33: 0.0005 | Q33: Quote | R33: =IF($K33="Yes",$C33*Cost!$B$6,0) -> 10 | S33: =IF($K33="Yes",$C33*Cost!$B$6*$O33,0) -> 0.02 | T33: =IF($K33="Yes",$C33*Cost!$B$7*$P33,0) -> 0.1 | V33: =IF(AND($K33="Yes",$B33<>"PCB",LEFT($I33,1)="C"),$I33,"") -> C25105 | W33: =IF($V33="",0,IF(COUNTIF($V$4:$V33,$V33)=1,1,0)) -> 0
A34: 2 USB audio bridge (CH32V307 + CPLD) | B34: R207, R208 | C34: 2 | D34: I²C SCL/SDA pull-ups to 3V3D (off with the DAC domain: no back-powering) | E34: 2.2 kΩ | F34: 0402 | G34: 1 % | H34: UNI-ROYAL 0402WGF2201TCE | I34: C25879 | J34: Basic | K34: Yes | M34: 2 | N34: 0 | O34: 0.002 | P34: 0.0005 | Q34: Quote | R34: =IF($K34="Yes",$C34*Cost!$B$6,0) -> 10 | S34: =IF($K34="Yes",$C34*Cost!$B$6*$O34,0) -> 0.02 | T34: =IF($K34="Yes",$C34*Cost!$B$7*$P34,0) -> 0.1 | V34: =IF(AND($K34="Yes",$B34<>"PCB",LEFT($I34,1)="C"),$I34,"") -> C25879 | W34: =IF($V34="",0,IF(COUNTIF($V$4:$V34,$V34)=1,1,0)) -> 0
A35: 2 USB audio bridge (CH32V307 + CPLD) | B35: J201 | C35: 1 | D35: Pads, CH32V307 2-wire debug (WCH-LinkE): 3V3, SWDIO, SWCLK, GND | E35: — | F35: Pads | G35: — | H35: No part | I35: — | J35: — | K35: No part | M35: 0 | N35: 0 | O35: 0 | P35: 0 | Q35: Estimate | R35: =IF($K35="Yes",$C35*Cost!$B$6,0) -> 0 | S35: =IF($K35="Yes",$C35*Cost!$B$6*$O35,0) -> 0 | T35: =IF($K35="Yes",$C35*Cost!$B$7*$P35,0) -> 0 | V35: =IF(AND($K35="Yes",$B35<>"PCB",LEFT($I35,1)="C"),$I35,"") | W35: =IF($V35="",0,IF(COUNTIF($V$4:$V35,$V35)=1,1,0)) -> 0
A36: 2 USB audio bridge (CH32V307 + CPLD) | B36: J202 | C36: 1 | D36: Pads, CPLD JTAG: 3V3, TCK, TMS, TDI, TDO, GND | E36: — | F36: Pads | G36: — | H36: No part | I36: — | J36: — | K36: No part | M36: 0 | N36: 0 | O36: 0 | P36: 0 | Q36: Estimate | R36: =IF($K36="Yes",$C36*Cost!$B$6,0) -> 0 | S36: =IF($K36="Yes",$C36*Cost!$B$6*$O36,0) -> 0 | T36: =IF($K36="Yes",$C36*Cost!$B$7*$P36,0) -> 0 | V36: =IF(AND($K36="Yes",$B36<>"PCB",LEFT($I36,1)="C"),$I36,"") | W36: =IF($V36="",0,IF(COUNTIF($V$4:$V36,$V36)=1,1,0)) -> 0
A37: 3 DAC (ES9018K2M) and its supplies | B37: U301 | C37: 1 | D37: DAC, 32-bit, PCM to 384 kHz, I²C; asynchronous (DPLL/jitter eliminator) mode; differential current-mode outputs | E37: — | F37: QFN-28 5 × 5 mm | G37: DNR 127 dB-A, THD+N −120 dB (datasheet, current mode) | H37: ESS ES9018K2M | I37: C2688377 | J37: Extended | K37: Yes | L37: Yes | M37: 29 | N37: 0 | O37: 3.4678 | P37: 2.28 | Q37: Quote | R37: =IF($K37="Yes",$C37*Cost!$B$6,0) -> 5 | S37: =IF($K37="Yes",$C37*Cost!$B$6*$O37,0) -> 17.339 | T37: =IF($K37="Yes",$C37*Cost!$B$7*$P37,0) -> 228 | U37: LCSC stock 724 | V37: =IF(AND($K37="Yes",$B37<>"PCB",LEFT($I37,1)="C"),$I37,"") -> C2688377 | W37: =IF($V37="",0,IF(COUNTIF($V$4:$V37,$V37)=1,1,0)) -> 1
A38: 3 DAC (ES9018K2M) and its supplies | B38: U302 | C38: 1 | D38: LDO, quiet 3.3 V for VCCA, AVCC_L, AVCC_R and VREF (3V3A), EN = AVCC_EN | E38: 3.3 V, 250 mA | F38: SOT-23-5 | G38: 6.5 µVrms, ±2 % | H38: TI LP5907MFX-3.3/NOPB | I38: C80670 | J38: Extended | K38: Yes | M38: 5 | N38: 0 | O38: 0.2104 | P38: 0.14 | Q38: Quote | R38: =IF($K38="Yes",$C38*Cost!$B$6,0) -> 5 | S38: =IF($K38="Yes",$C38*Cost!$B$6*$O38,0) -> 1.052 | T38: =IF($K38="Yes",$C38*Cost!$B$7*$P38,0) -> 14 | V38: =IF(AND($K38="Yes",$B38<>"PCB",LEFT($I38,1)="C"),$I38,"") -> C80670 | W38: =IF($V38="",0,IF(COUNTIF($V$4:$V38,$V38)=1,1,0)) -> 1
A39: 3 DAC (ES9018K2M) and its supplies | B39: C301 | C39: 1 | D39: LP5907 input (part of the 5 µF VBUS budget) | E39: 1 µF | F39: 0603 | G39: 25 V X5R | H39: Samsung CL10A105KB8NNNC | I39: C15849 | J39: Basic | K39: Yes | M39: 2 | N39: 0 | O39: 0.006 | P39: 0.0022 | Q39: Quote | R39: =IF($K39="Yes",$C39*Cost!$B$6,0) -> 5 | S39: =IF($K39="Yes",$C39*Cost!$B$6*$O39,0) -> 0.03 | T39: =IF($K39="Yes",$C39*Cost!$B$7*$P39,0) -> 0.22 | V39: =IF(AND($K39="Yes",$B39<>"PCB",LEFT($I39,1)="C"),$I39,"") -> C15849 | W39: =IF($V39="",0,IF(COUNTIF($V$4:$V39,$V39)=1,1,0)) -> 0
A40: 3 DAC (ES9018K2M) and its supplies | B40: C302 | C40: 1 | D40: LP5907 output (LP5907 total output capacitance 5.7 µF ≤ 10 µF) | E40: 1 µF | F40: 0603 | G40: 25 V X5R | H40: Samsung CL10A105KB8NNNC | I40: C15849 | J40: Basic | K40: Yes | M40: 2 | N40: 0 | O40: 0.006 | P40: 0.0022 | Q40: Quote | R40: =IF($K40="Yes",$C40*Cost!$B$6,0) -> 5 | S40: =IF($K40="Yes",$C40*Cost!$B$6*$O40,0) -> 0.03 | T40: =IF($K40="Yes",$C40*Cost!$B$7*$P40,0) -> 0.22 | V40: =IF(AND($K40="Yes",$B40<>"PCB",LEFT($I40,1)="C"),$I40,"") -> C15849 | W40: =IF($V40="",0,IF(COUNTIF($V$4:$V40,$V40)=1,1,0)) -> 0
A41: 3 DAC (ES9018K2M) and its supplies | B41: R303 | C41: 1 | D41: LP5907 EN pull-down (off until the MCU enables it) | E41: 100 kΩ | F41: 0402 | G41: 1 % | H41: UNI-ROYAL 0402WGF1003TCE | I41: C25741 | J41: Basic | K41: Yes | M41: 2 | N41: 0 | O41: 0.002 | P41: 0.0005 | Q41: Quote | R41: =IF($K41="Yes",$C41*Cost!$B$6,0) -> 5 | S41: =IF($K41="Yes",$C41*Cost!$B$6*$O41,0) -> 0.01 | T41: =IF($K41="Yes",$C41*Cost!$B$7*$P41,0) -> 0.05 | V41: =IF(AND($K41="Yes",$B41<>"PCB",LEFT($I41,1)="C"),$I41,"") -> C25741 | W41: =IF($V41="",0,IF(COUNTIF($V$4:$V41,$V41)=1,1,0)) -> 0
A42: 3 DAC (ES9018K2M) and its supplies | B42: R301, R302 | C42: 2 | D42: AVCC_L and AVCC_R feeds (separate branches from the LDO; ≈ 18 mV drop at 8 mA) | E42: 2.2 Ω | F42: 0805 | G42: 1 % | H42: UNI-ROYAL 0805W8F220JT5E | I42: C17521 | J42: Basic | K42: Yes | M42: 2 | N42: 0 | O42: 0.003 | P42: 0.001 | Q42: Quote | R42: =IF($K42="Yes",$C42*Cost!$B$6,0) -> 10 | S42: =IF($K42="Yes",$C42*Cost!$B$6*$O42,0) -> 0.03 | T42: =IF($K42="Yes",$C42*Cost!$B$7*$P42,0) -> 0.2 | V42: =IF(AND($K42="Yes",$B42<>"PCB",LEFT($I42,1)="C"),$I42,"") -> C17521 | W42: =IF($V42="",0,IF(COUNTIF($V$4:$V42,$V42)=1,1,0)) -> 1
A43: 3 DAC (ES9018K2M) and its supplies | B43: C303, C304 | C43: 2 | D43: AVCC_L and AVCC_R | E43: 2.2 µF | F43: 0402 | G43: 6.3 V X5R | H43: Samsung CL05A225MQ5NSNC | I43: C12530 | J43: Basic | K43: Yes | M43: 2 | N43: 0 | O43: 0.005 | P43: 0.0019 | Q43: Quote | R43: =IF($K43="Yes",$C43*Cost!$B$6,0) -> 10 | S43: =IF($K43="Yes",$C43*Cost!$B$6*$O43,0) -> 0.05 | T43: =IF($K43="Yes",$C43*Cost!$B$7*$P43,0) -> 0.38 | V43: =IF(AND($K43="Yes",$B43<>"PCB",LEFT($I43,1)="C"),$I43,"") -> C12530 | W43: =IF($V43="",0,IF(COUNTIF($V$4:$V43,$V43)=1,1,0)) -> 0
A44: 3 DAC (ES9018K2M) and its supplies | B44: C305–C309 | C44: 5 | D44: AVCC_L, AVCC_R, VCCA, DVCC, DVDD HF decoupling | E44: 100 nF | F44: 0402 | G44: 16 V X7R | H44: Samsung CL05B104KO5NNNC | I44: C1525 | J44: Basic | K44: Yes | M44: 2 | N44: 0 | O44: 0.003 | P44: 0.0011 | Q44: Quote | R44: =IF($K44="Yes",$C44*Cost!$B$6,0) -> 25 | S44: =IF($K44="Yes",$C44*Cost!$B$6*$O44,0) -> 0.075 | T44: =IF($K44="Yes",$C44*Cost!$B$7*$P44,0) -> 0.55 | V44: =IF(AND($K44="Yes",$B44<>"PCB",LEFT($I44,1)="C"),$I44,"") -> C1525 | W44: =IF($V44="",0,IF(COUNTIF($V$4:$V44,$V44)=1,1,0)) -> 0
A45: 3 DAC (ES9018K2M) and its supplies | B45: C310 | C45: 1 | D45: DVDD at the DAC pin (datasheet: ≥ 1 µF effective; 2.2 µF X5R recommended) | E45: 2.2 µF | F45: 0402 | G45: 6.3 V X5R | H45: Samsung CL05A225MQ5NSNC | I45: C12530 | J45: Basic | K45: Yes | M45: 2 | N45: 0 | O45: 0.005 | P45: 0.0019 | Q45: Quote | R45: =IF($K45="Yes",$C45*Cost!$B$6,0) -> 5 | S45: =IF($K45="Yes",$C45*Cost!$B$6*$O45,0) -> 0.025 | T45: =IF($K45="Yes",$C45*Cost!$B$7*$P45,0) -> 0.19 | V45: =IF(AND($K45="Yes",$B45<>"PCB",LEFT($I45,1)="C"),$I45,"") -> C12530 | W45: =IF($V45="",0,IF(COUNTIF($V$4:$V45,$V45)=1,1,0)) -> 0
A46: 3 DAC (ES9018K2M) and its supplies | B46: U303 | C46: 1 | D46: LDO, fixed 1.3 V for the external DVDD (required for FSR > 192 kHz), fed from 3V3D so DVDD ≤ DVCC during ramps | E46: 1.3 V, 300 mA | F46: SOT-23 | G46: ±1 %, ceramic-stable, 6 µA Iq | H46: Microne ME6216A13M3G | I46: C236662 | J46: Extended | K46: Yes | M46: 3 | N46: 0 | O46: 0.06 | P46: 0.038 | Q46: Quote | R46: =IF($K46="Yes",$C46*Cost!$B$6,0) -> 5 | S46: =IF($K46="Yes",$C46*Cost!$B$6*$O46,0) -> 0.3 | T46: =IF($K46="Yes",$C46*Cost!$B$7*$P46,0) -> 3.8 | U46: LCSC stock ≈ 410: reserve before ordering | V46: =IF(AND($K46="Yes",$B46<>"PCB",LEFT($I46,1)="C"),$I46,"") -> C236662 | W46: =IF($V46="",0,IF(COUNTIF($V$4:$V46,$V46)=1,1,0)) -> 1
A47: 3 DAC (ES9018K2M) and its supplies | B47: C311 | C47: 1 | D47: 1.3 V LDO input | E47: 1 µF | F47: 0603 | G47: 25 V X5R | H47: Samsung CL10A105KB8NNNC | I47: C15849 | J47: Basic | K47: Yes | M47: 2 | N47: 0 | O47: 0.006 | P47: 0.0022 | Q47: Quote | R47: =IF($K47="Yes",$C47*Cost!$B$6,0) -> 5 | S47: =IF($K47="Yes",$C47*Cost!$B$6*$O47,0) -> 0.03 | T47: =IF($K47="Yes",$C47*Cost!$B$7*$P47,0) -> 0.22 | V47: =IF(AND($K47="Yes",$B47<>"PCB",LEFT($I47,1)="C"),$I47,"") -> C15849 | W47: =IF($V47="",0,IF(COUNTIF($V$4:$V47,$V47)=1,1,0)) -> 0
A48: 3 DAC (ES9018K2M) and its supplies | B48: C312 | C48: 1 | D48: 1.3 V LDO output | E48: 1 µF | F48: 0603 | G48: 25 V X5R | H48: Samsung CL10A105KB8NNNC | I48: C15849 | J48: Basic | K48: Yes | M48: 2 | N48: 0 | O48: 0.006 | P48: 0.0022 | Q48: Quote | R48: =IF($K48="Yes",$C48*Cost!$B$6,0) -> 5 | S48: =IF($K48="Yes",$C48*Cost!$B$6*$O48,0) -> 0.03 | T48: =IF($K48="Yes",$C48*Cost!$B$7*$P48,0) -> 0.22 | V48: =IF(AND($K48="Yes",$B48<>"PCB",LEFT($I48,1)="C"),$I48,"") -> C15849 | W48: =IF($V48="",0,IF(COUNTIF($V$4:$V48,$V48)=1,1,0)) -> 0
A49: 3 DAC (ES9018K2M) and its supplies | B49: R305 | C49: 1 | D49: RESETB pull-down (DAC held in reset until firmware releases it) | E49: 100 kΩ | F49: 0402 | G49: 1 % | H49: UNI-ROYAL 0402WGF1003TCE | I49: C25741 | J49: Basic | K49: Yes | M49: 2 | N49: 0 | O49: 0.002 | P49: 0.0005 | Q49: Quote | R49: =IF($K49="Yes",$C49*Cost!$B$6,0) -> 5 | S49: =IF($K49="Yes",$C49*Cost!$B$6*$O49,0) -> 0.01 | T49: =IF($K49="Yes",$C49*Cost!$B$7*$P49,0) -> 0.05 | V49: =IF(AND($K49="Yes",$B49<>"PCB",LEFT($I49,1)="C"),$I49,"") -> C25741 | W49: =IF($V49="",0,IF(COUNTIF($V$4:$V49,$V49)=1,1,0)) -> 0
A50: 3 DAC (ES9018K2M) and its supplies | B50: R306 | C50: 1 | D50: ADDR strap (I²C address 0x90) | E50: 10 kΩ | F50: 0402 | G50: 1 % | H50: UNI-ROYAL 0402WGF1002TCE | I50: C25744 | J50: Basic | K50: Yes | M50: 2 | N50: 0 | O50: 0.002 | P50: 0.0005 | Q50: Quote | R50: =IF($K50="Yes",$C50*Cost!$B$6,0) -> 5 | S50: =IF($K50="Yes",$C50*Cost!$B$6*$O50,0) -> 0.01 | T50: =IF($K50="Yes",$C50*Cost!$B$7*$P50,0) -> 0.05 | V50: =IF(AND($K50="Yes",$B50<>"PCB",LEFT($I50,1)="C"),$I50,"") -> C25744 | W50: =IF($V50="",0,IF(COUNTIF($V$4:$V50,$V50)=1,1,0)) -> 0
A51: 3 DAC (ES9018K2M) and its supplies | B51: FB301 | C51: 1 | D51: Ferrite bead, 3V3D → DVCC (≈ 14 mA) | E51: 600 Ω @ 100 MHz | F51: 0603 | G51: 200 mA, 0.45 Ω | H51: Sunlord GZ1608D601TF | I51: C1002 | J51: Basic | K51: Yes | M51: 2 | N51: 0 | O51: 0.0127 | P51: 0.004 | Q51: Quote | R51: =IF($K51="Yes",$C51*Cost!$B$6,0) -> 5 | S51: =IF($K51="Yes",$C51*Cost!$B$6*$O51,0) -> 0.0635 | T51: =IF($K51="Yes",$C51*Cost!$B$7*$P51,0) -> 0.4 | V51: =IF(AND($K51="Yes",$B51<>"PCB",LEFT($I51,1)="C"),$I51,"") -> C1002 | W51: =IF($V51="",0,IF(COUNTIF($V$4:$V51,$V51)=1,1,0)) -> 1
A52: 4 I/V converters and output legs | B52: U403, U404 | C52: 2 | D52: Op-amp, dual, I/V converters, one amplifier per DAC pin (U403 = DACL, DACLB; U404 = DACR, DACRB); single input pair, so VREF 1.703 V sits 0.47 V inside the common-mode range (no input-pair transition) | E52: — | F52: SOIC-8 | G52: Vos ±35 µV max, 2.2 nV/√Hz, 18 MHz, CM (V−)+1.5 V to (V+)−1.5 V, 2.5 mA/ch max | H52: TI OPA2210IDR | I52: C1849415 | J52: Extended | K52: Yes | M52: 8 | N52: 0 | O52: 1.0035 | P52: 0.753 | Q52: Quote | R52: =IF($K52="Yes",$C52*Cost!$B$6,0) -> 10 | S52: =IF($K52="Yes",$C52*Cost!$B$6*$O52,0) -> 10.035 | T52: =IF($K52="Yes",$C52*Cost!$B$7*$P52,0) -> 150.6 | U52: JLCPCB part-page price (the PCBA order is charged at JLCPCB prices); LCSC lists US$2.67 at 10+; at the LCSC price the board would cost ≈ 1,753 NTD; JLCPCB available 76 → reserve 10; page notes an assembly fixture may be needed | V52: =IF(AND($K52="Yes",$B52<>"PCB",LEFT($I52,1)="C"),$I52,"") -> C1849415 | W52: =IF($V52="",0,IF(COUNTIF($V$4:$V52,$V52)=1,1,0)) -> 1
A53: 4 I/V converters and output legs | B53: R423–R426 | C53: 4 | D53: I/V feedback, part 1: 1 kΩ ∥ 5.1 kΩ = 836 Ω (Basic values; 750 Ω is Extended). 2 × 836/806 × 1.078 = 2.24 Vrms per leg before calibration | E53: 1 kΩ | F53: 0402 | G53: 1 % | H53: UNI-ROYAL 0402WGF1001TCE | I53: C11702 | J53: Basic | K53: Yes | M53: 2 | N53: 0 | O53: 0.002 | P53: 0.0005 | Q53: Quote | R53: =IF($K53="Yes",$C53*Cost!$B$6,0) -> 20 | S53: =IF($K53="Yes",$C53*Cost!$B$6*$O53,0) -> 0.04 | T53: =IF($K53="Yes",$C53*Cost!$B$7*$P53,0) -> 0.2 | V53: =IF(AND($K53="Yes",$B53<>"PCB",LEFT($I53,1)="C"),$I53,"") -> C11702 | W53: =IF($V53="",0,IF(COUNTIF($V$4:$V53,$V53)=1,1,0)) -> 1
A54: 4 I/V converters and output legs | B54: R434–R437 | C54: 4 | D54: I/V feedback, part 2 (in parallel with R423–R426) | E54: 5.1 kΩ | F54: 0402 | G54: 1 % | H54: UNI-ROYAL 0402WGF5101TCE | I54: C25905 | J54: Basic | K54: Yes | M54: 2 | N54: 0 | O54: 0.002 | P54: 0.0005 | Q54: Quote | R54: =IF($K54="Yes",$C54*Cost!$B$6,0) -> 20 | S54: =IF($K54="Yes",$C54*Cost!$B$6*$O54,0) -> 0.04 | T54: =IF($K54="Yes",$C54*Cost!$B$7*$P54,0) -> 0.2 | V54: =IF(AND($K54="Yes",$B54<>"PCB",LEFT($I54,1)="C"),$I54,"") -> C25905 | W54: =IF($V54="",0,IF(COUNTIF($V$4:$V54,$V54)=1,1,0)) -> 0
A55: 4 I/V converters and output legs | B55: R427–R430 | C55: 4 | D55: Resistor in series with each I/V feedback capacitor (ESS application circuit) | E55: 10 Ω | F55: 0603 | G55: 1 % | H55: UNI-ROYAL 0603WAF100JT5E | I55: C22859 | J55: Basic | K55: Yes | M55: 2 | N55: 0 | O55: 0.002 | P55: 0.0005 | Q55: Quote | R55: =IF($K55="Yes",$C55*Cost!$B$6,0) -> 20 | S55: =IF($K55="Yes",$C55*Cost!$B$6*$O55,0) -> 0.04 | T55: =IF($K55="Yes",$C55*Cost!$B$7*$P55,0) -> 0.2 | V55: =IF(AND($K55="Yes",$B55<>"PCB",LEFT($I55,1)="C"),$I55,"") -> C22859 | W55: =IF($V55="",0,IF(COUNTIF($V$4:$V55,$V55)=1,1,0)) -> 1
A56: 4 I/V converters and output legs | B56: C417–C420, C427–C430 | C56: 8 | D56: I/V feedback capacitor, two 330 pF C0G in parallel per converter = 660 pF (≈ 288 kHz with 836 Ω; no Basic C0G above 330 pF) | E56: 330 pF | F56: 0603 | G56: 50 V C0G | H56: Samsung CL10C331JB8NNNC | I56: C1664 | J56: Basic | K56: Yes | M56: 2 | N56: 0 | O56: 0.005 | P56: 0.0019 | Q56: Quote | R56: =IF($K56="Yes",$C56*Cost!$B$6,0) -> 40 | S56: =IF($K56="Yes",$C56*Cost!$B$6*$O56,0) -> 0.2 | T56: =IF($K56="Yes",$C56*Cost!$B$7*$P56,0) -> 1.52 | V56: =IF(AND($K56="Yes",$B56<>"PCB",LEFT($I56,1)="C"),$I56,"") -> C1664 | W56: =IF($V56="",0,IF(COUNTIF($V$4:$V56,$V56)=1,1,0)) -> 1
A57: 4 I/V converters and output legs | B57: R431 | C57: 1 | D57: VREF divider, top (from 3V3A) | E57: 15 kΩ | F57: 0402 | G57: 1 % | H57: UNI-ROYAL 0402WGF1502TCE | I57: C25756 | J57: Basic | K57: Yes | M57: 2 | N57: 0 | O57: 0.002 | P57: 0.0005 | Q57: Quote | R57: =IF($K57="Yes",$C57*Cost!$B$6,0) -> 5 | S57: =IF($K57="Yes",$C57*Cost!$B$6*$O57,0) -> 0.01 | T57: =IF($K57="Yes",$C57*Cost!$B$7*$P57,0) -> 0.05 | V57: =IF(AND($K57="Yes",$B57<>"PCB",LEFT($I57,1)="C"),$I57,"") -> C25756 | W57: =IF($V57="",0,IF(COUNTIF($V$4:$V57,$V57)=1,1,0)) -> 1
A58: 4 I/V converters and output legs | B58: R432 | C58: 1 | D58: VREF divider, bottom, part 1 (15 kΩ + 1 kΩ = 16 kΩ → VREF 1.703 V ≈ DAC zero-DC-current point) | E58: 15 kΩ | F58: 0402 | G58: 1 % | H58: UNI-ROYAL 0402WGF1502TCE | I58: C25756 | J58: Basic | K58: Yes | M58: 2 | N58: 0 | O58: 0.002 | P58: 0.0005 | Q58: Quote | R58: =IF($K58="Yes",$C58*Cost!$B$6,0) -> 5 | S58: =IF($K58="Yes",$C58*Cost!$B$6*$O58,0) -> 0.01 | T58: =IF($K58="Yes",$C58*Cost!$B$7*$P58,0) -> 0.05 | V58: =IF(AND($K58="Yes",$B58<>"PCB",LEFT($I58,1)="C"),$I58,"") -> C25756 | W58: =IF($V58="",0,IF(COUNTIF($V$4:$V58,$V58)=1,1,0)) -> 0
A59: 4 I/V converters and output legs | B59: R433 | C59: 1 | D59: VREF divider, bottom, part 2 | E59: 1 kΩ | F59: 0402 | G59: 1 % | H59: UNI-ROYAL 0402WGF1001TCE | I59: C11702 | J59: Basic | K59: Yes | M59: 2 | N59: 0 | O59: 0.002 | P59: 0.0005 | Q59: Quote | R59: =IF($K59="Yes",$C59*Cost!$B$6,0) -> 5 | S59: =IF($K59="Yes",$C59*Cost!$B$6*$O59,0) -> 0.01 | T59: =IF($K59="Yes",$C59*Cost!$B$7*$P59,0) -> 0.05 | V59: =IF(AND($K59="Yes",$B59<>"PCB",LEFT($I59,1)="C"),$I59,"") -> C11702 | W59: =IF($V59="",0,IF(COUNTIF($V$4:$V59,$V59)=1,1,0)) -> 0
A60: 4 I/V converters and output legs | B60: C421 | C60: 1 | D60: VREF filter at the divider (with C422: τ ≈ 1.5 ms; VREF noise is common mode to both pins of a pair) | E60: 100 nF | F60: 0402 | G60: 16 V X7R | H60: Samsung CL05B104KO5NNNC | I60: C1525 | J60: Basic | K60: Yes | M60: 2 | N60: 0 | O60: 0.003 | P60: 0.0011 | Q60: Quote | R60: =IF($K60="Yes",$C60*Cost!$B$6,0) -> 5 | S60: =IF($K60="Yes",$C60*Cost!$B$6*$O60,0) -> 0.015 | T60: =IF($K60="Yes",$C60*Cost!$B$7*$P60,0) -> 0.11 | V60: =IF(AND($K60="Yes",$B60<>"PCB",LEFT($I60,1)="C"),$I60,"") -> C1525 | W60: =IF($V60="",0,IF(COUNTIF($V$4:$V60,$V60)=1,1,0)) -> 0
A61: 4 I/V converters and output legs | B61: D401 | C61: 1 | D61: VREF clamp to 3V3A (anode = VREF): when AVCC collapses at unplug, VREF follows it, so the I/V converters never hold the DAC pins far above AVCC (ES9018K2M abs. max: GND < Vout < AVCC) | E61: 1N4148WS | F61: SOD-323 | G61: 100 V, 150 mA; reverse-biased 1.6 V in use | H61: JSCJ 1N4148WS | I61: C2128 | J61: Basic | K61: Yes | M61: 2 | N61: 0 | O61: 0.016 | P61: 0.012 | Q61: Quote | R61: =IF($K61="Yes",$C61*Cost!$B$6,0) -> 5 | S61: =IF($K61="Yes",$C61*Cost!$B$6*$O61,0) -> 0.08 | T61: =IF($K61="Yes",$C61*Cost!$B$7*$P61,0) -> 1.2 | V61: =IF(AND($K61="Yes",$B61<>"PCB",LEFT($I61,1)="C"),$I61,"") -> C2128 | W61: =IF($V61="",0,IF(COUNTIF($V$4:$V61,$V61)=1,1,0)) -> 1
A62: 4 I/V converters and output legs | B62: C422 | C62: 1 | D62: VREF HF decoupling, between the two OPA2210 | E62: 100 nF | F62: 0402 | G62: 16 V X7R | H62: Samsung CL05B104KO5NNNC | I62: C1525 | J62: Basic | K62: Yes | M62: 2 | N62: 0 | O62: 0.003 | P62: 0.0011 | Q62: Quote | R62: =IF($K62="Yes",$C62*Cost!$B$6,0) -> 5 | S62: =IF($K62="Yes",$C62*Cost!$B$6*$O62,0) -> 0.015 | T62: =IF($K62="Yes",$C62*Cost!$B$7*$P62,0) -> 0.11 | V62: =IF(AND($K62="Yes",$B62<>"PCB",LEFT($I62,1)="C"),$I62,"") -> C1525 | W62: =IF($V62="",0,IF(COUNTIF($V$4:$V62,$V62)=1,1,0)) -> 0
A63: 4 I/V converters and output legs | B63: C423–C426 | C63: 4 | D63: OPA2210 V+ and V− | E63: 100 nF | F63: 0402 | G63: 16 V X7R | H63: Samsung CL05B104KO5NNNC | I63: C1525 | J63: Basic | K63: Yes | M63: 2 | N63: 0 | O63: 0.003 | P63: 0.0011 | Q63: Quote | R63: =IF($K63="Yes",$C63*Cost!$B$6,0) -> 20 | S63: =IF($K63="Yes",$C63*Cost!$B$6*$O63,0) -> 0.06 | T63: =IF($K63="Yes",$C63*Cost!$B$7*$P63,0) -> 0.44 | V63: =IF(AND($K63="Yes",$B63<>"PCB",LEFT($I63,1)="C"),$I63,"") -> C1525 | W63: =IF($V63="",0,IF(COUNTIF($V$4:$V63,$V63)=1,1,0)) -> 0
A64: 4 I/V converters and output legs | B64: U401, U402 | C64: 2 | D64: Op-amp, dual, output legs; U401 = L+ and L−, U402 = R+ and R− (one amplifier per leg) | E64: — | F64: VSON-10 3 × 3 mm | G64: Isc +145/−130 mA typ; thermal pad to V− | H64: TI OPA1622IDRCR | I64: C2876559 | J64: Extended | K64: Yes | L64: Yes | M64: 11 | N64: 0 | O64: 1.7871 | P64: 1.6912 | Q64: Quote | R64: =IF($K64="Yes",$C64*Cost!$B$6,0) -> 10 | S64: =IF($K64="Yes",$C64*Cost!$B$6*$O64,0) -> 17.871 | T64: =IF($K64="Yes",$C64*Cost!$B$7*$P64,0) -> 338.24 | V64: =IF(AND($K64="Yes",$B64<>"PCB",LEFT($I64,1)="C"),$I64,"") -> C2876559 | W64: =IF($V64="",0,IF(COUNTIF($V$4:$V64,$V64)=1,1,0)) -> 1
A65: 4 I/V converters and output legs | B65: R401–R416 | C65: 16 | D65: 4-resistor difference amplifier per leg, fed by the I/V outputs (leg+ = I/V(DAC−) − I/V(DAC+), leg− the swap) | E65: 2.00 kΩ | F65: 0603 | G65: 0.1 %, 25 ppm thin film | H65: YAGEO RT0603BRD072KL | I65: C728588 | J65: Extended | K65: Yes | M65: 2 | N65: 0 | O65: 0.034 | P65: 0.025 | Q65: Quote | R65: =IF($K65="Yes",$C65*Cost!$B$6,0) -> 80 | S65: =IF($K65="Yes",$C65*Cost!$B$6*$O65,0) -> 2.72 | T65: =IF($K65="Yes",$C65*Cost!$B$7*$P65,0) -> 40 | V65: =IF(AND($K65="Yes",$B65<>"PCB",LEFT($I65,1)="C"),$I65,"") -> C728588 | W65: =IF($V65="",0,IF(COUNTIF($V$4:$V65,$V65)=1,1,0)) -> 1
A66: 4 I/V converters and output legs | B66: C401–C408 | C66: 8 | D66: Across each feedback and ground-leg resistor (≈ 241 kHz with 2 kΩ) | E66: 330 pF | F66: 0603 | G66: 50 V C0G | H66: Samsung CL10C331JB8NNNC | I66: C1664 | J66: Basic | K66: Yes | M66: 2 | N66: 0 | O66: 0.005 | P66: 0.0019 | Q66: Quote | R66: =IF($K66="Yes",$C66*Cost!$B$6,0) -> 40 | S66: =IF($K66="Yes",$C66*Cost!$B$6*$O66,0) -> 0.2 | T66: =IF($K66="Yes",$C66*Cost!$B$7*$P66,0) -> 1.52 | V66: =IF(AND($K66="Yes",$B66<>"PCB",LEFT($I66,1)="C"),$I66,"") -> C1664 | W66: =IF($V66="",0,IF(COUNTIF($V$4:$V66,$V66)=1,1,0)) -> 0
A67: 4 I/V converters and output legs | B67: R417–R420 | C67: 4 | D67: Output link per leg (0 Ω; fit 0.47 Ω only if the capacitive-load test needs it) | E67: 0 Ω | F67: 0402 | G67: jumper | H67: UNI-ROYAL 0402WGF0000TCE | I67: C17168 | J67: Basic | K67: Yes | M67: 2 | N67: 0 | O67: 0.002 | P67: 0.0005 | Q67: Quote | R67: =IF($K67="Yes",$C67*Cost!$B$6,0) -> 20 | S67: =IF($K67="Yes",$C67*Cost!$B$6*$O67,0) -> 0.04 | T67: =IF($K67="Yes",$C67*Cost!$B$7*$P67,0) -> 0.2 | V67: =IF(AND($K67="Yes",$B67<>"PCB",LEFT($I67,1)="C"),$I67,"") -> C17168 | W67: =IF($V67="",0,IF(COUNTIF($V$4:$V67,$V67)=1,1,0)) -> 1
A68: 4 I/V converters and output legs | B68: R421 | C68: 1 | D68: AMP_EN pull-down (both OPA1622 EN pins; amplifiers off by default) | E68: 100 kΩ | F68: 0402 | G68: 1 % | H68: UNI-ROYAL 0402WGF1003TCE | I68: C25741 | J68: Basic | K68: Yes | M68: 2 | N68: 0 | O68: 0.002 | P68: 0.0005 | Q68: Quote | R68: =IF($K68="Yes",$C68*Cost!$B$6,0) -> 5 | S68: =IF($K68="Yes",$C68*Cost!$B$6*$O68,0) -> 0.01 | T68: =IF($K68="Yes",$C68*Cost!$B$7*$P68,0) -> 0.05 | V68: =IF(AND($K68="Yes",$B68<>"PCB",LEFT($I68,1)="C"),$I68,"") -> C25741 | W68: =IF($V68="",0,IF(COUNTIF($V$4:$V68,$V68)=1,1,0)) -> 0
A69: 4 I/V converters and output legs | B69: C409–C412 | C69: 4 | D69: OPA1622 V+ and V− | E69: 100 nF | F69: 0402 | G69: 16 V X7R | H69: Samsung CL05B104KO5NNNC | I69: C1525 | J69: Basic | K69: Yes | M69: 2 | N69: 0 | O69: 0.003 | P69: 0.0011 | Q69: Quote | R69: =IF($K69="Yes",$C69*Cost!$B$6,0) -> 20 | S69: =IF($K69="Yes",$C69*Cost!$B$6*$O69,0) -> 0.06 | T69: =IF($K69="Yes",$C69*Cost!$B$7*$P69,0) -> 0.44 | V69: =IF(AND($K69="Yes",$B69<>"PCB",LEFT($I69,1)="C"),$I69,"") -> C1525 | W69: =IF($V69="",0,IF(COUNTIF($V$4:$V69,$V69)=1,1,0)) -> 0
A70: 4 I/V converters and output legs | B70: C413–C416 | C70: 4 | D70: OPA1622 local bulk, V+ and V− | E70: 10 µF | F70: 0805 | G70: 25 V X5R | H70: Samsung CL21A106KAYNNNE | I70: C15850 | J70: Basic | K70: Yes | M70: 2 | N70: 0 | O70: 0.02 | P70: 0.0077 | Q70: Quote | R70: =IF($K70="Yes",$C70*Cost!$B$6,0) -> 20 | S70: =IF($K70="Yes",$C70*Cost!$B$6*$O70,0) -> 0.4 | T70: =IF($K70="Yes",$C70*Cost!$B$7*$P70,0) -> 3.08 | V70: =IF(AND($K70="Yes",$B70<>"PCB",LEFT($I70,1)="C"),$I70,"") -> C15850 | W70: =IF($V70="",0,IF(COUNTIF($V$4:$V70,$V70)=1,1,0)) -> 1
A71: 5 Power: domains, current limit and ±3.8 V rails | B71: U502 | C71: 1 | D71: LDO 3.3 V, always-on MCU domain (3V3M) | E71: 3.3 V, 500 mA | F71: SOT-23-5 | G71: ±2 %, 100 mV at 100 mA | H71: Microne ME6211C33M5G-N | I71: C82942 | J71: Extended | K71: Yes | M71: 5 | N71: 0 | O71: 0.0603 | P71: 0.049 | Q71: Quote | R71: =IF($K71="Yes",$C71*Cost!$B$6,0) -> 5 | S71: =IF($K71="Yes",$C71*Cost!$B$6*$O71,0) -> 0.3015 | T71: =IF($K71="Yes",$C71*Cost!$B$7*$P71,0) -> 4.9 | V71: =IF(AND($K71="Yes",$B71<>"PCB",LEFT($I71,1)="C"),$I71,"") -> C82942 | W71: =IF($V71="",0,IF(COUNTIF($V$4:$V71,$V71)=1,1,0)) -> 1
A72: 5 Power: domains, current limit and ±3.8 V rails | B72: C501 | C72: 1 | D72: ME6211 (3V3M) input | E72: 1 µF | F72: 0603 | G72: 25 V X5R | H72: Samsung CL10A105KB8NNNC | I72: C15849 | J72: Basic | K72: Yes | M72: 2 | N72: 0 | O72: 0.006 | P72: 0.0022 | Q72: Quote | R72: =IF($K72="Yes",$C72*Cost!$B$6,0) -> 5 | S72: =IF($K72="Yes",$C72*Cost!$B$6*$O72,0) -> 0.03 | T72: =IF($K72="Yes",$C72*Cost!$B$7*$P72,0) -> 0.22 | V72: =IF(AND($K72="Yes",$B72<>"PCB",LEFT($I72,1)="C"),$I72,"") -> C15849 | W72: =IF($V72="",0,IF(COUNTIF($V$4:$V72,$V72)=1,1,0)) -> 0
A73: 5 Power: domains, current limit and ±3.8 V rails | B73: C502 | C73: 1 | D73: ME6211 (3V3M) output | E73: 1 µF | F73: 0603 | G73: 25 V X5R | H73: Samsung CL10A105KB8NNNC | I73: C15849 | J73: Basic | K73: Yes | M73: 2 | N73: 0 | O73: 0.006 | P73: 0.0022 | Q73: Quote | R73: =IF($K73="Yes",$C73*Cost!$B$6,0) -> 5 | S73: =IF($K73="Yes",$C73*Cost!$B$6*$O73,0) -> 0.03 | T73: =IF($K73="Yes",$C73*Cost!$B$7*$P73,0) -> 0.22 | V73: =IF(AND($K73="Yes",$B73<>"PCB",LEFT($I73,1)="C"),$I73,"") -> C15849 | W73: =IF($V73="",0,IF(COUNTIF($V$4:$V73,$V73)=1,1,0)) -> 0
A74: 5 Power: domains, current limit and ±3.8 V rails | B74: U504 | C74: 1 | D74: LDO 3.3 V, switched audio-digital domain (3V3D: CPLD, oscillators, DAC DVCC, 1.3 V LDO), CE = AUD_EN | E74: 3.3 V, 500 mA | F74: SOT-23-5 | G74: ±2 % | H74: Microne ME6211C33M5G-N | I74: C82942 | J74: Extended | K74: Yes | M74: 5 | N74: 0 | O74: 0.0603 | P74: 0.049 | Q74: Quote | R74: =IF($K74="Yes",$C74*Cost!$B$6,0) -> 5 | S74: =IF($K74="Yes",$C74*Cost!$B$6*$O74,0) -> 0.3015 | T74: =IF($K74="Yes",$C74*Cost!$B$7*$P74,0) -> 4.9 | V74: =IF(AND($K74="Yes",$B74<>"PCB",LEFT($I74,1)="C"),$I74,"") -> C82942 | W74: =IF($V74="",0,IF(COUNTIF($V$4:$V74,$V74)=1,1,0)) -> 0
A75: 5 Power: domains, current limit and ±3.8 V rails | B75: C503 | C75: 1 | D75: ME6211 (3V3D) input | E75: 1 µF | F75: 0603 | G75: 25 V X5R | H75: Samsung CL10A105KB8NNNC | I75: C15849 | J75: Basic | K75: Yes | M75: 2 | N75: 0 | O75: 0.006 | P75: 0.0022 | Q75: Quote | R75: =IF($K75="Yes",$C75*Cost!$B$6,0) -> 5 | S75: =IF($K75="Yes",$C75*Cost!$B$6*$O75,0) -> 0.03 | T75: =IF($K75="Yes",$C75*Cost!$B$7*$P75,0) -> 0.22 | V75: =IF(AND($K75="Yes",$B75<>"PCB",LEFT($I75,1)="C"),$I75,"") -> C15849 | W75: =IF($V75="",0,IF(COUNTIF($V$4:$V75,$V75)=1,1,0)) -> 0
A76: 5 Power: domains, current limit and ±3.8 V rails | B76: C504 | C76: 1 | D76: ME6211 (3V3D) output | E76: 1 µF | F76: 0603 | G76: 25 V X5R | H76: Samsung CL10A105KB8NNNC | I76: C15849 | J76: Basic | K76: Yes | M76: 2 | N76: 0 | O76: 0.006 | P76: 0.0022 | Q76: Quote | R76: =IF($K76="Yes",$C76*Cost!$B$6,0) -> 5 | S76: =IF($K76="Yes",$C76*Cost!$B$6*$O76,0) -> 0.03 | T76: =IF($K76="Yes",$C76*Cost!$B$7*$P76,0) -> 0.22 | V76: =IF(AND($K76="Yes",$B76<>"PCB",LEFT($I76,1)="C"),$I76,"") -> C15849 | W76: =IF($V76="",0,IF(COUNTIF($V$4:$V76,$V76)=1,1,0)) -> 0
... A88: 5 Power: domains, current limit and ±3.8 V rails | B88: FB501 | C88: 1 | D88: Ferrite bead, 5V_ANA → LM27762 VIN (charge-pump input ripple) | E88: 120 Ω @ 100 MHz | F88: 0603 | G88: 2 A, 50 mΩ | H88: Murata BLM18PG121SN1D | I88: C14709 | J88: Basic | K88: Yes | M88: 2 | N88: 0 | O88: 0.0157 | P88: 0.008 | Q88: Quote | R88: =IF($K88="Yes",$C88*Cost!$B$6,0) -> 5 | S88: =IF($K88="Yes",$C88*Cost!$B$6*$O88,0) -> 0.0785 | T88: =IF($K88="Yes",$C88*Cost!$B$7*$P88,0) -> 0.8 | V88: =IF(AND($K88="Yes",$B88<>"PCB",LEFT($I88,1)="C"),$I88,"") -> C14709 | W88: =IF($V88="",0,IF(COUNTIF($V$4:$V88,$V88)=1,1,0)) -> 1
A89: 5 Power: domains, current limit and ±3.8 V rails | B89: U501 | C89: 1 | D89: Charge pump + low-noise LDOs, ±3.8 V from 5V_ANA, EN± = RAIL_EN, PGOOD (active low) | E89: ±3.8 V | F89: WSON-12 2 × 3 mm | G89: ±250 mA, 2 MHz | H89: TI LM27762DSSR | I89: C473398 | J89: Extended | K89: Yes | L89: Yes | M89: 13 | N89: 0 | O89: 1.1014 | P89: 0.75 | Q89: Quote | R89: =IF($K89="Yes",$C89*Cost!$B$6,0) -> 5 | S89: =IF($K89="Yes",$C89*Cost!$B$6*$O89,0) -> 5.507 | T89: =IF($K89="Yes",$C89*Cost!$B$7*$P89,0) -> 75 | V89: =IF(AND($K89="Yes",$B89<>"PCB",LEFT($I89,1)="C"),$I89,"") -> C473398 | W89: =IF($V89="",0,IF(COUNTIF($V$4:$V89,$V89)=1,1,0)) -> 1
A90: 5 Power: domains, current limit and ±3.8 V rails | B90: C507 | C90: 1 | D90: LM27762 input | E90: 10 µF | F90: 0805 | G90: 25 V X5R | H90: Samsung CL21A106KAYNNNE | I90: C15850 | J90: Basic | K90: Yes | M90: 2 | N90: 0 | O90: 0.02 | P90: 0.0077 | Q90: Quote | R90: =IF($K90="Yes",$C90*Cost!$B$6,0) -> 5 | S90: =IF($K90="Yes",$C90*Cost!$B$6*$O90,0) -> 0.1 | T90: =IF($K90="Yes",$C90*Cost!$B$7*$P90,0) -> 0.77 | V90: =IF(AND($K90="Yes",$B90<>"PCB",LEFT($I90,1)="C"),$I90,"") -> C15850 | W90: =IF($V90="",0,IF(COUNTIF($V$4:$V90,$V90)=1,1,0)) -> 0
A91: 5 Power: domains, current limit and ±3.8 V rails | B91: C508 | C91: 1 | D91: LM27762 flying capacitor | E91: 1 µF | F91: 0603 | G91: 25 V X5R | H91: Samsung CL10A105KB8NNNC | I91: C15849 | J91: Basic | K91: Yes | M91: 2 | N91: 0 | O91: 0.006 | P91: 0.0022 | Q91: Quote | R91: =IF($K91="Yes",$C91*Cost!$B$6,0) -> 5 | S91: =IF($K91="Yes",$C91*Cost!$B$6*$O91,0) -> 0.03 | T91: =IF($K91="Yes",$C91*Cost!$B$7*$P91,0) -> 0.22 | V91: =IF(AND($K91="Yes",$B91<>"PCB",LEFT($I91,1)="C"),$I91,"") -> C15849 | W91: =IF($V91="",0,IF(COUNTIF($V$4:$V91,$V91)=1,1,0)) -> 0
A92: 5 Power: domains, current limit and ±3.8 V rails | B92: C509 | C92: 1 | D92: LM27762 charge-pump output (CP) | E92: 10 µF | F92: 0805 | G92: 25 V X5R | H92: Samsung CL21A106KAYNNNE | I92: C15850 | J92: Basic | K92: Yes | M92: 2 | N92: 0 | O92: 0.02 | P92: 0.0077 | Q92: Quote | R92: =IF($K92="Yes",$C92*Cost!$B$6,0) -> 5 | S92: =IF($K92="Yes",$C92*Cost!$B$6*$O92,0) -> 0.1 | T92: =IF($K92="Yes",$C92*Cost!$B$7*$P92,0) -> 0.77 | V92: =IF(AND($K92="Yes",$B92<>"PCB",LEFT($I92,1)="C"),$I92,"") -> C15850 | W92: =IF($V92="",0,IF(COUNTIF($V$4:$V92,$V92)=1,1,0)) -> 0
A93: 5 Power: domains, current limit and ±3.8 V rails | B93: C510 | C93: 1 | D93: LM27762 OUT+ | E93: 10 µF | F93: 0805 | G93: 25 V X5R | H93: Samsung CL21A106KAYNNNE | I93: C15850 | J93: Basic | K93: Yes | M93: 2 | N93: 0 | O93: 0.02 | P93: 0.0077 | Q93: Quote | R93: =IF($K93="Yes",$C93*Cost!$B$6,0) -> 5 | S93: =IF($K93="Yes",$C93*Cost!$B$6*$O93,0) -> 0.1 | T93: =IF($K93="Yes",$C93*Cost!$B$7*$P93,0) -> 0.77 | V93: =IF(AND($K93="Yes",$B93<>"PCB",LEFT($I93,1)="C"),$I93,"") -> C15850 | W93: =IF($V93="",0,IF(COUNTIF($V$4:$V93,$V93)=1,1,0)) -> 0
A94: 5 Power: domains, current limit and ±3.8 V rails | B94: C511 | C94: 1 | D94: LM27762 OUT− | E94: 10 µF | F94: 0805 | G94: 25 V X5R | H94: Samsung CL21A106KAYNNNE | I94: C15850 | J94: Basic | K94: Yes | M94: 2 | N94: 0 | O94: 0.02 | P94: 0.0077 | Q94: Quote | R94: =IF($K94="Yes",$C94*Cost!$B$6,0) -> 5 | S94: =IF($K94="Yes",$C94*Cost!$B$6*$O94,0) -> 0.1 | T94: =IF($K94="Yes",$C94*Cost!$B$7*$P94,0) -> 0.77 | V94: =IF(AND($K94="Yes",$B94<>"PCB",LEFT($I94,1)="C"),$I94,"") -> C15850 | W94: =IF($V94="",0,IF(COUNTIF($V$4:$V94,$V94)=1,1,0)) -> 0
A95: 5 Power: domains, current limit and ±3.8 V rails | B95: R501, R515 | C95: 2 | D95: LM27762 FB+ divider, top: 100 kΩ + 100 kΩ + 15 kΩ = 215 kΩ (+3.780 V = 1.2 × 315/100; 3.673–3.890 V incl. VFB and 1 % resistors) | E95: 100 kΩ | F95: 0402 | G95: 1 % | H95: UNI-ROYAL 0402WGF1003TCE | I95: C25741 | J95: Basic | K95: Yes | M95: 2 | N95: 0 | O95: 0.002 | P95: 0.0005 | Q95: Quote | R95: =IF($K95="Yes",$C95*Cost!$B$6,0) -> 10 | S95: =IF($K95="Yes",$C95*Cost!$B$6*$O95,0) -> 0.02 | T95: =IF($K95="Yes",$C95*Cost!$B$7*$P95,0) -> 0.1 | V95: =IF(AND($K95="Yes",$B95<>"PCB",LEFT($I95,1)="C"),$I95,"") -> C25741 | W95: =IF($V95="",0,IF(COUNTIF($V$4:$V95,$V95)=1,1,0)) -> 0
A96: 5 Power: domains, current limit and ±3.8 V rails | B96: R516 | C96: 1 | D96: LM27762 FB+ divider, top, third part | E96: 15 kΩ | F96: 0402 | G96: 1 % | H96: UNI-ROYAL 0402WGF1502TCE | I96: C25756 | J96: Basic | K96: Yes | M96: 2 | N96: 0 | O96: 0.002 | P96: 0.0005 | Q96: Quote | R96: =IF($K96="Yes",$C96*Cost!$B$6,0) -> 5 | S96: =IF($K96="Yes",$C96*Cost!$B$6*$O96,0) -> 0.01 | T96: =IF($K96="Yes",$C96*Cost!$B$7*$P96,0) -> 0.05 | V96: =IF(AND($K96="Yes",$B96<>"PCB",LEFT($I96,1)="C"),$I96,"") -> C25756 | W96: =IF($V96="",0,IF(COUNTIF($V$4:$V96,$V96)=1,1,0)) -> 0
A97: 5 Power: domains, current limit and ±3.8 V rails | B97: R502 | C97: 1 | D97: LM27762 FB+ divider, bottom (≥ 50 kΩ per datasheet) | E97: 100 kΩ | F97: 0402 | G97: 1 % | H97: UNI-ROYAL 0402WGF1003TCE | I97: C25741 | J97: Basic | K97: Yes | M97: 2 | N97: 0 | O97: 0.002 | P97: 0.0005 | Q97: Quote | R97: =IF($K97="Yes",$C97*Cost!$B$6,0) -> 5 | S97: =IF($K97="Yes",$C97*Cost!$B$6*$O97,0) -> 0.01 | T97: =IF($K97="Yes",$C97*Cost!$B$7*$P97,0) -> 0.05 | V97: =IF(AND($K97="Yes",$B97<>"PCB",LEFT($I97,1)="C"),$I97,"") -> C25741 | W97: =IF($V97="",0,IF(COUNTIF($V$4:$V97,$V97)=1,1,0)) -> 0
A98: 5 Power: domains, current limit and ±3.8 V rails | B98: R503, R517 | C98: 2 | D98: LM27762 FB− divider, top: 100 kΩ + 100 kΩ + 5.1 kΩ = 205.1 kΩ (−3.722 V = −1.22 × 305.1/100; 3.618–3.828 V incl. VFB and 1 % resistors) | E98: 100 kΩ | F98: 0402 | G98: 1 % | H98: UNI-ROYAL 0402WGF1003TCE | I98: C25741 | J98: Basic | K98: Yes | M98: 2 | N98: 0 | O98: 0.002 | P98: 0.0005 | Q98: Quote | R98: =IF($K98="Yes",$C98*Cost!$B$6,0) -> 10 | S98: =IF($K98="Yes",$C98*Cost!$B$6*$O98,0) -> 0.02 | T98: =IF($K98="Yes",$C98*Cost!$B$7*$P98,0) -> 0.1 | V98: =IF(AND($K98="Yes",$B98<>"PCB",LEFT($I98,1)="C"),$I98,"") -> C25741 | W98: =IF($V98="",0,IF(COUNTIF($V$4:$V98,$V98)=1,1,0)) -> 0
A99: 5 Power: domains, current limit and ±3.8 V rails | B99: R518 | C99: 1 | D99: LM27762 FB− divider, top, third part (was 10 kΩ; lowers |V−| by 60 mV for charge-pump headroom) | E99: 5.1 kΩ | F99: 0402 | G99: 1 % | H99: UNI-ROYAL 0402WGF5101TCE | I99: C25905 | J99: Basic | K99: Yes | M99: 2 | N99: 0 | O99: 0.002 | P99: 0.0005 | Q99: Quote | R99: =IF($K99="Yes",$C99*Cost!$B$6,0) -> 5 | S99: =IF($K99="Yes",$C99*Cost!$B$6*$O99,0) -> 0.01 | T99: =IF($K99="Yes",$C99*Cost!$B$7*$P99,0) -> 0.05 | V99: =IF(AND($K99="Yes",$B99<>"PCB",LEFT($I99,1)="C"),$I99,"") -> C25905 | W99: =IF($V99="",0,IF(COUNTIF($V$4:$V99,$V99)=1,1,0)) -> 0
A100: 5 Power: domains, current limit and ±3.8 V rails | B100: R504 | C100: 1 | D100: LM27762 FB− divider, bottom (≥ 50 kΩ per datasheet) | E100: 100 kΩ | F100: 0402 | G100: 1 % | H100: UNI-ROYAL 0402WGF1003TCE | I100: C25741 | J100: Basic | K100: Yes | M100: 2 | N100: 0 | O100: 0.002 | P100: 0.0005 | Q100: Quote | R100: =IF($K100="Yes",$C100*Cost!$B$6,0) -> 5 | S100: =IF($K100="Yes",$C100*Cost!$B$6*$O100,0) -> 0.01 | T100: =IF($K100="Yes",$C100*Cost!$B$7*$P100,0) -> 0.05 | V100: =IF(AND($K100="Yes",$B100<>"PCB",LEFT($I100,1)="C"),$I100,"") -> C25741 | W100: =IF($V100="",0,IF(COUNTIF($V$4:$V100,$V100)=1,1,0)) -> 0
A101: 5 Power: domains, current limit and ±3.8 V rails | B101: R505 | C101: 1 | D101: LM27762 PGOOD pull-up to 3V3M (MCU reads RAILS_OK_N) | E101: 100 kΩ | F101: 0402 | G101: 1 % | H101: UNI-ROYAL 0402WGF1003TCE | I101: C25741 | J101: Basic | K101: Yes | M101: 2 | N101: 0 | O101: 0.002 | P101: 0.0005 | Q101: Quote | R101: =IF($K101="Yes",$C101*Cost!$B$6,0) -> 5 | S101: =IF($K101="Yes",$C101*Cost!$B$6*$O101,0) -> 0.01 | T101: =IF($K101="Yes",$C101*Cost!$B$7*$P101,0) -> 0.05 | V101: =IF(AND($K101="Yes",$B101<>"PCB",LEFT($I101,1)="C"),$I101,"") -> C25741 | W101: =IF($V101="",0,IF(COUNTIF($V$4:$V101,$V101)=1,1,0)) -> 0
... A122: 6 Protection and control | B122: R618 | C122: 1 | D122: AMP_EN series resistor from the MCU GPIO | E122: 10 kΩ | F122: 0402 | G122: 1 % | H122: UNI-ROYAL 0402WGF1002TCE | I122: C25744 | J122: Basic | K122: Yes | M122: 2 | N122: 0 | O122: 0.002 | P122: 0.0005 | Q122: Quote | R122: =IF($K122="Yes",$C122*Cost!$B$6,0) -> 5 | S122: =IF($K122="Yes",$C122*Cost!$B$6*$O122,0) -> 0.01 | T122: =IF($K122="Yes",$C122*Cost!$B$7*$P122,0) -> 0.05 | V122: =IF(AND($K122="Yes",$B122<>"PCB",LEFT($I122,1)="C"),$I122,"") -> C25744 | W122: =IF($V122="",0,IF(COUNTIF($V$4:$V122,$V122)=1,1,0)) -> 0
A123: 7 Outputs, indicators, test, board | B123: J701 | C123: 1 | D123: Jack, 4.4 mm 5-pole balanced (L+, L−, R+, R−, GND) | E123: — | F123: Through-hole | G123: Gold-plated | H123: G-Switch GT-3321667P-01 | I123: C2762984 | J123: Extended | K123: Yes | M123: 0 | N123: 7 | O123: 6.8656 | P123: 4.7574 | Q123: Quote | R123: =IF($K123="Yes",$C123*Cost!$B$6,0) -> 5 | S123: =IF($K123="Yes",$C123*Cost!$B$6*$O123,0) -> 34.328 | T123: =IF($K123="Yes",$C123*Cost!$B$7*$P123,0) -> 475.74 | U123: No cheaper 4.4 mm jack at LCSC; stock 721 | V123: =IF(AND($K123="Yes",$B123<>"PCB",LEFT($I123,1)="C"),$I123,"") -> C2762984 | W123: =IF($V123="",0,IF(COUNTIF($V$4:$V123,$V123)=1,1,0)) -> 1
A124: 7 Outputs, indicators, test, board | B124: J702 | C124: 1 | D124: Jack, 3.5 mm (TRRS body with TRS plugs; ring 2 tied to GND) | E124: — | F124: SMD | G124: Gold-plated, 1 A | H124: HRO PJ-332A-6A | I124: C2848643 | J124: Extended | K124: Yes | M124: 6 | N124: 0 | O124: 0.2921 | P124: 0.2326 | Q124: Quote | R124: =IF($K124="Yes",$C124*Cost!$B$6,0) -> 5 | S124: =IF($K124="Yes",$C124*Cost!$B$6*$O124,0) -> 1.4605 | T124: =IF($K124="Yes",$C124*Cost!$B$7*$P124,0) -> 23.26 | U124: JLCPCB marks assembly difficulty "high" | V124: =IF(AND($K124="Yes",$B124<>"PCB",LEFT($I124,1)="C"),$I124,"") -> C2848643 | W124: =IF($V124="",0,IF(COUNTIF($V$4:$V124,$V124)=1,1,0)) -> 1
A125: 7 Outputs, indicators, test, board | B125: D701–D704 | C125: 4 | D125: ESD diode, bidirectional, one per jack leg (legs swing ≤ ±3.8 V) | E125: 5 V | F125: SOD-523 | G125: Vrwm 5 V, 12 pF | H125: GOODWORK LESD5D5.0CT1G | I125: C41399463 | J125: Extended | K125: Yes | M125: 2 | N125: 0 | O125: 0.02 | P125: 0.015 | Q125: Quote | R125: =IF($K125="Yes",$C125*Cost!$B$6,0) -> 20 | S125: =IF($K125="Yes",$C125*Cost!$B$6*$O125,0) -> 0.4 | T125: =IF($K125="Yes",$C125*Cost!$B$7*$P125,0) -> 6 | V125: =IF(AND($K125="Yes",$B125<>"PCB",LEFT($I125,1)="C"),$I125,"") -> C41399463 | W125: =IF($V125="",0,IF(COUNTIF($V$4:$V125,$V125)=1,1,0)) -> 1
A126: 7 Outputs, indicators, test, board | B126: D705 | C126: 1 | D126: LED, status (green), 3.3 V GPIO | E126: Green | F126: 0805 | G126: 2.6–3.1 V | H126: Hubei KENTO KT-0805G | I126: C2297 | J126: Basic | K126: Yes | M126: 2 | N126: 0 | O126: 0.0163 | P126: 0.01 | Q126: Quote | R126: =IF($K126="Yes",$C126*Cost!$B$6,0) -> 5 | S126: =IF($K126="Yes",$C126*Cost!$B$6*$O126,0) -> 0.0815 | T126: =IF($K126="Yes",$C126*Cost!$B$7*$P126,0) -> 1 | V126: =IF(AND($K126="Yes",$B126<>"PCB",LEFT($I126,1)="C"),$I126,"") -> C2297 | W126: =IF($V126="",0,IF(COUNTIF($V$4:$V126,$V126)=1,1,0)) -> 1
A127: 7 Outputs, indicators, test, board | B127: D706 | C127: 1 | D127: LED, fault (red), 3.3 V GPIO | E127: Red | F127: 0603 | G127: 1.8–2.4 V | H127: Hubei KENTO KT-0603R | I127: C2286 | J127: Basic | K127: Yes | M127: 2 | N127: 0 | O127: 0.0075 | P127: 0.0075 | Q127: Quote | R127: =IF($K127="Yes",$C127*Cost!$B$6,0) -> 5 | S127: =IF($K127="Yes",$C127*Cost!$B$6*$O127,0) -> 0.0375 | T127: =IF($K127="Yes",$C127*Cost!$B$7*$P127,0) -> 0.75 | V127: =IF(AND($K127="Yes",$B127<>"PCB",LEFT($I127,1)="C"),$I127,"") -> C2286 | W127: =IF($V127="",0,IF(COUNTIF($V$4:$V127,$V127)=1,1,0)) -> 1
A128: 7 Outputs, indicators, test, board | B128: R701, R702 | C128: 2 | D128: LED series resistors (≈ 0.5–0.7 mA) | E128: 2.2 kΩ | F128: 0402 | G128: 1 % | H128: UNI-ROYAL 0402WGF2201TCE | I128: C25879 | J128: Basic | K128: Yes | M128: 2 | N128: 0 | O128: 0.002 | P128: 0.0005 | Q128: Quote | R128: =IF($K128="Yes",$C128*Cost!$B$6,0) -> 10 | S128: =IF($K128="Yes",$C128*Cost!$B$6*$O128,0) -> 0.02 | T128: =IF($K128="Yes",$C128*Cost!$B$7*$P128,0) -> 0.1 | V128: =IF(AND($K128="Yes",$B128<>"PCB",LEFT($I128,1)="C"),$I128,"") -> C25879 | W128: =IF($V128="",0,IF(COUNTIF($V$4:$V128,$V128)=1,1,0)) -> 0
A129: 7 Outputs, indicators, test, board | B129: J703 | C129: 1 | D129: Header, 3.3 V I²S test port (MCLK monitor output, BCLK, LRCLK, SDATA, GND, 3V3 ref); an external source drives only BCLK, LRCLK and SDATA | E129: 1 × 6 | F129: 2.54 mm | G129: — | H129: Generic 2.54 mm header | I129: — | J129: — | K129: DNF | M129: 0 | N129: 0 | O129: 0.1 | P129: 0.1 | Q129: Estimate | R129: =IF($K129="Yes",$C129*Cost!$B$6,0) -> 0 | S129: =IF($K129="Yes",$C129*Cost!$B$6*$O129,0) -> 0 | T129: =IF($K129="Yes",$C129*Cost!$B$7*$P129,0) -> 0 | V129: =IF(AND($K129="Yes",$B129<>"PCB",LEFT($I129,1)="C"),$I129,"") | W129: =IF($V129="",0,IF(COUNTIF($V$4:$V129,$V129)=1,1,0)) -> 0
A130: 7 Outputs, indicators, test, board | B130: R703 | C130: 1 | D130: DNF (fitted with J703): 1 kΩ in series with the J703 MCLK pin, which is a monitor output only (limits contention if an instrument drives it) | E130: 1 kΩ | F130: 0402 | G130: 1 % | H130: UNI-ROYAL 0402WGF1001TCE | I130: C11702 | J130: Basic | K130: DNF | M130: 2 | N130: 0 | O130: 0.002 | P130: 0.0005 | Q130: Quote | R130: =IF($K130="Yes",$C130*Cost!$B$6,0) -> 0 | S130: =IF($K130="Yes",$C130*Cost!$B$6*$O130,0) -> 0 | T130: =IF($K130="Yes",$C130*Cost!$B$7*$P130,0) -> 0 | V130: =IF(AND($K130="Yes",$B130<>"PCB",LEFT($I130,1)="C"),$I130,"") | W130: =IF($V130="",0,IF(COUNTIF($V$4:$V130,$V130)=1,1,0)) -> 0
A131: 7 Outputs, indicators, test, board | B131: TP701–TP729 | C131: 29 | D131: Test pads: rails (5V_SYS, 5V_ANA, 3V3M, 3V3D, 3V3A, 1V3, +3.78 V, −3.72 V), clocks incl. the shared family-clock node, OSC48_EN, OSC44_EN, I²S, EN/PG/FLT/FAULT nodes, 4 GND | E131: — | F131: Pad | G131: — | H131: No part | I131: — | J131: — | K131: No part | M131: 0 | N131: 0 | O131: 0 | P131: 0 | Q131: Estimate | R131: =IF($K131="Yes",$C131*Cost!$B$6,0) -> 0 | S131: =IF($K131="Yes",$C131*Cost!$B$6*$O131,0) -> 0 | T131: =IF($K131="Yes",$C131*Cost!$B$7*$P131,0) -> 0 | V131: =IF(AND($K131="Yes",$B131<>"PCB",LEFT($I131,1)="C"),$I131,"") | W131: =IF($V131="",0,IF(COUNTIF($V$4:$V131,$V131)=1,1,0)) -> 0
...

Sheet Purchasing list
A1: Purchasing list — one line per LCSC number (fitted parts)
A2: Qty per board is summed from the Parts list by LCSC number. Line cost = qty for the run × sample-run-tier price, with a US$0.10 minimum per line for parts under US$0.05 (inputs on the Cost sheet); the Cost sheet takes the parts cost from this list. The bare PCBs are costed on the Cost sheet.
A3: Item | B3: Part type | C3: Part number (MPN) | D3: Value | E3: Package | F3: Rating / tolerance | G3: LCSC no. | H3: JLCPCB library type | I3: Designators | J3: Qty per board | K3: Qty for 5-board run | L3: Unit price US$ (sample-run tier) | M3: Unit price US$ (100-board tier) | N3: Leadless (X-ray) | O3: Minimum applies (< US$0.05) | P3: Line cost US$, 5-board run (incl. minimum) | Q3: Ext. per board US$ (100-board tier)
A4: 1 | B4: Connector | C4: G-Switch GT-3321667P-01 | D4: — | E4: Through-hole | F4: Gold-plated | G4: C2762984 | H4: Extended | I4: J701 | J4: =SUMIFS('Parts list'!$C$4:$C$133,'Parts list'!$I$4:$I$133,$G4,'Parts list'!$K$4:$K$133,"Yes") -> 1 | K4: =$J4*Cost!$B$6 -> 5 | L4: 6.8656 | M4: 4.7574 | O4: =IF(AND($L4>0,$L4<Cost!$B$9),"Yes","") | P4: =IF($O4="Yes",MAX($K4*$L4,Cost!$B$8),$K4*$L4) -> 34.328 | Q4: =$J4*$M4 -> 4.7574
A5: 2 | B5: IC | C5: TI OPA1622IDRCR | D5: — | E5: VSON-10 3 × 3 mm | F5: Isc +145/−130 mA typ; thermal pad to V− | G5: C2876559 | H5: Extended | I5: U401, U402 | J5: =SUMIFS('Parts list'!$C$4:$C$133,'Parts list'!$I$4:$I$133,$G5,'Parts list'!$K$4:$K$133,"Yes") -> 2 | K5: =$J5*Cost!$B$6 -> 10 | L5: 1.7871 | M5: 1.6912 | N5: Yes | O5: =IF(AND($L5>0,$L5<Cost!$B$9),"Yes","") | P5: =IF($O5="Yes",MAX($K5*$L5,Cost!$B$8),$K5*$L5) -> 17.871 | Q5: =$J5*$M5 -> 3.3824
A6: 3 | B6: IC | C6: ESS ES9018K2M | D6: — | E6: QFN-28 5 × 5 mm | F6: DNR 127 dB-A, THD+N −120 dB (datasheet, current mode) | G6: C2688377 | H6: Extended | I6: U301 | J6: =SUMIFS('Parts list'!$C$4:$C$133,'Parts list'!$I$4:$I$133,$G6,'Parts list'!$K$4:$K$133,"Yes") -> 1 | K6: =$J6*Cost!$B$6 -> 5 | L6: 3.4678 | M6: 2.28 | N6: Yes | O6: =IF(AND($L6>0,$L6<Cost!$B$9),"Yes","") | P6: =IF($O6="Yes",MAX($K6*$L6,Cost!$B$8),$K6*$L6) -> 17.339 | Q6: =$J6*$M6 -> 2.28
A7: 4 | B7: IC | C7: WCH CH32V307RCT6 | D7: — | E7: LQFP-64 10 × 10 mm | F7: 144 MHz, 3.3 V | G7: C2988083 | H7: Extended | I7: U201 | J7: =SUMIFS('Parts list'!$C$4:$C$133,'Parts list'!$I$4:$I$133,$G7,'Parts list'!$K$4:$K$133,"Yes") -> 1 | K7: =$J7*Cost!$B$6 -> 5 | L7: 3.45 | M7: 2.33 | O7: =IF(AND($L7>0,$L7<Cost!$B$9),"Yes","") | P7: =IF($O7="Yes",MAX($K7*$L7,Cost!$B$8),$K7*$L7) -> 17.25 | Q7: =$J7*$M7 -> 2.33
A8: 5 | B8: IC | C8: TI OPA2210IDR | D8: — | E8: SOIC-8 | F8: Vos ±35 µV max, 2.2 nV/√Hz, 18 MHz, CM (V−)+1.5 V to (V+)−1.5 V, 2.5 mA/ch max | G8: C1849415 | H8: Extended | I8: U403, U404 | J8: =SUMIFS('Parts list'!$C$4:$C$133,'Parts list'!$I$4:$I$133,$G8,'Parts list'!$K$4:$K$133,"Yes") -> 2 | K8: =$J8*Cost!$B$6 -> 10 | L8: 1.0035 | M8: 0.753 | O8: =IF(AND($L8>0,$L8<Cost!$B$9),"Yes","") | P8: =IF($O8="Yes",MAX($K8*$L8,Cost!$B$8),$K8*$L8) -> 10.035 | Q8: =$J8*$M8 -> 1.506
A9: 6 | B9: IC | C9: AGM AGRV2KQ32 | D9: — | E9: QFN-32 4 × 4 mm | F9: 3.3 V | G9: C18208899 | H9: Extended | I9: U202 | J9: =SUMIFS('Parts list'!$C$4:$C$133,'Parts list'!$I$4:$I$133,$G9,'Parts list'!$K$4:$K$133,"Yes") -> 1 | K9: =$J9*Cost!$B$6 -> 5 | L9: 1.6503 | M9: 1.11 | N9: Yes | O9: =IF(AND($L9>0,$L9<Cost!$B$9),"Yes","") | P9: =IF($O9="Yes",MAX($K9*$L9,Cost!$B$8),$K9*$L9) -> 8.2515 | Q9: =$J9*$M9 -> 1.11
A10: 7 | B10: IC | C10: TI LM27762DSSR | D10: ±3.8 V | E10: WSON-12 2 × 3 mm | F10: ±250 mA, 2 MHz | G10: C473398 | H10: Extended | I10: U501 | J10: =SUMIFS('Parts list'!$C$4:$C$133,'Parts list'!$I$4:$I$133,$G10,'Parts list'!$K$4:$K$133,"Yes") -> 1 | K10: =$J10*Cost!$B$6 -> 5 | L10: 1.1014 | M10: 0.75 | N10: Yes | O10: =IF(AND($L10>0,$L10<Cost!$B$9),"Yes","") | P10: =IF($O10="Yes",MAX($K10*$L10,Cost!$B$8),$K10*$L10) -> 5.507 | Q10: =$J10*$M10 -> 0.75
A11: 8 | B11: Oscillator | C11: SCTF SX3M80.000B20F30TNN | D11: 80 MHz | E11: 3.2 × 2.5 mm, 4-pad | F11: ±20 ppm tol., ±30 ppm stab., 40 mA max, duty 45–55 % | G11: C5179978 | H11: Extended | I11: X201 | J11: =SUMIFS('Parts list'!$C$4:$C$133,'Parts list'!$I$4:$I$133,$G11,'Parts list'!$K$4:$K$133,"Yes") -> 1 | K11: =$J11*Cost!$B$6 -> 5 | L11: 0.8916 | M11: 0.7211 | N11: Yes | O11: =IF(AND($L11>0,$L11<Cost!$B$9),"Yes","") | P11: =IF($O11="Yes",MAX($K11*$L11,Cost!$B$8),$K11*$L11) -> 4.458 | Q11: =$J11*$M11 -> 0.7211
A12: 9 | B12: IC | C12: TI TPS2553DBVR | D12: — | E12: SOT-23-6 | F12: 0.075–1.7 A adjustable, 85 mΩ, soft start | G12: C55266 | H12: Extended | I12: U503 | J12: =SUMIFS('Parts list'!$C$4:$C$133,'Parts list'!$I$4:$I$133,$G12,'Parts list'!$K$4:$K$133,"Yes") -> 1 | K12: =$J12*Cost!$B$6 -> 5 | L12: 0.5966 | M12: 0.3262 | O12: =IF(AND($L12>0,$L12<Cost!$B$9),"Yes","") | P12: =IF($O12="Yes",MAX($K12*$L12,Cost!$B$8),$K12*$L12) -> 2.983 | Q12: =$J12*$M12 -> 0.3262
A13: 10 | B13: Oscillator | C13: SCTF SX2M22.5792M20F30TNN | D13: 22.5792 MHz | E13: 2.5 × 2.0 mm, 4-pad | F13: ±20 ppm tol., ±30 ppm stab., 10 mA max | G13: C5452663 | H13: Extended | I13: X203 | J13: =SUMIFS('Parts list'!$C$4:$C$133,'Parts list'!$I$4:$I$133,$G13,'Parts list'!$K$4:$K$133,"Yes") -> 1 | K13: =$J13*Cost!$B$6 -> 5 | L13: 0.5455 | M13: 0.3085 | N13: Yes | O13: =IF(AND($L13>0,$L13<Cost!$B$9),"Yes","") | P13: =IF($O13="Yes",MAX($K13*$L13,Cost!$B$8),$K13*$L13) -> 2.7275 | Q13: =$J13*$M13 -> 0.3085
A14: 11 | B14: Resistor | C14: YAGEO RT0603BRD072KL | D14: 2.00 kΩ | E14: 0603 | F14: 0.1 %, 25 ppm thin film | G14: C728588 | H14: Extended | I14: R401–R416 | J14: =SUMIFS('Parts list'!$C$4:$C$133,'Parts list'!$I$4:$I$133,$G14,'Parts list'!$K$4:$K$133,"Yes") -> 16 | K14: =$J14*Cost!$B$6 -> 80 | L14: 0.034 | M14: 0.025 | O14: =IF(AND($L14>0,$L14<Cost!$B$9),"Yes","") -> Yes | P14: =IF($O14="Yes",MAX($K14*$L14,Cost!$B$8),$K14*$L14) -> 2.72 | Q14: =$J14*$M14 -> 0.4
A15: 12 | B15: Oscillator | C15: YXC OT322524.576MJBA4SL | D15: 24.576 MHz | E15: 3.2 × 2.5 mm, 4-pad | F15: ±10 ppm tol., ±20 ppm stab., 1.8–3.3 V | G15: C2831388 | H15: Extended | I15: X202 | J15: =SUMIFS('Parts list'!$C$4:$C$133,'Parts list'!$I$4:$I$133,$G15,'Parts list'!$K$4:$K$133,"Yes") -> 1 | K15: =$J15*Cost!$B$6 -> 5 | L15: 0.5075 | M15: 0.2907 | N15: Yes | O15: =IF(AND($L15>0,$L15<Cost!$B$9),"Yes","") | P15: =IF($O15="Yes",MAX($K15*$L15,Cost!$B$8),$K15*$L15) -> 2.5375 | Q15: =$J15*$M15 -> 0.2907
A16: 13 | B16: Connector | C16: HRO PJ-332A-6A | D16: — | E16: SMD | F16: Gold-plated, 1 A | G16: C2848643 | H16: Extended | I16: J702 | J16: =SUMIFS('Parts list'!$C$4:$C$133,'Parts list'!$I$4:$I$133,$G16,'Parts list'!$K$4:$K$133,"Yes") -> 1 | K16: =$J16*Cost!$B$6 -> 5 | L16: 0.2921 | M16: 0.2326 | O16: =IF(AND($L16>0,$L16<Cost!$B$9),"Yes","") | P16: =IF($O16="Yes",MAX($K16*$L16,Cost!$B$8),$K16*$L16) -> 1.4605 | Q16: =$J16*$M16 -> 0.2326
A17: 14 | B17: Crystal | C17: YXC X50328MSB2GI | D17: 8 MHz | E17: 5.0 × 3.2 mm, 2-pad | F17: ±10 ppm, CL 20 pF | G17: C115962 | H17: Basic | I17: Y201 | J17: =SUMIFS('Parts list'!$C$4:$C$133,'Parts list'!$I$4:$I$133,$G17,'Parts list'!$K$4:$K$133,"Yes") -> 1 | K17: =$J17*Cost!$B$6 -> 5 | L17: 0.2452 | M17: 0.2 | O17: =IF(AND($L17>0,$L17<Cost!$B$9),"Yes","") | P17: =IF($O17="Yes",MAX($K17*$L17,Cost!$B$8),$K17*$L17) -> 1.226 | Q17: =$J17*$M17 -> 0.2
A18: 15 | B18: IC | C18: TI LP5907MFX-3.3/NOPB | D18: 3.3 V, 250 mA | E18: SOT-23-5 | F18: 6.5 µVrms, ±2 % | G18: C80670 | H18: Extended | I18: U302 | J18: =SUMIFS('Parts list'!$C$4:$C$133,'Parts list'!$I$4:$I$133,$G18,'Parts list'!$K$4:$K$133,"Yes") -> 1 | K18: =$J18*Cost!$B$6 -> 5 | L18: 0.2104 | M18: 0.14 | O18: =IF(AND($L18>0,$L18<Cost!$B$9),"Yes","") | P18: =IF($O18="Yes",MAX($K18*$L18,Cost!$B$8),$K18*$L18) -> 1.052 | Q18: =$J18*$M18 -> 0.14
A19: 16 | B19: IC | C19: ST USBLC6-2SC6 | D19: — | E19: SOT-23-6 | F19: 5.25 V, 3.5 pF | G19: C7519 | H19: Extended | I19: U101 | J19: =SUMIFS('Parts list'!$C$4:$C$133,'Parts list'!$I$4:$I$133,$G19,'Parts list'!$K$4:$K$133,"Yes") -> 1 | K19: =$J19*Cost!$B$6 -> 5 | L19: 0.1844 | M19: 0.1439 | O19: =IF(AND($L19>0,$L19<Cost!$B$9),"Yes","") | P19: =IF($O19="Yes",MAX($K19*$L19,Cost!$B$8),$K19*$L19) -> 0.922 | Q19: =$J19*$M19 -> 0.1439
A20: 17 | B20: N-MOSFET | C20: JSCJ 2N7002 | D20: 2N7002 | E20: SOT-23 | F20: 60 V | G20: C8545 | H20: Basic | I20: Q501; Q601–Q610 | J20: =SUMIFS('Parts list'!$C$4:$C$133,'Parts list'!$I$4:$I$133,$G20,'Parts list'!$K$4:$K$133,"Yes") -> 11 | K20: =$J20*Cost!$B$6 -> 55 | L20: 0.0164 | M20: 0.01 | O20: =IF(AND($L20>0,$L20<Cost!$B$9),"Yes","") -> Yes | P20: =IF($O20="Yes",MAX($K20*$L20,Cost!$B$8),$K20*$L20) -> 0.902 | Q20: =$J20*$M20 -> 0.11
A21: 18 | B21: Capacitor | C21: Samsung CL21A106KAYNNNE | D21: 10 µF | E21: 0805 | F21: 25 V X5R | G21: C15850 | H21: Basic | I21: C413–C416; C507; C509; C510; C511 | J21: =SUMIFS('Parts list'!$C$4:$C$133,'Parts list'!$I$4:$I$133,$G21,'Parts list'!$K$4:$K$133,"Yes") -> 8 | K21: =$J21*Cost!$B$6 -> 40 | L21: 0.02 | M21: 0.0077 | O21: =IF(AND($L21>0,$L21<Cost!$B$9),"Yes","") -> Yes | P21: =IF($O21="Yes",MAX($K21*$L21,Cost!$B$8),$K21*$L21) -> 0.8 | Q21: =$J21*$M21 -> 0.0616
A22: 19 | B22: IC | C22: Microne ME6211C33M5G-N | D22: 3.3 V, 500 mA | E22: SOT-23-5 | F22: ±2 %, 100 mV at 100 mA | G22: C82942 | H22: Extended | I22: U502; U504 | J22: =SUMIFS('Parts list'!$C$4:$C$133,'Parts list'!$I$4:$I$133,$G22,'Parts list'!$K$4:$K$133,"Yes") -> 2 | K22: =$J22*Cost!$B$6 -> 10 | L22: 0.0603 | M22: 0.049 | O22: =IF(AND($L22>0,$L22<Cost!$B$9),"Yes","") | P22: =IF($O22="Yes",MAX($K22*$L22,Cost!$B$8),$K22*$L22) -> 0.603 | Q22: =$J22*$M22 -> 0.098
A23: 20 | B23: Connector | C23: SHOU HAN TYPE-C 16PIN 2MD(073) | D23: — | E23: SMD, right angle | F23: 5 V, 3 A | G23: C2765186 | H23: Extended | I23: J101 | J23: =SUMIFS('Parts list'!$C$4:$C$133,'Parts list'!$I$4:$I$133,$G23,'Parts list'!$K$4:$K$133,"Yes") -> 1 | K23: =$J23*Cost!$B$6 -> 5 | L23: 0.1 | M23: 0.0604 | O23: =IF(AND($L23>0,$L23<Cost!$B$9),"Yes","") | P23: =IF($O23="Yes",MAX($K23*$L23,Cost!$B$8),$K23*$L23) -> 0.5 | Q23: =$J23*$M23 -> 0.0604
A24: 21 | B24: Capacitor | C24: Samsung CL05B104KO5NNNC | D24: 100 nF | E24: 0402 | F24: 16 V X7R | G24: C1525 | H24: Basic | I24: C203–C210; C212; C213–C216; C217–C219; C305–C309; C421; C422; C423–C426; C409–C412; C605; C606 | J24: =SUMIFS('Parts list'!$C$4:$C$133,'Parts list'!$I$4:$I$133,$G24,'Parts list'!$K$4:$K$133,"Yes") -> 33 | K24: =$J24*Cost!$B$6 -> 165 | L24: 0.003 | M24: 0.0011 | O24: =IF(AND($L24>0,$L24<Cost!$B$9),"Yes","") -> Yes | P24: =IF($O24="Yes",MAX($K24*$L24,Cost!$B$8),$K24*$L24) -> 0.495 | Q24: =$J24*$M24 -> 0.0363
A25: 22 | B25: Capacitor | C25: Samsung CL10A105KB8NNNC | D25: 1 µF | E25: 0603 | F25: 25 V X5R | G25: C15849 | H25: Basic | I25: C102; C301; C302; C311; C312; C501; C502; C503; C504; C505; C506; C508; C601–C604 | J25: =SUMIFS('Parts list'!$C$4:$C$133,'Parts list'!$I$4:$I$133,$G25,'Parts list'!$K$4:$K$133,"Yes") -> 16 | K25: =$J25*Cost!$B$6 -> 80 | L25: 0.006 | M25: 0.0022 | O25: =IF(AND($L25>0,$L25<Cost!$B$9),"Yes","") -> Yes | P25: =IF($O25="Yes",MAX($K25*$L25,Cost!$B$8),$K25*$L25) -> 0.48 | Q25: =$J25*$M25 -> 0.0352
A26: 23 | B26: IC | C26: onsemi LM393DR2G | D26: — | E26: SOIC-8 | F26: 2–36 V | G26: C7955 | H26: Basic | I26: U601 | J26: =SUMIFS('Parts list'!$C$4:$C$133,'Parts list'!$I$4:$I$133,$G26,'Parts list'!$K$4:$K$133,"Yes") -> 1 | K26: =$J26*Cost!$B$6 -> 5 | L26: 0.09 | M26: 0.0564 | O26: =IF(AND($L26>0,$L26<Cost!$B$9),"Yes","") | P26: =IF($O26="Yes",MAX($K26*$L26,Cost!$B$8),$K26*$L26) -> 0.45 | Q26: =$J26*$M26 -> 0.0564
A27: 24 | B27: Diode | C27: Nexperia BAV99,215 | D27: BAV99 | E27: SOT-23 | F27: 100 V | G27: C2500 | H27: Basic | I27: D601–D604 | J27: =SUMIFS('Parts list'!$C$4:$C$133,'Parts list'!$I$4:$I$133,$G27,'Parts list'!$K$4:$K$133,"Yes") -> 4 | K27: =$J27*Cost!$B$6 -> 20 | L27: 0.0211 | M27: 0.0159 | O27: =IF(AND($L27>0,$L27<Cost!$B$9),"Yes","") -> Yes | P27: =IF($O27="Yes",MAX($K27*$L27,Cost!$B$8),$K27*$L27) -> 0.422 | Q27: =$J27*$M27 -> 0.0636
... A51: 48 | B51: Capacitor | C51: FH 0402B472K500NT | D51: 4.7 nF | E51: 0402 | F51: 50 V X7R | G51: C1538 | H51: Basic | I51: C101 | J51: =SUMIFS('Parts list'!$C$4:$C$133,'Parts list'!$I$4:$I$133,$G51,'Parts list'!$K$4:$K$133,"Yes") -> 1 | K51: =$J51*Cost!$B$6 -> 5 | L51: 0.002 | M51: 0.0006 | O51: =IF(AND($L51>0,$L51<Cost!$B$9),"Yes","") -> Yes | P51: =IF($O51="Yes",MAX($K51*$L51,Cost!$B$8),$K51*$L51) -> 0.1 | Q51: =$J51*$M51 -> 0.0006
B53: Total, all purchase lines | J53: =SUM(J4:J51) -> 232 | K53: =SUM(K4:K51) -> 1160 | O53: =COUNTIF(O4:O51,"Yes") -> 29 | P53: =SUM(P4:P51) -> 138.84 | Q53: =SUM(Q4:Q51) -> 19.6486

Sheet Cost
A1: Cost — 5-board sample run (JLCPCB Economic PCBA) and 100-unit reference
A2: Parts List v0.4 (24 Sep 2026, after the fifth review round) · parts at the LCSC tier matching the run quantity (100-board tier for the reference); OPA2210 at its JLCPCB part-page price · JLCPCB PCBA fee schedules · blue on yellow = input · every NTD figure uses the exchange rate in B5 · planning estimate until the JLCPCB quote after layout
A4: Inputs | B4: Value | C4: Unit | G4: Note
A5: Exchange rate | B5: 31.7 | C5: NTD per US$ | G5: fixed for the cost gate; applies to every NTD figure
A6: Boards in the sample run | B6: 5 | C6: boards | G6: JLCPCB Economic PCBA (one side, 2–50 boards)
A7: Boards in the reference build | B7: 100 | C7: boards | G7: JLCPCB Standard PCBA — reference only, not the budget basis
A8: Minimum line cost per purchasing line | B8: 0.1 | C8: US$ | G8: applied to purchasing lines whose unit price is below B9 (attrition / minimum-quantity allowance)
A9: Minimum applies below this unit price | B9: 0.05 | C9: US$ | G9: Purchasing list: line = MAX(qty × price, B8) when 0 < price < B9
A10: Cost target per board, 5-board run | B10: 1500 | C10: NTD | G10: ="WARNING above; = "&TEXT(B10*B6,"#,##0")&" NTD for "&TEXT(B6,"0")&" boards incl. bare PCBs and assembly fees; excl. shipping, import tax, programmers, enclosure, proof-of-concept hardware and a possible assembly-fixture fee" -> WARNING above; = 7,500 NTD for 5 boards incl. bare PCBs and assembly fees; excl. shipping, import tax, programmers, enclosure, proof-of-concept hardware and a possible assembly-fixture fee
A11: Ceiling per board, 5-board run (hard order gate) | B11: 1700 | C11: NTD | G11: Ceiling 1,700 NTD per board, set when the third oscillator was added; on 24 Sep 2026 the owner confirmed the budget is flexible as long as it does not surge; the actual JLCPCB quote from the real BOM/CPL files must pass the ceiling before ordering; FAIL above
A13: Board data (linked from the Parts list and Purchasing list) | B13: Value | C13: Unit | G13: Source
A14: Fitted BOM lines | B14: =COUNTIF('Parts list'!$K$4:$K$133,"Yes") -> 122 | C14: lines | G14: Parts list: Fit = Yes (includes the bare-PCB row)
A15: SMT-placed parts per board | B15: =SUMIFS('Parts list'!$C$4:$C$133,'Parts list'!$K$4:$K$133,"Yes",'Parts list'!$M$4:$M$133,">0",'Parts list'!$B$4:$B$133,"<>PCB") -> 231 | C15: parts | G15: Parts list: Qty where Fit = Yes and SMT joints per part > 0
A16: Through-hole parts per board | B16: =SUMIFS('Parts list'!$C$4:$C$133,'Parts list'!$K$4:$K$133,"Yes",'Parts list'!$N$4:$N$133,">0") -> 1 | C16: parts | G16: Parts list: through-hole joints per part > 0 (4.4 mm jack J701)
A17: Extended part types (incl. through-hole) | B17: =SUMIFS('Parts list'!$W$4:$W$133,'Parts list'!$J$4:$J$133,"Extended") -> 19 | C17: types | G17: Parts list helper W: distinct LCSC numbers, class Extended — every fitted Extended type, incl. the through-hole jack
A18: Basic part types | B18: =SUMIFS('Parts list'!$W$4:$W$133,'Parts list'!$J$4:$J$133,"Basic") -> 29 | C18: types | G18: Parts list helper W: distinct LCSC numbers, class Basic
A19: All part types | B19: =B17+B18 -> 48 | C19: types | G19: Extended + Basic (feeder loading on the 100-unit reference)
A20: SMT joints per board | B20: {=SUMPRODUCT(('Parts list'!$K$4:$K$133="Yes")*('Parts list'!$B$4:$B$133<>"PCB")*'Parts list'!$C$4:$C$133*'Parts list'!$M$4:$M$133)} -> 690 | C20: joints | G20: Parts list: Qty × SMT joints per part where Fit = Yes
A21: Through-hole joints per board | B21: {=SUMPRODUCT(('Parts list'!$K$4:$K$133="Yes")*'Parts list'!$C$4:$C$133*'Parts list'!$N$4:$N$133)} -> 7 | C21: joints | G21: Parts list: Qty × through-hole joints per part where Fit = Yes
A22: Leadless parts per board (X-ray) | B22: =SUMIFS('Parts list'!$C$4:$C$133,'Parts list'!$K$4:$K$133,"Yes",'Parts list'!$L$4:$L$133,"Yes") -> 8 | C22: parts | G22: Parts list: Leadless (X-ray) = Yes — CPLD, ES9018K2M, 2 × OPA1622, LM27762, three oscillators (80 / 24.576 / 22.5792 MHz)
A23: of which oscillators | B23: =SUMIFS('Parts list'!$C$4:$C$133,'Parts list'!$K$4:$K$133,"Yes",'Parts list'!$L$4:$L$133,"Yes",'Parts list'!$D$4:$D$133,"Oscillator*") -> 3 | C23: parts | G23: X201, X202 and X203 — counted conservatively (see levers)
A24: Extended through-hole part types | B24: =SUMIFS('Parts list'!$W$4:$W$133,'Parts list'!$J$4:$J$133,"Extended",'Parts list'!$N$4:$N$133,">0") -> 1 | C24: types | G24: J701 — Extended fee counted conservatively (see levers)
A25: Parts, 5-board run (incl. minimum) | B25: =SUM('Purchasing list'!$P$4:$P$51) -> 138.84 | C25: US$ | G25: Purchasing list: line costs, incl. the US$0.10 minimum for parts under US$0.05
A26: of which minimum-spend uplift | B26: =B25-SUMIFS('Parts list'!$S$4:$S$133,'Parts list'!$B$4:$B$133,"<>PCB") -> 0.899 | C26: US$ | G26: Purchasing list total minus the Parts list line costs before the minimum
A27: Bare 4-layer PCBs, 5-board run (estimate) | B27: =SUMIFS('Parts list'!$S$4:$S$133,'Parts list'!$B$4:$B$133,"PCB") -> 10 | C27: US$ | G27: Parts list: PCB row, qty × boards × unit price
A28: Parts per board, 100-board tier (bare PCB excluded) | B28: =SUMIFS('Parts list'!$T$4:$T$133,'Parts list'!$B$4:$B$133,"<>PCB")/$B$7 -> 19.6486 | C28: US$ | G28: Parts list: Line cost 100-board run ÷ boards
A29: Bare PCB per board, 100-board tier (estimate) | B29: =SUMIFS('Parts list'!$T$4:$T$133,'Parts list'!$B$4:$B$133,"PCB")/$B$7 -> 0.8 | C29: US$ | G29: Parts list: PCB row
A31: ="5-board sample run — "&TEXT($B$6,"0")&" boards, JLCPCB Economic PCBA" -> 5-board sample run — 5 boards, JLCPCB Economic PCBA
A32: PCBA fee (per order) | B32: Quantity | C32: Rate US$ | D32: Fixed US$ | E32: US$ | F32: NTD | G32: Basis
A33: Setup | D33: 8.18 | E33: =B33*C33+D33 -> 8.18 | F33: =E33*$B$5 -> 259.306 | G33: fixed fee per order
A34: Stencil | D34: 1.53 | E34: =B34*C34+D34 -> 1.53 | F34: =E34*$B$5 -> 48.501 | G34: fixed fee per order
A35: Extended part types | B35: =B17 -> 19 | C35: 3.07 | E35: =B35*C35+D35 -> 58.33 | F35: =E35*$B$5 -> 1849.061 | G35: =TEXT(B35,"0")&" fitted Extended part types × US$"&TEXT(C35,"0.00")&", incl. the through-hole 4.4 mm jack (counted conservatively)" -> 19 fitted Extended part types × US$3.07, incl. the through-hole 4.4 mm jack (counted conservatively)
A36: SMT joints | B36: =B20*$B$6 -> 3450 | C36: 0.0016 | E36: =B36*C36+D36 -> 5.52 | F36: =E36*$B$5 -> 174.984 | G36: =TEXT(B20,"#,##0")&" joints per board × "&TEXT($B$6,"0")&" boards" -> 690 joints per board × 5 boards
A37: X-ray (leadless parts) | B37: =B22*$B$6 -> 40 | C37: 0.82 | E37: =B37*C37+D37 -> 32.8 | F37: =E37*$B$5 -> 1039.76 | G37: =TEXT(B22,"0")&" leadless parts per board × "&TEXT($B$6,"0")&" boards (11–50-part tier); includes the "&TEXT(B23,"0")&" oscillators (counted conservatively)" -> 8 leadless parts per board × 5 boards (11–50-part tier); includes the 3 oscillators (counted conservatively)
A38: Through-hole joints | B38: =B21*$B$6 -> 35 | C38: 0.0164 | D38: 3.58 | E38: =IF(B38=0,0,B38*C38+D38) -> 4.154 | F38: =E38*$B$5 -> 131.6818 | G38: ="4.4 mm jack: "&TEXT(B21,"0")&" joints per board × "&TEXT($B$6,"0")&" boards, plus the hand-soldering fee per order" -> 4.4 mm jack: 7 joints per board × 5 boards, plus the hand-soldering fee per order
A39: Confirm Parts Placement | D39: 0.45 | E39: =B39*C39+D39 -> 0.45 | F39: =E39*$B$5 -> 14.265 | G39: fixed fee per order
A40: PCBA fees, total per order | E40: =SUM(E33:E39) -> 110.964 | F40: =E40*$B$5 -> 3517.5588
A42: 5-board run total | E42: US$ | F42: NTD | G42: Basis
A43: Parts (LCSC tier matching the run quantity) | E43: =B25 -> 138.84 | F43: =E43*$B$5 -> 4401.228 | G43: Purchasing list, incl. the minimum per line for parts under US$0.05
A44: Bare 4-layer PCBs (estimate) | E44: =B27 -> 10 | F44: =E44*$B$5 -> 317 | G44: =TEXT($B$6,"0")&" boards; Parts list PCB row" -> 5 boards; Parts list PCB row
A45: JLCPCB PCBA fees | E45: =E40 -> 110.964 | F45: =E45*$B$5 -> 3517.5588 | G45: Economic PCBA, itemised above
A46: Total, 5-board run | E46: =SUM(E43:E45) -> 259.804 | F46: =E46*$B$5 -> 8235.7868 | G46: ="for "&TEXT($B$6,"0")&" boards" -> for 5 boards
A47: Per board | E47: =E46/$B$6 -> 51.9608 | F47: =E47*$B$5 -> 1647.1574 | G47: cost-gate figure
A48: Target per board | F48: =$B$10 -> 1500 | G48: ="input B10; "&TEXT($B$10*$B$6,"#,##0")&" NTD for "&TEXT($B$6,"0")&" boards; WARNING above" -> input B10; 7,500 NTD for 5 boards; WARNING above
A49: Ceiling per board (hard order gate) | F49: =$B$11 -> 1700 | G49: input B11 (set when the third oscillator was added; 24 Sep 2026: the owner confirmed the budget is flexible as long as it does not surge; the JLCPCB quote must pass it before ordering); FAIL above
A50: Margin to the target per board | F50: =F48-F47 -> -147.15736 | G50: =IF(F50>=0,"within the target",TEXT(-F50,"#,##0")&" NTD over the target ("&TEXT(-F50/F48,"0.0%")&")") -> 147 NTD over the target (9.8%)
A51: Margin to the ceiling per board | F51: =F49-F47 -> 52.84264 | G51: =IF(F51>=0,TEXT(F51,"#,##0")&" NTD under the ceiling",TEXT(-F51,"#,##0")&" NTD over the ceiling") -> 53 NTD under the ceiling
A52: Cost-gate status | F52: =IF(F47<=F48,"PASS",IF(F47<=F49,"WARNING","FAIL")) -> WARNING | G52: ="PASS ≤ "&TEXT(F48,"#,##0")&" NTD per board (target); WARNING ≤ "&TEXT(F49,"#,##0")&" (ceiling, hard order gate); FAIL > "&TEXT(F49,"#,##0") -> PASS ≤ 1,500 NTD per board (target); WARNING ≤ 1,700 (ceiling, hard order gate); FAIL > 1,700
A54: Conservative fee items and levers — effect on the 5-board run
A55: Item | B55: Quantity | C55: Rate US$ | D55: Current US$ | E55: Change US$ (run) | F55: NTD per board | G55: Basis
A56: Through-hole jack not charged the Extended fee | B56: =B24 -> 1 | C56: =C35 -> 3.07 | E56: =-B56*C56 -> -3.07 | F56: =E56*$B$5/$B$6 -> -19.4638 | G56: JLCPCB does not say whether through-hole parts pay the Extended fee (JLCPCB help text, Notes sheet); counted above
A57: Oscillators not X-rayed (X201, X202, X203) | B57: =B23*$B$6 -> 15 | C57: =C37 -> 0.82 | E57: =-B57*C57 -> -12.3 | F57: =E57*$B$5/$B$6 -> -77.982 | G57: ="JLCPCB X-rays ""BGA, QFN, and other leadless packages""; oscillators are not named; "&IF(B23=0,"no oscillator counted",TEXT(B23,"0")&" oscillators × "&TEXT(F57/B23,"+0.0;-0.0")&" NTD per board each")&"; counted above" -> JLCPCB X-rays "BGA, QFN, and other leadless packages"; oscillators are not named; 3 oscillators × -26.0 NTD per board each; counted above
A58: Per-board total without the conservative items | F58: =F47+F56+F57 -> 1549.7116 | G58: ="≈ "&TEXT(F58,"#,##0")&" NTD per board — "&IF(F58<=F48,"under","over")&" the "&TEXT(F48,"#,##0")&" NTD target" -> ≈ 1,550 NTD per board — over the 1,500 NTD target
A59: Cheaper 4.4 mm jack — current J701 cost | B59: =SUMIFS('Parts list'!$R$4:$R$133,'Parts list'!$B$4:$B$133,"J701") -> 5 | C59: =SUMIFS('Parts list'!$O$4:$O$133,'Parts list'!$B$4:$B$133,"J701") -> 6.8656 | D59: =B59*C59 -> 34.328 | F59: =D59*$B$5/$B$6 -> 217.63952 | G59: ="no cheaper 4.4 mm jack at LCSC (SMD option not available); each US$1.00 off its unit price would save "&TEXT($B$5,"0.0")&" NTD per board" -> no cheaper 4.4 mm jack at LCSC (SMD option not available); each US$1.00 off its unit price would save 31.7 NTD per board
A60: Reduction needed to reach PASS (target) | E60: =F60*$B$6/$B$5 -> 23.21094 | F60: =MAX(0,F47-F48) -> 147.15736 | G60: ="per-board reduction that brings the total to the "&TEXT(F48,"#,##0")&" NTD target" -> per-board reduction that brings the total to the 1,500 NTD target
A61: OPA2210 at the LCSC price (price risk, not counted) | B61: =SUMIFS('Parts list'!$R$4:$R$133,'Parts list'!$B$4:$B$133,"U403, U404") -> 10 | C61: 2.67 | D61: =B61*SUMIFS('Parts list'!$O$4:$O$133,'Parts list'!$B$4:$B$133,"U403, U404") -> 10.035 | E61: =B61*C61-D61 -> 16.665 | F61: =E61*$B$5/$B$6 -> 105.6561 | G61: ="JLCPCB part-page price counted (the PCBA order is charged at JLCPCB prices; JLCPCB available 76 → reserve "&TEXT(B61,"0")&"); at the LCSC price (input C61, 10+ tier) the board would cost ≈ "&TEXT(F47+F61,"#,##0")&" NTD — "&IF(F47+F61>F49,"above","within")&" the ceiling" -> JLCPCB part-page price counted (the PCBA order is charged at JLCPCB prices; JLCPCB available 76 → reserve 10); at the LCSC price (input C61, 10+ tier) the board would cost ≈ 1,753 NTD — above the ceiling
A63: ="100-unit reference — "&TEXT($B$7,"0")&" boards, JLCPCB Standard PCBA (reference only; not the budget basis)" -> 100-unit reference — 100 boards, JLCPCB Standard PCBA (reference only; not the budget basis)
A64: PCBA fee (per order) | B64: Quantity | C64: Rate US$ | D64: Fixed US$ | E64: US$ | F64: NTD | G64: Basis
A65: Setup (single side) | D65: 25.56 | E65: =B65*C65+D65 -> 25.56 | F65: =E65*$B$5 -> 810.252 | G65: fixed fee per order
A66: Stencil | D66: 8.21 | E66: =B66*C66+D66 -> 8.21 | F66: =E66*$B$5 -> 260.257 | G66: fixed fee per order
A67: Fixtures | D67: 41.04 | E67: =B67*C67+D67 -> 41.04 | F67: =E67*$B$5 -> 1300.968 | G67: fixed fee, 100–199-board tier
A68: Feeder loading (all part types) | B68: =B19 -> 48 | C68: 1.53 | E68: =B68*C68+D68 -> 73.44 | F68: =E68*$B$5 -> 2328.048 | G68: =TEXT(B68,"0")&" part types (Extended + Basic) × US$"&TEXT(C68,"0.00") -> 48 part types (Extended + Basic) × US$1.53
A69: SMT joints | B69: =B20*$B$7 -> 69000 | C69: 0.0016 | E69: =B69*C69+D69 -> 110.4 | F69: =E69*$B$5 -> 3499.68 | G69: =TEXT(B20,"#,##0")&" joints per board × "&TEXT($B$7,"0")&" boards" -> 690 joints per board × 100 boards
A70: X-ray (leadless parts) | B70: =B22*$B$7 -> 800 | C70: 0.25 | E70: =B70*C70+D70 -> 200 | F70: =E70*$B$5 -> 6340 | G70: =TEXT(B22,"0")&" leadless parts per board × "&TEXT($B$7,"0")&" boards (501–1,000-part tier)" -> 8 leadless parts per board × 100 boards (501–1,000-part tier)
A71: Through-hole joints | B71: =B21*$B$7 -> 700 | C71: 0.0164 | D71: 3.58 | E71: =IF(B71=0,0,B71*C71+D71) -> 15.06 | F71: =E71*$B$5 -> 477.402 | G71: ="4.4 mm jack: "&TEXT(B21,"0")&" joints per board × "&TEXT($B$7,"0")&" boards, plus the hand-soldering fee per order" -> 4.4 mm jack: 7 joints per board × 100 boards, plus the hand-soldering fee per order
A72: Confirm Parts Placement | D72: 0.45 | E72: =B72*C72+D72 -> 0.45 | F72: =E72*$B$5 -> 14.265 | G72: fixed fee per order
A73: PCBA fees, total per order | E73: =SUM(E65:E72) -> 474.16 | F73: =E73*$B$5 -> 15030.872
A75: Cost per board, 100-unit reference | E75: US$ | F75: NTD | G75: Basis
A76: Parts (100-board tier) | E76: =B28 -> 19.6486 | F76: =E76*$B$5 -> 622.86062 | G76: Parts list: fitted lines except the PCB row
A77: Bare PCB (estimate) | E77: =B29 -> 0.8 | F77: =E77*$B$5 -> 25.36 | G77: Parts list: PCB row
A78: PCBA fees per board | E78: =E73/$B$7 -> 4.7416 | F78: =E78*$B$5 -> 150.30872 | G78: ="order total ÷ "&TEXT($B$7,"0")&" boards" -> order total ÷ 100 boards
A79: Total per board, 100-unit reference | E79: =SUM(E76:E78) -> 25.1902 | F79: =E79*$B$5 -> 798.52934 | G79: reference line only
A81: Excludes shipping, import tax, the WCH-LinkE and CPLD programming cable, the enclosure, proof-of-concept hardware (Stage 2 board ≈ US$79 ≈ 2,500 NTD for two) and a possible JLCPCB assembly-fixture fee (X202 and OPA2210 part pages). Planning estimate: the gate becomes final with the JLCPCB quote from the real BOM / CPL files after layout.

Sheet Notes & open items
A1: Notes & open items
A2: Parts List v0.4 · Diego Yang · 24 Sep 2026 · companion to Design Specification v0.6 and Schematic Design Notes v0.5 · Parts List v0.3 is kept unchanged as history
A4: About this list
A5: 1 | B5: ="Covers every component of every circuit: "&TEXT(COUNTA('Parts list'!$B$4:$B$133),"0")&" BOM lines ("&TEXT(Cost!B14,"0")&" fitted, "&TEXT(COUNTIF('Parts list'!$K$4:$K$133,"DNF"),"0")&" DNF), "&TEXT(Cost!B15,"0")&" SMT-placed parts and "&TEXT(Cost!B16,"0")&" through-hole part (4.4 mm jack) per board; "&TEXT(COUNTA('Purchasing list'!$C$4:$C$51),"0")&" purchasing lines." -> Covers every component of every circuit: 130 BOM lines (122 fitted, 4 DNF), 231 SMT-placed parts and 1 through-hole part (4.4 mm jack) per board; 48 purchasing lines.
A6: 2 | B6: Designators are grouped by block: 1xx USB-C input and sensing, 2xx USB audio bridge, 3xx DAC and its supplies, 4xx I/V converters and output legs, 5xx power domains, current limit and rails, 6xx protection and control, 7xx outputs, indicators, test and board.
A7: 3 | B7: Fit: Yes = placed on every board; DNF = footprint only (U205 clock mux and R215, the fallback for the shared family-clock node; R703 and the J703 I²S test header); No part = copper only (J201 / J202 debug pads, TP701–TP729 test pads, 4 mounting holes and 3 fiducials).
A8: 4 | B8: One part per line. Every fitted part has an LCSC number and a JLCPCB class verified on the JLCPCB part page or the JLCPCB basic-parts list — except X202 (24.576 MHz oscillator), whose class is not shown on its part page and is assumed Extended (conservative); the Purchasing list has one line per LCSC number and quantities summed from the Parts list.
A9: 5 | B9: Legend: Quote = listing price at the tier matching the run quantity (LCSC; the OPA2210 line uses its JLCPCB part-page price, see its note); Estimate = planning price (bare PCB, DNF header); blue on yellow = input on the Cost sheet; Parts list columns V–W are helpers that count distinct part types by LCSC number.
A11: Change log
A12: 1 | B12: 24 Sep 2026 — Parts List v0.3 after the fourth review round (reviews R4-A, R4-B and R4-C of Spec v0.4 / Notes v0.3 / Parts List v0.2). Parts List v0.2 stays unchanged as history.
A13: 2 | B13: 24 Sep 2026 — Current limit: TI TPS2553DBVR (C55266) current-limited switch feeds the LM27762 (Default 0.157–0.213 A, High 0.393–0.498 A); RILIM from Basic values 100 kΩ + 47 kΩ, High limit via 2N7002 + 100 kΩ.
A14: 3 | B14: 24 Sep 2026 — Power domains: second ME6211C33M5G-N (U504, switched 3V3D domain with CE) added beside the always-on 3V3M ME6211; LP5907 EN and TPS2553 EN switch the audio domains.
A15: 4 | B15: 24 Sep 2026 — Clock: one 100 MHz oscillator YXC OT3225100MJBA4SL (C4353707) replaces the two audio oscillators (22.5792 / 24.576 MHz); the ES9018K2M runs in its asynchronous (DPLL) mode.
A16: 5 | B16: 24 Sep 2026 — I/V op-amp: TI OPA2197IDR (C139363, Vos ±0.25 mV max) replaces the OPA1678 (±2 mV max).
A17: 6 | B17: 24 Sep 2026 — 1.3 V DVDD: Microne ME6216A13M3G (C236662, fixed, ±1 %, ceramic-stable) replaces the AMS1117-ADJ, fed from the switched 3V3D domain.
A18: 7 | B18: 24 Sep 2026 — Ferrite: Murata BLM18PG121SN1D (C14709, Basic, 2 A, 50 mΩ) in the 5V_ANA path; Sunlord GZ1608D601TF (C1002, 200 mA / 450 mΩ) only on the DAC DVCC branch (≈ 14 mA).
A19: 8 | B19: 24 Sep 2026 — Protection: all-2N7002 fault latch (Q601–Q609, JSCJ 2N7002 C8545) with PGOOD hardware kill and ≈ 60 ms set-path blanking; the MMBT3904 / MMBT3906 transistors are gone.
A20: 9 | B20: 24 Sep 2026 — Basic value combinations instead of Extended values: 100 k + 47 k (TPS2553 RILIM, DC-detect filter), 1 k ∥ 5.1 k = 836 Ω (I/V feedback), 15 k + 1 k (VREF divider), 2 × 330 pF C0G (I/V feedback capacitor), 100 k + 100 k + 15 k / 10 k (LM27762 feedback).
A21: 10 | B21: 24 Sep 2026 — Other part changes: Basic 5032 8 MHz crystal YXC X50328MSB2GI (C115962); GOODWORK LESD5D5.0CT1G ESD diodes (C41399463); SHOU HAN TYPE-C 16-pin receptacle (C2765186); 0805 green status LED KT-0805G (C2297, Basic).
A22: 11 | B22: 24 Sep 2026 — Design context: headphone rails ±3.78 V (was ±4.5 V); output calibrated to 1.75 Vrms per leg; parts list rebuilt one part per line with an LCSC number and a verified class on every fitted line.
A23: 12 | B23: 24 Sep 2026 — Cost: 1,536 NTD per board (v0.2) → 1,540 NTD per board (US$242.95 = 7,702 NTD for 5 boards); gate WARNING, 10 NTD under the approved ceiling of 1,550 NTD at the time. Verified prices are mostly lower; new parts and three more Extended types are counted.
... A28: 17 | B28: 24 Sep 2026 — v0.4 (fifth review round): MCLK oscillator 80 MHz (SCTF SX3M80.000B20F30TNN) replaces 100 MHz; I/V op-amp OPA2210IDR replaces OPA2197IDR; both family-oscillator enables 2.2 kΩ pull-downs, node pull-down R214, DNF mux U205/R215; overload latch parts Q610 and D606; VREF clamp D401 and C421 100 nF; R518 5.1 kΩ (−3.722 V rail); DNF R703 for the test-header MCLK monitor; 29 test pads; cost 1,666 → 1,647 NTD per board
A29: Pricing rules
A30: 1 | B30: Price tier: the LCSC tier that matches the run quantity — 1+ tier for one-per-board ICs (5 pieces), 10+ tier for two-per-board parts (10 pieces). The Parts list column "Unit price US$ (sample-run tier)" already holds that price. Exception: the OPA2210 (U403, U404) is priced at its JLCPCB part page (10+ US$1.0035), because the PCBA order is charged at JLCPCB prices; LCSC lists US$2.67 at 10+.
A31: 2 | B31: ="Minimum: US$"&TEXT(Cost!B8,"0.00")&" per purchasing line for parts under US$"&TEXT(Cost!B9,"0.00")&" (attrition / minimum-quantity allowance): line cost = MAX(qty for the run × unit price, US$"&TEXT(Cost!B8,"0.00")&"). It applies to "&TEXT('Purchasing list'!O53,"0")&" of the "&TEXT(COUNTA('Purchasing list'!$C$4:$C$51),"0")&" purchasing lines and adds US$"&TEXT(Cost!B26,"0.00")&" to the run." -> Minimum: US$0.10 per purchasing line for parts under US$0.05 (attrition / minimum-quantity allowance): line cost = MAX(qty for the run × unit price, US$0.10). It applies to 29 of the 48 purchasing lines and adds US$0.90 to the run.
A32: 3 | B32: ="Exchange rate: "&TEXT(Cost!B5,"0.0")&" NTD per US$, fixed for the cost gate; the single input cell Cost!B5 drives every NTD figure." -> Exchange rate: 31.7 NTD per US$, fixed for the cost gate; the single input cell Cost!B5 drives every NTD figure.
A33: 4 | B33: ="Bare PCBs (estimate): 4 layers, ≤ 80 × 60 mm, 90 Ω USB pair; US$"&TEXT(SUMIFS('Parts list'!$O$4:$O$133,'Parts list'!$B$4:$B$133,"PCB"),"0.00")&" per board for the 5-board run (US$"&TEXT(Cost!B27,"0")&" for "&TEXT(Cost!B6,"0")&") and US$"&TEXT(SUMIFS('Parts list'!$P$4:$P$133,'Parts list'!$B$4:$B$133,"PCB"),"0.00")&" per board for the 100-unit reference." -> Bare PCBs (estimate): 4 layers, ≤ 80 × 60 mm, 90 Ω USB pair; US$2.00 per board for the 5-board run (US$10 for 5) and US$0.80 per board for the 100-unit reference.
A34: 5 | B34: 100-unit reference: JLCPCB Standard PCBA with parts at the 100-board tier — for information only, not the budget basis.
A35: 6 | B35: Prices, classes and stock come from LCSC and JLCPCB pages indexed Jun–Sep 2026 (cached copies) — check again before ordering. The cost is a planning estimate; the gate becomes final with the JLCPCB quote from the real BOM / CPL files after layout.
A37: Stock to reserve (JLCPCB parts library, before ordering)
A38: 1 | B38: ="OPA2210IDR (C1849415, U403, U404): JLCPCB available quantity 76 → reserve "&TEXT(Cost!B61,"0")&" (2 per board); priced at its JLCPCB part page." -> OPA2210IDR (C1849415, U403, U404): JLCPCB available quantity 76 → reserve 10 (2 per board); priced at its JLCPCB part page.
A39: 2 | B39: CH32V307RCT6 (C2988083): LCSC stock 119.
A40: 3 | B40: ME6216A13M3G (C236662): LCSC stock ≈ 410.
A41: 4 | B41: 4.4 mm jack G-Switch GT-3321667P-01 (C2762984): LCSC stock 721.
A42: 5 | B42: ES9018K2M (C2688377): LCSC stock 724; AGRV2KQ32 (C18208899): LCSC stock 980.
A43: 6 | B43: The 5-board run needs 5 of each (10 of the OPA2210; Purchasing list, Qty for 5-board run): enough today, but not deep — reserve or pre-order in the JLCPCB parts library (LCSC stock seen Jun–Sep 2026; OPA2210: JLCPCB available quantity).
A45: Fee assumptions (JLCPCB Economic PCBA)
A46: 1 | B46: Setup US$8.18, stencil US$1.53, US$3.07 per Extended part type, US$0.0016 per SMT joint, X-ray US$0.82 per leadless part (11–50-part tier), through-hole US$0.0164 per joint + US$3.58 hand-soldering per order, Confirm Parts Placement US$0.45; one side only, 2–50 boards.
A47: 2 | B47: ="Through-hole Extended fee counted conservatively: JLCPCB does not say whether through-hole parts pay it; a third-party guide says they do not. If not charged: "&TEXT(Cost!F56,"+0.0;-0.0")&" NTD per board." -> Through-hole Extended fee counted conservatively: JLCPCB does not say whether through-hole parts pay it; a third-party guide says they do not. If not charged: -19.5 NTD per board.
A48: 3 | B48: ="Oscillator X-ray counted conservatively: JLCPCB names BGA, QFN and other leadless packages, not oscillators. If the three oscillators (X201, X202, X203) are not X-rayed: "&IF(Cost!B23=0,"+0.0",TEXT(Cost!F57/Cost!B23,"+0.0;-0.0"))&" NTD per board each ("&TEXT(Cost!F57,"+0.0;-0.0")&" together). Without the through-hole fee and the oscillator X-ray: ≈ "&TEXT(Cost!F58,"#,##0")&" NTD per board." -> Oscillator X-ray counted conservatively: JLCPCB names BGA, QFN and other leadless packages, not oscillators. If the three oscillators (X201, X202, X203) are not X-rayed: -26.0 NTD per board each (-78.0 together). Without the through-hole fee and the oscillator X-ray: ≈ 1,550 NTD per board.
A49: 4 | B49: JLCPCB help text: "Extended Components Fee: For Economic PCBA orders, an additional labor fee applies to extended components that require extra feeder setup or changeover on pick-and-place machines." Pricing table: "Feeder Loading $3.07 Extend"; "Hand-soldering Labor $3.58 per order".
A50: 5 | B50: JLCPCB help text: "X-ray inspection is required for components such as BGA, QFN, and other leadless packages whose solder joints are not visible after SMT assembly"; fee "1–10 pcs: $1.64/pc, 11–50 pcs: $0.82/pc, 51–200 pcs: $0.49/pc". Third-party guide (PedalPCB forum): "Through-hole parts are always 'Extended' but do not incur a $3-per-part cost."
A52: Exclusions
A53: 1 | B53: Not in the cost and outside the ceiling: shipping, import tax, the WCH-LinkE and CPLD programming cable, the enclosure, proof-of-concept hardware (Stage 2 board ≈ US$79 ≈ 2,500 NTD for two) and a possible JLCPCB assembly-fixture fee (fixture notes on the X202 and OPA2210 part pages).
A54: 2 | B54: The DNF parts (U205, R215, R703 and the I²S test header J703) and the copper-only items (debug pads, test pads, mounting holes, fiducials) carry no part cost.
A56: Open items relevant to purchasing (Design Specification v0.6, risks and open items)
A57: 1 | B57: Stock of CH32V307, ES9018K2M, AGRV2K, ME6216, the 4.4 mm jack and the OPA2210 (JLCPCB 76) is thin → reserve the parts (section above).
A58: 2 | B58: ="OPA2210 (U403, U404, C1849415): JLCPCB stock 76 and price (JLCPCB US$"&TEXT(SUMIFS('Parts list'!$O$4:$O$133,'Parts list'!$B$4:$B$133,"U403, U404"),"0.00")&" vs LCSC US$"&TEXT(Cost!C61,"0.00")&" at 10+) → reserve "&TEXT(Cost!B61,"0")&" in the JLCPCB parts library; at the LCSC price ≈ "&TEXT(Cost!F47+Cost!F61,"#,##0")&" NTD per board ("&IF(Cost!F47+Cost!F61>Cost!F49,"above","within")&" the ceiling)." -> OPA2210 (U403, U404, C1849415): JLCPCB stock 76 and price (JLCPCB US$1.00 vs LCSC US$2.67 at 10+) → reserve 10 in the JLCPCB parts library; at the LCSC price ≈ 1,753 NTD per board (above the ceiling).
A59: 3 | B59: ="Cost is "&TEXT(Cost!F47,"#,##0")&" NTD per board — "&Cost!F52&", "&Cost!G51&"; "&Cost!G50&" (conservative) → the JLCPCB quote from the real BOM / CPL files after layout must pass the "&TEXT(Cost!F49,"#,##0")&" NTD ceiling before ordering." -> Cost is 1,647 NTD per board — WARNING, 53 NTD under the ceiling; 147 NTD over the target (9.8%) (conservative) → the JLCPCB quote from the real BOM / CPL files after layout must pass the 1,700 NTD ceiling before ordering.
A60: 4 | B60: JLCPCB assembly-fixture notes on the X202 and OPA2210 part pages → a possible fixture fee, not in the estimate (outside the ceiling) → confirm in the JLCPCB quote.
A61: 5 | B61: X202 (24.576 MHz oscillator, C2831388): the JLCPCB class is not shown on its part page → assumed Extended (conservative; its US$3.07 Extended fee is counted) — confirm in the JLCPCB quote.
A62: 6 | B62: Oscillator disable time and disabled-output state are not specified in the SCTF (X203) and YXC (X202) datasheets → measure on the Stage 2 proof-of-concept board (scope on the shared family-clock node); fallback: the DNF mux U205 + R215 (fit them, remove R210 and R211), already built on one of the two Stage 2 boards. Gate: Stage 2.
A63: 7 | B63: Stage 2 digital proof-of-concept board, now mandatory (layout gate: clock handover, all 8 rates, USB currents in every state): ≈ US$79 ≈ 2,500 NTD for two assembled boards (parts ≈ US$18, fees ≈ US$53 incl. 9 Extended types and X-ray of 4–5 leadless parts per board, PCBs ≈ US$8) — outside the board budget; Stage 1 stays ≈ US$48–57.
A64: 8 | B64: OPA2210 stability with the DAC pin capacitance and the 10 Ω + 660 pF feedback network → SPICE before layout (may change R427–R430 and C417–C420 / C427–C430).
A65: 9 | B65: Own USB Audio Class 2.0 firmware and CPLD logic (top risk: host compatibility of high-speed isochronous streaming with feedback) — owner decision 24 Sep 2026 (unchanged): Firmware: own UAC2 firmware on the CH32V307's high-speed USB port, built on WCH's register-level high-speed USB device examples; the CPLD logic is our own too. Reference: the USBAudioToI2S project (Apache-2.0) is kept only as a known-good comparison and reference; keep its license notices if any code is copied. TinyUSB is an alternative only if its CH32V307 high-speed audio path proves reliable. Descriptors: 0x80 (bus-powered) and 0xFA (500 mA); test VID/PID 1209:0001 during development only, a real PID before publishing; serial number from the chip's 96-bit unique ID. Gate (two-stage proof of concept; layout starts only after it passes): Stage 1 on three boards — WCH CH32V307V-EVT-R1, an AGM 2K-LUT CPLD board and an ES9018K2M I²S-input DAC board (≈ US$48–57); Stage 2 digital proof-of-concept board, now mandatory (two boards: shared family-clock node on one, mux U205 fitted on the other). Pass criteria: enumeration and host volume/mute on Windows, macOS and Linux; all 8 rates bit-perfect; PLL relock after every family change with no runt pulses; CPLD timing met at 80 MHz (system clock) and at the PLL output (49.152 MHz); USB currents in every state (attached, not configured ≤ 100 mA; configured digital ≤ 256 mA; suspend ≤ 2.5 mA).
A66: 10 | B66: Oscillator stock: X201 (80 MHz, C5179978) LCSC 2,503, X202 1,755 and X203 1,426 → enough for the 5-board run (5 of each); check again before ordering.
A67: 11 | B67: Other risks tracked in the Design Specification v0.6 (MCU / CPLD / oscillator currents incl. the USB Default-mode estimated maximum of 0.469 A — 31 mA margin, measured on the Stage 2 board before layout; AGRV2K I/O state during configuration; CH32V307 SPI/I²S link clock; USB suspend; DAC offset and null point; OPA1622 swing at the rails; LM27762 charge-pump resistance and the momentary negative-rail dropout at the 4.40 V stress corner; unplug pop and transient; 4.4 mm leg short; rail-stuck energy in High mode) are measurements or design checks with no purchasing change today.

Sheet Checks
A1: Checks — formula-based self-checks
A2: Each check recomputes a figure from the lists or the Cost sheet and compares it with the expected value. Two-sided checks: OK when |Difference| ≤ Tolerance. One-sided gate checks: OK / WARNING when Difference ≤ 0. Expected counts and totals are the cost-model results of 24 Sep 2026 for Parts List v0.4 (fifth review round) — update them when the BOM changes.
A4: Check | B4: Expected | C4: Actual | D4: Difference | E4: Tolerance | F4: Result | G4: Basis
A5: BOM lines in the Parts list | B5: 130 | C5: =COUNTA('Parts list'!$B$4:$B$133) -> 130 | D5: =C5-B5 -> 0 | E5: 0 | F5: =IF(ABS(D5)<=E5,"OK","CHECK") -> OK | G5: Parts list rows 4–133
A6: Fitted BOM lines | B6: 122 | C6: =Cost!B14 -> 122 | D6: =C6-B6 -> 0 | E6: 0 | F6: =IF(ABS(D6)<=E6,"OK","CHECK") -> OK | G6: Cost sheet (Fit = Yes, incl. the bare-PCB row)
A7: SMT-placed parts per board | B7: 231 | C7: =Cost!B15 -> 231 | D7: =C7-B7 -> 0 | E7: 0 | F7: =IF(ABS(D7)<=E7,"OK","CHECK") -> OK | G7: Cost sheet (Fit = Yes, SMT joints > 0)
A8: Extended part types (incl. through-hole) | B8: 19 | C8: =Cost!B17 -> 19 | D8: =C8-B8 -> 0 | E8: 0 | F8: =IF(ABS(D8)<=E8,"OK","CHECK") -> OK | G8: Cost sheet (drives the US$3.07-per-type fee)
A9: Basic part types | B9: 29 | C9: =Cost!B18 -> 29 | D9: =C9-B9 -> 0 | E9: 0 | F9: =IF(ABS(D9)<=E9,"OK","CHECK") -> OK | G9: Cost sheet
A10: Leadless (X-ray) parts per board | B10: 8 | C10: =Cost!B22 -> 8 | D10: =C10-B10 -> 0 | E10: 0 | F10: =IF(ABS(D10)<=E10,"OK","CHECK") -> OK | G10: Cost sheet (drives the X-ray fee)
A11: SMT joints per board | B11: 690 | C11: =Cost!B20 -> 690 | D11: =C11-B11 -> 0 | E11: 0 | F11: =IF(ABS(D11)<=E11,"OK","CHECK") -> OK | G11: Cost sheet (drives the SMT joint fee)
A12: Through-hole joints per board | B12: 7 | C12: =Cost!B21 -> 7 | D12: =C12-B12 -> 0 | E12: 0 | F12: =IF(ABS(D12)<=E12,"OK","CHECK") -> OK | G12: Cost sheet (drives the through-hole fee)
A13: Purchase lines | B13: 48 | C13: =COUNTA('Purchasing list'!$C$4:$C$51) -> 48 | D13: =C13-B13 -> 0 | E13: 0 | F13: =IF(ABS(D13)<=E13,"OK","CHECK") -> OK | G13: Purchasing list rows 4–51, one per LCSC number
A14: Purchasing lines, class Extended = Extended part types | B14: =Cost!B17 -> 19 | C14: =COUNTIF('Purchasing list'!$H$4:$H$51,"Extended") -> 19 | D14: =C14-B14 -> 0 | E14: 0 | F14: =IF(ABS(D14)<=E14,"OK","CHECK") -> OK | G14: Purchasing list vs Parts list helper count
A15: Purchasing lines, class Basic = Basic part types | B15: =Cost!B18 -> 29 | C15: =COUNTIF('Purchasing list'!$H$4:$H$51,"Basic") -> 29 | D15: =C15-B15 -> 0 | E15: 0 | F15: =IF(ABS(D15)<=E15,"OK","CHECK") -> OK | G15: Purchasing list vs Parts list helper count
A16: Purchasing qty per board = SMT-placed + through-hole parts | B16: =Cost!B15+Cost!B16 -> 232 | C16: =SUM('Purchasing list'!$J$4:$J$51) -> 232 | D16: =C16-B16 -> 0 | E16: 0 | F16: =IF(ABS(D16)<=E16,"OK","CHECK") -> OK | G16: every fitted part appears once in the Purchasing list
A17: Purchasing cost before the minimum = Parts list line costs (US$, 5-board run) | B17: =SUMIFS('Parts list'!$S$4:$S$133,'Parts list'!$B$4:$B$133,"<>PCB") -> 137.941 | C17: =SUMPRODUCT('Purchasing list'!$K$4:$K$51,'Purchasing list'!$L$4:$L$51) -> 137.941 | D17: =C17-B17 -> 0 | E17: 0.005 | F17: =IF(ABS(D17)<=E17,"OK","CHECK") -> OK | G17: purchasing prices and quantities match the Parts list
A18: Purchasing per-board cost = Cost sheet (US$, 100-board tier) | B18: =Cost!B28 -> 19.6486 | C18: =SUM('Purchasing list'!$Q$4:$Q$51) -> 19.6486 | D18: =C18-B18 -> 0 | E18: 0.005 | F18: =IF(ABS(D18)<=E18,"OK","CHECK") -> OK | G18: purchasing prices and quantities match the Parts list
A19: Total, 5-board run: Cost sheet = purchasing lines + PCB + fee lines (US$) | B19: =Cost!E46 -> 259.804 | C19: =SUM('Purchasing list'!$P$4:$P$51)+SUMIFS('Parts list'!$S$4:$S$133,'Parts list'!$B$4:$B$133,"PCB")+SUM(Cost!$E$33:$E$39) -> 259.804 | D19: =C19-B19 -> 0 | E19: 0.005 | F19: =IF(ABS(D19)<=E19,"OK","CHECK") -> OK | G19: recomputed from the Purchasing list, the Parts list PCB row and the seven fee lines
A20: Summary total = Cost sheet total (NTD) | B20: =Cost!F46 -> 8235.7868 | C20: =Summary!B9 -> 8235.7868 | D20: =C20-B20 -> 0 | E20: 0.005 | F20: =IF(ABS(D20)<=E20,"OK","CHECK") -> OK | G20: Summary links to the Cost sheet
A21: Parts, 5-board run (US$) | B21: 138.84 | C21: =Cost!E43 -> 138.84 | D21: =C21-B21 -> 0 | E21: 0.01 | F21: =IF(ABS(D21)<=E21,"OK","CHECK") -> OK | G21: cost-model result 24 Sep 2026 (Parts List v0.4)
A22: Total, 5-board run (US$) | B22: 259.8 | C22: =Cost!E46 -> 259.804 | D22: =C22-B22 -> 0.004 | E22: 0.01 | F22: =IF(ABS(D22)<=E22,"OK","CHECK") -> OK | G22: cost-model result 24 Sep 2026 (Parts List v0.4)
A23: Per-board total, 5-board run (NTD) | B23: 1647 | C23: =Cost!F47 -> 1647.1574 | D23: =C23-B23 -> 0.15736 | E23: 1 | F23: =IF(ABS(D23)<=E23,"OK","CHECK") -> OK | G23: cost-model result 24 Sep 2026 (Parts List v0.4; ±1 NTD)
A24: Block 4 parts per board: I/V converters and output legs (NTD) | B24: 202 | C24: =Summary!C40 -> 201.96704 | D24: =C24-B24 -> -0.03296 | E24: 1 | F24: =IF(ABS(D24)<=E24,"OK","CHECK") -> OK | G24: cost-model result (rounded; sample-run tier, before the minimum)
A25: 100-unit reference per board (NTD) | B25: 799 | C25: =Cost!F79 -> 798.52934 | D25: =C25-B25 -> -0.47066 | E25: 1 | F25: =IF(ABS(D25)<=E25,"OK","CHECK") -> OK | G25: cost-model result 24 Sep 2026 (Parts List v0.4; ±1 NTD)
A26: Per board without the conservative fee items (NTD) | B26: 1550 | C26: =Cost!F58 -> 1549.7116 | D26: =C26-B26 -> -0.28844 | E26: 1 | F26: =IF(ABS(D26)<=E26,"OK","CHECK") -> OK | G26: without the through-hole Extended fee and the X-ray of the three oscillators: ≈ 1,550 NTD per board (±1 NTD)
A27: Fitted parts without an LCSC number or with a class other than Basic / Extended | B27: 0 | C27: =COUNTIFS('Parts list'!$K$4:$K$133,"Yes",'Parts list'!$B$4:$B$133,"<>PCB")-COUNTIFS('Parts list'!$K$4:$K$133,"Yes",'Parts list'!$B$4:$B$133,"<>PCB",'Parts list'!$I$4:$I$133,"C*",'Parts list'!$J$4:$J$133,"Basic")-COUNTIFS('Parts list'!$K$4:$K$133,"Yes",'Parts list'!$B$4:$B$133,"<>PCB",'Parts list'!$I$4:$I$133,"C*",'Parts list'!$J$4:$J$133,"Extended") -> 0 | D27: =C27-B27 -> 0 | E27: 0 | F27: =IF(ABS(D27)<=E27,"OK","CHECK") -> OK | G27: every fitted part line (bare-PCB row excluded) has an LCSC number (C…) and JLCPCB class Basic or Extended — no "likely", no "Assign"
A28: Per-board total within the ceiling (NTD) | B28: =Cost!F49 -> 1700 | C28: =Cost!F47 -> 1647.1574 | D28: =C28-B28 -> -52.84264 | E28: 0 | F28: =IF(D28<=E28,"OK","CHECK") -> OK | G28: ="one-sided: OK at or under the "&TEXT(B28,"#,##0")&" NTD ceiling (hard order gate, set when the third oscillator was added; the JLCPCB quote must pass it); above it the gate is FAIL" -> one-sided: OK at or under the 1,700 NTD ceiling (hard order gate, set when the third oscillator was added; the JLCPCB quote must pass it); above it the gate is FAIL
A29: Per-board total within the target (NTD) | B29: =Cost!F48 -> 1500 | C29: =Cost!F47 -> 1647.1574 | D29: =C29-B29 -> 147.15736 | E29: 0 | F29: =IF(D29<=E29,"OK","WARNING") -> WARNING | G29: =IF(D29<=E29,"within the target","over the target by "&TEXT(D29,"#,##0")&" NTD per board — allowed up to the ceiling (reported, not a failed check)") -> over the target by 147 NTD per board — allowed up to the ceiling (reported, not a failed check)
A30: Cost-gate status (target 1,500 WARN / ceiling 1,700 FAIL) | B30: WARNING | C30: =Cost!F52 -> WARNING | F30: =IF(C30=B30,"OK","CHECK") -> OK | G30: ="expected WARNING: "&TEXT(C23,"#,##0")&" NTD per board, "&TEXT(B28-C23,"#,##0")&" NTD under the "&TEXT(B28,"#,##0")&" NTD ceiling; on 24 Sep 2026 the owner confirmed the budget is flexible as long as it does not surge" -> expected WARNING: 1,647 NTD per board, 53 NTD under the 1,700 NTD ceiling; on 24 Sep 2026 the owner confirmed the budget is flexible as long as it does not surge
A32: All checks | F32: =IF(COUNTIF(F5:F30,"CHECK")>0,TEXT(COUNTIF(F5:F30,"CHECK"),"0")&" to check",IF(COUNTIF(F5:F30,"WARNING")>0,"ALL OK — target WARNING","ALL OK")) -> ALL OK — target WARNING | G32: =TEXT(COUNTIF(F5:F30,"OK"),"0")&" of "&TEXT(ROWS(F5:F30),"0")&" checks OK; "&TEXT(COUNTIF(F5:F30,"WARNING"),"0")&" WARNING (target overrun, within the ceiling); "&TEXT(COUNTIF(F5:F30,"CHECK"),"0")&" to check" -> 25 of 26 checks OK; 1 WARNING (target overrun, within the ceiling); 0 to check
A34: External links
A35: Every formula in this workbook references only its own sheets (Summary, Parts list, Purchasing list, Cost, Notes & open items, Checks); there are no external workbook links. Copying a sheet into another workbook can create links — repeat the file check after any copy.
A36: File check at save (Parts List v0.4, 24 Sep 2026): the saved .xlsx opened as a zip has no xl/externalLinks part and no externalReferences entry; none of its 1,187 cell formulas (nor any table-column or conditional-format formula) contains "["; recalculation shows no formula errors.
