Workbook

Sheet Summary
A1: USB DAC + Balanced Headphone Amplifier — Parts List v0.2
A2: Diego Yang · 23 Sep 2026, revised 24 Sep 2026 (DAC current-mode output, option B) · cost-driven redesign (v0.4 architecture) · companion to Design Specification v0.4 and Schematic Design Notes v0.3 · supersedes Parts List v0.1
A4: 5-board sample run — cost gate
A5: Key figure | B5: Value | C5: Unit | D5: Basis
A6: Parts (LCSC 1–9-piece prices) | B6: =Cost!F41 -> 4491.145 | C6: NTD | D6: ="US$ "&TEXT(Cost!E41,"#,##0.00")&"; includes the US$"&TEXT(Cost!B8,"0.00")&" minimum per estimated passive line" -> US$ 141.68; includes the US$0.10 minimum per estimated passive line
A7: Bare 4-layer PCBs (estimate) | B7: =Cost!F42 -> 317 | C7: NTD | D7: ="US$ "&TEXT(Cost!E42,"#,##0.00")&" for "&TEXT(Cost!B6,"0")&" boards" -> US$ 10.00 for 5 boards
A8: JLCPCB Economic PCBA fees | B8: =Cost!F43 -> 2872.8442 | C8: NTD | D8: ="US$ "&TEXT(Cost!E43,"#,##0.00")&"; itemised on the Cost sheet" -> US$ 90.63; itemised on the Cost sheet
A9: Total, 5-board run | B9: =Cost!F44 -> 7680.9892 | C9: NTD | D9: ="US$ "&TEXT(Cost!E44,"#,##0.00")&" at "&TEXT(Cost!B5,"0.0")&" NTD per US$" -> US$ 242.30 at 31.7 NTD per US$
A10: Per board | B10: =Cost!F45 -> 1536.1978 | C10: NTD | D10: ="US$ "&TEXT(Cost!E45,"#,##0.00")&" per board — the cost-gate figure" -> US$ 48.46 per board — the cost-gate figure
A11: Target per board | B11: =Cost!F46 -> 1500 | C11: NTD | D11: =TEXT(Cost!B10*Cost!B6,"#,##0")&" NTD for "&TEXT(Cost!B6,"0")&" boards; WARNING above; incl. bare PCBs and assembly fees; excl. shipping, import tax, programmers, enclosure" -> 7,500 NTD for 5 boards; WARNING above; incl. bare PCBs and assembly fees; excl. shipping, import tax, programmers, enclosure
A12: Approved ceiling per board | B12: =Cost!F47 -> 1550 | C12: NTD | D12: owner decision 24 Sep 2026 ("a little bit off-budget is acceptable"); FAIL above
A13: Margin to the target | B13: =Cost!F48 -> -36.19785 | C13: NTD per board | D13: =Cost!G48 -> 36 NTD over the target (2.4%)
A14: Margin to the approved ceiling | B14: =Cost!F49 -> 13.80215 | C14: NTD per board | D14: =Cost!G49 -> 14 NTD under the approved ceiling
A15: Cost-gate status | B15: =Cost!F50 -> WARNING | D15: =Cost!G50 -> PASS ≤ 1,500 NTD per board (target); WARNING ≤ 1,550 (approved ceiling); FAIL > 1,550
A16: Self-checks | B16: =Checks!F26 -> ALL OK — target WARNING | D16: Checks sheet: counts, cross-sheet totals, the 1,536 NTD result and the gate rule
A18: Counts
A19: Count | B19: Value | C19: Unit | D19: Basis
A20: BOM lines | B20: =COUNTA('Parts list'!$B$4:$B$84) -> 81 | C20: lines | D20: every component of every circuit
A21: Fitted lines | B21: =Cost!B14 -> 76 | C21: lines | D21: Fit = Yes, including the bare-PCB row
A22: SMT-placed parts per board | B22: =Cost!B15 -> 181 | C22: parts | D22: ="plus "&TEXT(Cost!B16,"0")&" through-hole part (4.4 mm jack J701)" -> plus 1 through-hole part (4.4 mm jack J701)
A23: Extended part types | B23: =Cost!B17 -> 14 | C23: types | D23: ="US$"&TEXT(Cost!C33,"0.00")&" each on the sample run" -> US$3.07 each on the sample run
A24: Basic part types | B24: =Cost!B18 -> 39 | C24: types | D24: no per-type fee; "Basic (likely)" parts still to confirm
A25: Leadless (X-ray) parts per board | B25: =Cost!B21 -> 7 | C25: parts | D25: CPLD, ES9018K2M, 2 × OPA1622, LM27762, 2 oscillators
A26: SMT joints per board | B26: =Cost!B20 -> 579 | C26: joints | D26: Qty × SMT joints per part, fitted lines
A27: Purchase lines | B27: =COUNTA('Purchasing list'!$C$4:$C$57) -> 54 | C27: lines | D27: fitted parts merged by part number / specification
A29: Reference only — 100-unit build
A30: Key figure | B30: Value | C30: Unit | D30: Basis
A31: Total per board, 100-unit build | B31: =Cost!F77 -> 772.29125 | C31: NTD | D31: ="JLCPCB Standard PCBA, parts at the 100-board tier; US$ "&TEXT(Cost!E77,"#,##0.00")&" per board — not the budget basis" -> JLCPCB Standard PCBA, parts at the 100-board tier; US$ 24.36 per board — not the budget basis
A33: Parts cost per board by block (1–9-piece prices)
A34: Block | B34: US$ per board | C34: NTD per board | D34: Main cost items
A35: 1 USB-C input and protection | B35: {=SUMPRODUCT(('Parts list'!$A$4:$A$84=$A35)*('Parts list'!$K$4:$K$84="Yes")*('Parts list'!$B$4:$B$84<>"PCB")*'Parts list'!$C$4:$C$84*'Parts list'!$N$4:$N$84)} -> 0.4073 | C35: =B35*Cost!$B$5 -> 12.91141 | D35: USB-C receptacle, USBLC6-2SC6 ESD array
A36: 2 USB audio bridge (CH32V307 + CPLD) | B36: {=SUMPRODUCT(('Parts list'!$A$4:$A$84=$A36)*('Parts list'!$K$4:$K$84="Yes")*('Parts list'!$B$4:$B$84<>"PCB")*'Parts list'!$C$4:$C$84*'Parts list'!$N$4:$N$84)} -> 6.3363 | C36: =B36*Cost!$B$5 -> 200.86071 | D36: CH32V307RCT6, AGRV2KQ32 CPLD, 8 MHz crystal, 2 audio oscillators
A37: 3 DAC (ES9018K2M) | B37: {=SUMPRODUCT(('Parts list'!$A$4:$A$84=$A37)*('Parts list'!$K$4:$K$84="Yes")*('Parts list'!$B$4:$B$84<>"PCB")*'Parts list'!$C$4:$C$84*'Parts list'!$N$4:$N$84)} -> 3.8734 | C37: =B37*Cost!$B$5 -> 122.78678 | D37: ES9018K2M, LP5907-3.3 and AMS1117-ADJ LDOs
A38: 4 I/V converters and output legs (2 × OPA1678 + 2 × OPA1622) | B38: {=SUMPRODUCT(('Parts list'!$A$4:$A$84=$A38)*('Parts list'!$K$4:$K$84="Yes")*('Parts list'!$B$4:$B$84<>"PCB")*'Parts list'!$C$4:$C$84*'Parts list'!$N$4:$N$84)} -> 8.3232 | C38: =B38*Cost!$B$5 -> 263.84544 | D38: 2 × OPA1678 I/V converters, 2 × OPA1622, 16 × 2.00 kΩ 0.1 % resistors
A39: 5 Power (digital 3.3 V and analog ±4.5 V) | B39: {=SUMPRODUCT(('Parts list'!$A$4:$A$84=$A39)*('Parts list'!$K$4:$K$84="Yes")*('Parts list'!$B$4:$B$84<>"PCB")*'Parts list'!$C$4:$C$84*'Parts list'!$N$4:$N$84)} -> 1.2794 | C39: =B39*Cost!$B$5 -> 40.55698 | D39: LM27762, ME6211C33
A40: 6 Protection and control | B40: {=SUMPRODUCT(('Parts list'!$A$4:$A$84=$A40)*('Parts list'!$K$4:$K$84="Yes")*('Parts list'!$B$4:$B$84<>"PCB")*'Parts list'!$C$4:$C$84*'Parts list'!$N$4:$N$84)} -> 0.339 | C40: =B40*Cost!$B$5 -> 10.7463 | D40: LM393, fault-latch transistors
A41: 7 Outputs, indicators, test, board | B41: {=SUMPRODUCT(('Parts list'!$A$4:$A$84=$A41)*('Parts list'!$K$4:$K$84="Yes")*('Parts list'!$B$4:$B$84<>"PCB")*'Parts list'!$C$4:$C$84*'Parts list'!$N$4:$N$84)} -> 7.4297 | C41: =B41*Cost!$B$5 -> 235.52149 | D41: ="4.4 mm jack J701 ("&TEXT(SUMIFS('Parts list'!$N$4:$N$84,'Parts list'!$B$4:$B$84,"J701")*Cost!$B$5,"#,##0")&" NTD), 3.5 mm jack, ESD diodes, LEDs" -> 4.4 mm jack J701 (218 NTD), 3.5 mm jack, ESD diodes, LEDs
A42: Minimum-spend allowance (estimated passive lines) | B42: =Cost!B24/Cost!B6 -> 0.347 | C42: =B42*Cost!$B$5 -> 10.9999 | D42: ="US$"&TEXT(Cost!B8,"0.00")&" minimum per estimated passive line, spread over "&TEXT(Cost!B6,"0")&" boards" -> US$0.10 minimum per estimated passive line, spread over 5 boards
A43: Parts per board | B43: =SUM(B35:B42) -> 28.3353 | C43: =B43*Cost!$B$5 -> 898.22901 | D43: ="= Cost sheet parts ÷ "&TEXT(Cost!B6,"0")&" boards (bare PCB excluded)" -> = Cost sheet parts ÷ 5 boards (bare PCB excluded)
A45: What changed from v0.1
A46: Area | B46: Change
A47: Power input | B47: Single USB-C 5 V port (data + power), bus-powered within the USB 2.0 500 mA budget.
A48: USB bridge | B48: WCH CH32V307RCT6 MCU + AGM AGRV2KQ32 CPLD USB-to-I²S bridge, following the open-source USBAudioToI2S project (replaces the XMOS XU316).
A49: DAC | B49: ESS ES9018K2M (replaces the AKM AK4493).
A50: Output stage | B50: DAC in current mode (option B, 24 Sep 2026): 2 × TI OPA1678 I/V converters per the ESS application circuit, feeding 2 × TI OPA1622 as four difference amplifiers (U401 = L+ / L−, U402 = R+ / R−); fixed gain.
A51: Analog power | B51: TI LM27762 charge pump + low-noise LDOs for ±4.5 V.
A52: Protection | B52: No relays: an LM393 window comparator sets a 3.3 V hardware fault latch that pulls both OPA1622 EN pins and the LM27762 EN+ / EN− low.
A53: Removed | B53: USB PD power port, CH224A, eFuse, LM317 / LM337, relays, gain switch, XU316, AK4493, OPA1612.
A54: Sourcing | B54: Every part is now an LCSC / JLCPCB part (some LCSC numbers still to assign — see Notes & open items).
A55: Cost basis | B55: The cost gate now applies to the 5-board sample run (incl. bare PCBs and assembly fees): target 1,500 NTD per board, approved ceiling 1,550 NTD per board (owner decision 24 Sep 2026); the 100-unit build is a reference line only.

Sheet Parts list
A1: Parts list — every BOM line, grouped by block
A2: Unit prices in US$ at the LCSC 1–9-piece tier (5-board sample run) and the 100-board tier (reference). Line costs use the inputs on the Cost sheet: boards per run and the minimum spend per estimated passive line. Helper columns U–V count distinct SMT part types.
A3: Block | B3: Designators | C3: Qty per board | D3: Description | E3: Value | F3: Package | G3: Rating / tolerance | H3: Part number (MPN) | I3: Source / LCSC no. | J3: JLCPCB library type | K3: Fit | L3: Leadless (X-ray) | M3: SMT joints per part | N3: Unit price US$ (1–9 pcs, sample run) | O3: Unit price US$ (100-board tier) | P3: Price basis | Q3: Qty for 5-board run | R3: Line cost US$, 5-board run | S3: Line cost US$, 100-board run (reference) | T3: Notes | U3: Part-type key (helper) | V3: New SMT part type (helper)
A4: 1 USB-C input and protection | B4: J101 | C4: 1 | D4: USB-C receptacle, 16-pin, USB 2.0 (data + 5 V power) | E4: — | F4: SMD | G4: 20 V, 5 A | H4: HRO TYPE-C-31-M-12 | I4: LCSC C165948 | J4: Extended | K4: Yes | M4: 20 | N4: 0.1879 | O4: 0.129 | P4: Quote | Q4: =IF($K4="Yes",$C4*Cost!$B$6,0) -> 5 | R4: =IF($K4<>"Yes",0,IF(AND($P4="Estimate",$N4>0,$B4<>"PCB"),MAX($C4*Cost!$B$6*$N4,Cost!$B$8),$C4*Cost!$B$6*$N4)) -> 0.9395 | S4: =IF($K4="Yes",$C4*Cost!$B$7*$O4,0) -> 12.9 | U4: =IF(AND($K4="Yes",$M4>0,$B4<>"PCB"),IF(LEFT($H4,7)="Generic","G|"&$E4&"|"&$F4&"|"&$G4,"M|"&$H4),"") -> M|HRO TYPE-C-31-M-12 | V4: =IF($U4="",0,IF(COUNTIF($U$4:$U4,$U4)=1,1,0)) -> 1
A5: 1 USB-C input and protection | B5: R101, R102 | C5: 2 | D5: Resistor, CC1/CC2 pull-down (Rd, USB-C sink) | E5: 5.1 kΩ | F5: 0402 | G5: 1% | H5: Generic (match a JLCPCB Basic part) | I5: Assign | J5: Basic (likely) | K5: Yes | M5: 2 | N5: 0.004 | O5: 0.001 | P5: Estimate | Q5: =IF($K5="Yes",$C5*Cost!$B$6,0) -> 10 | R5: =IF($K5<>"Yes",0,IF(AND($P5="Estimate",$N5>0,$B5<>"PCB"),MAX($C5*Cost!$B$6*$N5,Cost!$B$8),$C5*Cost!$B$6*$N5)) -> 0.1 | S5: =IF($K5="Yes",$C5*Cost!$B$7*$O5,0) -> 0.2 | U5: =IF(AND($K5="Yes",$M5>0,$B5<>"PCB"),IF(LEFT($H5,7)="Generic","G|"&$E5&"|"&$F5&"|"&$G5,"M|"&$H5),"") -> G|5.1 kΩ|0402|1% | V5: =IF($U5="",0,IF(COUNTIF($U$4:$U5,$U5)=1,1,0)) -> 1
A6: 1 USB-C input and protection | B6: R103 | C6: 1 | D6: Resistor, shield to GND (bleed) | E6: 1 MΩ | F6: 0603 | G6: 1% | H6: Generic (match a JLCPCB Basic part) | I6: Assign | J6: Basic (likely) | K6: Yes | M6: 2 | N6: 0.004 | O6: 0.0012 | P6: Estimate | Q6: =IF($K6="Yes",$C6*Cost!$B$6,0) -> 5 | R6: =IF($K6<>"Yes",0,IF(AND($P6="Estimate",$N6>0,$B6<>"PCB"),MAX($C6*Cost!$B$6*$N6,Cost!$B$8),$C6*Cost!$B$6*$N6)) -> 0.1 | S6: =IF($K6="Yes",$C6*Cost!$B$7*$O6,0) -> 0.12 | U6: =IF(AND($K6="Yes",$M6>0,$B6<>"PCB"),IF(LEFT($H6,7)="Generic","G|"&$E6&"|"&$F6&"|"&$G6,"M|"&$H6),"") -> G|1 MΩ|0603|1% | V6: =IF($U6="",0,IF(COUNTIF($U$4:$U6,$U6)=1,1,0)) -> 1
A7: 1 USB-C input and protection | B7: C101 | C7: 1 | D7: Capacitor, shield to GND (RF) | E7: 4.7 nF | F7: 0402 | G7: 50 V X7R | H7: Generic (match a JLCPCB Basic part) | I7: Assign | J7: Basic (likely) | K7: Yes | M7: 2 | N7: 0.005 | O7: 0.0015 | P7: Estimate | Q7: =IF($K7="Yes",$C7*Cost!$B$6,0) -> 5 | R7: =IF($K7<>"Yes",0,IF(AND($P7="Estimate",$N7>0,$B7<>"PCB"),MAX($C7*Cost!$B$6*$N7,Cost!$B$8),$C7*Cost!$B$6*$N7)) -> 0.1 | S7: =IF($K7="Yes",$C7*Cost!$B$7*$O7,0) -> 0.15 | U7: =IF(AND($K7="Yes",$M7>0,$B7<>"PCB"),IF(LEFT($H7,7)="Generic","G|"&$E7&"|"&$F7&"|"&$G7,"M|"&$H7),"") -> G|4.7 nF|0402|50 V X7R | V7: =IF($U7="",0,IF(COUNTIF($U$4:$U7,$U7)=1,1,0)) -> 1
A8: 1 USB-C input and protection | B8: U101 | C8: 1 | D8: ESD array, D+, D−, VBUS | E8: — | F8: SOT-23-6 | G8: 5.25 V | H8: ST USBLC6-2SC6 | I8: LCSC C7519 | J8: Extended | K8: Yes | M8: 6 | N8: 0.1844 | O8: 0.13 | P8: Quote | Q8: =IF($K8="Yes",$C8*Cost!$B$6,0) -> 5 | R8: =IF($K8<>"Yes",0,IF(AND($P8="Estimate",$N8>0,$B8<>"PCB"),MAX($C8*Cost!$B$6*$N8,Cost!$B$8),$C8*Cost!$B$6*$N8)) -> 0.922 | S8: =IF($K8="Yes",$C8*Cost!$B$7*$O8,0) -> 13 | U8: =IF(AND($K8="Yes",$M8>0,$B8<>"PCB"),IF(LEFT($H8,7)="Generic","G|"&$E8&"|"&$F8&"|"&$G8,"M|"&$H8),"") -> M|ST USBLC6-2SC6 | V8: =IF($U8="",0,IF(COUNTIF($U$4:$U8,$U8)=1,1,0)) -> 1
A9: 1 USB-C input and protection | B9: FB101 | C9: 1 | D9: Ferrite bead, VBUS → 5V_SYS (keeps switching noise off the cable) | E9: 600 Ω | F9: 0603 | G9: 1.3 A, 0.15 Ω | H9: Sunlord GZ1608D601TF | I9: LCSC C1015 (verify Basic) | J9: Basic (likely) | K9: Yes | M9: 2 | N9: 0.01 | O9: 0.003 | P9: Estimate | Q9: =IF($K9="Yes",$C9*Cost!$B$6,0) -> 5 | R9: =IF($K9<>"Yes",0,IF(AND($P9="Estimate",$N9>0,$B9<>"PCB"),MAX($C9*Cost!$B$6*$N9,Cost!$B$8),$C9*Cost!$B$6*$N9)) -> 0.1 | S9: =IF($K9="Yes",$C9*Cost!$B$7*$O9,0) -> 0.3 | U9: =IF(AND($K9="Yes",$M9>0,$B9<>"PCB"),IF(LEFT($H9,7)="Generic","G|"&$E9&"|"&$F9&"|"&$G9,"M|"&$H9),"") -> M|Sunlord GZ1608D601TF | V9: =IF($U9="",0,IF(COUNTIF($U$4:$U9,$U9)=1,1,0)) -> 1
A10: 1 USB-C input and protection | B10: C102 | C10: 1 | D10: Capacitor, VBUS at the connector (total VBUS capacitance budget ≤ 10 µF, see notes) | E10: 1 µF | F10: 0402 | G10: 10 V X5R | H10: Generic (match a JLCPCB Basic part) | I10: Assign | J10: Basic (likely) | K10: Yes | M10: 2 | N10: 0.008 | O10: 0.003 | P10: Estimate | Q10: =IF($K10="Yes",$C10*Cost!$B$6,0) -> 5 | R10: =IF($K10<>"Yes",0,IF(AND($P10="Estimate",$N10>0,$B10<>"PCB"),MAX($C10*Cost!$B$6*$N10,Cost!$B$8),$C10*Cost!$B$6*$N10)) -> 0.1 | S10: =IF($K10="Yes",$C10*Cost!$B$7*$O10,0) -> 0.3 | U10: =IF(AND($K10="Yes",$M10>0,$B10<>"PCB"),IF(LEFT($H10,7)="Generic","G|"&$E10&"|"&$F10&"|"&$G10,"M|"&$H10),"") -> G|1 µF|0402|10 V X5R | V10: =IF($U10="",0,IF(COUNTIF($U$4:$U10,$U10)=1,1,0)) -> 1
A11: 2 USB audio bridge (CH32V307 + CPLD) | B11: U201 | C11: 1 | D11: MCU, RISC-V, USB 2.0 High-Speed with built-in PHY; runs the open-source UAC2 firmware | E11: — | F11: LQFP-64 10 × 10 mm | G11: 144 MHz, 3.3 V | H11: WCH CH32V307RCT6 | I11: LCSC C2988083 | J11: Extended | K11: Yes | M11: 64 | N11: 3.45 | O11: 2.3305 | P11: Quote | Q11: =IF($K11="Yes",$C11*Cost!$B$6,0) -> 5 | R11: =IF($K11<>"Yes",0,IF(AND($P11="Estimate",$N11>0,$B11<>"PCB"),MAX($C11*Cost!$B$6*$N11,Cost!$B$8),$C11*Cost!$B$6*$N11)) -> 17.25 | S11: =IF($K11="Yes",$C11*Cost!$B$7*$O11,0) -> 233.05 | U11: =IF(AND($K11="Yes",$M11>0,$B11<>"PCB"),IF(LEFT($H11,7)="Generic","G|"&$E11&"|"&$F11&"|"&$G11,"M|"&$H11),"") -> M|WCH CH32V307RCT6 | V11: =IF($U11="",0,IF(COUNTIF($U$4:$U11,$U11)=1,1,0)) -> 1
A12: 2 USB audio bridge (CH32V307 + CPLD) | B12: Y201 | C12: 1 | D12: Crystal, CH32V307 HSE (USB HS PHY reference; frequency per WCH EVT / reference schematic) | E12: 8 MHz | F12: 3.2 × 2.5 mm | G12: ±20 ppm | H12: Generic (match a JLCPCB Basic part) | I12: Assign | J12: Basic (likely) | K12: Yes | M12: 4 | N12: 0.1 | O12: 0.08 | P12: Estimate | Q12: =IF($K12="Yes",$C12*Cost!$B$6,0) -> 5 | R12: =IF($K12<>"Yes",0,IF(AND($P12="Estimate",$N12>0,$B12<>"PCB"),MAX($C12*Cost!$B$6*$N12,Cost!$B$8),$C12*Cost!$B$6*$N12)) -> 0.5 | S12: =IF($K12="Yes",$C12*Cost!$B$7*$O12,0) -> 8 | U12: =IF(AND($K12="Yes",$M12>0,$B12<>"PCB"),IF(LEFT($H12,7)="Generic","G|"&$E12&"|"&$F12&"|"&$G12,"M|"&$H12),"") -> G|8 MHz|3.2 × 2.5 mm|±20 ppm | V12: =IF($U12="",0,IF(COUNTIF($U$4:$U12,$U12)=1,1,0)) -> 1
A13: 2 USB audio bridge (CH32V307 + CPLD) | B13: C201, C202 | C13: 2 | D13: Capacitor, crystal load | E13: 20 pF | F13: 0402 | G13: 50 V C0G | H13: Generic (match a JLCPCB Basic part) | I13: Assign | J13: Basic (likely) | K13: Yes | M13: 2 | N13: 0.005 | O13: 0.0015 | P13: Estimate | Q13: =IF($K13="Yes",$C13*Cost!$B$6,0) -> 10 | R13: =IF($K13<>"Yes",0,IF(AND($P13="Estimate",$N13>0,$B13<>"PCB"),MAX($C13*Cost!$B$6*$N13,Cost!$B$8),$C13*Cost!$B$6*$N13)) -> 0.1 | S13: =IF($K13="Yes",$C13*Cost!$B$7*$O13,0) -> 0.3 | U13: =IF(AND($K13="Yes",$M13>0,$B13<>"PCB"),IF(LEFT($H13,7)="Generic","G|"&$E13&"|"&$F13&"|"&$G13,"M|"&$H13),"") -> G|20 pF|0402|50 V C0G | V13: =IF($U13="",0,IF(COUNTIF($U$4:$U13,$U13)=1,1,0)) -> 1
A14: 2 USB audio bridge (CH32V307 + CPLD) | B14: C203–C210 | C14: 8 | D14: Capacitor, CH32V307 VDD/VDDA/VIO decoupling (one per supply pin) | E14: 100 nF | F14: 0402 | G14: 16 V X7R | H14: Generic (match a JLCPCB Basic part) | I14: Assign | J14: Basic (likely) | K14: Yes | M14: 2 | N14: 0.005 | O14: 0.0015 | P14: Estimate | Q14: =IF($K14="Yes",$C14*Cost!$B$6,0) -> 40 | R14: =IF($K14<>"Yes",0,IF(AND($P14="Estimate",$N14>0,$B14<>"PCB"),MAX($C14*Cost!$B$6*$N14,Cost!$B$8),$C14*Cost!$B$6*$N14)) -> 0.2 | S14: =IF($K14="Yes",$C14*Cost!$B$7*$O14,0) -> 1.2 | U14: =IF(AND($K14="Yes",$M14>0,$B14<>"PCB"),IF(LEFT($H14,7)="Generic","G|"&$E14&"|"&$F14&"|"&$G14,"M|"&$H14),"") -> G|100 nF|0402|16 V X7R | V14: =IF($U14="",0,IF(COUNTIF($U$4:$U14,$U14)=1,1,0)) -> 1
A15: 2 USB audio bridge (CH32V307 + CPLD) | B15: C211 | C15: 1 | D15: Capacitor, CH32V307 3V3 bulk | E15: 10 µF | F15: 0805 | G15: 10 V X5R | H15: Generic (match a JLCPCB Basic part) | I15: Assign | J15: Basic (likely) | K15: Yes | M15: 2 | N15: 0.02 | O15: 0.01 | P15: Estimate | Q15: =IF($K15="Yes",$C15*Cost!$B$6,0) -> 5 | R15: =IF($K15<>"Yes",0,IF(AND($P15="Estimate",$N15>0,$B15<>"PCB"),MAX($C15*Cost!$B$6*$N15,Cost!$B$8),$C15*Cost!$B$6*$N15)) -> 0.1 | S15: =IF($K15="Yes",$C15*Cost!$B$7*$O15,0) -> 1 | U15: =IF(AND($K15="Yes",$M15>0,$B15<>"PCB"),IF(LEFT($H15,7)="Generic","G|"&$E15&"|"&$F15&"|"&$G15,"M|"&$H15),"") -> G|10 µF|0805|10 V X5R | V15: =IF($U15="",0,IF(COUNTIF($U$4:$U15,$U15)=1,1,0)) -> 1
... A17: 2 USB audio bridge (CH32V307 + CPLD) | B17: R202 | C17: 1 | D17: Resistor, BOOT0 pull-down | E17: 10 kΩ | F17: 0402 | G17: 1% | H17: Generic (match a JLCPCB Basic part) | I17: Assign | J17: Basic (likely) | K17: Yes | M17: 2 | N17: 0.004 | O17: 0.001 | P17: Estimate | Q17: =IF($K17="Yes",$C17*Cost!$B$6,0) -> 5 | R17: =IF($K17<>"Yes",0,IF(AND($P17="Estimate",$N17>0,$B17<>"PCB"),MAX($C17*Cost!$B$6*$N17,Cost!$B$8),$C17*Cost!$B$6*$N17)) -> 0.1 | S17: =IF($K17="Yes",$C17*Cost!$B$7*$O17,0) -> 0.1 | U17: =IF(AND($K17="Yes",$M17>0,$B17<>"PCB"),IF(LEFT($H17,7)="Generic","G|"&$E17&"|"&$F17&"|"&$G17,"M|"&$H17),"") -> G|10 kΩ|0402|1% | V17: =IF($U17="",0,IF(COUNTIF($U$4:$U17,$U17)=1,1,0)) -> 1
A18: 2 USB audio bridge (CH32V307 + CPLD) | B18: U202 | C18: 1 | D18: CPLD, 2K LUT with PLL: generates I²S BCLK/LRCLK and the DAC MCLK from the two audio oscillators (firmware from the same open-source project) | E18: — | F18: QFN-32 4 × 4 mm | G18: 3.3 V | H18: AGM AGRV2KQ32 | I18: LCSC C18208899 | J18: Extended | K18: Yes | L18: Yes | M18: 33 | N18: 1.6503 | O18: 1.1117 | P18: Quote | Q18: =IF($K18="Yes",$C18*Cost!$B$6,0) -> 5 | R18: =IF($K18<>"Yes",0,IF(AND($P18="Estimate",$N18>0,$B18<>"PCB"),MAX($C18*Cost!$B$6*$N18,Cost!$B$8),$C18*Cost!$B$6*$N18)) -> 8.2515 | S18: =IF($K18="Yes",$C18*Cost!$B$7*$O18,0) -> 111.17 | U18: =IF(AND($K18="Yes",$M18>0,$B18<>"PCB"),IF(LEFT($H18,7)="Generic","G|"&$E18&"|"&$F18&"|"&$G18,"M|"&$H18),"") -> M|AGM AGRV2KQ32 | V18: =IF($U18="",0,IF(COUNTIF($U$4:$U18,$U18)=1,1,0)) -> 1
A19: 2 USB audio bridge (CH32V307 + CPLD) | B19: C213–C216 | C19: 4 | D19: Capacitor, CPLD decoupling | E19: 100 nF | F19: 0402 | G19: 16 V X7R | H19: Generic (match a JLCPCB Basic part) | I19: Assign | J19: Basic (likely) | K19: Yes | M19: 2 | N19: 0.005 | O19: 0.0015 | P19: Estimate | Q19: =IF($K19="Yes",$C19*Cost!$B$6,0) -> 20 | R19: =IF($K19<>"Yes",0,IF(AND($P19="Estimate",$N19>0,$B19<>"PCB"),MAX($C19*Cost!$B$6*$N19,Cost!$B$8),$C19*Cost!$B$6*$N19)) -> 0.1 | S19: =IF($K19="Yes",$C19*Cost!$B$7*$O19,0) -> 0.6 | U19: =IF(AND($K19="Yes",$M19>0,$B19<>"PCB"),IF(LEFT($H19,7)="Generic","G|"&$E19&"|"&$F19&"|"&$G19,"M|"&$H19),"") -> G|100 nF|0402|16 V X7R | V19: =IF($U19="",0,IF(COUNTIF($U$4:$U19,$U19)=1,1,0)) -> 0
A20: 2 USB audio bridge (CH32V307 + CPLD) | B20: X201 | C20: 1 | D20: Oscillator, 44.1 kHz family, 3.3 V CMOS | E20: 22.5792 MHz | F20: 3.2 × 2.5 mm | G20: ±25 ppm | H20: Generic (Extended part expected) | I20: Assign | J20: Extended | K20: Yes | L20: Yes | M20: 4 | N20: 0.5 | O20: 0.35 | P20: Estimate | Q20: =IF($K20="Yes",$C20*Cost!$B$6,0) -> 5 | R20: =IF($K20<>"Yes",0,IF(AND($P20="Estimate",$N20>0,$B20<>"PCB"),MAX($C20*Cost!$B$6*$N20,Cost!$B$8),$C20*Cost!$B$6*$N20)) -> 2.5 | S20: =IF($K20="Yes",$C20*Cost!$B$7*$O20,0) -> 35 | U20: =IF(AND($K20="Yes",$M20>0,$B20<>"PCB"),IF(LEFT($H20,7)="Generic","G|"&$E20&"|"&$F20&"|"&$G20,"M|"&$H20),"") -> G|22.5792 MHz|3.2 × 2.5 mm|±25 ppm | V20: =IF($U20="",0,IF(COUNTIF($U$4:$U20,$U20)=1,1,0)) -> 1
A21: 2 USB audio bridge (CH32V307 + CPLD) | B21: X202 | C21: 1 | D21: Oscillator, 48 kHz family, 3.3 V CMOS | E21: 24.576 MHz | F21: 3.2 × 2.5 mm | G21: ±25 ppm | H21: Generic (Extended part expected) | I21: Assign | J21: Extended | K21: Yes | L21: Yes | M21: 4 | N21: 0.5 | O21: 0.35 | P21: Estimate | Q21: =IF($K21="Yes",$C21*Cost!$B$6,0) -> 5 | R21: =IF($K21<>"Yes",0,IF(AND($P21="Estimate",$N21>0,$B21<>"PCB"),MAX($C21*Cost!$B$6*$N21,Cost!$B$8),$C21*Cost!$B$6*$N21)) -> 2.5 | S21: =IF($K21="Yes",$C21*Cost!$B$7*$O21,0) -> 35 | U21: =IF(AND($K21="Yes",$M21>0,$B21<>"PCB"),IF(LEFT($H21,7)="Generic","G|"&$E21&"|"&$F21&"|"&$G21,"M|"&$H21),"") -> G|24.576 MHz|3.2 × 2.5 mm|±25 ppm | V21: =IF($U21="",0,IF(COUNTIF($U$4:$U21,$U21)=1,1,0)) -> 1
A22: 2 USB audio bridge (CH32V307 + CPLD) | B22: C217, C218 | C22: 2 | D22: Capacitor, oscillator VDD | E22: 100 nF | F22: 0402 | G22: 16 V X7R | H22: Generic (match a JLCPCB Basic part) | I22: Assign | J22: Basic (likely) | K22: Yes | M22: 2 | N22: 0.005 | O22: 0.0015 | P22: Estimate | Q22: =IF($K22="Yes",$C22*Cost!$B$6,0) -> 10 | R22: =IF($K22<>"Yes",0,IF(AND($P22="Estimate",$N22>0,$B22<>"PCB"),MAX($C22*Cost!$B$6*$N22,Cost!$B$8),$C22*Cost!$B$6*$N22)) -> 0.1 | S22: =IF($K22="Yes",$C22*Cost!$B$7*$O22,0) -> 0.3 | U22: =IF(AND($K22="Yes",$M22>0,$B22<>"PCB"),IF(LEFT($H22,7)="Generic","G|"&$E22&"|"&$F22&"|"&$G22,"M|"&$H22),"") -> G|100 nF|0402|16 V X7R | V22: =IF($U22="",0,IF(COUNTIF($U$4:$U22,$U22)=1,1,0)) -> 0
A23: 2 USB audio bridge (CH32V307 + CPLD) | B23: R203–R206 | C23: 4 | D23: Resistor, series on MCLK/BCLK/LRCLK/SDATA toward the DAC (source termination) | E23: 33 Ω | F23: 0402 | G23: 1% | H23: Generic (match a JLCPCB Basic part) | I23: Assign | J23: Basic (likely) | K23: Yes | M23: 2 | N23: 0.004 | O23: 0.001 | P23: Estimate | Q23: =IF($K23="Yes",$C23*Cost!$B$6,0) -> 20 | R23: =IF($K23<>"Yes",0,IF(AND($P23="Estimate",$N23>0,$B23<>"PCB"),MAX($C23*Cost!$B$6*$N23,Cost!$B$8),$C23*Cost!$B$6*$N23)) -> 0.1 | S23: =IF($K23="Yes",$C23*Cost!$B$7*$O23,0) -> 0.4 | U23: =IF(AND($K23="Yes",$M23>0,$B23<>"PCB"),IF(LEFT($H23,7)="Generic","G|"&$E23&"|"&$F23&"|"&$G23,"M|"&$H23),"") -> G|33 Ω|0402|1% | V23: =IF($U23="",0,IF(COUNTIF($U$4:$U23,$U23)=1,1,0)) -> 1
A24: 2 USB audio bridge (CH32V307 + CPLD) | B24: R207, R208 | C24: 2 | D24: Resistor, I²C SCL/SDA pull-ups to 3V3 | E24: 2.2 kΩ | F24: 0402 | G24: 1% | H24: Generic (match a JLCPCB Basic part) | I24: Assign | J24: Basic (likely) | K24: Yes | M24: 2 | N24: 0.004 | O24: 0.001 | P24: Estimate | Q24: =IF($K24="Yes",$C24*Cost!$B$6,0) -> 10 | R24: =IF($K24<>"Yes",0,IF(AND($P24="Estimate",$N24>0,$B24<>"PCB"),MAX($C24*Cost!$B$6*$N24,Cost!$B$8),$C24*Cost!$B$6*$N24)) -> 0.1 | S24: =IF($K24="Yes",$C24*Cost!$B$7*$O24,0) -> 0.2 | U24: =IF(AND($K24="Yes",$M24>0,$B24<>"PCB"),IF(LEFT($H24,7)="Generic","G|"&$E24&"|"&$F24&"|"&$G24,"M|"&$H24),"") -> G|2.2 kΩ|0402|1% | V24: =IF($U24="",0,IF(COUNTIF($U$4:$U24,$U24)=1,1,0)) -> 1
A25: 2 USB audio bridge (CH32V307 + CPLD) | B25: J201 | C25: 1 | D25: Pads, CH32V307 2-wire debug (WCH-LinkE): 3V3, SWDIO, SWCLK, GND | E25: — | F25: Pads | G25: — | H25: No part | I25: — | J25: — | K25: No part | M25: 0 | N25: 0 | O25: 0 | P25: Estimate | Q25: =IF($K25="Yes",$C25*Cost!$B$6,0) -> 0 | R25: =IF($K25<>"Yes",0,IF(AND($P25="Estimate",$N25>0,$B25<>"PCB"),MAX($C25*Cost!$B$6*$N25,Cost!$B$8),$C25*Cost!$B$6*$N25)) -> 0 | S25: =IF($K25="Yes",$C25*Cost!$B$7*$O25,0) -> 0 | U25: =IF(AND($K25="Yes",$M25>0,$B25<>"PCB"),IF(LEFT($H25,7)="Generic","G|"&$E25&"|"&$F25&"|"&$G25,"M|"&$H25),"") | V25: =IF($U25="",0,IF(COUNTIF($U$4:$U25,$U25)=1,1,0)) -> 0
A26: 2 USB audio bridge (CH32V307 + CPLD) | B26: J202 | C26: 1 | D26: Pads, CPLD JTAG: 3V3, TCK, TMS, TDI, TDO, GND | E26: — | F26: Pads | G26: — | H26: No part | I26: — | J26: — | K26: No part | M26: 0 | N26: 0 | O26: 0 | P26: Estimate | Q26: =IF($K26="Yes",$C26*Cost!$B$6,0) -> 0 | R26: =IF($K26<>"Yes",0,IF(AND($P26="Estimate",$N26>0,$B26<>"PCB"),MAX($C26*Cost!$B$6*$N26,Cost!$B$8),$C26*Cost!$B$6*$N26)) -> 0 | S26: =IF($K26="Yes",$C26*Cost!$B$7*$O26,0) -> 0 | U26: =IF(AND($K26="Yes",$M26>0,$B26<>"PCB"),IF(LEFT($H26,7)="Generic","G|"&$E26&"|"&$F26&"|"&$G26,"M|"&$H26),"") | V26: =IF($U26="",0,IF(COUNTIF($U$4:$U26,$U26)=1,1,0)) -> 0
A27: 3 DAC (ES9018K2M) | B27: U301 | C27: 1 | D27: DAC, 32-bit, PCM to 384 kHz, I²C control, voltage-mode differential outputs | E27: — | F27: QFN-28 5 × 5 mm | G27: DNR 127 dB, THD+N −120 dB (datasheet) | H27: ESS ES9018K2M | I27: LCSC C2688377 | J27: Extended | K27: Yes | L27: Yes | M27: 29 | N27: 3.4678 | O27: 2.278 | P27: Quote | Q27: =IF($K27="Yes",$C27*Cost!$B$6,0) -> 5 | R27: =IF($K27<>"Yes",0,IF(AND($P27="Estimate",$N27>0,$B27<>"PCB"),MAX($C27*Cost!$B$6*$N27,Cost!$B$8),$C27*Cost!$B$6*$N27)) -> 17.339 | S27: =IF($K27="Yes",$C27*Cost!$B$7*$O27,0) -> 227.8 | U27: =IF(AND($K27="Yes",$M27>0,$B27<>"PCB"),IF(LEFT($H27,7)="Generic","G|"&$E27&"|"&$F27&"|"&$G27,"M|"&$H27),"") -> M|ESS ES9018K2M | V27: =IF($U27="",0,IF(COUNTIF($U$4:$U27,$U27)=1,1,0)) -> 1
A28: 3 DAC (ES9018K2M) | B28: U302 | C28: 1 | D28: LDO, quiet 3.3 V for AVCC_L, AVCC_R and VCCA (from 5V_SYS) | E28: 3.3 V, 250 mA | F28: SOT-23-5 | G28: 6.5 µVrms | H28: TI LP5907MFX-3.3/NOPB | I28: Assign LCSC no. | J28: Extended | K28: Yes | M28: 5 | N28: 0.1746 | O28: 0.109 | P28: Estimate | Q28: =IF($K28="Yes",$C28*Cost!$B$6,0) -> 5 | R28: =IF($K28<>"Yes",0,IF(AND($P28="Estimate",$N28>0,$B28<>"PCB"),MAX($C28*Cost!$B$6*$N28,Cost!$B$8),$C28*Cost!$B$6*$N28)) -> 0.873 | S28: =IF($K28="Yes",$C28*Cost!$B$7*$O28,0) -> 10.9 | U28: =IF(AND($K28="Yes",$M28>0,$B28<>"PCB"),IF(LEFT($H28,7)="Generic","G|"&$E28&"|"&$F28&"|"&$G28,"M|"&$H28),"") -> M|TI LP5907MFX-3.3/NOPB | V28: =IF($U28="",0,IF(COUNTIF($U$4:$U28,$U28)=1,1,0)) -> 1
A29: 3 DAC (ES9018K2M) | B29: C301, C302 | C29: 2 | D29: Capacitor, LP5907 input and output (keep total output capacitance ≤ 10 µF) | E29: 1 µF | F29: 0402 | G29: 10 V X5R | H29: Generic (match a JLCPCB Basic part) | I29: Assign | J29: Basic (likely) | K29: Yes | M29: 2 | N29: 0.008 | O29: 0.003 | P29: Estimate | Q29: =IF($K29="Yes",$C29*Cost!$B$6,0) -> 10 | R29: =IF($K29<>"Yes",0,IF(AND($P29="Estimate",$N29>0,$B29<>"PCB"),MAX($C29*Cost!$B$6*$N29,Cost!$B$8),$C29*Cost!$B$6*$N29)) -> 0.1 | S29: =IF($K29="Yes",$C29*Cost!$B$7*$O29,0) -> 0.6 | U29: =IF(AND($K29="Yes",$M29>0,$B29<>"PCB"),IF(LEFT($H29,7)="Generic","G|"&$E29&"|"&$F29&"|"&$G29,"M|"&$H29),"") -> G|1 µF|0402|10 V X5R | V29: =IF($U29="",0,IF(COUNTIF($U$4:$U29,$U29)=1,1,0)) -> 0
A30: 3 DAC (ES9018K2M) | B30: R301, R302 | C30: 2 | D30: Resistor, AVCC_L and AVCC_R feed (separate branches from the LDO) | E30: 1 Ω | F30: 0603 | G30: 1% | H30: Generic (match a JLCPCB Basic part) | I30: Assign | J30: Basic (likely) | K30: Yes | M30: 2 | N30: 0.004 | O30: 0.0012 | P30: Estimate | Q30: =IF($K30="Yes",$C30*Cost!$B$6,0) -> 10 | R30: =IF($K30<>"Yes",0,IF(AND($P30="Estimate",$N30>0,$B30<>"PCB"),MAX($C30*Cost!$B$6*$N30,Cost!$B$8),$C30*Cost!$B$6*$N30)) -> 0.1 | S30: =IF($K30="Yes",$C30*Cost!$B$7*$O30,0) -> 0.24 | U30: =IF(AND($K30="Yes",$M30>0,$B30<>"PCB"),IF(LEFT($H30,7)="Generic","G|"&$E30&"|"&$F30&"|"&$G30,"M|"&$H30),"") -> G|1 Ω|0603|1% | V30: =IF($U30="",0,IF(COUNTIF($U$4:$U30,$U30)=1,1,0)) -> 1
A31: 3 DAC (ES9018K2M) | B31: C303, C304 | C31: 2 | D31: Capacitor, AVCC_L and AVCC_R (2.2 µF keeps the LP5907 total at 5.7 µF, under its 10 µF limit) | E31: 2.2 µF | F31: 0603 | G31: 6.3 V X5R | H31: Generic (match a JLCPCB Basic part) | I31: Assign | J31: Basic (likely) | K31: Yes | M31: 2 | N31: 0.012 | O31: 0.005 | P31: Estimate | Q31: =IF($K31="Yes",$C31*Cost!$B$6,0) -> 10 | R31: =IF($K31<>"Yes",0,IF(AND($P31="Estimate",$N31>0,$B31<>"PCB"),MAX($C31*Cost!$B$6*$N31,Cost!$B$8),$C31*Cost!$B$6*$N31)) -> 0.12 | S31: =IF($K31="Yes",$C31*Cost!$B$7*$O31,0) -> 1 | U31: =IF(AND($K31="Yes",$M31>0,$B31<>"PCB"),IF(LEFT($H31,7)="Generic","G|"&$E31&"|"&$F31&"|"&$G31,"M|"&$H31),"") -> G|2.2 µF|0603|6.3 V X5R | V31: =IF($U31="",0,IF(COUNTIF($U$4:$U31,$U31)=1,1,0)) -> 1
A32: 3 DAC (ES9018K2M) | B32: C305–C309 | C32: 5 | D32: Capacitor, AVCC_L, AVCC_R, VCCA, DVCC, DVDD HF decoupling | E32: 100 nF | F32: 0402 | G32: 16 V X7R | H32: Generic (match a JLCPCB Basic part) | I32: Assign | J32: Basic (likely) | K32: Yes | M32: 2 | N32: 0.005 | O32: 0.0015 | P32: Estimate | Q32: =IF($K32="Yes",$C32*Cost!$B$6,0) -> 25 | R32: =IF($K32<>"Yes",0,IF(AND($P32="Estimate",$N32>0,$B32<>"PCB"),MAX($C32*Cost!$B$6*$N32,Cost!$B$8),$C32*Cost!$B$6*$N32)) -> 0.125 | S32: =IF($K32="Yes",$C32*Cost!$B$7*$O32,0) -> 0.75 | U32: =IF(AND($K32="Yes",$M32>0,$B32<>"PCB"),IF(LEFT($H32,7)="Generic","G|"&$E32&"|"&$F32&"|"&$G32,"M|"&$H32),"") -> G|100 nF|0402|16 V X7R | V32: =IF($U32="",0,IF(COUNTIF($U$4:$U32,$U32)=1,1,0)) -> 0
A33: 3 DAC (ES9018K2M) | B33: C310 | C33: 1 | D33: Capacitor, DVDD (datasheet: ≥ 1 µF effective at 1.2 V; 2.2 µF X5R recommended) | E33: 2.2 µF | F33: 0603 | G33: 6.3 V X5R | H33: Generic (match a JLCPCB Basic part) | I33: Assign | J33: Basic (likely) | K33: Yes | M33: 2 | N33: 0.012 | O33: 0.005 | P33: Estimate | Q33: =IF($K33="Yes",$C33*Cost!$B$6,0) -> 5 | R33: =IF($K33<>"Yes",0,IF(AND($P33="Estimate",$N33>0,$B33<>"PCB"),MAX($C33*Cost!$B$6*$N33,Cost!$B$8),$C33*Cost!$B$6*$N33)) -> 0.1 | S33: =IF($K33="Yes",$C33*Cost!$B$7*$O33,0) -> 0.5 | U33: =IF(AND($K33="Yes",$M33>0,$B33<>"PCB"),IF(LEFT($H33,7)="Generic","G|"&$E33&"|"&$F33&"|"&$G33,"M|"&$H33),"") -> G|2.2 µF|0603|6.3 V X5R | V33: =IF($U33="",0,IF(COUNTIF($U$4:$U33,$U33)=1,1,0)) -> 0
A34: 3 DAC (ES9018K2M) | B34: U303 | C34: 1 | D34: LDO, external DVDD 1.3 V (datasheet: required for FSR > 192 kHz), from 3V3 | E34: 1.3 V, ≥ 50 mA | F34: SOT-223 | G34: Adjustable, 1.25 V ref | H34: AMS1117-ADJ | I34: Assign LCSC no. | J34: Basic (likely) | K34: Yes | M34: 4 | N34: 0.08 | O34: 0.05 | P34: Estimate | Q34: =IF($K34="Yes",$C34*Cost!$B$6,0) -> 5 | R34: =IF($K34<>"Yes",0,IF(AND($P34="Estimate",$N34>0,$B34<>"PCB"),MAX($C34*Cost!$B$6*$N34,Cost!$B$8),$C34*Cost!$B$6*$N34)) -> 0.4 | S34: =IF($K34="Yes",$C34*Cost!$B$7*$O34,0) -> 5 | U34: =IF(AND($K34="Yes",$M34>0,$B34<>"PCB"),IF(LEFT($H34,7)="Generic","G|"&$E34&"|"&$F34&"|"&$G34,"M|"&$H34),"") -> M|AMS1117-ADJ | V34: =IF($U34="",0,IF(COUNTIF($U$4:$U34,$U34)=1,1,0)) -> 1
A35: 3 DAC (ES9018K2M) | B35: R303, R304 | C35: 2 | D35: Resistor, 1.3 V divider 240 Ω / 10 Ω (5.2 mA also meets the minimum load) | E35: 240 Ω / 10 Ω | F35: 0402 | G35: 1% | H35: Generic (match a JLCPCB Basic part) | I35: Assign | J35: Basic (likely) | K35: Yes | M35: 2 | N35: 0.004 | O35: 0.001 | P35: Estimate | Q35: =IF($K35="Yes",$C35*Cost!$B$6,0) -> 10 | R35: =IF($K35<>"Yes",0,IF(AND($P35="Estimate",$N35>0,$B35<>"PCB"),MAX($C35*Cost!$B$6*$N35,Cost!$B$8),$C35*Cost!$B$6*$N35)) -> 0.1 | S35: =IF($K35="Yes",$C35*Cost!$B$7*$O35,0) -> 0.2 | U35: =IF(AND($K35="Yes",$M35>0,$B35<>"PCB"),IF(LEFT($H35,7)="Generic","G|"&$E35&"|"&$F35&"|"&$G35,"M|"&$H35),"") -> G|240 Ω / 10 Ω|0402|1% | V35: =IF($U35="",0,IF(COUNTIF($U$4:$U35,$U35)=1,1,0)) -> 1
A36: 3 DAC (ES9018K2M) | B36: C311, C312 | C36: 2 | D36: Capacitor, 1.3 V LDO input and output | E36: 10 µF | F36: 0805 | G36: 10 V X5R | H36: Generic (match a JLCPCB Basic part) | I36: Assign | J36: Basic (likely) | K36: Yes | M36: 2 | N36: 0.02 | O36: 0.01 | P36: Estimate | Q36: =IF($K36="Yes",$C36*Cost!$B$6,0) -> 10 | R36: =IF($K36<>"Yes",0,IF(AND($P36="Estimate",$N36>0,$B36<>"PCB"),MAX($C36*Cost!$B$6*$N36,Cost!$B$8),$C36*Cost!$B$6*$N36)) -> 0.2 | S36: =IF($K36="Yes",$C36*Cost!$B$7*$O36,0) -> 2 | U36: =IF(AND($K36="Yes",$M36>0,$B36<>"PCB"),IF(LEFT($H36,7)="Generic","G|"&$E36&"|"&$F36&"|"&$G36,"M|"&$H36),"") -> G|10 µF|0805|10 V X5R | V36: =IF($U36="",0,IF(COUNTIF($U$4:$U36,$U36)=1,1,0)) -> 0
A37: 3 DAC (ES9018K2M) | B37: R305 | C37: 1 | D37: Resistor, RESETB pull-down (DAC held in reset at power-up) | E37: 100 kΩ | F37: 0402 | G37: 1% | H37: Generic (match a JLCPCB Basic part) | I37: Assign | J37: Basic (likely) | K37: Yes | M37: 2 | N37: 0.004 | O37: 0.001 | P37: Estimate | Q37: =IF($K37="Yes",$C37*Cost!$B$6,0) -> 5 | R37: =IF($K37<>"Yes",0,IF(AND($P37="Estimate",$N37>0,$B37<>"PCB"),MAX($C37*Cost!$B$6*$N37,Cost!$B$8),$C37*Cost!$B$6*$N37)) -> 0.1 | S37: =IF($K37="Yes",$C37*Cost!$B$7*$O37,0) -> 0.1 | U37: =IF(AND($K37="Yes",$M37>0,$B37<>"PCB"),IF(LEFT($H37,7)="Generic","G|"&$E37&"|"&$F37&"|"&$G37,"M|"&$H37),"") -> G|100 kΩ|0402|1% | V37: =IF($U37="",0,IF(COUNTIF($U$4:$U37,$U37)=1,1,0)) -> 1
A38: 3 DAC (ES9018K2M) | B38: R306 | C38: 1 | D38: Resistor, ADDR strap (I²C address 0x90) | E38: 10 kΩ | F38: 0402 | G38: 1% | H38: Generic (match a JLCPCB Basic part) | I38: Assign | J38: Basic (likely) | K38: Yes | M38: 2 | N38: 0.004 | O38: 0.001 | P38: Estimate | Q38: =IF($K38="Yes",$C38*Cost!$B$6,0) -> 5 | R38: =IF($K38<>"Yes",0,IF(AND($P38="Estimate",$N38>0,$B38<>"PCB"),MAX($C38*Cost!$B$6*$N38,Cost!$B$8),$C38*Cost!$B$6*$N38)) -> 0.1 | S38: =IF($K38="Yes",$C38*Cost!$B$7*$O38,0) -> 0.1 | U38: =IF(AND($K38="Yes",$M38>0,$B38<>"PCB"),IF(LEFT($H38,7)="Generic","G|"&$E38&"|"&$F38&"|"&$G38,"M|"&$H38),"") -> G|10 kΩ|0402|1% | V38: =IF($U38="",0,IF(COUNTIF($U$4:$U38,$U38)=1,1,0)) -> 0
A39: 3 DAC (ES9018K2M) | B39: FB301 | C39: 1 | D39: Ferrite bead, 3V3 → DVCC | E39: 600 Ω | F39: 0603 | G39: 1.3 A | H39: Sunlord GZ1608D601TF | I39: LCSC C1015 (verify Basic) | J39: Basic (likely) | K39: Yes | M39: 2 | N39: 0.01 | O39: 0.003 | P39: Estimate | Q39: =IF($K39="Yes",$C39*Cost!$B$6,0) -> 5 | R39: =IF($K39<>"Yes",0,IF(AND($P39="Estimate",$N39>0,$B39<>"PCB"),MAX($C39*Cost!$B$6*$N39,Cost!$B$8),$C39*Cost!$B$6*$N39)) -> 0.1 | S39: =IF($K39="Yes",$C39*Cost!$B$7*$O39,0) -> 0.3 | U39: =IF(AND($K39="Yes",$M39>0,$B39<>"PCB"),IF(LEFT($H39,7)="Generic","G|"&$E39&"|"&$F39&"|"&$G39,"M|"&$H39),"") -> M|Sunlord GZ1608D601TF | V39: =IF($U39="",0,IF(COUNTIF($U$4:$U39,$U39)=1,1,0)) -> 0
A40: 4 I/V converters and output legs (2 × OPA1678 + 2 × OPA1622) | B40: U401, U402 | C40: 2 | D40: Op-amp, dual; U401 = L+ and L−, U402 = R+ and R− (one amplifier per leg, no paralleling) | E40: — | F40: VSON-10 3 × 3 mm | G40: Isc +145/−130 mA typ; thermal pad to V− | H40: TI OPA1622IDRCR | I40: LCSC C2876559 | J40: Extended | K40: Yes | L40: Yes | M40: 11 | N40: 2.6271 | O40: 2.1108 | P40: Quote | Q40: =IF($K40="Yes",$C40*Cost!$B$6,0) -> 10 | R40: =IF($K40<>"Yes",0,IF(AND($P40="Estimate",$N40>0,$B40<>"PCB"),MAX($C40*Cost!$B$6*$N40,Cost!$B$8),$C40*Cost!$B$6*$N40)) -> 26.271 | S40: =IF($K40="Yes",$C40*Cost!$B$7*$O40,0) -> 422.16 | U40: =IF(AND($K40="Yes",$M40>0,$B40<>"PCB"),IF(LEFT($H40,7)="Generic","G|"&$E40&"|"&$F40&"|"&$G40,"M|"&$H40),"") -> M|TI OPA1622IDRCR | V40: =IF($U40="",0,IF(COUNTIF($U$4:$U40,$U40)=1,1,0)) -> 1
A41: 4 I/V converters and output legs (2 × OPA1678 + 2 × OPA1622) | B41: R401–R416 | C41: 16 | D41: Resistor, 4-resistor difference amplifier per leg, fed by the I/V outputs (leg+ = I/V(DAC−) − I/V(DAC+), leg− the swap); matching sets common-mode rejection | E41: 2.00 kΩ | F41: 0603 | G41: 0.1% 25 ppm thin film | H41: Generic (Extended part expected) | I41: Assign | J41: Extended | K41: Yes | M41: 2 | N41: 0.05 | O41: 0.03 | P41: Estimate | Q41: =IF($K41="Yes",$C41*Cost!$B$6,0) -> 80 | R41: =IF($K41<>"Yes",0,IF(AND($P41="Estimate",$N41>0,$B41<>"PCB"),MAX($C41*Cost!$B$6*$N41,Cost!$B$8),$C41*Cost!$B$6*$N41)) -> 4 | S41: =IF($K41="Yes",$C41*Cost!$B$7*$O41,0) -> 48 | U41: =IF(AND($K41="Yes",$M41>0,$B41<>"PCB"),IF(LEFT($H41,7)="Generic","G|"&$E41&"|"&$F41&"|"&$G41,"M|"&$H41),"") -> G|2.00 kΩ|0603|0.1% 25 ppm thin film | V41: =IF($U41="",0,IF(COUNTIF($U$4:$U41,$U41)=1,1,0)) -> 1
A42: 4 I/V converters and output legs (2 × OPA1678 + 2 × OPA1622) | B42: C401–C408 | C42: 8 | D42: Capacitor, across each feedback and ground-leg resistor (≈ 170 kHz low-pass with 2 kΩ) | E42: 470 pF | F42: 0603 | G42: 50 V C0G | H42: Generic (match a JLCPCB Basic part) | I42: Assign | J42: Basic (likely) | K42: Yes | M42: 2 | N42: 0.01 | O42: 0.004 | P42: Estimate | Q42: =IF($K42="Yes",$C42*Cost!$B$6,0) -> 40 | R42: =IF($K42<>"Yes",0,IF(AND($P42="Estimate",$N42>0,$B42<>"PCB"),MAX($C42*Cost!$B$6*$N42,Cost!$B$8),$C42*Cost!$B$6*$N42)) -> 0.4 | S42: =IF($K42="Yes",$C42*Cost!$B$7*$O42,0) -> 3.2 | U42: =IF(AND($K42="Yes",$M42>0,$B42<>"PCB"),IF(LEFT($H42,7)="Generic","G|"&$E42&"|"&$F42&"|"&$G42,"M|"&$H42),"") -> G|470 pF|0603|50 V C0G | V42: =IF($U42="",0,IF(COUNTIF($U$4:$U42,$U42)=1,1,0)) -> 1
A43: 4 I/V converters and output legs (2 × OPA1678 + 2 × OPA1622) | B43: U403, U404 | C43: 2 | D43: Op-amp, dual, current-to-voltage (I/V) converters, one amplifier per DAC pin (U403 = DACL, DACLB; U404 = DACR, DACRB), as in the ESS application circuit | E43: — | F43: SOIC-8 | G43: 4.5 nV/√Hz, rail-to-rail output, ±2.25 to ±18 V | H43: TI OPA1678IDR | I43: LCSC C192421 | J43: Extended | K43: Yes | M43: 8 | N43: 0.97 | O43: 0.8368 | P43: Quote | Q43: =IF($K43="Yes",$C43*Cost!$B$6,0) -> 10 | R43: =IF($K43<>"Yes",0,IF(AND($P43="Estimate",$N43>0,$B43<>"PCB"),MAX($C43*Cost!$B$6*$N43,Cost!$B$8),$C43*Cost!$B$6*$N43)) -> 9.7 | S43: =IF($K43="Yes",$C43*Cost!$B$7*$O43,0) -> 167.36 | U43: =IF(AND($K43="Yes",$M43>0,$B43<>"PCB"),IF(LEFT($H43,7)="Generic","G|"&$E43&"|"&$F43&"|"&$G43,"M|"&$H43),"") -> M|TI OPA1678IDR | V43: =IF($U43="",0,IF(COUNTIF($U$4:$U43,$U43)=1,1,0)) -> 1
A44: 4 I/V converters and output legs (2 × OPA1678 + 2 × OPA1622) | B44: R423–R426 | C44: 4 | D44: Resistor, I/V feedback (sets 2.0 Vrms per leg: 2 × 750/806 × 1.078 Vrms) | E44: 750 Ω | F44: 0603 | G44: 1% | H44: Generic (match a JLCPCB Basic part) | I44: Assign | J44: Basic (likely) | K44: Yes | M44: 2 | N44: 0.004 | O44: 0.0012 | P44: Estimate | Q44: =IF($K44="Yes",$C44*Cost!$B$6,0) -> 20 | R44: =IF($K44<>"Yes",0,IF(AND($P44="Estimate",$N44>0,$B44<>"PCB"),MAX($C44*Cost!$B$6*$N44,Cost!$B$8),$C44*Cost!$B$6*$N44)) -> 0.1 | S44: =IF($K44="Yes",$C44*Cost!$B$7*$O44,0) -> 0.48 | U44: =IF(AND($K44="Yes",$M44>0,$B44<>"PCB"),IF(LEFT($H44,7)="Generic","G|"&$E44&"|"&$F44&"|"&$G44,"M|"&$H44),"") -> G|750 Ω|0603|1% | V44: =IF($U44="",0,IF(COUNTIF($U$4:$U44,$U44)=1,1,0)) -> 1
A45: 4 I/V converters and output legs (2 × OPA1678 + 2 × OPA1622) | B45: R427–R430 | C45: 4 | D45: Resistor, in series with each I/V feedback capacitor (ESS application circuit) | E45: 10 Ω | F45: 0402 | G45: 1% | H45: Generic (match a JLCPCB Basic part) | I45: Assign | J45: Basic (likely) | K45: Yes | M45: 2 | N45: 0.004 | O45: 0.001 | P45: Estimate | Q45: =IF($K45="Yes",$C45*Cost!$B$6,0) -> 20 | R45: =IF($K45<>"Yes",0,IF(AND($P45="Estimate",$N45>0,$B45<>"PCB"),MAX($C45*Cost!$B$6*$N45,Cost!$B$8),$C45*Cost!$B$6*$N45)) -> 0.1 | S45: =IF($K45="Yes",$C45*Cost!$B$7*$O45,0) -> 0.4 | U45: =IF(AND($K45="Yes",$M45>0,$B45<>"PCB"),IF(LEFT($H45,7)="Generic","G|"&$E45&"|"&$F45&"|"&$G45,"M|"&$H45),"") -> G|10 Ω|0402|1% | V45: =IF($U45="",0,IF(COUNTIF($U$4:$U45,$U45)=1,1,0)) -> 1
A46: 4 I/V converters and output legs (2 × OPA1678 + 2 × OPA1622) | B46: C417–C420 | C46: 4 | D46: Capacitor, I/V feedback (≈ 141 kHz with 750 Ω) | E46: 1.5 nF | F46: 0603 | G46: 50 V C0G | H46: Generic (match a JLCPCB Basic part) | I46: Assign | J46: Basic (likely) | K46: Yes | M46: 2 | N46: 0.01 | O46: 0.004 | P46: Estimate | Q46: =IF($K46="Yes",$C46*Cost!$B$6,0) -> 20 | R46: =IF($K46<>"Yes",0,IF(AND($P46="Estimate",$N46>0,$B46<>"PCB"),MAX($C46*Cost!$B$6*$N46,Cost!$B$8),$C46*Cost!$B$6*$N46)) -> 0.2 | S46: =IF($K46="Yes",$C46*Cost!$B$7*$O46,0) -> 1.6 | U46: =IF(AND($K46="Yes",$M46>0,$B46<>"PCB"),IF(LEFT($H46,7)="Generic","G|"&$E46&"|"&$F46&"|"&$G46,"M|"&$H46),"") -> G|1.5 nF|0603|50 V C0G | V46: =IF($U46="",0,IF(COUNTIF($U$4:$U46,$U46)=1,1,0)) -> 1
A47: 4 I/V converters and output legs (2 × OPA1678 + 2 × OPA1622) | B47: R431, R432 | C47: 2 | D47: Resistor, VREF divider from 3V3A (10.0 kΩ / 10.7 kΩ → 1.706 V, the DAC zero-DC-current point ≈ 1.70 V) | E47: 10.0 kΩ / 10.7 kΩ | F47: 0402 | G47: 1% | H47: Generic (match a JLCPCB Basic part) | I47: Assign | J47: Basic (likely) | K47: Yes | M47: 2 | N47: 0.004 | O47: 0.001 | P47: Estimate | Q47: =IF($K47="Yes",$C47*Cost!$B$6,0) -> 10 | R47: =IF($K47<>"Yes",0,IF(AND($P47="Estimate",$N47>0,$B47<>"PCB"),MAX($C47*Cost!$B$6*$N47,Cost!$B$8),$C47*Cost!$B$6*$N47)) -> 0.1 | S47: =IF($K47="Yes",$C47*Cost!$B$7*$O47,0) -> 0.2 | U47: =IF(AND($K47="Yes",$M47>0,$B47<>"PCB"),IF(LEFT($H47,7)="Generic","G|"&$E47&"|"&$F47&"|"&$G47,"M|"&$H47),"") -> G|10.0 kΩ / 10.7 kΩ|0402|1% | V47: =IF($U47="",0,IF(COUNTIF($U$4:$U47,$U47)=1,1,0)) -> 1
A48: 4 I/V converters and output legs (2 × OPA1678 + 2 × OPA1622) | B48: C421 | C48: 1 | D48: Capacitor, VREF filter (≈ 3 Hz with the divider) | E48: 10 µF | F48: 0805 | G48: 10 V X5R | H48: Generic (match a JLCPCB Basic part) | I48: Assign | J48: Basic (likely) | K48: Yes | M48: 2 | N48: 0.02 | O48: 0.01 | P48: Estimate | Q48: =IF($K48="Yes",$C48*Cost!$B$6,0) -> 5 | R48: =IF($K48<>"Yes",0,IF(AND($P48="Estimate",$N48>0,$B48<>"PCB"),MAX($C48*Cost!$B$6*$N48,Cost!$B$8),$C48*Cost!$B$6*$N48)) -> 0.1 | S48: =IF($K48="Yes",$C48*Cost!$B$7*$O48,0) -> 1 | U48: =IF(AND($K48="Yes",$M48>0,$B48<>"PCB"),IF(LEFT($H48,7)="Generic","G|"&$E48&"|"&$F48&"|"&$G48,"M|"&$H48),"") -> G|10 µF|0805|10 V X5R | V48: =IF($U48="",0,IF(COUNTIF($U$4:$U48,$U48)=1,1,0)) -> 0
A49: 4 I/V converters and output legs (2 × OPA1678 + 2 × OPA1622) | B49: C422 | C49: 1 | D49: Capacitor, VREF HF decoupling | E49: 100 nF | F49: 0402 | G49: 16 V X7R | H49: Generic (match a JLCPCB Basic part) | I49: Assign | J49: Basic (likely) | K49: Yes | M49: 2 | N49: 0.005 | O49: 0.0015 | P49: Estimate | Q49: =IF($K49="Yes",$C49*Cost!$B$6,0) -> 5 | R49: =IF($K49<>"Yes",0,IF(AND($P49="Estimate",$N49>0,$B49<>"PCB"),MAX($C49*Cost!$B$6*$N49,Cost!$B$8),$C49*Cost!$B$6*$N49)) -> 0.1 | S49: =IF($K49="Yes",$C49*Cost!$B$7*$O49,0) -> 0.15 | U49: =IF(AND($K49="Yes",$M49>0,$B49<>"PCB"),IF(LEFT($H49,7)="Generic","G|"&$E49&"|"&$F49&"|"&$G49,"M|"&$H49),"") -> G|100 nF|0402|16 V X7R | V49: =IF($U49="",0,IF(COUNTIF($U$4:$U49,$U49)=1,1,0)) -> 0
A50: 4 I/V converters and output legs (2 × OPA1678 + 2 × OPA1622) | B50: C423–C426 | C50: 4 | D50: Capacitor, OPA1678 V+ and V− | E50: 100 nF | F50: 0402 | G50: 16 V X7R | H50: Generic (match a JLCPCB Basic part) | I50: Assign | J50: Basic (likely) | K50: Yes | M50: 2 | N50: 0.005 | O50: 0.0015 | P50: Estimate | Q50: =IF($K50="Yes",$C50*Cost!$B$6,0) -> 20 | R50: =IF($K50<>"Yes",0,IF(AND($P50="Estimate",$N50>0,$B50<>"PCB"),MAX($C50*Cost!$B$6*$N50,Cost!$B$8),$C50*Cost!$B$6*$N50)) -> 0.1 | S50: =IF($K50="Yes",$C50*Cost!$B$7*$O50,0) -> 0.6 | U50: =IF(AND($K50="Yes",$M50>0,$B50<>"PCB"),IF(LEFT($H50,7)="Generic","G|"&$E50&"|"&$F50&"|"&$G50,"M|"&$H50),"") -> G|100 nF|0402|16 V X7R | V50: =IF($U50="",0,IF(COUNTIF($U$4:$U50,$U50)=1,1,0)) -> 0
A51: 4 I/V converters and output legs (2 × OPA1678 + 2 × OPA1622) | B51: R417–R420 | C51: 4 | D51: Link, output series per leg (fit 0.47 Ω only if the capacitive-load test needs it) | E51: 0 Ω | F51: 0603 | G51: — | H51: Generic (match a JLCPCB Basic part) | I51: Assign | J51: Basic (likely) | K51: Yes | M51: 2 | N51: 0.004 | O51: 0.0012 | P51: Estimate | Q51: =IF($K51="Yes",$C51*Cost!$B$6,0) -> 20 | R51: =IF($K51<>"Yes",0,IF(AND($P51="Estimate",$N51>0,$B51<>"PCB"),MAX($C51*Cost!$B$6*$N51,Cost!$B$8),$C51*Cost!$B$6*$N51)) -> 0.1 | S51: =IF($K51="Yes",$C51*Cost!$B$7*$O51,0) -> 0.48 | U51: =IF(AND($K51="Yes",$M51>0,$B51<>"PCB"),IF(LEFT($H51,7)="Generic","G|"&$E51&"|"&$F51&"|"&$G51,"M|"&$H51),"") -> G|0 Ω|0603|— | V51: =IF($U51="",0,IF(COUNTIF($U$4:$U51,$U51)=1,1,0)) -> 1
A52: 4 I/V converters and output legs (2 × OPA1678 + 2 × OPA1622) | B52: R421, R422 | C52: 2 | D52: Resistor, EN pull-downs (amplifiers off at power-up) | E52: 100 kΩ | F52: 0402 | G52: 1% | H52: Generic (match a JLCPCB Basic part) | I52: Assign | J52: Basic (likely) | K52: Yes | M52: 2 | N52: 0.004 | O52: 0.001 | P52: Estimate | Q52: =IF($K52="Yes",$C52*Cost!$B$6,0) -> 10 | R52: =IF($K52<>"Yes",0,IF(AND($P52="Estimate",$N52>0,$B52<>"PCB"),MAX($C52*Cost!$B$6*$N52,Cost!$B$8),$C52*Cost!$B$6*$N52)) -> 0.1 | S52: =IF($K52="Yes",$C52*Cost!$B$7*$O52,0) -> 0.2 | U52: =IF(AND($K52="Yes",$M52>0,$B52<>"PCB"),IF(LEFT($H52,7)="Generic","G|"&$E52&"|"&$F52&"|"&$G52,"M|"&$H52),"") -> G|100 kΩ|0402|1% | V52: =IF($U52="",0,IF(COUNTIF($U$4:$U52,$U52)=1,1,0)) -> 0
... A54: 4 I/V converters and output legs (2 × OPA1678 + 2 × OPA1622) | B54: C413–C416 | C54: 4 | D54: Capacitor, OPA1622 local bulk V+ and V− | E54: 10 µF | F54: 0805 | G54: 10 V X5R | H54: Generic (match a JLCPCB Basic part) | I54: Assign | J54: Basic (likely) | K54: Yes | M54: 2 | N54: 0.02 | O54: 0.01 | P54: Estimate | Q54: =IF($K54="Yes",$C54*Cost!$B$6,0) -> 20 | R54: =IF($K54<>"Yes",0,IF(AND($P54="Estimate",$N54>0,$B54<>"PCB"),MAX($C54*Cost!$B$6*$N54,Cost!$B$8),$C54*Cost!$B$6*$N54)) -> 0.4 | S54: =IF($K54="Yes",$C54*Cost!$B$7*$O54,0) -> 4 | U54: =IF(AND($K54="Yes",$M54>0,$B54<>"PCB"),IF(LEFT($H54,7)="Generic","G|"&$E54&"|"&$F54&"|"&$G54,"M|"&$H54),"") -> G|10 µF|0805|10 V X5R | V54: =IF($U54="",0,IF(COUNTIF($U$4:$U54,$U54)=1,1,0)) -> 0
A55: 5 Power (digital 3.3 V and analog ±4.5 V) | B55: U501 | C55: 1 | D55: Charge pump + low-noise LDOs, ±4.5 V at up to ±250 mA from 5 V, separate EN±, power-good | E55: ±4.5 V | F55: WSON-12 2 × 3 mm | G55: 2.7–5.5 V in, 2 MHz | H55: TI LM27762DSSR | I55: LCSC C473398 | J55: Extended | K55: Yes | L55: Yes | M55: 13 | N55: 1.1014 | O55: 0.7468 | P55: Quote | Q55: =IF($K55="Yes",$C55*Cost!$B$6,0) -> 5 | R55: =IF($K55<>"Yes",0,IF(AND($P55="Estimate",$N55>0,$B55<>"PCB"),MAX($C55*Cost!$B$6*$N55,Cost!$B$8),$C55*Cost!$B$6*$N55)) -> 5.507 | S55: =IF($K55="Yes",$C55*Cost!$B$7*$O55,0) -> 74.68 | U55: =IF(AND($K55="Yes",$M55>0,$B55<>"PCB"),IF(LEFT($H55,7)="Generic","G|"&$E55&"|"&$F55&"|"&$G55,"M|"&$H55),"") -> M|TI LM27762DSSR | V55: =IF($U55="",0,IF(COUNTIF($U$4:$U55,$U55)=1,1,0)) -> 1
A56: 5 Power (digital 3.3 V and analog ±4.5 V) | B56: C501 | C56: 1 | D56: Capacitor, LM27762 input (part of the ≤ 10 µF VBUS budget) | E56: 4.7 µF | F56: 0603 | G56: 10 V X5R | H56: Generic (match a JLCPCB Basic part) | I56: Assign | J56: Basic (likely) | K56: Yes | M56: 2 | N56: 0.012 | O56: 0.005 | P56: Estimate | Q56: =IF($K56="Yes",$C56*Cost!$B$6,0) -> 5 | R56: =IF($K56<>"Yes",0,IF(AND($P56="Estimate",$N56>0,$B56<>"PCB"),MAX($C56*Cost!$B$6*$N56,Cost!$B$8),$C56*Cost!$B$6*$N56)) -> 0.1 | S56: =IF($K56="Yes",$C56*Cost!$B$7*$O56,0) -> 0.5 | U56: =IF(AND($K56="Yes",$M56>0,$B56<>"PCB"),IF(LEFT($H56,7)="Generic","G|"&$E56&"|"&$F56&"|"&$G56,"M|"&$H56),"") -> G|4.7 µF|0603|10 V X5R | V56: =IF($U56="",0,IF(COUNTIF($U$4:$U56,$U56)=1,1,0)) -> 1
A57: 5 Power (digital 3.3 V and analog ±4.5 V) | B57: C502 | C57: 1 | D57: Capacitor, LM27762 flying capacitor | E57: 1 µF | F57: 0603 | G57: 10 V X7R | H57: Generic (match a JLCPCB Basic part) | I57: Assign | J57: Basic (likely) | K57: Yes | M57: 2 | N57: 0.01 | O57: 0.004 | P57: Estimate | Q57: =IF($K57="Yes",$C57*Cost!$B$6,0) -> 5 | R57: =IF($K57<>"Yes",0,IF(AND($P57="Estimate",$N57>0,$B57<>"PCB"),MAX($C57*Cost!$B$6*$N57,Cost!$B$8),$C57*Cost!$B$6*$N57)) -> 0.1 | S57: =IF($K57="Yes",$C57*Cost!$B$7*$O57,0) -> 0.4 | U57: =IF(AND($K57="Yes",$M57>0,$B57<>"PCB"),IF(LEFT($H57,7)="Generic","G|"&$E57&"|"&$F57&"|"&$G57,"M|"&$H57),"") -> G|1 µF|0603|10 V X7R | V57: =IF($U57="",0,IF(COUNTIF($U$4:$U57,$U57)=1,1,0)) -> 1
A58: 5 Power (digital 3.3 V and analog ±4.5 V) | B58: C503, C504 | C58: 2 | D58: Capacitor, LM27762 charge-pump output (CPOUT) and LDO outputs (per datasheet) | E58: 10 µF | F58: 0805 | G58: 10 V X5R | H58: Generic (match a JLCPCB Basic part) | I58: Assign | J58: Basic (likely) | K58: Yes | M58: 2 | N58: 0.02 | O58: 0.01 | P58: Estimate | Q58: =IF($K58="Yes",$C58*Cost!$B$6,0) -> 10 | R58: =IF($K58<>"Yes",0,IF(AND($P58="Estimate",$N58>0,$B58<>"PCB"),MAX($C58*Cost!$B$6*$N58,Cost!$B$8),$C58*Cost!$B$6*$N58)) -> 0.2 | S58: =IF($K58="Yes",$C58*Cost!$B$7*$O58,0) -> 2 | U58: =IF(AND($K58="Yes",$M58>0,$B58<>"PCB"),IF(LEFT($H58,7)="Generic","G|"&$E58&"|"&$F58&"|"&$G58,"M|"&$H58),"") -> G|10 µF|0805|10 V X5R | V58: =IF($U58="",0,IF(COUNTIF($U$4:$U58,$U58)=1,1,0)) -> 0
A59: 5 Power (digital 3.3 V and analog ±4.5 V) | B59: C505 | C59: 1 | D59: Capacitor, LM27762 negative LDO output | E59: 10 µF | F59: 0805 | G59: 10 V X5R | H59: Generic (match a JLCPCB Basic part) | I59: Assign | J59: Basic (likely) | K59: Yes | M59: 2 | N59: 0.02 | O59: 0.01 | P59: Estimate | Q59: =IF($K59="Yes",$C59*Cost!$B$6,0) -> 5 | R59: =IF($K59<>"Yes",0,IF(AND($P59="Estimate",$N59>0,$B59<>"PCB"),MAX($C59*Cost!$B$6*$N59,Cost!$B$8),$C59*Cost!$B$6*$N59)) -> 0.1 | S59: =IF($K59="Yes",$C59*Cost!$B$7*$O59,0) -> 1 | U59: =IF(AND($K59="Yes",$M59>0,$B59<>"PCB"),IF(LEFT($H59,7)="Generic","G|"&$E59&"|"&$F59&"|"&$G59,"M|"&$H59),"") -> G|10 µF|0805|10 V X5R | V59: =IF($U59="",0,IF(COUNTIF($U$4:$U59,$U59)=1,1,0)) -> 0
A60: 5 Power (digital 3.3 V and analog ±4.5 V) | B60: R501–R504 | C60: 4 | D60: Resistor, LM27762 feedback dividers for +4.5 V and −4.5 V (values per datasheet equations) | E60: [per datasheet] | F60: 0402 | G60: 1% | H60: Generic (match a JLCPCB Basic part) | I60: Assign | J60: Basic (likely) | K60: Yes | M60: 2 | N60: 0.004 | O60: 0.001 | P60: Estimate | Q60: =IF($K60="Yes",$C60*Cost!$B$6,0) -> 20 | R60: =IF($K60<>"Yes",0,IF(AND($P60="Estimate",$N60>0,$B60<>"PCB"),MAX($C60*Cost!$B$6*$N60,Cost!$B$8),$C60*Cost!$B$6*$N60)) -> 0.1 | S60: =IF($K60="Yes",$C60*Cost!$B$7*$O60,0) -> 0.4 | U60: =IF(AND($K60="Yes",$M60>0,$B60<>"PCB"),IF(LEFT($H60,7)="Generic","G|"&$E60&"|"&$F60&"|"&$G60,"M|"&$H60),"") -> G|[per datasheet]|0402|1% | V60: =IF($U60="",0,IF(COUNTIF($U$4:$U60,$U60)=1,1,0)) -> 1
A61: 5 Power (digital 3.3 V and analog ±4.5 V) | B61: R505 | C61: 1 | D61: Resistor, LM27762 PG pull-up to 3V3 (RAILS_OK_N → MCU) | E61: 100 kΩ | F61: 0402 | G61: 1% | H61: Generic (match a JLCPCB Basic part) | I61: Assign | J61: Basic (likely) | K61: Yes | M61: 2 | N61: 0.004 | O61: 0.001 | P61: Estimate | Q61: =IF($K61="Yes",$C61*Cost!$B$6,0) -> 5 | R61: =IF($K61<>"Yes",0,IF(AND($P61="Estimate",$N61>0,$B61<>"PCB"),MAX($C61*Cost!$B$6*$N61,Cost!$B$8),$C61*Cost!$B$6*$N61)) -> 0.1 | S61: =IF($K61="Yes",$C61*Cost!$B$7*$O61,0) -> 0.1 | U61: =IF(AND($K61="Yes",$M61>0,$B61<>"PCB"),IF(LEFT($H61,7)="Generic","G|"&$E61&"|"&$F61&"|"&$G61,"M|"&$H61),"") -> G|100 kΩ|0402|1% | V61: =IF($U61="",0,IF(COUNTIF($U$4:$U61,$U61)=1,1,0)) -> 0
A62: 5 Power (digital 3.3 V and analog ±4.5 V) | B62: U502 | C62: 1 | D62: LDO, digital 3V3 for MCU, CPLD, oscillators and DAC DVCC (low dropout) | E62: 3.3 V, 500 mA | F62: SOT-23-5 | G62: ≈ 100 mV dropout at 100 mA | H62: Microne ME6211C33M5G-N | I62: Assign LCSC no. | J62: Basic (likely) | K62: Yes | M62: 5 | N62: 0.06 | O62: 0.04 | P62: Estimate | Q62: =IF($K62="Yes",$C62*Cost!$B$6,0) -> 5 | R62: =IF($K62<>"Yes",0,IF(AND($P62="Estimate",$N62>0,$B62<>"PCB"),MAX($C62*Cost!$B$6*$N62,Cost!$B$8),$C62*Cost!$B$6*$N62)) -> 0.3 | S62: =IF($K62="Yes",$C62*Cost!$B$7*$O62,0) -> 4 | U62: =IF(AND($K62="Yes",$M62>0,$B62<>"PCB"),IF(LEFT($H62,7)="Generic","G|"&$E62&"|"&$F62&"|"&$G62,"M|"&$H62),"") -> M|Microne ME6211C33M5G-N | V62: =IF($U62="",0,IF(COUNTIF($U$4:$U62,$U62)=1,1,0)) -> 1
A63: 5 Power (digital 3.3 V and analog ±4.5 V) | B63: C506, C507 | C63: 2 | D63: Capacitor, 3V3 LDO input and output | E63: 1 µF | F63: 0402 | G63: 10 V X5R | H63: Generic (match a JLCPCB Basic part) | I63: Assign | J63: Basic (likely) | K63: Yes | M63: 2 | N63: 0.008 | O63: 0.003 | P63: Estimate | Q63: =IF($K63="Yes",$C63*Cost!$B$6,0) -> 10 | R63: =IF($K63<>"Yes",0,IF(AND($P63="Estimate",$N63>0,$B63<>"PCB"),MAX($C63*Cost!$B$6*$N63,Cost!$B$8),$C63*Cost!$B$6*$N63)) -> 0.1 | S63: =IF($K63="Yes",$C63*Cost!$B$7*$O63,0) -> 0.6 | U63: =IF(AND($K63="Yes",$M63>0,$B63<>"PCB"),IF(LEFT($H63,7)="Generic","G|"&$E63&"|"&$F63&"|"&$G63,"M|"&$H63),"") -> G|1 µF|0402|10 V X5R | V63: =IF($U63="",0,IF(COUNTIF($U$4:$U63,$U63)=1,1,0)) -> 0
A64: 6 Protection and control | B64: U601 | C64: 1 | D64: Comparator, dual, open collector, on ±4.5 V: window detector for DC on any leg | E64: — | F64: SOIC-8 | G64: 2–36 V | H64: LM393DR (any Basic source) | I64: Assign LCSC no. | J64: Basic (likely) | K64: Yes | M64: 8 | N64: 0.05 | O64: 0.03 | P64: Estimate | Q64: =IF($K64="Yes",$C64*Cost!$B$6,0) -> 5 | R64: =IF($K64<>"Yes",0,IF(AND($P64="Estimate",$N64>0,$B64<>"PCB"),MAX($C64*Cost!$B$6*$N64,Cost!$B$8),$C64*Cost!$B$6*$N64)) -> 0.25 | S64: =IF($K64="Yes",$C64*Cost!$B$7*$O64,0) -> 3 | U64: =IF(AND($K64="Yes",$M64>0,$B64<>"PCB"),IF(LEFT($H64,7)="Generic","G|"&$E64&"|"&$F64&"|"&$G64,"M|"&$H64),"") -> M|LM393DR (any Basic source) | V64: =IF($U64="",0,IF(COUNTIF($U$4:$U64,$U64)=1,1,0)) -> 1
A65: 6 Protection and control | B65: R601–R604 | C65: 4 | D65: Resistor, DC-detect filter, one per leg | E65: 100 kΩ | F65: 0402 | G65: 1% | H65: Generic (match a JLCPCB Basic part) | I65: Assign | J65: Basic (likely) | K65: Yes | M65: 2 | N65: 0.004 | O65: 0.001 | P65: Estimate | Q65: =IF($K65="Yes",$C65*Cost!$B$6,0) -> 20 | R65: =IF($K65<>"Yes",0,IF(AND($P65="Estimate",$N65>0,$B65<>"PCB"),MAX($C65*Cost!$B$6*$N65,Cost!$B$8),$C65*Cost!$B$6*$N65)) -> 0.1 | S65: =IF($K65="Yes",$C65*Cost!$B$7*$O65,0) -> 0.4 | U65: =IF(AND($K65="Yes",$M65>0,$B65<>"PCB"),IF(LEFT($H65,7)="Generic","G|"&$E65&"|"&$F65&"|"&$G65,"M|"&$H65),"") -> G|100 kΩ|0402|1% | V65: =IF($U65="",0,IF(COUNTIF($U$4:$U65,$U65)=1,1,0)) -> 0
A66: 6 Protection and control | B66: C601–C604 | C66: 4 | D66: Capacitor, DC-detect filter (τ = 100 ms) | E66: 1 µF | F66: 0603 | G66: 10 V X7R | H66: Generic (match a JLCPCB Basic part) | I66: Assign | J66: Basic (likely) | K66: Yes | M66: 2 | N66: 0.01 | O66: 0.004 | P66: Estimate | Q66: =IF($K66="Yes",$C66*Cost!$B$6,0) -> 20 | R66: =IF($K66<>"Yes",0,IF(AND($P66="Estimate",$N66>0,$B66<>"PCB"),MAX($C66*Cost!$B$6*$N66,Cost!$B$8),$C66*Cost!$B$6*$N66)) -> 0.2 | S66: =IF($K66="Yes",$C66*Cost!$B$7*$O66,0) -> 1.6 | U66: =IF(AND($K66="Yes",$M66>0,$B66<>"PCB"),IF(LEFT($H66,7)="Generic","G|"&$E66&"|"&$F66&"|"&$G66,"M|"&$H66),"") -> G|1 µF|0603|10 V X7R | V66: =IF($U66="",0,IF(COUNTIF($U$4:$U66,$U66)=1,1,0)) -> 0
A67: 6 Protection and control | B67: D601–D604 | C67: 4 | D67: Diode pair, diode-OR of each leg into MAX and MIN nodes | E67: BAV99 | F67: SOT-23 | G67: — | H67: Generic (match a JLCPCB Basic part) | I67: Assign | J67: Basic (likely) | K67: Yes | M67: 3 | N67: 0.012 | O67: 0.006 | P67: Estimate | Q67: =IF($K67="Yes",$C67*Cost!$B$6,0) -> 20 | R67: =IF($K67<>"Yes",0,IF(AND($P67="Estimate",$N67>0,$B67<>"PCB"),MAX($C67*Cost!$B$6*$N67,Cost!$B$8),$C67*Cost!$B$6*$N67)) -> 0.24 | S67: =IF($K67="Yes",$C67*Cost!$B$7*$O67,0) -> 2.4 | U67: =IF(AND($K67="Yes",$M67>0,$B67<>"PCB"),IF(LEFT($H67,7)="Generic","G|"&$E67&"|"&$F67&"|"&$G67,"M|"&$H67),"") -> G|BAV99|SOT-23|— | V67: =IF($U67="",0,IF(COUNTIF($U$4:$U67,$U67)=1,1,0)) -> 1
... A75: 6 Protection and control | B75: C605 | C75: 1 | D75: Capacitor, latch power-up set (latch starts in the fault state until firmware clears it) | E75: 100 nF | F75: 0402 | G75: 16 V X7R | H75: Generic (match a JLCPCB Basic part) | I75: Assign | J75: Basic (likely) | K75: Yes | M75: 2 | N75: 0.005 | O75: 0.0015 | P75: Estimate | Q75: =IF($K75="Yes",$C75*Cost!$B$6,0) -> 5 | R75: =IF($K75<>"Yes",0,IF(AND($P75="Estimate",$N75>0,$B75<>"PCB"),MAX($C75*Cost!$B$6*$N75,Cost!$B$8),$C75*Cost!$B$6*$N75)) -> 0.1 | S75: =IF($K75="Yes",$C75*Cost!$B$7*$O75,0) -> 0.15 | U75: =IF(AND($K75="Yes",$M75>0,$B75<>"PCB"),IF(LEFT($H75,7)="Generic","G|"&$E75&"|"&$F75&"|"&$G75,"M|"&$H75),"") -> G|100 nF|0402|16 V X7R | V75: =IF($U75="",0,IF(COUNTIF($U$4:$U75,$U75)=1,1,0)) -> 0
A76: 7 Outputs, indicators, test, board | B76: J701 | C76: 1 | D76: Jack, 4.4 mm 5-pole balanced (L+, L−, R+, R−, GND) | E76: — | F76: Through-hole | G76: Gold-plated | H76: G-Switch GT-3321667P-01 | I76: LCSC C2762984 | J76: Extended | K76: Yes | M76: 0 | N76: 6.8656 | O76: 4.2768 | P76: Quote | Q76: =IF($K76="Yes",$C76*Cost!$B$6,0) -> 5 | R76: =IF($K76<>"Yes",0,IF(AND($P76="Estimate",$N76>0,$B76<>"PCB"),MAX($C76*Cost!$B$6*$N76,Cost!$B$8),$C76*Cost!$B$6*$N76)) -> 34.328 | S76: =IF($K76="Yes",$C76*Cost!$B$7*$O76,0) -> 427.68 | T76: THT: ≈ 7 hand-soldered joints | U76: =IF(AND($K76="Yes",$M76>0,$B76<>"PCB"),IF(LEFT($H76,7)="Generic","G|"&$E76&"|"&$F76&"|"&$G76,"M|"&$H76),"") | V76: =IF($U76="",0,IF(COUNTIF($U$4:$U76,$U76)=1,1,0)) -> 0
A77: 7 Outputs, indicators, test, board | B77: J702 | C77: 1 | D77: Jack, 3.5 mm (TRRS body used with TRS plugs; ring 2 tied to GND) | E77: — | F77: SMD | G77: Gold-plated, 1 A | H77: HRO PJ-332A-6A | I77: LCSC C2848643 | J77: Extended | K77: Yes | M77: 6 | N77: 0.2921 | O77: 0.2326 | P77: Quote | Q77: =IF($K77="Yes",$C77*Cost!$B$6,0) -> 5 | R77: =IF($K77<>"Yes",0,IF(AND($P77="Estimate",$N77>0,$B77<>"PCB"),MAX($C77*Cost!$B$6*$N77,Cost!$B$8),$C77*Cost!$B$6*$N77)) -> 1.4605 | S77: =IF($K77="Yes",$C77*Cost!$B$7*$O77,0) -> 23.26 | U77: =IF(AND($K77="Yes",$M77>0,$B77<>"PCB"),IF(LEFT($H77,7)="Generic","G|"&$E77&"|"&$F77&"|"&$G77,"M|"&$H77),"") -> M|HRO PJ-332A-6A | V77: =IF($U77="",0,IF(COUNTIF($U$4:$U77,$U77)=1,1,0)) -> 1
A78: 7 Outputs, indicators, test, board | B78: D701–D704 | C78: 4 | D78: ESD diode, bidirectional, one per jack leg | E78: PESD15VL1BA | F78: SOD-323 | G78: 15 V standoff, 16 pF typ | H78: Nexperia PESD15VL1BA,115 | I78: LCSC C85378 | J78: Extended | K78: Yes | M78: 2 | N78: 0.06 | O78: 0.0318 | P78: Quote | Q78: =IF($K78="Yes",$C78*Cost!$B$6,0) -> 20 | R78: =IF($K78<>"Yes",0,IF(AND($P78="Estimate",$N78>0,$B78<>"PCB"),MAX($C78*Cost!$B$6*$N78,Cost!$B$8),$C78*Cost!$B$6*$N78)) -> 1.2 | S78: =IF($K78="Yes",$C78*Cost!$B$7*$O78,0) -> 12.72 | U78: =IF(AND($K78="Yes",$M78>0,$B78<>"PCB"),IF(LEFT($H78,7)="Generic","G|"&$E78&"|"&$F78&"|"&$G78,"M|"&$H78),"") -> M|Nexperia PESD15VL1BA,115 | V78: =IF($U78="",0,IF(COUNTIF($U$4:$U78,$U78)=1,1,0)) -> 1
A79: 7 Outputs, indicators, test, board | B79: D705, D706 | C79: 2 | D79: LED, status (green) and fault (red), driven directly by 3.3 V GPIO | E79: — | F79: 0603 | G79: — | H79: Generic (match a JLCPCB Basic part) | I79: Assign | J79: Basic (likely) | K79: Yes | M79: 2 | N79: 0.012 | O79: 0.006 | P79: Estimate | Q79: =IF($K79="Yes",$C79*Cost!$B$6,0) -> 10 | R79: =IF($K79<>"Yes",0,IF(AND($P79="Estimate",$N79>0,$B79<>"PCB"),MAX($C79*Cost!$B$6*$N79,Cost!$B$8),$C79*Cost!$B$6*$N79)) -> 0.12 | S79: =IF($K79="Yes",$C79*Cost!$B$7*$O79,0) -> 1.2 | U79: =IF(AND($K79="Yes",$M79>0,$B79<>"PCB"),IF(LEFT($H79,7)="Generic","G|"&$E79&"|"&$F79&"|"&$G79,"M|"&$H79),"") -> G|—|0603|— | V79: =IF($U79="",0,IF(COUNTIF($U$4:$U79,$U79)=1,1,0)) -> 1
A80: 7 Outputs, indicators, test, board | B80: R701, R702 | C80: 2 | D80: Resistor, LED series | E80: 1 kΩ | F80: 0402 | G80: 1% | H80: Generic (match a JLCPCB Basic part) | I80: Assign | J80: Basic (likely) | K80: Yes | M80: 2 | N80: 0.004 | O80: 0.001 | P80: Estimate | Q80: =IF($K80="Yes",$C80*Cost!$B$6,0) -> 10 | R80: =IF($K80<>"Yes",0,IF(AND($P80="Estimate",$N80>0,$B80<>"PCB"),MAX($C80*Cost!$B$6*$N80,Cost!$B$8),$C80*Cost!$B$6*$N80)) -> 0.1 | S80: =IF($K80="Yes",$C80*Cost!$B$7*$O80,0) -> 0.2 | U80: =IF(AND($K80="Yes",$M80>0,$B80<>"PCB"),IF(LEFT($H80,7)="Generic","G|"&$E80&"|"&$F80&"|"&$G80,"M|"&$H80),"") -> G|1 kΩ|0402|1% | V80: =IF($U80="",0,IF(COUNTIF($U$4:$U80,$U80)=1,1,0)) -> 1
A81: 7 Outputs, indicators, test, board | B81: J703 | C81: 1 | D81: Header, 3.3 V I²S test port (MCLK, BCLK, LRCLK, SDATA, GND, 3V3 ref) | E81: 1 × 6 | F81: 2.54 mm | G81: — | H81: Generic (Extended part expected) | I81: Assign | J81: — | K81: DNF | M81: 0 | N81: 0.1 | O81: 0.05 | P81: Estimate | Q81: =IF($K81="Yes",$C81*Cost!$B$6,0) -> 0 | R81: =IF($K81<>"Yes",0,IF(AND($P81="Estimate",$N81>0,$B81<>"PCB"),MAX($C81*Cost!$B$6*$N81,Cost!$B$8),$C81*Cost!$B$6*$N81)) -> 0 | S81: =IF($K81="Yes",$C81*Cost!$B$7*$O81,0) -> 0 | U81: =IF(AND($K81="Yes",$M81>0,$B81<>"PCB"),IF(LEFT($H81,7)="Generic","G|"&$E81&"|"&$F81&"|"&$G81,"M|"&$H81),"") | V81: =IF($U81="",0,IF(COUNTIF($U$4:$U81,$U81)=1,1,0)) -> 0
A82: 7 Outputs, indicators, test, board | B82: TP701–TP724 | C82: 24 | D82: Test pads: rails, clocks, I²S, EN/PG/fault nodes, 4 GND (copper only) | E82: — | F82: Pad | G82: — | H82: No part | I82: — | J82: — | K82: No part | M82: 0 | N82: 0 | O82: 0 | P82: Estimate | Q82: =IF($K82="Yes",$C82*Cost!$B$6,0) -> 0 | R82: =IF($K82<>"Yes",0,IF(AND($P82="Estimate",$N82>0,$B82<>"PCB"),MAX($C82*Cost!$B$6*$N82,Cost!$B$8),$C82*Cost!$B$6*$N82)) -> 0 | S82: =IF($K82="Yes",$C82*Cost!$B$7*$O82,0) -> 0 | U82: =IF(AND($K82="Yes",$M82>0,$B82<>"PCB"),IF(LEFT($H82,7)="Generic","G|"&$E82&"|"&$F82&"|"&$G82,"M|"&$H82),"") | V82: =IF($U82="",0,IF(COUNTIF($U$4:$U82,$U82)=1,1,0)) -> 0
A83: 7 Outputs, indicators, test, board | B83: MH, FID | C83: 7 | D83: M3 mounting holes (4) and fiducials (3) | E83: — | F83: — | G83: — | H83: No part | I83: — | J83: — | K83: No part | M83: 0 | N83: 0 | O83: 0 | P83: Estimate | Q83: =IF($K83="Yes",$C83*Cost!$B$6,0) -> 0 | R83: =IF($K83<>"Yes",0,IF(AND($P83="Estimate",$N83>0,$B83<>"PCB"),MAX($C83*Cost!$B$6*$N83,Cost!$B$8),$C83*Cost!$B$6*$N83)) -> 0 | S83: =IF($K83="Yes",$C83*Cost!$B$7*$O83,0) -> 0 | U83: =IF(AND($K83="Yes",$M83>0,$B83<>"PCB"),IF(LEFT($H83,7)="Generic","G|"&$E83&"|"&$F83&"|"&$G83,"M|"&$H83),"") | V83: =IF($U83="",0,IF(COUNTIF($U$4:$U83,$U83)=1,1,0)) -> 0
A84: 7 Outputs, indicators, test, board | B84: PCB | C84: 1 | D84: Bare board, 4 layers, ≤ 80 × 60 mm, 90 Ω USB pair | E84: — | F84: — | G84: JLCPCB | H84: JLCPCB | I84: JLCPCB | J84: — | K84: Yes | M84: 0 | N84: 2 | O84: 0.8 | P84: Estimate | Q84: =IF($K84="Yes",$C84*Cost!$B$6,0) -> 5 | R84: =IF($K84<>"Yes",0,IF(AND($P84="Estimate",$N84>0,$B84<>"PCB"),MAX($C84*Cost!$B$6*$N84,Cost!$B$8),$C84*Cost!$B$6*$N84)) -> 10 | S84: =IF($K84="Yes",$C84*Cost!$B$7*$O84,0) -> 80 | U84: =IF(AND($K84="Yes",$M84>0,$B84<>"PCB"),IF(LEFT($H84,7)="Generic","G|"&$E84&"|"&$F84&"|"&$G84,"M|"&$H84),"") | V84: =IF($U84="",0,IF(COUNTIF($U$4:$U84,$U84)=1,1,0)) -> 0
A86: Totals, fitted lines (line-cost columns include the bare-PCB row) | Q86: =SUM(Q4:Q84) -> 915 | R86: =SUM(R4:R84) -> 151.6765 | S86: =SUM(S4:S84) -> 1997.2
A87: Parts only (bare PCB excluded) | R87: =SUMIFS(R4:R84,B4:B84,"<>PCB") -> 141.6765 | S87: =SUMIFS(S4:S84,B4:B84,"<>PCB") -> 1917.2

Sheet Purchasing list
A1: Purchasing list — fitted parts merged by part number / specification
A2: One row per distinct part; generic parts are merged by value, package and rating. Ext. cost = quantity × unit price; the US$0.10 minimum spend per estimated passive line is applied on the Parts list and in the Cost sheet, not here. The bare PCBs are costed on the Cost sheet.
A3: Item | B3: Part type | C3: Part number (MPN) | D3: Value | E3: Package | F3: Rating / tolerance | G3: Source / LCSC no. | H3: JLCPCB library type | I3: Designators | J3: Qty per board | K3: Qty for 5-board run | L3: Unit price US$ (1–9 pcs) | M3: Unit price US$ (100-board tier) | N3: Price basis | O3: Leadless (X-ray) | P3: Ext. cost US$, 5-board run | Q3: Ext. per board US$ (100-board tier)
A4: 1 | B4: Jack | C4: G-Switch GT-3321667P-01 | D4: — | E4: Through-hole | F4: Gold-plated | G4: LCSC C2762984 | H4: Extended | I4: J701 | J4: 1 | K4: =$J4*Cost!$B$6 -> 5 | L4: 6.8656 | M4: 4.2768 | N4: Quote | P4: =$K4*$L4 -> 34.328 | Q4: =$J4*$M4 -> 4.2768
A5: 2 | B5: Op-amp | C5: TI OPA1622IDRCR | D5: — | E5: VSON-10 3 × 3 mm | F5: Isc +145/−130 mA typ; thermal pad to V− | G5: LCSC C2876559 | H5: Extended | I5: U401, U402 | J5: 2 | K5: =$J5*Cost!$B$6 -> 10 | L5: 2.6271 | M5: 2.1108 | N5: Quote | O5: Yes | P5: =$K5*$L5 -> 26.271 | Q5: =$J5*$M5 -> 4.2216
A6: 3 | B6: DAC | C6: ESS ES9018K2M | D6: — | E6: QFN-28 5 × 5 mm | F6: DNR 127 dB, THD+N −120 dB (datasheet) | G6: LCSC C2688377 | H6: Extended | I6: U301 | J6: 1 | K6: =$J6*Cost!$B$6 -> 5 | L6: 3.4678 | M6: 2.278 | N6: Quote | O6: Yes | P6: =$K6*$L6 -> 17.339 | Q6: =$J6*$M6 -> 2.278
A7: 4 | B7: MCU | C7: WCH CH32V307RCT6 | D7: — | E7: LQFP-64 10 × 10 mm | F7: 144 MHz, 3.3 V | G7: LCSC C2988083 | H7: Extended | I7: U201 | J7: 1 | K7: =$J7*Cost!$B$6 -> 5 | L7: 3.45 | M7: 2.3305 | N7: Quote | P7: =$K7*$L7 -> 17.25 | Q7: =$J7*$M7 -> 2.3305
A8: 5 | B8: Op-amp | C8: TI OPA1678IDR | D8: — | E8: SOIC-8 | F8: 4.5 nV/√Hz, rail-to-rail output, ±2.25 to ±18 V | G8: LCSC C192421 | H8: Extended | I8: U403, U404 | J8: 2 | K8: =$J8*Cost!$B$6 -> 10 | L8: 0.97 | M8: 0.8368 | N8: Quote | P8: =$K8*$L8 -> 9.7 | Q8: =$J8*$M8 -> 1.6736
A9: 6 | B9: CPLD | C9: AGM AGRV2KQ32 | D9: — | E9: QFN-32 4 × 4 mm | F9: 3.3 V | G9: LCSC C18208899 | H9: Extended | I9: U202 | J9: 1 | K9: =$J9*Cost!$B$6 -> 5 | L9: 1.6503 | M9: 1.1117 | N9: Quote | O9: Yes | P9: =$K9*$L9 -> 8.2515 | Q9: =$J9*$M9 -> 1.1117
A10: 7 | B10: Charge pump + low-noise LDOs | C10: TI LM27762DSSR | D10: ±4.5 V | E10: WSON-12 2 × 3 mm | F10: 2.7–5.5 V in, 2 MHz | G10: LCSC C473398 | H10: Extended | I10: U501 | J10: 1 | K10: =$J10*Cost!$B$6 -> 5 | L10: 1.1014 | M10: 0.7468 | N10: Quote | O10: Yes | P10: =$K10*$L10 -> 5.507 | Q10: =$J10*$M10 -> 0.7468
A11: 8 | B11: Jack | C11: HRO PJ-332A-6A | D11: — | E11: SMD | F11: Gold-plated, 1 A | G11: LCSC C2848643 | H11: Extended | I11: J702 | J11: 1 | K11: =$J11*Cost!$B$6 -> 5 | L11: 0.2921 | M11: 0.2326 | N11: Quote | P11: =$K11*$L11 -> 1.4605 | Q11: =$J11*$M11 -> 0.2326
A12: 9 | B12: ESD diode | C12: Nexperia PESD15VL1BA,115 | D12: PESD15VL1BA | E12: SOD-323 | F12: 15 V standoff, 16 pF typ | G12: LCSC C85378 | H12: Extended | I12: D701–D704 | J12: 4 | K12: =$J12*Cost!$B$6 -> 20 | L12: 0.06 | M12: 0.0318 | N12: Quote | P12: =$K12*$L12 -> 1.2 | Q12: =$J12*$M12 -> 0.1272
A13: 10 | B13: USB-C receptacle | C13: HRO TYPE-C-31-M-12 | D13: — | E13: SMD | F13: 20 V, 5 A | G13: LCSC C165948 | H13: Extended | I13: J101 | J13: 1 | K13: =$J13*Cost!$B$6 -> 5 | L13: 0.1879 | M13: 0.129 | N13: Quote | P13: =$K13*$L13 -> 0.9395 | Q13: =$J13*$M13 -> 0.129
A14: 11 | B14: ESD array | C14: ST USBLC6-2SC6 | D14: — | E14: SOT-23-6 | F14: 5.25 V | G14: LCSC C7519 | H14: Extended | I14: U101 | J14: 1 | K14: =$J14*Cost!$B$6 -> 5 | L14: 0.1844 | M14: 0.13 | N14: Quote | P14: =$K14*$L14 -> 0.922 | Q14: =$J14*$M14 -> 0.13
A15: 12 | B15: LDO | C15: TI LP5907MFX-3.3/NOPB | D15: 3.3 V, 250 mA | E15: SOT-23-5 | F15: 6.5 µVrms | G15: Assign LCSC no. | H15: Extended | I15: U302 | J15: 1 | K15: =$J15*Cost!$B$6 -> 5 | L15: 0.1746 | M15: 0.109 | N15: Estimate | P15: =$K15*$L15 -> 0.873 | Q15: =$J15*$M15 -> 0.109
A16: 13 | B16: LDO | C16: AMS1117-ADJ | D16: 1.3 V, ≥ 50 mA | E16: SOT-223 | F16: Adjustable, 1.25 V ref | G16: Assign LCSC no. | H16: Basic (likely) | I16: U303 | J16: 1 | K16: =$J16*Cost!$B$6 -> 5 | L16: 0.08 | M16: 0.05 | N16: Estimate | P16: =$K16*$L16 -> 0.4 | Q16: =$J16*$M16 -> 0.05
A17: 14 | B17: LDO | C17: Microne ME6211C33M5G-N | D17: 3.3 V, 500 mA | E17: SOT-23-5 | F17: ≈ 100 mV dropout at 100 mA | G17: Assign LCSC no. | H17: Basic (likely) | I17: U502 | J17: 1 | K17: =$J17*Cost!$B$6 -> 5 | L17: 0.06 | M17: 0.04 | N17: Estimate | P17: =$K17*$L17 -> 0.3 | Q17: =$J17*$M17 -> 0.04
A18: 15 | B18: Comparator | C18: LM393DR (any Basic source) | D18: — | E18: SOIC-8 | F18: 2–36 V | G18: Assign LCSC no. | H18: Basic (likely) | I18: U601 | J18: 1 | K18: =$J18*Cost!$B$6 -> 5 | L18: 0.05 | M18: 0.03 | N18: Estimate | P18: =$K18*$L18 -> 0.25 | Q18: =$J18*$M18 -> 0.03
A19: 16 | B19: Ferrite bead | C19: Sunlord GZ1608D601TF | D19: 600 Ω | E19: 0603 | F19: 1.3 A, 0.15 Ω | G19: LCSC C1015 (verify Basic) | H19: Basic (likely) | I19: FB101; FB301 | J19: 2 | K19: =$J19*Cost!$B$6 -> 10 | L19: 0.01 | M19: 0.003 | N19: Estimate | P19: =$K19*$L19 -> 0.1 | Q19: =$J19*$M19 -> 0.006
A20: 17 | B20: Resistor | C20: Generic (Extended part expected) | D20: 2.00 kΩ | E20: 0603 | F20: 0.1% 25 ppm thin film | G20: Assign | H20: Extended | I20: R401–R416 | J20: 16 | K20: =$J20*Cost!$B$6 -> 80 | L20: 0.05 | M20: 0.03 | N20: Estimate | P20: =$K20*$L20 -> 4 | Q20: =$J20*$M20 -> 0.48
A21: 18 | B21: Oscillator | C21: Generic (Extended part expected) | D21: 22.5792 MHz | E21: 3.2 × 2.5 mm | F21: ±25 ppm | G21: Assign | H21: Extended | I21: X201 | J21: 1 | K21: =$J21*Cost!$B$6 -> 5 | L21: 0.5 | M21: 0.35 | N21: Estimate | O21: Yes | P21: =$K21*$L21 -> 2.5 | Q21: =$J21*$M21 -> 0.35
A22: 19 | B22: Oscillator | C22: Generic (Extended part expected) | D22: 24.576 MHz | E22: 3.2 × 2.5 mm | F22: ±25 ppm | G22: Assign | H22: Extended | I22: X202 | J22: 1 | K22: =$J22*Cost!$B$6 -> 5 | L22: 0.5 | M22: 0.35 | N22: Estimate | O22: Yes | P22: =$K22*$L22 -> 2.5 | Q22: =$J22*$M22 -> 0.35
A23: 20 | B23: Capacitor | C23: Generic (match a JLCPCB Basic part) | D23: 10 µF | E23: 0805 | F23: 10 V X5R | G23: Assign | H23: Basic (likely) | I23: C211; C311, C312; C421; C413–C416; C503, C504; C505 | J23: 11 | K23: =$J23*Cost!$B$6 -> 55 | L23: 0.02 | M23: 0.01 | N23: Estimate | P23: =$K23*$L23 -> 1.1 | Q23: =$J23*$M23 -> 0.11
A24: 21 | B24: Capacitor | C24: Generic (match a JLCPCB Basic part) | D24: 100 nF | E24: 0402 | F24: 16 V X7R | G24: Assign | H24: Basic (likely) | I24: C203–C210; C213–C216; C217, C218; C305–C309; C422; C423–C426; C409–C412; C605 | J24: 29 | K24: =$J24*Cost!$B$6 -> 145 | L24: 0.005 | M24: 0.0015 | N24: Estimate | P24: =$K24*$L24 -> 0.725 | Q24: =$J24*$M24 -> 0.0435
A25: 22 | B25: Crystal | C25: Generic (match a JLCPCB Basic part) | D25: 8 MHz | E25: 3.2 × 2.5 mm | F25: ±20 ppm | G25: Assign | H25: Basic (likely) | I25: Y201 | J25: 1 | K25: =$J25*Cost!$B$6 -> 5 | L25: 0.1 | M25: 0.08 | N25: Estimate | P25: =$K25*$L25 -> 0.5 | Q25: =$J25*$M25 -> 0.08
A26: 23 | B26: Capacitor | C26: Generic (match a JLCPCB Basic part) | D26: 470 pF | E26: 0603 | F26: 50 V C0G | G26: Assign | H26: Basic (likely) | I26: C401–C408 | J26: 8 | K26: =$J26*Cost!$B$6 -> 40 | L26: 0.01 | M26: 0.004 | N26: Estimate | P26: =$K26*$L26 -> 0.4 | Q26: =$J26*$M26 -> 0.032
A27: 24 | B27: Capacitor | C27: Generic (match a JLCPCB Basic part) | D27: 1 µF | E27: 0603 | F27: 10 V X7R | G27: Assign | H27: Basic (likely) | I27: C502; C601–C604 | J27: 5 | K27: =$J27*Cost!$B$6 -> 25 | L27: 0.01 | M27: 0.004 | N27: Estimate | P27: =$K27*$L27 -> 0.25 | Q27: =$J27*$M27 -> 0.02
A28: 25 | B28: Diode pair | C28: Generic (match a JLCPCB Basic part) | D28: BAV99 | E28: SOT-23 | F28: — | G28: Assign | H28: Basic (likely) | I28: D601–D604 | J28: 4 | K28: =$J28*Cost!$B$6 -> 20 | L28: 0.012 | M28: 0.006 | N28: Estimate | P28: =$K28*$L28 -> 0.24 | Q28: =$J28*$M28 -> 0.024
A29: 26 | B29: Capacitor | C29: Generic (match a JLCPCB Basic part) | D29: 1 µF | E29: 0402 | F29: 10 V X5R | G29: Assign | H29: Basic (likely) | I29: C102; C301, C302; C506, C507 | J29: 5 | K29: =$J29*Cost!$B$6 -> 25 | L29: 0.008 | M29: 0.003 | N29: Estimate | P29: =$K29*$L29 -> 0.2 | Q29: =$J29*$M29 -> 0.015
A30: 27 | B30: Capacitor | C30: Generic (match a JLCPCB Basic part) | D30: 1.5 nF | E30: 0603 | F30: 50 V C0G | G30: Assign | H30: Basic (likely) | I30: C417–C420 | J30: 4 | K30: =$J30*Cost!$B$6 -> 20 | L30: 0.01 | M30: 0.004 | N30: Estimate | P30: =$K30*$L30 -> 0.2 | Q30: =$J30*$M30 -> 0.016
A31: 28 | B31: NPN + PNP pair forming the 3.3 V fault latch (powered from 3V3 | C31: Generic (match a JLCPCB Basic part) | D31: MMBT3904 / MMBT3906 | E31: SOT-23 | F31: 40 V | G31: Assign | H31: Basic (likely) | I31: Q602, Q603 | J31: 2 | K31: =$J31*Cost!$B$6 -> 10 | L31: 0.02 | M31: 0.01 | N31: Estimate | P31: =$K31*$L31 -> 0.2 | Q31: =$J31*$M31 -> 0.02
A32: 29 | B32: N-MOSFET | C32: Generic (match a JLCPCB Basic part) | D32: 2N7002 | E32: SOT-23 | F32: 60 V | G32: Assign | H32: Basic (likely) | I32: Q605, Q606 | J32: 2 | K32: =$J32*Cost!$B$6 -> 10 | L32: 0.02 | M32: 0.01 | N32: Estimate | P32: =$K32*$L32 -> 0.2 | Q32: =$J32*$M32 -> 0.02
A33: 30 | B33: Capacitor | C33: Generic (match a JLCPCB Basic part) | D33: 2.2 µF | E33: 0603 | F33: 6.3 V X5R | G33: Assign | H33: Basic (likely) | I33: C303, C304; C310 | J33: 3 | K33: =$J33*Cost!$B$6 -> 15 | L33: 0.012 | M33: 0.005 | N33: Estimate | P33: =$K33*$L33 -> 0.18 | Q33: =$J33*$M33 -> 0.015
A34: 31 | B34: Resistor | C34: Generic (match a JLCPCB Basic part) | D34: 100 kΩ | E34: 0402 | F34: 1% | G34: Assign | H34: Basic (likely) | I34: R305; R421, R422; R505; R601–R604 | J34: 8 | K34: =$J34*Cost!$B$6 -> 40 | L34: 0.004 | M34: 0.001 | N34: Estimate | P34: =$K34*$L34 -> 0.16 | Q34: =$J34*$M34 -> 0.008
... A57: 54 | B57: Resistor | C57: Generic (match a JLCPCB Basic part) | D57: 47 kΩ | E57: 0402 | F57: 1% | G57: Assign | H57: Basic (likely) | I57: R611 | J57: 1 | K57: =$J57*Cost!$B$6 -> 5 | L57: 0.004 | M57: 0.001 | N57: Estimate | P57: =$K57*$L57 -> 0.02 | Q57: =$J57*$M57 -> 0.001
B59: Total, all purchase lines | J59: =SUM(J4:J57) -> 182 | K59: =SUM(K4:K57) -> 910 | P59: =SUM(P4:P57) -> 139.9415 | Q59: =SUM(Q4:Q57) -> 19.172

Sheet Cost
A1: Cost — 5-board sample run (JLCPCB Economic PCBA) and 100-unit reference
A2: Revised 24 Sep 2026 (DAC current-mode output, option B) · parts at LCSC 1–9-piece prices (100-board tier for the reference) · JLCPCB PCBA fee schedules · blue on yellow = input · every NTD figure uses the exchange rate in B5
A4: Inputs | B4: Value | C4: Unit | G4: Note
A5: Exchange rate | B5: 31.7 | C5: NTD per US$ | G5: fixed for the cost gate; applies to every NTD figure
A6: Boards in the sample run | B6: 5 | C6: boards | G6: JLCPCB Economic PCBA (one side, 2–50 boards)
A7: Boards in the reference build | B7: 100 | C7: boards | G7: JLCPCB Standard PCBA — reference only, not the budget basis
A8: Minimum spend per estimated passive line | B8: 0.1 | C8: US$ | G8: 5-board run: line = MAX(qty × boards × 1–9-piece price, this value) when Price basis = Estimate and price > 0
A9: Through-hole joints per board | B9: 7 | C9: joints | G9: J701 4.4 mm jack, hand-soldered
A10: Cost target per board, 5-board run | B10: 1500 | C10: NTD | G10: WARNING above; = 7,500 NTD for 5 boards incl. bare PCBs and assembly fees; excl. shipping, import tax, programmers, enclosure
A11: Approved ceiling per board, 5-board run | B11: 1550 | C11: NTD | G11: owner decision 24 Sep 2026 ("a little bit off-budget is acceptable"); FAIL above
A13: Board data (linked from the Parts list) | B13: Value | C13: Unit | G13: Source
A14: Fitted BOM lines | B14: =COUNTIF('Parts list'!$K$4:$K$84,"Yes") -> 76 | C14: lines | G14: Parts list: Fit = Yes (includes the bare-PCB row)
A15: SMT-placed parts per board | B15: =SUMIFS('Parts list'!$C$4:$C$84,'Parts list'!$K$4:$K$84,"Yes",'Parts list'!$M$4:$M$84,">0",'Parts list'!$B$4:$B$84,"<>PCB") -> 181 | C15: parts | G15: Parts list: Qty where Fit = Yes and SMT joints per part > 0
A16: Through-hole parts per board | B16: =SUMIFS('Parts list'!$C$4:$C$84,'Parts list'!$K$4:$K$84,"Yes",'Parts list'!$F$4:$F$84,"Through-hole") -> 1 | C16: parts | G16: Parts list: Package = Through-hole (4.4 mm jack J701)
A17: Extended SMT part types | B17: =SUMIFS('Parts list'!$V$4:$V$84,'Parts list'!$J$4:$J$84,"<>Basic",'Parts list'!$J$4:$J$84,"<>Basic (likely)") -> 14 | C17: types | G17: Parts list helper V: distinct MPN, or value + package + rating for generic parts; library type not Basic
A18: Basic SMT part types | B18: =SUMIFS('Parts list'!$V$4:$V$84,'Parts list'!$J$4:$J$84,"Basic")+SUMIFS('Parts list'!$V$4:$V$84,'Parts list'!$J$4:$J$84,"Basic (likely)") -> 39 | C18: types | G18: Parts list helper V: library type Basic or Basic (likely)
A19: All SMT part types | B19: =B17+B18 -> 53 | C19: types | G19: Extended + Basic (feeder loading on the 100-unit reference)
A20: SMT joints per board | B20: {=SUMPRODUCT(('Parts list'!$K$4:$K$84="Yes")*('Parts list'!$B$4:$B$84<>"PCB")*'Parts list'!$C$4:$C$84*'Parts list'!$M$4:$M$84)} -> 579 | C20: joints | G20: Parts list: Qty × SMT joints per part where Fit = Yes
A21: Leadless parts per board (X-ray) | B21: =SUMIFS('Parts list'!$C$4:$C$84,'Parts list'!$K$4:$K$84,"Yes",'Parts list'!$L$4:$L$84,"Yes") -> 7 | C21: parts | G21: Parts list: Leadless (X-ray) = Yes — CPLD, ES9018K2M, 2 × OPA1622, LM27762, 2 oscillators
A22: of which oscillators | B22: =SUMIFS('Parts list'!$C$4:$C$84,'Parts list'!$K$4:$K$84,"Yes",'Parts list'!$L$4:$L$84,"Yes",'Parts list'!$D$4:$D$84,"Oscillator*") -> 2 | C22: parts | G22: X201, X202 — JLCPCB may not X-ray them
A23: Parts, 5-board run (bare PCB excluded) | B23: =SUMIFS('Parts list'!$R$4:$R$84,'Parts list'!$B$4:$B$84,"<>PCB") -> 141.6765 | C23: US$ | G23: Parts list: Line cost 5-board run, all lines except the PCB row (includes the minimum spend)
A24: of which minimum-spend uplift | B24: {=B23-B6*SUMPRODUCT(('Parts list'!$K$4:$K$84="Yes")*('Parts list'!$B$4:$B$84<>"PCB")*'Parts list'!$C$4:$C$84*'Parts list'!$N$4:$N$84)} -> 1.735 | C24: US$ | G24: line costs above plain qty × boards × 1–9-piece price
A25: Bare 4-layer PCBs, 5-board run (estimate) | B25: =SUMIFS('Parts list'!$R$4:$R$84,'Parts list'!$B$4:$B$84,"PCB") -> 10 | C25: US$ | G25: Parts list: PCB row, qty × boards × unit price
A26: Parts per board, 100-board tier (bare PCB excluded) | B26: =SUMIFS('Parts list'!$S$4:$S$84,'Parts list'!$B$4:$B$84,"<>PCB")/$B$7 -> 19.172 | C26: US$ | G26: Parts list: Line cost 100-board run ÷ boards
A27: Bare PCB per board, 100-board tier (estimate) | B27: =SUMIFS('Parts list'!$S$4:$S$84,'Parts list'!$B$4:$B$84,"PCB")/$B$7 -> 0.8 | C27: US$ | G27: Parts list: PCB row
A29: ="5-board sample run — "&TEXT($B$6,"0")&" boards, JLCPCB Economic PCBA" -> 5-board sample run — 5 boards, JLCPCB Economic PCBA
A30: PCBA fee (per order) | B30: Quantity | C30: Rate US$ | D30: Fixed US$ | E30: US$ | F30: NTD | G30: Basis
A31: Setup | D31: 8.18 | E31: =B31*C31+D31 -> 8.18 | F31: =E31*$B$5 -> 259.306 | G31: fixed fee per order
A32: Stencil | D32: 1.53 | E32: =B32*C32+D32 -> 1.53 | F32: =E32*$B$5 -> 48.501 | G32: fixed fee per order
A33: Extended part types | B33: =B17 -> 14 | C33: 3.07 | E33: =B33*C33+D33 -> 42.98 | F33: =E33*$B$5 -> 1362.466 | G33: =TEXT(B33,"0")&" Extended SMT part types × US$"&TEXT(C33,"0.00")&" (Basic parts carry no per-type fee)" -> 14 Extended SMT part types × US$3.07 (Basic parts carry no per-type fee)
A34: SMT joints | B34: =B20*$B$6 -> 2895 | C34: 0.0016 | E34: =B34*C34+D34 -> 4.632 | F34: =E34*$B$5 -> 146.8344 | G34: =TEXT(B20,"#,##0")&" joints per board × "&TEXT($B$6,"0")&" boards" -> 579 joints per board × 5 boards
A35: X-ray (leadless parts) | B35: =B21*$B$6 -> 35 | C35: 0.82 | E35: =B35*C35+D35 -> 28.7 | F35: =E35*$B$5 -> 909.79 | G35: =TEXT(B21,"0")&" leadless parts per board × "&TEXT($B$6,"0")&" boards (11–50-part tier); includes both oscillators" -> 7 leadless parts per board × 5 boards (11–50-part tier); includes both oscillators
A36: Through-hole joints | B36: =$B$9*$B$6 -> 35 | C36: 0.0164 | D36: 3.58 | E36: =B36*C36+D36 -> 4.154 | F36: =E36*$B$5 -> 131.6818 | G36: ="4.4 mm jack: "&TEXT($B$9,"0")&" joints per board × "&TEXT($B$6,"0")&" boards, plus a fixed fee per order" -> 4.4 mm jack: 7 joints per board × 5 boards, plus a fixed fee per order
A37: Confirm Parts Placement | D37: 0.45 | E37: =B37*C37+D37 -> 0.45 | F37: =E37*$B$5 -> 14.265 | G37: fixed fee per order
A38: PCBA fees, total per order | E38: =SUM(E31:E37) -> 90.626 | F38: =E38*$B$5 -> 2872.8442
A40: 5-board run total | E40: US$ | F40: NTD | G40: Basis
A41: Parts (LCSC 1–9-piece prices) | E41: =B23 -> 141.6765 | F41: =E41*$B$5 -> 4491.145 | G41: Parts list: fitted lines except the PCB row, incl. the minimum spend per estimated passive line
A42: Bare 4-layer PCBs (estimate) | E42: =B25 -> 10 | F42: =E42*$B$5 -> 317 | G42: =TEXT($B$6,"0")&" boards; Parts list PCB row" -> 5 boards; Parts list PCB row
A43: JLCPCB PCBA fees | E43: =E38 -> 90.626 | F43: =E43*$B$5 -> 2872.8442 | G43: Economic PCBA, itemised above
A44: Total, 5-board run | E44: =SUM(E41:E43) -> 242.3025 | F44: =E44*$B$5 -> 7680.9892 | G44: ="for "&TEXT($B$6,"0")&" boards" -> for 5 boards
A45: Per board | E45: =E44/$B$6 -> 48.4605 | F45: =E45*$B$5 -> 1536.1978 | G45: cost-gate figure
A46: Target per board | F46: =$B$10 -> 1500 | G46: ="input B10; "&TEXT($B$10*$B$6,"#,##0")&" NTD for "&TEXT($B$6,"0")&" boards; WARNING above" -> input B10; 7,500 NTD for 5 boards; WARNING above
A47: Approved ceiling per board | F47: =$B$11 -> 1550 | G47: input B11 (owner decision 24 Sep 2026); FAIL above
A48: Margin to the target per board | F48: =F46-F45 -> -36.19785 | G48: =IF(F48>=0,"within the target",TEXT(-F48,"#,##0")&" NTD over the target ("&TEXT(-F48/F46,"0.0%")&")") -> 36 NTD over the target (2.4%)
A49: Margin to the approved ceiling per board | F49: =F47-F45 -> 13.80215 | G49: =IF(F49>=0,TEXT(F49,"#,##0")&" NTD under the approved ceiling","over the approved ceiling") -> 14 NTD under the approved ceiling
A50: Cost-gate status | F50: =IF(F45<=F46,"PASS",IF(F45<=F47,"WARNING","FAIL")) -> WARNING | G50: ="PASS ≤ "&TEXT(F46,"#,##0")&" NTD per board (target); WARNING ≤ "&TEXT(F47,"#,##0")&" (approved ceiling); FAIL > "&TEXT(F47,"#,##0") -> PASS ≤ 1,500 NTD per board (target); WARNING ≤ 1,550 (approved ceiling); FAIL > 1,550
A52: Levers — effect on the 5-board run
A53: Lever | B53: Quantity | C53: Rate US$ | D53: Current US$ | E53: Change US$ (run) | F53: NTD per board | G53: Basis
A54: Oscillators not X-rayed | B54: =B22*$B$6 -> 10 | C54: =C35 -> 0.82 | E54: =-B54*C54 -> -8.2 | F54: =E54*$B$5/$B$6 -> -51.988 | G54: ="JLCPCB may not X-ray the two oscillators (the X-ray fee above counts them); total would be ≈ "&TEXT(F45+F54,"#,##0")&" NTD per board" -> JLCPCB may not X-ray the two oscillators (the X-ray fee above counts them); total would be ≈ 1,484 NTD per board
A55: Cheaper 4.4 mm jack — current J701 cost | B55: =SUMIFS('Parts list'!$Q$4:$Q$84,'Parts list'!$B$4:$B$84,"J701") -> 5 | C55: =SUMIFS('Parts list'!$N$4:$N$84,'Parts list'!$B$4:$B$84,"J701") -> 6.8656 | D55: =B55*C55 -> 34.328 | F55: =D55*$B$5/$B$6 -> 217.63952 | G55: ="current cost per board at 1–9 pcs = the most a cheaper jack can save; each US$1.00 off its unit price saves "&TEXT($B$5,"0.0")&" NTD per board" -> current cost per board at 1–9 pcs = the most a cheaper jack can save; each US$1.00 off its unit price saves 31.7 NTD per board
A56: Buy 10 CH32V307RCT6 (10+ tier) | B56: 10 | C56: 2.98 | D56: =SUMIFS('Parts list'!$R$4:$R$84,'Parts list'!$B$4:$B$84,"U201") -> 17.25 | E56: =B56*C56-D56 -> 12.55 | F56: =E56*$B$5/$B$6 -> 79.567 | G56: LCSC 10+ price (brief §2); positive = the order costs more — buying 10 saves only if the 10+ price is below half the 1–9-piece price (the 5 extra parts are spares)
A57: Buy 10 AGRV2KQ32 (10+ tier) | B57: 10 | C57: 1.4 | D57: =SUMIFS('Parts list'!$R$4:$R$84,'Parts list'!$B$4:$B$84,"U202") -> 8.2515 | E57: =B57*C57-D57 -> 5.7485 | F57: =E57*$B$5/$B$6 -> 36.44549 | G57: LCSC 10+ price (brief §2); positive = the order costs more — buying 10 saves only if the 10+ price is below half the 1–9-piece price (the 5 extra parts are spares)
A58: Buy 10 LM27762DSSR (10+ tier) | B58: 10 | C58: 0.95 | D58: =SUMIFS('Parts list'!$R$4:$R$84,'Parts list'!$B$4:$B$84,"U501") -> 5.507 | E58: =B58*C58-D58 -> 3.993 | F58: =E58*$B$5/$B$6 -> 25.31562 | G58: LCSC 10+ price (brief §2); positive = the order costs more — buying 10 saves only if the 10+ price is below half the 1–9-piece price (the 5 extra parts are spares)
A59: Reduction needed to reach PASS (target) | E59: =F59*$B$6/$B$5 -> 5.7094401 | F59: =MAX(0,F45-F46) -> 36.19785 | G59: ="per-board reduction that brings the total to the "&TEXT(F46,"#,##0")&" NTD target" -> per-board reduction that brings the total to the 1,500 NTD target
A61: ="100-unit reference — "&TEXT($B$7,"0")&" boards, JLCPCB Standard PCBA (reference only; not the budget basis)" -> 100-unit reference — 100 boards, JLCPCB Standard PCBA (reference only; not the budget basis)
A62: PCBA fee (per order) | B62: Quantity | C62: Rate US$ | D62: Fixed US$ | E62: US$ | F62: NTD | G62: Basis
A63: Setup (single side) | D63: 25.56 | E63: =B63*C63+D63 -> 25.56 | F63: =E63*$B$5 -> 810.252 | G63: fixed fee per order
A64: Stencil | D64: 8.21 | E64: =B64*C64+D64 -> 8.21 | F64: =E64*$B$5 -> 260.257 | G64: fixed fee per order
A65: Fixtures | D65: 41.04 | E65: =B65*C65+D65 -> 41.04 | F65: =E65*$B$5 -> 1300.968 | G65: fixed fee, 100–199-board tier
A66: Feeder loading (all SMT part types) | B66: =B19 -> 53 | C66: 1.53 | E66: =B66*C66+D66 -> 81.09 | F66: =E66*$B$5 -> 2570.553 | G66: =TEXT(B66,"0")&" SMT part types (Extended + Basic) × US$"&TEXT(C66,"0.00") -> 53 SMT part types (Extended + Basic) × US$1.53
A67: SMT joints | B67: =B20*$B$7 -> 57900 | C67: 0.0016 | E67: =B67*C67+D67 -> 92.64 | F67: =E67*$B$5 -> 2936.688 | G67: =TEXT(B20,"#,##0")&" joints per board × "&TEXT($B$7,"0")&" boards" -> 579 joints per board × 100 boards
A68: X-ray (leadless parts) | B68: =B21*$B$7 -> 700 | C68: 0.25 | E68: =B68*C68+D68 -> 175 | F68: =E68*$B$5 -> 5547.5 | G68: =TEXT(B21,"0")&" leadless parts per board × "&TEXT($B$7,"0")&" boards (501–1,000-part tier)" -> 7 leadless parts per board × 100 boards (501–1,000-part tier)
A69: Through-hole joints | B69: =$B$9*$B$7 -> 700 | C69: 0.0164 | D69: 3.58 | E69: =B69*C69+D69 -> 15.06 | F69: =E69*$B$5 -> 477.402 | G69: ="4.4 mm jack: "&TEXT($B$9,"0")&" joints per board × "&TEXT($B$7,"0")&" boards, plus a fixed fee per order" -> 4.4 mm jack: 7 joints per board × 100 boards, plus a fixed fee per order
A70: Confirm Parts Placement | D70: 0.45 | E70: =B70*C70+D70 -> 0.45 | F70: =E70*$B$5 -> 14.265 | G70: fixed fee per order
A71: PCBA fees, total per order | E71: =SUM(E63:E70) -> 439.05 | F71: =E71*$B$5 -> 13917.885
A73: Cost per board, 100-unit reference | E73: US$ | F73: NTD | G73: Basis
A74: Parts (100-board tier) | E74: =B26 -> 19.172 | F74: =E74*$B$5 -> 607.7524 | G74: Parts list: fitted lines except the PCB row
A75: Bare PCB (estimate) | E75: =B27 -> 0.8 | F75: =E75*$B$5 -> 25.36 | G75: Parts list: PCB row
A76: PCBA fees per board | E76: =E71/$B$7 -> 4.3905 | F76: =E76*$B$5 -> 139.17885 | G76: ="order total ÷ "&TEXT($B$7,"0")&" boards" -> order total ÷ 100 boards
A77: Total per board, 100-unit reference | E77: =SUM(E74:E76) -> 24.3625 | F77: =E77*$B$5 -> 772.29125 | G77: reference line only
A79: Excludes shipping, import tax, the WCH-LinkE and CPLD programming cable, and the enclosure.

Sheet Notes & open items
A1: Notes & open items
A2: Parts List v0.2 · Diego Yang · 23 Sep 2026, revised 24 Sep 2026 (option B: DAC current-mode output) · companion to Design Specification v0.4 and Schematic Design Notes v0.3
A4: About this list
A5: 1 | B5: ="Covers every component of every circuit of the v0.4 architecture: "&TEXT(COUNTA('Parts list'!$B$4:$B$84),"0")&" BOM lines ("&TEXT(Cost!B14,"0")&" fitted), "&TEXT(Cost!B15,"0")&" SMT-placed parts and "&TEXT(Cost!B16,"0")&" through-hole part (4.4 mm jack) per board." -> Covers every component of every circuit of the v0.4 architecture: 81 BOM lines (76 fitted), 181 SMT-placed parts and 1 through-hole part (4.4 mm jack) per board.
A6: 2 | B6: Designators are grouped by block: 1xx USB-C input and protection, 2xx USB audio bridge, 3xx DAC, 4xx output legs, 5xx power, 6xx protection and control, 7xx outputs, indicators, test and board.
A7: 3 | B7: Fit: Yes = placed on every board; DNF = footprint only, part not placed (J703 I²S test header); No part = copper only (J201 / J202 debug pads, TP701–TP724 test pads, 4 mounting holes and 3 fiducials).
A8: 4 | B8: Generic passives and small discretes get LCSC numbers at the KiCad BOM step, value-matched to JLCPCB Basic parts; the Purchasing list merges them by value, package and rating (one part type each).
A9: 5 | B9: Legend: Quote = LCSC listing price; Estimate = planning price (generic parts and parts without an LCSC number yet); blue on yellow = input on the Cost sheet; Parts list columns U–V are helpers that count distinct SMT part types.
A11: Why v0.2 — cost-driven redesign (brief §1)
A12: 1 | B12: Three independent reviews of Spec v0.3 / Notes v0.2 / Parts List v0.1 found blockers. With every fix applied, the v0.3 architecture (XMOS XU316 + AKM AK4493SEQ + 4 × OPA1622 + 15 V USB PD power) was estimated at ≈ 17,100 NTD for 5 boards (≈ 3,400 NTD per board).
A13: 2 | B13: The owner clarified the budget: ≤ 1,500 NTD per board refers to the 5-board sample run (≈ 7,500 NTD for five assembled boards, including the bare PCBs and JLCPCB assembly fees, excluding shipping, import tax, programmers and enclosure). It is not a 100-unit average.
A14: 3 | B14: The owner chose a redesign to 1,500 NTD per board with a cheaper USB bridge, DAC and amplifier, accepting lower drive than K1000 / Susvara-class headphones.
A15: 4 | B15: v0.4 architecture: CH32V307RCT6 + AGRV2KQ32 CPLD USB bridge (open-source USBAudioToI2S, Apache-2.0) with 22.5792 / 24.576 MHz oscillators; ES9018K2M DAC, in current mode since 24 Sep 2026 (option B): 2 × OPA1678 I/V converters feed 2 × OPA1622 used as four difference amplifiers; single USB-C port, bus-powered within 500 mA; LM27762 ±4.5 V; ME6211C33 (digital 3.3 V), LP5907-3.3 (DAC analog) and AMS1117-ADJ (1.30 V DVDD); LM393 window comparator + 3.3 V hardware fault latch instead of relays; fixed gain with DAC digital volume.
A16: 5 | B16: Dropped: 15 V USB PD power port, CH224A, eFuse, inverting buck-boost, LM317 / LM337, relays, gain switch, DC servo, paralleled halves, K1000 1 W target. Kept: 3.5 mm unbalanced + 4.4 mm balanced jacks, ≥ 384 kHz, JLCPCB PCBA, CI / AI review / measurement automation.
A18: Assumptions
A19: 1 | B19: Prices: LCSC 1–9-piece tier for the 5-board sample run (Quote = LCSC listing; Estimate = planning price). The 100-board tier is used only for the 100-unit reference.
A20: 2 | B20: ="Minimum spend: US$"&TEXT(Cost!B8,"0.00")&" per estimated passive line on the 5-board run — line cost = MAX(qty × boards × 1–9-piece price, US$"&TEXT(Cost!B8,"0.00")&") when Price basis = Estimate and the price is > 0. It adds US$"&TEXT(Cost!B24,"0.00")&" to the run." -> Minimum spend: US$0.10 per estimated passive line on the 5-board run — line cost = MAX(qty × boards × 1–9-piece price, US$0.10) when Price basis = Estimate and the price is > 0. It adds US$1.74 to the run.
A21: 3 | B21: ="Exchange rate: "&TEXT(Cost!B5,"0.0")&" NTD per US$, fixed for the cost gate; the single input cell Cost!B5 drives every NTD figure." -> Exchange rate: 31.7 NTD per US$, fixed for the cost gate; the single input cell Cost!B5 drives every NTD figure.
A22: 4 | B22: ="Bare PCBs (estimate): 4 layers, ≤ 80 × 60 mm, 90 Ω USB pair; US$"&TEXT(SUMIFS('Parts list'!$N$4:$N$84,'Parts list'!$B$4:$B$84,"PCB"),"0.00")&" per board for the 5-board run (US$"&TEXT(Cost!B25,"0")&" for "&TEXT(Cost!B6,"0")&") and US$"&TEXT(SUMIFS('Parts list'!$O$4:$O$84,'Parts list'!$B$4:$B$84,"PCB"),"0.00")&" per board for the 100-unit reference." -> Bare PCBs (estimate): 4 layers, ≤ 80 × 60 mm, 90 Ω USB pair; US$2.00 per board for the 5-board run (US$10 for 5) and US$0.80 per board for the 100-unit reference.
A23: 5 | B23: JLCPCB Economic PCBA for the sample run (one side only, 2–50 boards): setup, stencil, US$3.07 per Extended part type, SMT joints, X-ray per leadless part, through-hole joints for the 4.4 mm jack and Confirm Parts Placement — itemised on the Cost sheet.
A24: 6 | B24: ="X-ray: the "&TEXT(Cost!B21,"0")&" leadless parts per board include both oscillators; JLCPCB may not X-ray them (US$"&TEXT(-Cost!E54,"0.00")&" less for the run, "&TEXT(-Cost!F54,"0")&" NTD per board, if not)." -> X-ray: the 7 leadless parts per board include both oscillators; JLCPCB may not X-ray them (US$8.20 less for the run, 52 NTD per board, if not).
A25: 7 | B25: Part types: Extended types carry the per-type fee; "Basic (likely)" parts are counted as Basic (no fee) until confirmed in the JLCPCB library — each one that turns out Extended adds US$3.07 to the run.
A26: 8 | B26: 100-unit reference: JLCPCB Standard PCBA with parts at the 100-board tier — for information only, not the budget basis.
A28: Exclusions
A29: 1 | B29: Not in the cost: shipping, import tax, the WCH-LinkE and CPLD programming cable, and the enclosure.
A30: 2 | B30: The DNF I²S test header (J703) and the copper-only items (debug pads, test pads, mounting holes, fiducials) carry no part cost.
A32: Open items — parts and cost (close before ordering)
A33: 1 | B33: Assign LCSC numbers: oscillators X201 / X202 (3225, 3.3 V, 22.5792 / 24.576 MHz), LP5907-3.3 (U302), ME6211C33 (U502), AMS1117-ADJ (U303), LM393 (U601) and the 8 MHz crystal (Y201); then every generic passive at the KiCad BOM step.
A34: 2 | B34: Confirm the "Basic (likely)" parts in the JLCPCB library: ME6211C33, AMS1117-ADJ, LM393, Sunlord GZ1608D601TF ferrite (LCSC C1015), 8 MHz crystal, and the generic passives, diodes and transistors.
A35: 3 | B35: Confirm whether JLCPCB X-rays the two oscillators (lever on the Cost sheet).
A36: 4 | B36: CI BOM rule: every fitted part has an LCSC number and stock ≥ the 5-board quantity (Purchasing list, Qty for 5-board run).
A37: 5 | B37: ="Cost gate is "&Cost!F50&" at "&TEXT(Cost!F45,"#,##0")&" NTD per board: "&Cost!G48&"; "&Cost!G49&" (target "&TEXT(Cost!F46,"#,##0")&" NTD, approved ceiling "&TEXT(Cost!F47,"#,##0")&" NTD — owner decision 24 Sep 2026)." -> Cost gate is WARNING at 1,536 NTD per board: 36 NTD over the target (2.4%); 14 NTD under the approved ceiling (target 1,500 NTD, approved ceiling 1,550 NTD — owner decision 24 Sep 2026).
A38: 6 | B38: ="Cost levers: if JLCPCB does not X-ray the two oscillators, −"&TEXT(-Cost!F54,"#,##0")&" NTD per board → ≈ "&TEXT(Cost!F45+Cost!F54,"#,##0")&" NTD ("&IF(Cost!F45+Cost!F54<=Cost!F46,"back under","still over")&" the target); a cheaper 4.4 mm jack — J701 costs ≈ "&TEXT(Cost!F55,"#,##0")&" NTD per board now (each US$1 saved = "&TEXT(Cost!B5,"0.0")&" NTD per board). Buying 10 of the 5-piece ICs raises the order total (Cost sheet)." -> Cost levers: if JLCPCB does not X-ray the two oscillators, −52 NTD per board → ≈ 1,484 NTD (back under the target); a cheaper 4.4 mm jack — J701 costs ≈ 218 NTD per board now (each US$1 saved = 31.7 NTD per board). Buying 10 of the 5-piece ICs raises the order total (Cost sheet).
A40: Open items — design (brief §8, updated 24 Sep 2026; may change parts)
A41: 1 | B41: Firmware from a small open-source project (top risk): build USBAudioToI2S before layout; keep the reference pin map; fallback is an XMOS-based v2 (budget permitting).
A42: 2 | B42: CLOSED 24 Sep 2026 — ES9018K2M output loading: the datasheet gives 806 Ω ±11 % per DAC pin (p.31), so the direct 2 kΩ difference-amplifier load cost 5.1 dB of level; resolved by the move to current mode with OPA1678 I/V converters (ESS application circuit, p.27).
A43: 3 | B43: Confirm the VREF ≈ 1.70 V null point at bring-up: DC at the I/V outputs ≈ VREF at idle (DAC zero-DC-current point; VREF = 1.706 V from R431 / R432).
A44: 4 | B44: OPA1678 stability with the DAC pin capacitance (10 Ω + 1.5 nF C0G feedback network, R427–R430 / C417–C420) — SPICE check.
A45: 5 | B45: USB current estimate 0.49 A worst case vs the 0.5 A USB 2.0 limit (was 0.47 A; OPA1678 quiescent and I/V output currents added); idle ≈ 0.25 A — measure at bring-up.
A46: 6 | B46: DAC differential DC offset at idle (assumption: DAC pin-to-pin mismatch ≤ 1 mV); worst-case balanced output offset ≤ 14.7 mV against the ±15 mV target — close to its limit.
A47: 7 | B47: The datasheet says an external DVDD should be shut down in standby; the AMS1117-ADJ (U303) has no enable — confirm the behaviour or add an enable-capable LDO.
A48: 8 | B48: CH32V307 HSE frequency (Y201) and USB High-Speed layout per the WCH reference.
A49: 9 | B49: OPA1622 swing at 100 mA on ±4.5 V (datasheet Fig. 38 / 39).
A50: 10 | B50: Both jacks are live; one headphone at a time; a 4.4 mm-to-3.5 mm adapter shorts leg− (current limit, one amplifier per package) — warn in the manual.
A51: 11 | B51: Thermal and 2 MHz charge-pump noise coupling into the analog area — layout separation.
A53: DFA / DFT / CI (brief §10)
A54: 1 | B54: Economic PCBA, one side only, 2–50 boards; prefer JLCPCB Basic parts (no per-type fee): all passives, transistors, LM393, ME6211, AMS1117, ferrite, crystal.
A55: 2 | B55: Leadless parts (X-ray): CPLD, ES9018K2M, 2 × OPA1622, LM27762, 2 oscillators (the OPA1678 is SOIC-8, leaded).
A56: 3 | B56: DFT: test pad on every rail (5V_SYS, 3V3, 3V3A, 1V3, +4.5 V, −4.5 V), clocks, I²S, EN / PG / fault; debug pads for the MCU and CPLD; DNF I²S header.
A57: 4 | B57: CI cost gate for the 5-board run: fixed 31.7 NTD per US$; WARN > 1,500 NTD per board (target), FAIL > 1,550 (approved ceiling, owner decision 24 Sep 2026; previously FAIL > 1,500, WARN > 1,425), plus a 100-unit reference line — the same rule as the Cost sheet.
A58: 5 | B58: External links: every formula references only this workbook's own sheets; links appear when sheets are copied into another workbook — the Checks sheet records the file check.
A60: Change log
A61: 1 | B61: 23 Sep 2026 — C303, C304 (AVCC_L, AVCC_R) changed from 4.7 µF 0603 10 V X5R to 2.2 µF 0603 6.3 V X5R: the LP5907 output capacitance was over its 10 µF limit; 2.2 µF keeps the LP5907 total at 5.7 µF. Price basis unchanged (Estimate: US$0.012 at 1–9 pcs, US$0.005 at 100).
A62: 2 | B62: 23 Sep 2026 — Purchasing list: the 4.7 µF 0603 10 V X5R line covers C501 only; the 2.2 µF 0603 6.3 V X5R line covers C303, C304 and C310. Counts, totals and the 1,447 NTD per board result were unchanged.
A63: 3 | B63: 24 Sep 2026 — DAC outputs changed to current mode per ESS application circuit (datasheet p.27); reason: each DAC pin is 806 Ω ±11 % (datasheet p.31), the 2 kΩ direct load cost 5.1 dB of level.
A64: 4 | B64: 24 Sep 2026 — BOM: block 4 is now "I/V converters and output legs (2 × OPA1678 + 2 × OPA1622)" with 8 new lines: U403 / U404 OPA1678IDR (LCSC C192421, Extended), R423–R426 750 Ω 1 %, R427–R430 10 Ω, C417–C420 1.5 nF C0G, R431 / R432 10.0 kΩ / 10.7 kΩ VREF divider, C421 10 µF, C422 100 nF, C423–C426 100 nF. Now 81 BOM lines (76 fitted), 181 placed parts, 14 Extended + 39 Basic types, 579 SMT joints, 54 purchase lines.
A65: 5 | B65: 24 Sep 2026 — Cost: 5-board run 1,447 → 1,536 NTD per board (US$242.30 = 7,681 NTD). Cost gate changed by the owner ("a little bit off-budget is acceptable"): target 1,500 NTD per board (WARNING above), approved ceiling 1,550 NTD per board (FAIL above) → WARNING, 36 NTD over the target and 14 NTD under the ceiling.

Sheet Checks
A1: Checks — formula-based self-checks
A2: Each check recomputes a figure from the lists or the Cost sheet and compares it with the expected value. Two-sided checks: OK when |Difference| ≤ Tolerance. One-sided gate checks: OK / WARNING when Difference ≤ 0. Expected counts and totals are the calc results of 24 Sep 2026 (option B) — update them when the BOM changes.
A4: Check | B4: Expected | C4: Actual | D4: Difference | E4: Tolerance | F4: Result | G4: Basis
A5: BOM lines in the Parts list | B5: 81 | C5: =COUNTA('Parts list'!$B$4:$B$84) -> 81 | D5: =C5-B5 -> 0 | E5: 0 | F5: =IF(ABS(D5)<=E5,"OK","CHECK") -> OK | G5: Parts list rows 4–84
A6: Fitted BOM lines | B6: 76 | C6: =Cost!B14 -> 76 | D6: =C6-B6 -> 0 | E6: 0 | F6: =IF(ABS(D6)<=E6,"OK","CHECK") -> OK | G6: Cost sheet (Fit = Yes)
A7: SMT-placed parts per board | B7: 181 | C7: =Cost!B15 -> 181 | D7: =C7-B7 -> 0 | E7: 0 | F7: =IF(ABS(D7)<=E7,"OK","CHECK") -> OK | G7: Cost sheet (Fit = Yes, SMT joints > 0)
A8: Extended part types | B8: 14 | C8: =Cost!B17 -> 14 | D8: =C8-B8 -> 0 | E8: 0 | F8: =IF(ABS(D8)<=E8,"OK","CHECK") -> OK | G8: Cost sheet (drives the US$3.07-per-type fee)
A9: Basic part types | B9: 39 | C9: =Cost!B18 -> 39 | D9: =C9-B9 -> 0 | E9: 0 | F9: =IF(ABS(D9)<=E9,"OK","CHECK") -> OK | G9: Cost sheet
A10: Leadless (X-ray) parts per board | B10: 7 | C10: =Cost!B21 -> 7 | D10: =C10-B10 -> 0 | E10: 0 | F10: =IF(ABS(D10)<=E10,"OK","CHECK") -> OK | G10: Cost sheet (drives the X-ray fee)
A11: SMT joints per board | B11: 579 | C11: =Cost!B20 -> 579 | D11: =C11-B11 -> 0 | E11: 0 | F11: =IF(ABS(D11)<=E11,"OK","CHECK") -> OK | G11: Cost sheet (drives the SMT joint fee)
A12: Purchase lines | B12: 54 | C12: =COUNTA('Purchasing list'!$C$4:$C$57) -> 54 | D12: =C12-B12 -> 0 | E12: 0 | F12: =IF(ABS(D12)<=E12,"OK","CHECK") -> OK | G12: Purchasing list rows 4–57
A13: Purchasing qty per board = SMT-placed + through-hole parts | B13: =Cost!B15+Cost!B16 -> 182 | C13: =SUM('Purchasing list'!$J$4:$J$57) -> 182 | D13: =C13-B13 -> 0 | E13: 0 | F13: =IF(ABS(D13)<=E13,"OK","CHECK") -> OK | G13: every fitted placed part appears once in the Purchasing list
A14: Purchasing ext. cost = Parts list before the minimum spend (US$, 5-board run) | B14: =Cost!B23-Cost!B24 -> 139.9415 | C14: =SUM('Purchasing list'!$P$4:$P$57) -> 139.9415 | D14: =C14-B14 -> 0 | E14: 0.005 | F14: =IF(ABS(D14)<=E14,"OK","CHECK") -> OK | G14: grouping keeps quantities and prices
A15: Purchasing per-board cost = Cost sheet (US$, 100-board tier) | B15: =Cost!B26 -> 19.172 | C15: =SUM('Purchasing list'!$Q$4:$Q$57) -> 19.172 | D15: =C15-B15 -> 0 | E15: 0.005 | F15: =IF(ABS(D15)<=E15,"OK","CHECK") -> OK | G15: grouping keeps quantities and prices
A16: Total, 5-board run: Cost sheet = Parts list lines + fee lines (US$) | B16: =Cost!E44 -> 242.3025 | C16: =SUM('Parts list'!$R$4:$R$84)+SUM(Cost!$E$31:$E$37) -> 242.3025 | D16: =C16-B16 -> 0 | E16: 0.005 | F16: =IF(ABS(D16)<=E16,"OK","CHECK") -> OK | G16: recomputed from the Parts list line costs (incl. PCB row) and the seven fee lines
A17: Summary total = Cost sheet total (NTD) | B17: =Cost!F44 -> 7680.9892 | C17: =Summary!B9 -> 7680.9892 | D17: =C17-B17 -> 0 | E17: 0.005 | F17: =IF(ABS(D17)<=E17,"OK","CHECK") -> OK | G17: Summary links to the Cost sheet
A18: Total, 5-board run (US$) | B18: 242.3 | C18: =Cost!E44 -> 242.3025 | D18: =C18-B18 -> 0.0025 | E18: 0.01 | F18: =IF(ABS(D18)<=E18,"OK","CHECK") -> OK | G18: calc result 24 Sep 2026
A19: Per-board total, 5-board run (NTD) | B19: 1536 | C19: =Cost!F45 -> 1536.1978 | D19: =C19-B19 -> 0.19785 | E19: 1 | F19: =IF(ABS(D19)<=E19,"OK","CHECK") -> OK | G19: calc result 24 Sep 2026 (±1 NTD)
A20: Block 4 parts per board: I/V converters and output legs (NTD) | B20: 264 | C20: =Summary!C38 -> 263.84544 | D20: =C20-B20 -> -0.15456 | E20: 0.5 | F20: =IF(ABS(D20)<=E20,"OK","CHECK") -> OK | G20: calc result 24 Sep 2026 (1–9-piece prices, before the minimum spend)
A21: 100-unit reference per board (NTD) | B21: 772 | C21: =Cost!F77 -> 772.29125 | D21: =C21-B21 -> 0.29125 | E21: 1 | F21: =IF(ABS(D21)<=E21,"OK","CHECK") -> OK | G21: calc result 24 Sep 2026 (±1 NTD)
A22: Per-board total within the approved ceiling (NTD) | B22: =Cost!F47 -> 1550 | C22: =Cost!F45 -> 1536.1978 | D22: =C22-B22 -> -13.80215 | E22: 0 | F22: =IF(D22<=E22,"OK","CHECK") -> OK | G22: one-sided: OK at or under the 1,550 NTD approved ceiling (owner decision 24 Sep 2026); above it the gate is FAIL
A23: Per-board total within the target (NTD) | B23: =Cost!F46 -> 1500 | C23: =Cost!F45 -> 1536.1978 | D23: =C23-B23 -> 36.19785 | E23: 0 | F23: =IF(D23<=E23,"OK","WARNING") -> WARNING | G23: =IF(D23<=E23,"within the target","over the target by "&TEXT(D23,"#,##0")&" NTD per board — allowed up to the approved ceiling (reported, not a failed check)") -> over the target by 36 NTD per board — allowed up to the approved ceiling (reported, not a failed check)
A24: Cost-gate status (target 1,500 WARN / ceiling 1,550 FAIL) | B24: WARNING | C24: =Cost!F50 -> WARNING | F24: =IF(C24=B24,"OK","CHECK") -> OK | G24: owner decision 24 Sep 2026; expected WARNING at 1,536 NTD per board
A26: All checks | F26: =IF(COUNTIF(F5:F24,"CHECK")>0,TEXT(COUNTIF(F5:F24,"CHECK"),"0")&" to check",IF(COUNTIF(F5:F24,"WARNING")>0,"ALL OK — target WARNING","ALL OK")) -> ALL OK — target WARNING | G26: =TEXT(COUNTIF(F5:F24,"OK"),"0")&" of "&TEXT(ROWS(F5:F24),"0")&" checks OK; "&TEXT(COUNTIF(F5:F24,"WARNING"),"0")&" WARNING (target overrun, within the approved ceiling); "&TEXT(COUNTIF(F5:F24,"CHECK"),"0")&" to check" -> 19 of 20 checks OK; 1 WARNING (target overrun, within the approved ceiling); 0 to check
A28: External links
A29: Every formula in this workbook references only its own sheets (Summary, Parts list, Purchasing list, Cost, Notes & open items, Checks); there are no external workbook links. Copying a sheet into another workbook can create links — repeat the file check after any copy.
A30: File check at save (24 Sep 2026 revision): the saved .xlsx opened as a zip has no xl/externalLinks part and no externalReferences entry; none of its 823 cell formulas (nor any table-column or conditional-format formula) contains "["; recalculation shows no formula errors.
