Workbook

Sheet Summary
A1: Parts List v0.9 — USB-C DAC + balanced headphone amplifier
A2: Diego Yang · 26 Sep 2026 · tenth review round · companion to Design Specification v1.1 and Schematic Design Notes v1.0; release calculations in DAC_HPA_Calculation_Package_v1.1.zip (one verification command) · JLCPCB Standard PCBA, top side, 5 boards + owner-fitted parts · Parts List v0.8 is kept unchanged as history
A4: Stage readiness (26 Sep 2026)
A5: Stage | B5: Verdict | C5: Gate / condition
A6: Schematic capture | B6: GO | C6: Capture v1.0 uses the old J702 map (tip on pin 1, sleeve on pin 4, 'Mount' on 5/6). Recapture sheet 7 to the J702 map from the maker drawing (Notes sheet), and sheet 6 to Parts List v0.9 (the protection sheet)
A7: Provisional placement | B7: GO (100 × 80 mm) | C7: top side; zone fills Z4 52 %, Z7 59.0 % against the 60 % zone rule (59.6 % overall)
A8: Schematic freeze | B8: HOLD | C8: for G-1…G-4. J701 and J702 contact maps are documented from the maker drawings and confirmed on two samples at G-2 (including J701 pads 11/12 and the J702 break contacts); J101 at G-1.
A9: Routing | B9: HOLD | C9: no manufacturing data from the provisional connector assignments
A10: Fabrication/assembly order | B10: HOLD | C10: for the layout review and G-5/G-6, including JLCPCB's written confirmation of how the J101 shell stakes S1–S4 and the J702 pads 1/2 are soldered (or the owner fallback), and the 2416 film-capacitor reflow
A12: Board and parts (live from the lists)
A13: Item | B13: Value | C13: Details
A14: BOM lines | B14: =Checks!C11 -> 179 | C14: ="incl. "&COUNTIF('Parts list'!$M$4:$M$185,"Pads")&" copper-pad lines and "&COUNTIF('Parts list'!$M$4:$M$185,"No")&" DNF lines; plus 3 layout lines (test pads, mounting holes/fiducials, bare PCB)" -> incl. 3 copper-pad lines and 8 DNF lines; plus 3 layout lines (test pads, mounting holes/fiducials, bare PCB)
A15: Fitted component lines | B15: =Cost!B26 -> 168 | C15: ="placed by JLCPCB "&TEXT(Cost!B26-Cost!B27,"0")&"; owner-fitted "&TEXT(Cost!B27,"0")&" (K601–K604, J701, D102, R509)" -> placed by JLCPCB 164; owner-fitted 4 (K601–K604, J701, D102, R509)
A16: Fitted parts per board | B16: =Cost!B28 -> 462 | C16: ="placed by JLCPCB "&TEXT(Cost!B29,"0")&"; owner-fitted "&TEXT(Cost!B28-Cost!B29,"0") -> placed by JLCPCB 455; owner-fitted 7
A17: Unique part numbers (fitted) | B17: ='Parts list'!$AB$187 -> 115 | C17: ="JLCPCB-placed part types "&TEXT(Cost!B32,"0")&" (Basic "&TEXT(Cost!B33,"0")&", Extended or to confirm "&TEXT(Cost!B34,"0")&")" -> JLCPCB-placed part types 111 (Basic 34, Extended or to confirm 77)
A18: SMT joints per board | B18: ='Parts list'!$O$187 -> 1339 | C18: ="through-hole "&TEXT('Parts list'!$P$187,"0")&" (J101 shell stakes 4, J701 12 owner-fitted, J702 slot terminals 2); leadless (X-ray) parts "&TEXT(Cost!B35,"0") -> through-hole 18 (J101 shell stakes 4, J701 12 owner-fitted, J702 slot terminals 2); leadless (X-ray) parts 10
A19: Netlist pin rows | B19: =Checks!C27 -> 1445 | C19: ="component pins "&TEXT(Checks!C28,"#,##0")&" + 52 test pads; nets "&TEXT(Checks!C32,"0")&"; design check 0 issues" -> component pins 1,393 + 52 test pads; nets 247; design check 0 issues
A20: Value decodes from the part number (lines) | B20: ='Parts list'!$AC$187 -> 118 | C20: ="mismatches with the Value column: "&TEXT('Parts list'!$AG$187,"0")&"; parts cross-check: "&TEXT(Checks!C7,"0")&" lines, "&TEXT(Checks!C8,"0")&" mismatches" -> mismatches with the Value column: 0; parts cross-check: 80 lines, 0 mismatches
A21: Stress check, current rows | B21: ='Stress check'!B192 -> 181 | C21: ="OK "&'Stress check'!B187&", THIN "&'Stress check'!B188&", AVAIL "&'Stress check'!B189&", DATA-GAP "&'Stress check'!B190&", FAIL "&'Stress check'!B191 -> OK 146, THIN 17, AVAIL 14, DATA-GAP 4, FAIL 0
A22: Evidence register rows | B22: ='Evidence register'!C130 -> 120 | C22: ="G "&'Evidence register'!C126&", E "&'Evidence register'!C127&", Q "&'Evidence register'!C128&" (open; none has passed, no board exists), retired or process rows "&'Evidence register'!C129 -> G 13, E 80, Q 22 (open; none has passed, no board exists), retired or process rows 5
A23: Designators added against v0.8 | B23: ='Changes vs v0.8'!C30 -> 65 | C23: ="removed "&'Changes vs v0.8'!C31&", changed "&'Changes vs v0.8'!C32&" ("&'Changes vs v0.8'!C34&" change lines)" -> removed 22, changed 4 (24 change lines)
A24: Buy-now part numbers | B24: ='Purchasing list'!$T$116 -> 18 | C24: ="pre-order "&COUNTIF('Purchasing list'!$T$4:$T$114,"Pre-order")&"; new buy-now line TLV3402IDGKR; TLV1704 only if ≥ 31 are in LCSC stock at order time (Ordering plan, section A)" -> pre-order 8; new buy-now line TLV3402IDGKR; TLV1704 only if ≥ 31 are in LCSC stock at order time (Ordering plan, section A)
A25: Owner LCSC order: order-rule flags | B25: ='Purchasing list'!$Q$152 -> 0 | C25: ="every owner LCSC quantity meets the LCSC minimum and multiple (Purchasing list column Q)" -> every owner LCSC quantity meets the LCSC minimum and multiple (Purchasing list column Q)
A28: Cost for information — 5 assembled boards (no cost limit; an estimate until the supplier orders and the JLCPCB quote exist)
A29: Item | B29: US$ | C29: NTD | D29: Details
A30: JLCPCB order (Standard PCBA) | B30: =Cost!E95 -> 787.82652 | C30: =Cost!F95 -> 24997.735 | D30: ="parts "&TEXT(Cost!E90,"0.00")&", fees "&TEXT(Cost!E91,"0.00")&", global sourcing "&TEXT(Cost!E92,"0.00")&", PCB "&TEXT(Cost!E93,"0.00")&", shipping "&TEXT(Cost!E94,"0.00") -> parts 397.33, fees 312.97, global sourcing 29.52, PCB 23.00, shipping 25.00
A31: Owner purchase (DigiKey + LCSC) | B31: =Cost!E96 -> 161.6 | C31: =Cost!F96 -> 5127.568 | D31: ="DigiKey "&TEXT(Cost!E82,"0.00")&" + LCSC "&TEXT(Cost!E86,"0.00")&" (owner-fitted parts and gate samples, shipping and tax)" -> DigiKey 105.63 + LCSC 55.97 (owner-fitted parts and gate samples, shipping and tax)
A32: Total per 5-board order | B32: =Cost!E97 -> 949.42652 | C32: =Cost!F97 -> 30125.303 | D32: ="at "&TEXT(Cost!B5,"0.00")&" NTD per US$; an estimate until the supplier orders and the JLCPCB quote exist" -> at 31.73 NTD per US$; an estimate until the supplier orders and the JLCPCB quote exist
A33: Equivalent per assembled board | B33: =Cost!E98 -> 189.8853 | C33: =Cost!F98 -> 6025.0607 | D33: ="JLCPCB "&TEXT(Cost!E99,"0.00")&" + owner "&TEXT(Cost!E100,"0.00") -> JLCPCB 157.57 + owner 32.32
A34: (information) Total with Economic PCBA | B34: =Cost!E101 -> 934.49652 | C34: =Cost!F101 -> 29651.575 | D34: Economic is not chosen (CPLD pitch limit, connector reflow)
A35: Change vs the v1.0 set (Parts List v0.8) | B35: =Cost!E104 -> 93.28652 | D35: ="v1.0 set: US$ "&TEXT(Cost!B24,"#,##0.00")&"; earlier record: the v1.0 set was +"&TEXT(Cost!E105,"0.00")&" against the v0.9 set (US$ "&TEXT(Cost!D105,"#,##0.00")&")" -> v1.0 set: US$ 856.14; earlier record: the v1.0 set was +97.32 against the v0.9 set (US$ 758.82)
A36: Earlier round's comparison: saving vs US$ 1,072.87 | B36: =Cost!E102 -> 123.44348 | C36: =Cost!F102 -> 3916.8616 | D36: =TEXT(Cost!E102/Cost!B21,"0.0%")&" of US$ "&TEXT(Cost!B21,"#,##0.00")&"; "&TEXT(Cost!E103,"0.00")&" per board" -> 11.5% of US$ 1,072.87; 24.69 per board
A37: Line items rounded to the cent; totals computed from unrounded values. Prices, stock and JLCPCB classes are those of the web-page copies read on 26 Sep 2026.
A38: Checks
A39: All checks | B39: =Checks!F77 -> 2 to check | D39: =Checks!G77 -> 63 of 65 checks OK
A40: Cost reconciliation with the cost report | B40: =Cost!F176 -> ALL OK | D40: =Cost!G176 -> 51 of 51 figures match the cost report
A41: Open item: no JLCPCB-placed part at a process limit | B41: OPEN | D41: until JLCPCB's written answer on how the J101 shell stakes S1–S4 and the J702 slot pads 1/2 are soldered (G-6); not counted as a pass
A42: Open point for the owner: slot-pad copper ring of J701 / J702 (decide before the G-3 overlay) | B42: OPEN | D42: J702 0.20 mm (0.60 mm slots in 1.00 mm pads), J701 0.25 mm (0.50 mm slots in 1.00 mm pads; 0.20 mm at the +0.10 mm slot tolerance) — above JLCPCB's 0.18 mm minimum, at or below its 0.25 mm recommendation, below this design's 0.30 mm rule; the pads stay as the maker drawings give them until the owner decides (Notes sheet); not counted as a pass
A43: What changed in v0.9 (details on the Notes sheet)
A44: 1 | B44: History-robust hardware protection: per-leg over-range stages U611/U612 (TLV1704) and low-level persistence stages U613–U620 (TLV3402IDGKR) replace the per-leg RC window stage; the pair persistence detector and the re-arm latch are unchanged. From any reachable pre-fault state (rail-bounded, E): DC ±2 V on a leg removed ≤ 27.2 ms, ±1 V ≤ 102.7 ms; rail-stuck leg 26.48 / 13.24 mJ at 16 / 32 Ω on the 4.049 V R501-fallback rail.
A45: 2 | B45: Hardware requirement with a level floor: |leg| ≥ 0.34 V and |pair| ≥ 0.68 V (R-74, E); frozen codes with 0.34 V ≤ |leg| ≤ 1.008 V are removed ≤ 118.8 ms (the bound at the floor); below the floor the firmware tiers apply, with deadlines stated for the swept history set (T3 ≥ 0.178 / 0.195 V within 2.36 s).
A46: 3 | B46: Re-arm latch described by the implemented condition: a trip that pulls node H below HREF clears the latch within ≤ 0.346 ms (0.383 ms with the R501 fallback); the latch tests (A-39) are open obligations.
A47: 4 | B47: Fault energy: the Spec DC-energy definition is kept; under it every calculated case meets 30 / 15 mJ under the stated engineering-estimate assumptions. The one exception needing the owner's attention is the High-mode 32 Ω balanced frozen full-scale case: it meets 15 mJ only with the typical output-swing credit (A-45), so it remains an owner decision with a bring-up energy test. Total terminal energies are published for information (32 Ω balanced, High mode 24.1–24.7 mJ).
A48: 5 | B48: Calibration rule: the content boundaries are guaranteed only at or below the calibrated level; an uncalibrated board runs at −4.5 dB. LPW content boundary with the 10 nA leakage allowance (E): steady offsets below 0.116 FS never mute, at or above 0.162 FS they mute on every unit; full-scale sines below 6.5 Hz (6.54 Hz with the allowance) and squares up to about 7 Hz can mute.
A49: 6 | B49: Boot self-test: all implemented (pairwise) tests every boot, 3.68 s (alternative: 2.96 s, rotating the over-range direction, so all implemented tests run within four boots); new steps (f) LPW and (g) OR and the (e) word; PC15 = N6_ORTEST; per-channel coverage comes at production.
A50: 7 | B50: Parts: TLV3402IDGKR buy now into the JLCPCB part library (about 152 in stock); TLV1704AIPWR 6 per board (≥ 31 in LCSC stock at order time); FH C0G 0603 / 1206 and onsemi MMBT3904LT1G (Q623–Q627) at the PCBA order; zone fills Z4 52 %, Z7 59.0 %.
A51: 8 | B51: New Changes vs v0.8 sheet (65 designators added, 22 removed, 4 changed); Evidence register rebuilt (120 rows: G 13, E 80, Q 22, 5 retired or process rows, R-70 now an open process item; no Q row has passed, because no board exists); stress check 181 current rows, 0 FAIL.
A52: 9 | B52: Schematic-capture review and maker drawings (26 Sep 2026): J701 follows the owner-approved 12-pad map, which the G-Switch maker drawing confirms (pads 11/12 are mounting tabs; 12 owner-fitted THT joints); J702 takes its contact map from the HRO maker drawing — sleeve and ring 2 on GND, ring 1 on JACK_RP, tip on JACK_LP, and pins 5/6, the break contacts, with no connection; G-2 confirms both maps on two samples. How JLCPCB solders the J101 shell stakes S1–S4 and the J702 slot pads 1/2 (the two GND terminals) is an owner question before the order (fallback: the owner hand-solders them); no manufacturing data from the provisional connector assignments.
A53: 10 | B53: Update of 26 Sep 2026: jack maps from the maker drawings; Parts list, Netlist, Nets, Stress check, Changes vs v0.8 and Evidence register re-imported from the refreshed design data (1445 netlist pin rows = 1393 component pins + 52 test pads; SMT 1339 / THT 18 joints per board: J101 4, J701 12, J702 2); cost US$ 949.43 = NTD 30,125 (−US$ 0.01: J702 SMT joints 6 → 4); the Checks sheet also checks the J701 / J702 netlist rows pin by pin.
A55: Owner decisions and actions — adopted defaults (alternatives and their costs on the Notes sheet)
A56: Decision | B56: Adopted default | D56: Alternative
A57: 1. 32 Ω balanced frozen full scale, High mode | B57: A: a stated E item (A-45) plus the bring-up energy test, 0 parts; it meets 15 mJ only with the typical output-swing credit | D57: B: calibrated full scale −0.6 dB and a −5.1 dB default, 0 parts — breaks the 300 Ω power targets (about 27 mW)
A58: 2. Fault-energy definition | B58: keep the Spec DC-energy definition; publish the total terminal energies | D58: a total-energy requirement would need a hardware change (fast over-range stage: 16 parts, Z4 about 60 %)
A59: 3. Boot self-test time | B59: all implemented (pairwise) tests every boot, 3.68 s | D59: 2.96 s, rotating the over-range direction, so all implemented tests run within four boots
A60: 4. Self-test coverage | B60: A: pairwise, stated as a limitation; per-channel coverage at the production per-leg injection; 0 parts | D60: B: per-channel OR test, +1 part, 4.65 s; C: B plus per-channel LPW tests, about +4 to 6 parts, 5.92 s
A61: 5. LPW content boundary (A-44) | B61: adopted: a filtered tap beyond the level for ≥ 70.8 ms may mute (raw full-scale excursion ≥ 62.9 ms); steady offsets below 0.116 FS never mute, from 0.162 FS always (10 nA allowance); 0 parts | D61: none that keeps the hardware requirement
A62: 6. Board size | B62: 100 × 80 mm carried over (fill 59.6 %: Z4 52 %, Z7 59.0 %) | D62: 100 × 70 mm: fill 68 %, above the 60 % zone rule; not recommended
A63: 7. Output impedance (R-15): contact-resistance assumption | B63: kept by the owner (27 Sep 2026): J701/J702 50 mΩ per contact, 0 Ω links 50 mΩ each; R-15 stays E (0.251 / 0.383 Ω) until the bring-up output-impedance measurement | D63: none: the maker drawings give no contact-resistance maximum that would make these terms G
A64: 8. Owner action before the order: JLCPCB process question | B64: ask JLCPCB how it solders the J101 shell stakes S1–S4 and the J702 slot pads 1/2 (question quoted on the Notes sheet) | D64: fallback, no cost: the owner hand-solders S1–S4 (4 joints) and J702 pads 1/2 (2 joints) from the bottom side before the first plug-in; J702 becomes owner-fitted if JLCPCB cannot assemble it
A66: Sheets in this workbook
A67: Parts list | B67: every BOM line with value, rating, part number, sourcing, fit (owner flag), joints, prices and 5-board quantities
A68: Purchasing list | B68: the JLCPCB order by part number and the two owner orders, with the order-rule check
A69: Cost | B69: inputs, fees, global-sourcing extras, owner orders, totals and the reconciliation with section 1 of the cost report
A70: Ordering plan | B70: buy-now and pre-order lines, owner orders, fitting order, global-sourced lines, order remarks, release gates
A71: Changes vs v0.8 | B71: added, removed and changed parts of the tenth review round
A72: Netlist | B72: every pin of every part and test pad
A73: Nets | B73: one line per net, pin counts checked live
A74: Stress check | B74: every current stress row against its datasheet limit
A75: Evidence register | B75: every requirement and limit with its evidence class (G / E / Q) and its capping input
A76: Notes & open items | B76: what changed, owner decisions, limitations, thin margins, open qualification obligations, sourcing risks, gates, open items and the change log
A77: Checks | B77: the workbook checks itself

Sheet Parts list
A1: Parts list — every BOM line, grouped by block
A2: One part per line, grouped by block. Fit: Yes = placed by JLCPCB; Owner = owner-fitted (bought by the owner, hand-soldered after delivery, not in the JLCPCB order); No = DNF; Pads = copper only; No part = layout items; Board = bare PCB. Unit prices in US$ (LCSC/JLCPCB sample tier; distributor prices for global-sourced and owner-bought parts). No spare-parts stock: JLCPCB lines buy the exact 5-board quantity plus attrition (Cost sheet inputs); a pre-ordered LCSC line buys at least its LCSC order quantity. Helper columns Z–AG feed the Checks sheet (AC–AG: the value decoded from the part number against the Value column).
A3: Block | B3: Designators | C3: Qty per board | D3: Description | E3: Value | F3: Package | G3: Rating / tolerance | H3: Part number (MPN) | I3: LCSC no. | J3: JLCPCB class | K3: Source | L3: Stock and sourcing | M3: Fit (Yes = JLCPCB, Owner = owner-fitted) | N3: Leadless (X-ray) | O3: SMT joints per part | P3: Through-hole joints per part | Q3: Unit price US$ | R3: Qty for 5 boards | S3: Line cost US$, 5 boards (exact) | T3: Attrition rule | U3: LCSC order quantity (input) | V3: Qty to buy (5 boards + attrition) | W3: Line cost US$ (qty to buy) | X3: Datasheet | Y3: Notes | Z3: Designator list (helper) | AA3: Designators on line (helper) | AB3: New MPN (helper) | AC3: Value-code family (helper) | AD3: Value code (helper) | AE3: Value from part number, Ω or F (helper) | AF3: Value as entered, Ω or F (helper) | AG3: Value check (helper)
A4: 1 USB-C input, OVP and sensing | B4: C101 | C4: 1 | D4: DNF: shell-to-GND RF capacitor (only if R107 becomes a bleed resistor) | E4: 4.7 nF | F4: 0402 | G4: 50 V X7R | H4: FH 0402B472K500NT | I4: C1538 | J4: Basic | K4: — (DNF) | L4: As in Parts List v0.6 | M4: No | O4: 2 | P4: 0 | Q4: 0.002 | R4: =IF(OR($M4="Yes",$M4="Owner"),$C4*Cost!$B$6,0) -> 0 | S4: =$R4*$Q4 -> 0 | T4: — | V4: =IF($M4="Owner",$R4,IF($M4<>"Yes",0,MAX(IF(LEFT($T4,7)="Passive",$R4+MAX(Cost!$B$8,ROUNDUP(Cost!$B$7*$R4,0)),$R4+Cost!$B$9),N($U4)))) -> 0 | W4: =$V4*$Q4 -> 0 | X4: https://www.lcsc.com/product-detail/C1538.html | Y4: Unchanged | Z4: ,C101, | AA4: =IF($Z4="",0,LEN($Z4)-LEN(SUBSTITUTE($Z4,",",""))-1) -> 1 | AB4: =IF(OR($M4="Yes",$M4="Owner"),IF(COUNTIFS($H$4:$H4,$H4,$M$4:$M4,"Yes")+COUNTIFS($H$4:$H4,$H4,$M$4:$M4,"Owner")=1,1,0),0) -> 0 | AC4: FH | AD4: =IF(ISNUMBER(FIND("CG",$H4)),MID($H4,FIND("CG",$H4)+2,3),MID($H4,FIND(" 0",$H4)+6,3)) -> 472 | AE4: =IF(ISNUMBER(FIND("R",$AD4)),SUBSTITUTE($AD4,"R",".")*1,LEFT($AD4,2)*10^RIGHT($AD4,1))*10^-12 -> 4.7e-09 | AF4: {=LEFT($E4,FIND(" ",$E4)-1)*IFERROR(INDEX({1000,1000000,0.000000000001,0.000000001,0.000001},MATCH(MID($E4,FIND(" ",$E4)+1,1),{"k","M","p","n","µ"},0)),1)} -> 4.7e-09 | AG4: =IF(AND(RIGHT($E4,1)="F",ABS($AF4-$AE4)<=Checks!$C$6*$AE4),"OK","CHECK") -> OK
A5: 1 USB-C input, OVP and sensing | B5: C102 | C5: 1 | D5: VBUS input capacitor at J101 / U102 IN, also the U502 input capacitor (attach region A ≤ 29.6 µC with the 3V3M charge; hard-short kick with D102: U102 IN ≤ 17.08 V) | E5: 2.2 µF | F5: 0805 | G5: 25 V X5R ±10 % | H5: Samsung CL21A225KAFNNNE | I5: C87994 | J5: Extended | K5: JLCPCB library | L5: LCSC C87994; DigiKey 80,862 (23 Sep 2026) — confirm the stock in the JLCPCB BOM tool at order | M5: Yes | O5: 2 | P5: 0 | Q5: 0.02 | R5: =IF(OR($M5="Yes",$M5="Owner"),$C5*Cost!$B$6,0) -> 5 | S5: =$R5*$Q5 -> 0.1 | T5: Passive: +5 %, min +2 | V5: =IF($M5="Owner",$R5,IF($M5<>"Yes",0,MAX(IF(LEFT($T5,7)="Passive",$R5+MAX(Cost!$B$8,ROUNDUP(Cost!$B$7*$R5,0)),$R5+Cost!$B$9),N($U5)))) -> 7 | W5: =$V5*$Q5 -> 0.14 | Y5: Changed 4.7 µF → 2.2 µF (suspend power cut: the 3V3M capacitors now charge at plug-in through U502) | Z5: ,C102, | AA5: =IF($Z5="",0,LEN($Z5)-LEN(SUBSTITUTE($Z5,",",""))-1) -> 1 | AB5: =IF(OR($M5="Yes",$M5="Owner"),IF(COUNTIFS($H$4:$H5,$H5,$M$4:$M5,"Yes")+COUNTIFS($H$4:$H5,$H5,$M$4:$M5,"Owner")=1,1,0),0) -> 1 | AC5: Samsung CL | AD5: =MID($H5,FIND("CL",$H5)+5,3) -> 225 | AE5: =IF(ISNUMBER(FIND("R",$AD5)),SUBSTITUTE($AD5,"R",".")*1,LEFT($AD5,2)*10^RIGHT($AD5,1))*10^-12 -> 2.2e-06 | AF5: {=LEFT($E5,FIND(" ",$E5)-1)*IFERROR(INDEX({1000,1000000,0.000000000001,0.000000001,0.000001},MATCH(MID($E5,FIND(" ",$E5)+1,1),{"k","M","p","n","µ"},0)),1)} -> 2.2e-06 | AG5: =IF(AND(RIGHT($E5,1)="F",ABS($AF5-$AE5)<=Checks!$C$6*$AE5),"OK","CHECK") -> OK
A6: 1 USB-C input, OVP and sensing | B6: C103 | C6: 1 | D6: VBUS_SENSE ADC input capacitor at PA1 (tau 3.6 µs with R105/R106; brown-out watchdog acts before the MCU reset) | E6: 100 pF | F6: 0402 | G6: 50 V C0G ±5 % | H6: Samsung CL05C101JB5NNNC | I6: C1546 | J6: Basic | K6: JLCPCB library | L6: JLCPCB Basic | M6: Yes | O6: 2 | P6: 0 | Q6: 0.002 | R6: =IF(OR($M6="Yes",$M6="Owner"),$C6*Cost!$B$6,0) -> 5 | S6: =$R6*$Q6 -> 0.01 | T6: Passive: +5 %, min +2 | V6: =IF($M6="Owner",$R6,IF($M6<>"Yes",0,MAX(IF(LEFT($T6,7)="Passive",$R6+MAX(Cost!$B$8,ROUNDUP(Cost!$B$7*$R6,0)),$R6+Cost!$B$9),N($U6)))) -> 7 | W6: =$V6*$Q6 -> 0.014 | X6: https://www.lcsc.com/product-detail/C1546.html | Y6: Changed from 10 nF X7R to 100 pF C0G (fast brown-out detection) | Z6: ,C103, | AA6: =IF($Z6="",0,LEN($Z6)-LEN(SUBSTITUTE($Z6,",",""))-1) -> 1 | AB6: =IF(OR($M6="Yes",$M6="Owner"),IF(COUNTIFS($H$4:$H6,$H6,$M$4:$M6,"Yes")+COUNTIFS($H$4:$H6,$H6,$M$4:$M6,"Owner")=1,1,0),0) -> 1 | AC6: Samsung CL | AD6: =MID($H6,FIND("CL",$H6)+5,3) -> 101 | AE6: =IF(ISNUMBER(FIND("R",$AD6)),SUBSTITUTE($AD6,"R",".")*1,LEFT($AD6,2)*10^RIGHT($AD6,1))*10^-12 -> 1e-10 | AF6: {=LEFT($E6,FIND(" ",$E6)-1)*IFERROR(INDEX({1000,1000000,0.000000000001,0.000000001,0.000001},MATCH(MID($E6,FIND(" ",$E6)+1,1),{"k","M","p","n","µ"},0)),1)} -> 1e-10 | AG6: =IF(AND(RIGHT($E6,1)="F",ABS($AF6-$AE6)<=Checks!$C$6*$AE6),"OK","CHECK") -> OK
A7: 1 USB-C input, OVP and sensing | B7: C104 | C7: 1 | D7: U102 EN delay capacitor (EN to GND, with R109 470 k): U102 switches on 3.31–55.3 ms after plug-in at every corner | E7: 100 nF | F7: 0402 | G7: 16 V X7R ±10 % | H7: Samsung CL05B104KO5NNNC | I7: C1525 | J7: Basic | K7: JLCPCB library | L7: JLCPCB Basic | M7: Yes | O7: 2 | P7: 0 | Q7: 0.0045 | R7: =IF(OR($M7="Yes",$M7="Owner"),$C7*Cost!$B$6,0) -> 5 | S7: =$R7*$Q7 -> 0.0225 | T7: Passive: +5 %, min +2 | V7: =IF($M7="Owner",$R7,IF($M7<>"Yes",0,MAX(IF(LEFT($T7,7)="Passive",$R7+MAX(Cost!$B$8,ROUNDUP(Cost!$B$7*$R7,0)),$R7+Cost!$B$9),N($U7)))) -> 7 | W7: =$V7*$Q7 -> 0.0315 | X7: https://www.lcsc.com/product-detail/C1525.html | Y7: New; the two plug-in charge regions stay ≥ 1.96 ms apart | Z7: ,C104, | AA7: =IF($Z7="",0,LEN($Z7)-LEN(SUBSTITUTE($Z7,",",""))-1) -> 1 | AB7: =IF(OR($M7="Yes",$M7="Owner"),IF(COUNTIFS($H$4:$H7,$H7,$M$4:$M7,"Yes")+COUNTIFS($H$4:$H7,$H7,$M$4:$M7,"Owner")=1,1,0),0) -> 1 | AC7: Samsung CL | AD7: =MID($H7,FIND("CL",$H7)+5,3) -> 104 | AE7: =IF(ISNUMBER(FIND("R",$AD7)),SUBSTITUTE($AD7,"R",".")*1,LEFT($AD7,2)*10^RIGHT($AD7,1))*10^-12 -> 1e-07 | AF7: {=LEFT($E7,FIND(" ",$E7)-1)*IFERROR(INDEX({1000,1000000,0.000000000001,0.000000001,0.000001},MATCH(MID($E7,FIND(" ",$E7)+1,1),{"k","M","p","n","µ"},0)),1)} -> 1e-07 | AG7: =IF(AND(RIGHT($E7,1)="F",ABS($AF7-$AE7)<=Checks!$C$6*$AE7),"OK","CHECK") -> OK
A8: 1 USB-C input, OVP and sensing | B8: D102 | C8: 1 | D8: VBUS TVS at J101 (VBUS-GND, unidirectional, cathode to VBUS): U102 IN ≤ 17.08 V at a 5V_SYS hard short with no tIOS credit (20 V absolute maximum); VRWM 12 V so a mis-set 9 V source is below stand-off | E8: 12 V | F8: DO-214AB (SMC) | G8: VRWM 12 V, VBR 13.3-14.7 V, VC 19.9 V at 150.8 A, IR ≤ 2 µA at 12 V (25 °C), 3000 W | H8: Littelfuse SMDJ12A | I8: — | J8: — | K8: Owner purchase (DigiKey) | L8: Owner purchase (DigiKey): 5,498 in stock (Sep 2026), US$ 1.01 at 10+; LCSC SMDJ12A (MDD C2994091, TSC C3717799) out of stock; LGE C5806873 not adopted (IR/VBR maximum not verifiable) | M8: Owner | O8: 2 | P8: 0 | Q8: 1.01 | R8: =IF(OR($M8="Yes",$M8="Owner"),$C8*Cost!$B$6,0) -> 5 | S8: =$R8*$Q8 -> 5.05 | T8: Owner purchase: 5 × qty | V8: =IF($M8="Owner",$R8,IF($M8<>"Yes",0,MAX(IF(LEFT($T8,7)="Passive",$R8+MAX(Cost!$B$8,ROUNDUP(Cost!$B$7*$R8,0)),$R8+Cost!$B$9),N($U8)))) -> 5 | W8: =$V8*$Q8 -> 5.05 | X8: https://www.littelfuse.com/products/overvoltage-protection/tvs-diodes/surface-mount/smdj/smdj12a | Y8: Owner-fitted: hand-soldered after delivery, not placed by JLCPCB; fitted first, before the first USB plug-in; SMC lands with toes +0.3 mm, ≥ 1.5 mm iron clearance, ≤ 5 mm from J101; polarity gate G-4 (band = cathode = VBUS) | Z8: ,D102, | AA8: =IF($Z8="",0,LEN($Z8)-LEN(SUBSTITUTE($Z8,",",""))-1) -> 1 | AB8: =IF(OR($M8="Yes",$M8="Owner"),IF(COUNTIFS($H$4:$H8,$H8,$M$4:$M8,"Yes")+COUNTIFS($H$4:$H8,$H8,$M$4:$M8,"Owner")=1,1,0),0) -> 1
A9: 1 USB-C input, OVP and sensing | B9: J101 | C9: 1 | D9: USB-C receptacle, USB 2.0: 16 contacts on the 12 composite GCT solder lands (shared A1/B12, A4/B9, B4/A9, B1/A12; single A5, A6, A7, A8, B5, B6, B7, B8) plus the plated shell stakes S1–S4; the provisional footprint uses the 16 JLCPCB pad IDs (each shared land is two touching pads on one net), plus two Ø0.65 mm non-plated locating holes; pin-in-paste on S1–S4 only after JLCPCB confirms the process and the aperture geometry (G-6); fallback: the owner hand-solders S1–S4 from the bottom side before the first plug-in (the stakes carry the shell and the mechanical retention); shell to GND via R107 | E9: — | F9: SMD horizontal top mount, 0.95 mm shell stakes | G9: 48 V DC (GCT page; drawing 20 V), VBUS 5 A, GND 6.25 A, others 0.25 A, 40 mΩ max; solder peak 255 °C (-0/+5) max 5 s | H9: GCT USB4105-GF-A | I9: C3020560 | J9: Extended | K9: Global sourcing | L9: LCSC out of stock (14 Sep 2026); DigiKey 127,933 (24 Sep 2026) → JLCPCB global sourcing; JLCPCB lists it as Economic and Standard, assembly difficulty high | M9: Yes | O9: 12 | P9: 4 | Q9: 1.09 | R9: =IF(OR($M9="Yes",$M9="Owner"),$C9*Cost!$B$6,0) -> 5 | S9: =$R9*$Q9 -> 5.45 | T9: Other: +1 | V9: =IF($M9="Owner",$R9,IF($M9<>"Yes",0,MAX(IF(LEFT($T9,7)="Passive",$R9+MAX(Cost!$B$8,ROUNDUP(Cost!$B$7*$R9,0)),$R9+Cost!$B$9),N($U9)))) -> 6 | W9: =$V9*$Q9 -> 6.54 | X9: https://gct.co/connector/usb4105 (drawing text: https://www.mouser.com/datasheet/2/837/USB4105-1948910.pdf) | Y9: Changed from the SHOU HAN receptacle; pads named by contact per the GCT drawing; Standard PCBA reflow 240 °C (JLCPCB to confirm the dwell, order remark); provisional footprint J101_USB4105-GF-A_12lands_4stakes (label ↔ JLCPCB pad-ID mapping on the Notes sheet); gates G-1 continuity (2 samples) and G-3 1:1 overlay; the S1–S4 soldering process is a G-6 order-release item | Z9: ,J101, | AA9: =IF($Z9="",0,LEN($Z9)-LEN(SUBSTITUTE($Z9,",",""))-1) -> 1 | AB9: =IF(OR($M9="Yes",$M9="Owner"),IF(COUNTIFS($H$4:$H9,$H9,$M$4:$M9,"Yes")+COUNTIFS($H$4:$H9,$H9,$M$4:$M9,"Owner")=1,1,0),0) -> 1
A10: 1 USB-C input, OVP and sensing | B10: R101, R102 | C10: 2 | D10: CC1/CC2 Rd pull-down (USB-C sink) | E10: 5.1 kΩ | F10: 0402 | G10: 1 % | H10: UNI-ROYAL 0402WGF5101TCE | I10: C25905 | J10: Basic | K10: JLCPCB library | L10: As in Parts List v0.6 | M10: Yes | O10: 2 | P10: 0 | Q10: 0.002 | R10: =IF(OR($M10="Yes",$M10="Owner"),$C10*Cost!$B$6,0) -> 10 | S10: =$R10*$Q10 -> 0.02 | T10: Passive: +5 %, min +2 | V10: =IF($M10="Owner",$R10,IF($M10<>"Yes",0,MAX(IF(LEFT($T10,7)="Passive",$R10+MAX(Cost!$B$8,ROUNDUP(Cost!$B$7*$R10,0)),$R10+Cost!$B$9),N($U10)))) -> 12 | W10: =$V10*$Q10 -> 0.024 | X10: https://www.lcsc.com/product-detail/C25905.html | Y10: Unchanged | Z10: ,R101,R102, | AA10: =IF($Z10="",0,LEN($Z10)-LEN(SUBSTITUTE($Z10,",",""))-1) -> 2 | AB10: =IF(OR($M10="Yes",$M10="Owner"),IF(COUNTIFS($H$4:$H10,$H10,$M$4:$M10,"Yes")+COUNTIFS($H$4:$H10,$H10,$M$4:$M10,"Owner")=1,1,0),0) -> 1 | AC10: UNI-ROYAL | AD10: =MID($H10,18,4) -> 5101 | AE10: =LEFT($AD10,3)*IF(ISNUMBER(--RIGHT($AD10,1)),10^RIGHT($AD10,1),10^(0-FIND(RIGHT($AD10,1),"JKLM"))) -> 5100 | AF10: {=LEFT($E10,FIND(" ",$E10)-1)*IFERROR(INDEX({1000,1000000,0.000000000001,0.000000001,0.000001},MATCH(MID($E10,FIND(" ",$E10)+1,1),{"k","M","p","n","µ"},0)),1)} -> 5100 | AG10: =IF(AND(RIGHT($E10,1)="Ω",ABS($AF10-$AE10)<=Checks!$C$6*$AE10),"OK","CHECK") -> OK
A11: 1 USB-C input, OVP and sensing | B11: R103, R104 | C11: 2 | D11: CC1/CC2 series resistor to MCU ADC (CC1_ADC, CC2_ADC) | E11: 10 kΩ | F11: 0402 | G11: 1 % | H11: UNI-ROYAL 0402WGF1002TCE | I11: C25744 | J11: Basic | K11: JLCPCB library | L11: As in Parts List v0.6 | M11: Yes | O11: 2 | P11: 0 | Q11: 0.002 | R11: =IF(OR($M11="Yes",$M11="Owner"),$C11*Cost!$B$6,0) -> 10 | S11: =$R11*$Q11 -> 0.02 | T11: Passive: +5 %, min +2 | V11: =IF($M11="Owner",$R11,IF($M11<>"Yes",0,MAX(IF(LEFT($T11,7)="Passive",$R11+MAX(Cost!$B$8,ROUNDUP(Cost!$B$7*$R11,0)),$R11+Cost!$B$9),N($U11)))) -> 12 | W11: =$V11*$Q11 -> 0.024 | X11: https://www.lcsc.com/product-detail/C25744.html | Y11: Unchanged | Z11: ,R103,R104, | AA11: =IF($Z11="",0,LEN($Z11)-LEN(SUBSTITUTE($Z11,",",""))-1) -> 2 | AB11: =IF(OR($M11="Yes",$M11="Owner"),IF(COUNTIFS($H$4:$H11,$H11,$M$4:$M11,"Yes")+COUNTIFS($H$4:$H11,$H11,$M$4:$M11,"Owner")=1,1,0),0) -> 1 | AC11: UNI-ROYAL | AD11: =MID($H11,18,4) -> 1002 | AE11: =LEFT($AD11,3)*IF(ISNUMBER(--RIGHT($AD11,1)),10^RIGHT($AD11,1),10^(0-FIND(RIGHT($AD11,1),"JKLM"))) -> 10000 | AF11: {=LEFT($E11,FIND(" ",$E11)-1)*IFERROR(INDEX({1000,1000000,0.000000000001,0.000000001,0.000001},MATCH(MID($E11,FIND(" ",$E11)+1,1),{"k","M","p","n","µ"},0)),1)} -> 10000 | AG11: =IF(AND(RIGHT($E11,1)="Ω",ABS($AF11-$AE11)<=Checks!$C$6*$AE11),"OK","CHECK") -> OK
A12: 1 USB-C input, OVP and sensing | B12: R105 | C12: 1 | D12: VBUS_SENSE divider top, from 5V_SYS | E12: 100 kΩ | F12: 0402 | G12: 1 % | H12: UNI-ROYAL 0402WGF1003TCE | I12: C25741 | J12: Basic | K12: JLCPCB library | L12: As in Parts List v0.6 | M12: Yes | O12: 2 | P12: 0 | Q12: 0.0033 | R12: =IF(OR($M12="Yes",$M12="Owner"),$C12*Cost!$B$6,0) -> 5 | S12: =$R12*$Q12 -> 0.0165 | T12: Passive: +5 %, min +2 | V12: =IF($M12="Owner",$R12,IF($M12<>"Yes",0,MAX(IF(LEFT($T12,7)="Passive",$R12+MAX(Cost!$B$8,ROUNDUP(Cost!$B$7*$R12,0)),$R12+Cost!$B$9),N($U12)))) -> 7 | W12: =$V12*$Q12 -> 0.0231 | X12: https://www.lcsc.com/product-detail/C25741.html | Y12: Now on 5V_SYS (after the OVP) | Z12: ,R105, | AA12: =IF($Z12="",0,LEN($Z12)-LEN(SUBSTITUTE($Z12,",",""))-1) -> 1 | AB12: =IF(OR($M12="Yes",$M12="Owner"),IF(COUNTIFS($H$4:$H12,$H12,$M$4:$M12,"Yes")+COUNTIFS($H$4:$H12,$H12,$M$4:$M12,"Owner")=1,1,0),0) -> 1 | AC12: UNI-ROYAL | AD12: =MID($H12,18,4) -> 1003 | AE12: =LEFT($AD12,3)*IF(ISNUMBER(--RIGHT($AD12,1)),10^RIGHT($AD12,1),10^(0-FIND(RIGHT($AD12,1),"JKLM"))) -> 100000 | AF12: {=LEFT($E12,FIND(" ",$E12)-1)*IFERROR(INDEX({1000,1000000,0.000000000001,0.000000001,0.000001},MATCH(MID($E12,FIND(" ",$E12)+1,1),{"k","M","p","n","µ"},0)),1)} -> 100000 | AG12: =IF(AND(RIGHT($E12,1)="Ω",ABS($AF12-$AE12)<=Checks!$C$6*$AE12),"OK","CHECK") -> OK
A13: 1 USB-C input, OVP and sensing | B13: R106 | C13: 1 | D13: VBUS_SENSE divider bottom (k = 0.3197; 5.55 V → 1.77 V) | E13: 47 kΩ | F13: 0402 | G13: 1 % | H13: UNI-ROYAL 0402WGF4702TCE | I13: C25792 | J13: Basic | K13: JLCPCB library | L13: As in Parts List v0.6 | M13: Yes | O13: 2 | P13: 0 | Q13: 0.002 | R13: =IF(OR($M13="Yes",$M13="Owner"),$C13*Cost!$B$6,0) -> 5 | S13: =$R13*$Q13 -> 0.01 | T13: Passive: +5 %, min +2 | V13: =IF($M13="Owner",$R13,IF($M13<>"Yes",0,MAX(IF(LEFT($T13,7)="Passive",$R13+MAX(Cost!$B$8,ROUNDUP(Cost!$B$7*$R13,0)),$R13+Cost!$B$9),N($U13)))) -> 7 | W13: =$V13*$Q13 -> 0.014 | X13: https://www.lcsc.com/product-detail/C25792.html | Y13: Unchanged value | Z13: ,R106, | AA13: =IF($Z13="",0,LEN($Z13)-LEN(SUBSTITUTE($Z13,",",""))-1) -> 1 | AB13: =IF(OR($M13="Yes",$M13="Owner"),IF(COUNTIFS($H$4:$H13,$H13,$M$4:$M13,"Yes")+COUNTIFS($H$4:$H13,$H13,$M$4:$M13,"Owner")=1,1,0),0) -> 1 | AC13: UNI-ROYAL | AD13: =MID($H13,18,4) -> 4702 | AE13: =LEFT($AD13,3)*IF(ISNUMBER(--RIGHT($AD13,1)),10^RIGHT($AD13,1),10^(0-FIND(RIGHT($AD13,1),"JKLM"))) -> 47000 | AF13: {=LEFT($E13,FIND(" ",$E13)-1)*IFERROR(INDEX({1000,1000000,0.000000000001,0.000000001,0.000001},MATCH(MID($E13,FIND(" ",$E13)+1,1),{"k","M","p","n","µ"},0)),1)} -> 47000 | AG13: =IF(AND(RIGHT($E13,1)="Ω",ABS($AF13-$AE13)<=Checks!$C$6*$AE13),"OK","CHECK") -> OK
A14: 1 USB-C input, OVP and sensing | B14: R107 | C14: 1 | D14: USB-C shell to GND (0 Ω) | E14: 0 Ω | F14: 0402 | G14: jumper | H14: UNI-ROYAL 0402WGF0000TCE | I14: C17168 | J14: Basic | K14: JLCPCB library | L14: As in Parts List v0.6 | M14: Yes | O14: 2 | P14: 0 | Q14: 0.002 | R14: =IF(OR($M14="Yes",$M14="Owner"),$C14*Cost!$B$6,0) -> 5 | S14: =$R14*$Q14 -> 0.01 | T14: Passive: +5 %, min +2 | V14: =IF($M14="Owner",$R14,IF($M14<>"Yes",0,MAX(IF(LEFT($T14,7)="Passive",$R14+MAX(Cost!$B$8,ROUNDUP(Cost!$B$7*$R14,0)),$R14+Cost!$B$9),N($U14)))) -> 7 | W14: =$V14*$Q14 -> 0.014 | X14: https://www.lcsc.com/product-detail/C17168.html | Y14: Unchanged | Z14: ,R107, | AA14: =IF($Z14="",0,LEN($Z14)-LEN(SUBSTITUTE($Z14,",",""))-1) -> 1 | AB14: =IF(OR($M14="Yes",$M14="Owner"),IF(COUNTIFS($H$4:$H14,$H14,$M$4:$M14,"Yes")+COUNTIFS($H$4:$H14,$H14,$M$4:$M14,"Owner")=1,1,0),0) -> 1 | AC14: UNI-ROYAL | AD14: =MID($H14,18,4) -> 0000 | AE14: =LEFT($AD14,3)*IF(ISNUMBER(--RIGHT($AD14,1)),10^RIGHT($AD14,1),10^(0-FIND(RIGHT($AD14,1),"JKLM"))) -> 0 | AF14: {=LEFT($E14,FIND(" ",$E14)-1)*IFERROR(INDEX({1000,1000000,0.000000000001,0.000000001,0.000001},MATCH(MID($E14,FIND(" ",$E14)+1,1),{"k","M","p","n","µ"},0)),1)} -> 0 | AG14: =IF(AND(RIGHT($E14,1)="Ω",ABS($AF14-$AE14)<=Checks!$C$6*$AE14),"OK","CHECK") -> OK
A15: 1 USB-C input, OVP and sensing | B15: R108 | C15: 1 | D15: U102 current-limit resistor (IOS 870/970/1077 mA ≥ the 760.77 mA of state S4: +109 mA to the minimum; 765.27 mA with the NDK X201 second source) | E15: 100 kΩ | F15: 0402 | G15: 1 %, 62.5 mW | H15: UNI-ROYAL 0402WGF1003TCE | I15: C25741 | J15: Basic | K15: JLCPCB library | L15: JLCPCB Basic (same type as R105, R303, R511–R513) | M15: Yes | O15: 2 | P15: 0 | Q15: 0.0033 | R15: =IF(OR($M15="Yes",$M15="Owner"),$C15*Cost!$B$6,0) -> 5 | S15: =$R15*$Q15 -> 0.0165 | T15: Passive: +5 %, min +2 | V15: =IF($M15="Owner",$R15,IF($M15<>"Yes",0,MAX(IF(LEFT($T15,7)="Passive",$R15+MAX(Cost!$B$8,ROUNDUP(Cost!$B$7*$R15,0)),$R15+Cost!$B$9),N($U15)))) -> 7 | W15: =$V15*$Q15 -> 0.0231 | X15: https://www.lcsc.com/product-detail/C19709.html | Y15: Cost patch: changed 86.6 k (Extended) → 100 k (Basic) | Z15: ,R108, | AA15: =IF($Z15="",0,LEN($Z15)-LEN(SUBSTITUTE($Z15,",",""))-1) -> 1 | AB15: =IF(OR($M15="Yes",$M15="Owner"),IF(COUNTIFS($H$4:$H15,$H15,$M$4:$M15,"Yes")+COUNTIFS($H$4:$H15,$H15,$M$4:$M15,"Owner")=1,1,0),0) -> 0 | AC15: UNI-ROYAL | AD15: =MID($H15,18,4) -> 1003 | AE15: =LEFT($AD15,3)*IF(ISNUMBER(--RIGHT($AD15,1)),10^RIGHT($AD15,1),10^(0-FIND(RIGHT($AD15,1),"JKLM"))) -> 100000 | AF15: {=LEFT($E15,FIND(" ",$E15)-1)*IFERROR(INDEX({1000,1000000,0.000000000001,0.000000001,0.000001},MATCH(MID($E15,FIND(" ",$E15)+1,1),{"k","M","p","n","µ"},0)),1)} -> 100000 | AG15: =IF(AND(RIGHT($E15,1)="Ω",ABS($AF15-$AE15)<=Checks!$C$6*$AE15),"OK","CHECK") -> OK
A16: 1 USB-C input, OVP and sensing | B16: R109 | C16: 1 | D16: U102 EN pull-up to VBUS (TI: ≥ 300 k; with C104, U102 switches on 3.3–55 ms after plug-in) | E16: 470 kΩ | F16: 0402 | G16: 1 %, 62.5 mW | H16: UNI-ROYAL 0402WGF4703TCE | I16: C25790 | J16: Basic (not verified) | K16: JLCPCB library | L16: Same type as R532 | M16: Yes | O16: 2 | P16: 0 | Q16: 0.002 | R16: =IF(OR($M16="Yes",$M16="Owner"),$C16*Cost!$B$6,0) -> 5 | S16: =$R16*$Q16 -> 0.01 | T16: Passive: +5 %, min +2 | V16: =IF($M16="Owner",$R16,IF($M16<>"Yes",0,MAX(IF(LEFT($T16,7)="Passive",$R16+MAX(Cost!$B$8,ROUNDUP(Cost!$B$7*$R16,0)),$R16+Cost!$B$9),N($U16)))) -> 7 | W16: =$V16*$Q16 -> 0.014 | X16: https://www.lcsc.com/product-detail/C25774.html | Y16: Cost patch: changed 300 k → 470 k (one part type less); USB D+ attach ≤ 79.2 ms against the 100 ms USB limit | Z16: ,R109, | AA16: =IF($Z16="",0,LEN($Z16)-LEN(SUBSTITUTE($Z16,",",""))-1) -> 1 | AB16: =IF(OR($M16="Yes",$M16="Owner"),IF(COUNTIFS($H$4:$H16,$H16,$M$4:$M16,"Yes")+COUNTIFS($H$4:$H16,$H16,$M$4:$M16,"Owner")=1,1,0),0) -> 1 | AC16: UNI-ROYAL | AD16: =MID($H16,18,4) -> 4703 | AE16: =LEFT($AD16,3)*IF(ISNUMBER(--RIGHT($AD16,1)),10^RIGHT($AD16,1),10^(0-FIND(RIGHT($AD16,1),"JKLM"))) -> 470000 | AF16: {=LEFT($E16,FIND(" ",$E16)-1)*IFERROR(INDEX({1000,1000000,0.000000000001,0.000000001,0.000001},MATCH(MID($E16,FIND(" ",$E16)+1,1),{"k","M","p","n","µ"},0)),1)} -> 470000 | AG16: =IF(AND(RIGHT($E16,1)="Ω",ABS($AF16-$AE16)<=Checks!$C$6*$AE16),"OK","CHECK") -> OK
A17: 1 USB-C input, OVP and sensing | B17: U101 | C17: 1 | D17: ESD array D+/D−; VBUS pin (5) tied to 3V3M (5V_SYS is off in suspend; on 5V_SYS the D+ pull-up would back-feed it through the upper diode) | E17: — | F17: SOT-23-6 | G17: IRM ≤ 150 nA at 5.25 V, 3.5 pF | H17: ST USBLC6-2SC6 | I17: C7519 | J17: Extended | K17: JLCPCB library | L17: As in Parts List v0.6 | M17: Yes | O17: 6 | P17: 0 | Q17: 0.1844 | R17: =IF(OR($M17="Yes",$M17="Owner"),$C17*Cost!$B$6,0) -> 5 | S17: =$R17*$Q17 -> 0.922 | T17: Other: +1 | V17: =IF($M17="Owner",$R17,IF($M17<>"Yes",0,MAX(IF(LEFT($T17,7)="Passive",$R17+MAX(Cost!$B$8,ROUNDUP(Cost!$B$7*$R17,0)),$R17+Cost!$B$9),N($U17)))) -> 6 | W17: =$V17*$Q17 -> 1.1064 | X17: https://www.st.com/resource/en/datasheet/usblc6-2.pdf | Y17: Pin 5 moved from 5V_SYS to 3V3M (suspend power cut) | Z17: ,U101, | AA17: =IF($Z17="",0,LEN($Z17)-LEN(SUBSTITUTE($Z17,",",""))-1) -> 1 | AB17: =IF(OR($M17="Yes",$M17="Owner"),IF(COUNTIFS($H$4:$H17,$H17,$M$4:$M17,"Yes")+COUNTIFS($H$4:$H17,$H17,$M$4:$M17,"Owner")=1,1,0),0) -> 1
A18: 1 USB-C input, OVP and sensing | B18: U102 | C18: 1 | D18: Input OVP eFuse: 5.25-5.55 V output clamp, OVLO 6.8-8.45 V, 20 V abs max IN, 99 mΩ max, built-in soft start | E18: — | F18: WSON-6 2 × 2 (DRV) + pad | G18: IOS 0.87–1.08 A with R108 100 k | H18: TI TPS25200DRVR | I18: C128401 | J18: Extended | K18: JLCPCB library | L18: JLCPCB 19,166 available (Aug 2026) | M18: Yes | N18: Yes | O18: 7 | P18: 0 | Q18: 0.44 | R18: =IF(OR($M18="Yes",$M18="Owner"),$C18*Cost!$B$6,0) -> 5 | S18: =$R18*$Q18 -> 2.2 | T18: Other: +1 | V18: =IF($M18="Owner",$R18,IF($M18<>"Yes",0,MAX(IF(LEFT($T18,7)="Passive",$R18+MAX(Cost!$B$8,ROUNDUP(Cost!$B$7*$R18,0)),$R18+Cost!$B$9),N($U18)))) -> 6 | W18: =$V18*$Q18 -> 2.64 | X18: https://www.ti.com/lit/ds/symlink/tps25200.pdf | Y18: New: VBUS → 5V_SYS; FAULT (pin 3) not connected; pad to GND | Z18: ,U102, | AA18: =IF($Z18="",0,LEN($Z18)-LEN(SUBSTITUTE($Z18,",",""))-1) -> 1 | AB18: =IF(OR($M18="Yes",$M18="Owner"),IF(COUNTIFS($H$4:$H18,$H18,$M$4:$M18,"Yes")+COUNTIFS($H$4:$H18,$H18,$M$4:$M18,"Owner")=1,1,0),0) -> 1
A19: 1 USB-C input, OVP and sensing | B19: U103 | C19: 1 | D19: CC1/CC2 ESD, 2 channels, low capacitance, at J101 | E19: — | F19: SOT-5X3 (DRL) 5-pin | G19: VRWM 5.5 V, VBR ≥ 6.5 V, 10 nA at 2.5 V, 1.5 pF, IEC ±25 kV | H19: TI TPD2E2U06DRLR | I19: C1972959 | J19: Extended (not verified) | K19: JLCPCB library | L19: JLCPCB 4,257 (Apr 2025); DigiKey 87,628 | M19: Yes | O19: 5 | P19: 0 | Q19: 0.22 | R19: =IF(OR($M19="Yes",$M19="Owner"),$C19*Cost!$B$6,0) -> 5 | S19: =$R19*$Q19 -> 1.1 | T19: Other: +1 | V19: =IF($M19="Owner",$R19,IF($M19<>"Yes",0,MAX(IF(LEFT($T19,7)="Passive",$R19+MAX(Cost!$B$8,ROUNDUP(Cost!$B$7*$R19,0)),$R19+Cost!$B$9),N($U19)))) -> 6 | W19: =$V19*$Q19 -> 1.32 | X19: https://www.ti.com/lit/ds/symlink/tpd2e2u06.pdf | Y19: New; pin 1/2 NC, 3 CC1, 4 GND, 5 CC2 | Z19: ,U103, | AA19: =IF($Z19="",0,LEN($Z19)-LEN(SUBSTITUTE($Z19,",",""))-1) -> 1 | AB19: =IF(OR($M19="Yes",$M19="Owner"),IF(COUNTIFS($H$4:$H19,$H19,$M$4:$M19,"Yes")+COUNTIFS($H$4:$H19,$H19,$M$4:$M19,"Owner")=1,1,0),0) -> 1
A20: 2 USB audio bridge (CH32V307 + AGRV2K CPLD + clocks) | B20: C201, C202 | C20: 2 | D20: Crystal load capacitors | E20: 33 pF | F20: 0402 | G20: 50 V C0G | H20: FH 0402CG330J500NT | I20: C1562 | J20: Basic | K20: JLCPCB library | L20: JLCPCB Basic | M20: Yes | O20: 2 | P20: 0 | Q20: 0.002 | R20: =IF(OR($M20="Yes",$M20="Owner"),$C20*Cost!$B$6,0) -> 10 | S20: =$R20*$Q20 -> 0.02 | T20: Passive: +5 %, min +2 | V20: =IF($M20="Owner",$R20,IF($M20<>"Yes",0,MAX(IF(LEFT($T20,7)="Passive",$R20+MAX(Cost!$B$8,ROUNDUP(Cost!$B$7*$R20,0)),$R20+Cost!$B$9),N($U20)))) -> 12 | W20: =$V20*$Q20 -> 0.024 | X20: https://www.lcsc.com/product-detail/C1562.html | Y20: 2 × (20 − 3.5) pF | Z20: ,C201,C202, | AA20: =IF($Z20="",0,LEN($Z20)-LEN(SUBSTITUTE($Z20,",",""))-1) -> 2 | AB20: =IF(OR($M20="Yes",$M20="Owner"),IF(COUNTIFS($H$4:$H20,$H20,$M$4:$M20,"Yes")+COUNTIFS($H$4:$H20,$H20,$M$4:$M20,"Owner")=1,1,0),0) -> 1 | AC20: FH | AD20: =IF(ISNUMBER(FIND("CG",$H20)),MID($H20,FIND("CG",$H20)+2,3),MID($H20,FIND(" 0",$H20)+6,3)) -> 330 | AE20: =IF(ISNUMBER(FIND("R",$AD20)),SUBSTITUTE($AD20,"R",".")*1,LEFT($AD20,2)*10^RIGHT($AD20,1))*10^-12 -> 3.3e-11 | AF20: {=LEFT($E20,FIND(" ",$E20)-1)*IFERROR(INDEX({1000,1000000,0.000000000001,0.000000001,0.000001},MATCH(MID($E20,FIND(" ",$E20)+1,1),{"k","M","p","n","µ"},0)),1)} -> 3.3e-11 | AG20: =IF(AND(RIGHT($E20,1)="F",ABS($AF20-$AE20)<=Checks!$C$6*$AE20),"OK","CHECK") -> OK
A21: 2 USB audio bridge (CH32V307 + AGRV2K CPLD + clocks) | B21: C203-C210, C212-C215, C218, C219, C222-C224 | C21: 17 | D21: 100 nF: decoupling (MCU ×8, CPLD ×3, X202/X203, U205, U206, U208) and NRST filter C212 | E21: 100 nF | F21: 0402 | G21: 16 V X7R | H21: Samsung CL05B104KO5NNNC | I21: C1525 | J21: Basic | K21: JLCPCB library | L21: JLCPCB Basic | M21: Yes | O21: 2 | P21: 0 | Q21: 0.0045 | R21: =IF(OR($M21="Yes",$M21="Owner"),$C21*Cost!$B$6,0) -> 85 | S21: =$R21*$Q21 -> 0.3825 | T21: Passive: +5 %, min +2 | V21: =IF($M21="Owner",$R21,IF($M21<>"Yes",0,MAX(IF(LEFT($T21,7)="Passive",$R21+MAX(Cost!$B$8,ROUNDUP(Cost!$B$7*$R21,0)),$R21+Cost!$B$9),N($U21)))) -> 90 | W21: =$V21*$Q21 -> 0.405 | X21: https://www.lcsc.com/product-detail/C1525.html | Y21: C216 retired; C213–C215 at CPLD pins 6/16/32; C212 = NRST filter; C217 now its own 10 nF line; C224 new (U208) | Z21: ,C203,C204,C205,C206,C207,C208,C209,C210,C212,C213,C214,C215,C218,C219,C222,C223,C224, | AA21: =IF($Z21="",0,LEN($Z21)-LEN(SUBSTITUTE($Z21,",",""))-1) -> 17 | AB21: =IF(OR($M21="Yes",$M21="Owner"),IF(COUNTIFS($H$4:$H21,$H21,$M$4:$M21,"Yes")+COUNTIFS($H$4:$H21,$H21,$M$4:$M21,"Owner")=1,1,0),0) -> 0 | AC21: Samsung CL | AD21: =MID($H21,FIND("CL",$H21)+5,3) -> 104 | AE21: =IF(ISNUMBER(FIND("R",$AD21)),SUBSTITUTE($AD21,"R",".")*1,LEFT($AD21,2)*10^RIGHT($AD21,1))*10^-12 -> 1e-07 | AF21: {=LEFT($E21,FIND(" ",$E21)-1)*IFERROR(INDEX({1000,1000000,0.000000000001,0.000000001,0.000001},MATCH(MID($E21,FIND(" ",$E21)+1,1),{"k","M","p","n","µ"},0)),1)} -> 1e-07 | AG21: =IF(AND(RIGHT($E21,1)="F",ABS($AF21-$AE21)<=Checks!$C$6*$AE21),"OK","CHECK") -> OK
A22: 2 USB audio bridge (CH32V307 + AGRV2K CPLD + clocks) | B22: C211 | C22: 1 | D22: MCU 3V3M bulk | E22: 2.2 µF | F22: 0402 | G22: 6.3 V X5R (≈ 1.1 µF at 3.3 V DC bias) | H22: Samsung CL05A225MQ5NSNC | I22: C12530 | J22: Basic | K22: JLCPCB library | L22: JLCPCB Basic | M22: Yes | O22: 2 | P22: 0 | Q22: 0.005 | R22: =IF(OR($M22="Yes",$M22="Owner"),$C22*Cost!$B$6,0) -> 5 | S22: =$R22*$Q22 -> 0.025 | T22: Passive: +5 %, min +2 | V22: =IF($M22="Owner",$R22,IF($M22<>"Yes",0,MAX(IF(LEFT($T22,7)="Passive",$R22+MAX(Cost!$B$8,ROUNDUP(Cost!$B$7*$R22,0)),$R22+Cost!$B$9),N($U22)))) -> 7 | W22: =$V22*$Q22 -> 0.035 | X22: https://www.lcsc.com/product-detail/C12530.html | Y22: Kept (counted in the attach-charge budget) | Z22: ,C211, | AA22: =IF($Z22="",0,LEN($Z22)-LEN(SUBSTITUTE($Z22,",",""))-1) -> 1 | AB22: =IF(OR($M22="Yes",$M22="Owner"),IF(COUNTIFS($H$4:$H22,$H22,$M$4:$M22,"Yes")+COUNTIFS($H$4:$H22,$H22,$M$4:$M22,"Owner")=1,1,0),0) -> 1 | AC22: Samsung CL | AD22: =MID($H22,FIND("CL",$H22)+5,3) -> 225 | AE22: =IF(ISNUMBER(FIND("R",$AD22)),SUBSTITUTE($AD22,"R",".")*1,LEFT($AD22,2)*10^RIGHT($AD22,1))*10^-12 -> 2.2e-06 | AF22: {=LEFT($E22,FIND(" ",$E22)-1)*IFERROR(INDEX({1000,1000000,0.000000000001,0.000000001,0.000001},MATCH(MID($E22,FIND(" ",$E22)+1,1),{"k","M","p","n","µ"},0)),1)} -> 2.2e-06 | AG22: =IF(AND(RIGHT($E22,1)="F",ABS($AF22-$AE22)<=Checks!$C$6*$AE22),"OK","CHECK") -> OK
A23: 2 USB audio bridge (CH32V307 + AGRV2K CPLD + clocks) | B23: C217 | C23: 1 | D23: X201 high-frequency bypass at the VCC pad | E23: 10 nF | F23: 0402 | G23: 50 V X7R | H23: Samsung CL05B103KB5NNNC | I23: C15195 | J23: Basic | K23: JLCPCB library | L23: JLCPCB Basic | M23: Yes | O23: 2 | P23: 0 | Q23: 0.002 | R23: =IF(OR($M23="Yes",$M23="Owner"),$C23*Cost!$B$6,0) -> 5 | S23: =$R23*$Q23 -> 0.01 | T23: Passive: +5 %, min +2 | V23: =IF($M23="Owner",$R23,IF($M23<>"Yes",0,MAX(IF(LEFT($T23,7)="Passive",$R23+MAX(Cost!$B$8,ROUNDUP(Cost!$B$7*$R23,0)),$R23+Cost!$B$9),N($U23)))) -> 7 | W23: =$V23*$Q23 -> 0.014 | X23: https://www.lcsc.com/product-detail/C15195.html | Y23: Changed 100 nF → 10 nF; Kyocera: "mount high frequency type capacitor 0.01 µF to the nearest position of oscillator" | Z23: ,C217, | AA23: =IF($Z23="",0,LEN($Z23)-LEN(SUBSTITUTE($Z23,",",""))-1) -> 1 | AB23: =IF(OR($M23="Yes",$M23="Owner"),IF(COUNTIFS($H$4:$H23,$H23,$M$4:$M23,"Yes")+COUNTIFS($H$4:$H23,$H23,$M$4:$M23,"Owner")=1,1,0),0) -> 1 | AC23: Samsung CL | AD23: =MID($H23,FIND("CL",$H23)+5,3) -> 103 | AE23: =IF(ISNUMBER(FIND("R",$AD23)),SUBSTITUTE($AD23,"R",".")*1,LEFT($AD23,2)*10^RIGHT($AD23,1))*10^-12 -> 1e-08 | AF23: {=LEFT($E23,FIND(" ",$E23)-1)*IFERROR(INDEX({1000,1000000,0.000000000001,0.000000001,0.000001},MATCH(MID($E23,FIND(" ",$E23)+1,1),{"k","M","p","n","µ"},0)),1)} -> 1e-08 | AG23: =IF(AND(RIGHT($E23,1)="F",ABS($AF23-$AE23)<=Checks!$C$6*$AE23),"OK","CHECK") -> OK
A24: 2 USB audio bridge (CH32V307 + AGRV2K CPLD + clocks) | B24: C220, C221 | C24: 2 | D24: Bulk: CPLD FB202 branch; MCU VDDA | E24: 1 µF | F24: 0603 | G24: 50 V X5R | H24: Samsung CL10A105KB8NNNC | I24: C15849 | J24: Basic | K24: JLCPCB library | L24: JLCPCB Basic | M24: Yes | O24: 2 | P24: 0 | Q24: 0.006 | R24: =IF(OR($M24="Yes",$M24="Owner"),$C24*Cost!$B$6,0) -> 10 | S24: =$R24*$Q24 -> 0.06 | T24: Passive: +5 %, min +2 | V24: =IF($M24="Owner",$R24,IF($M24<>"Yes",0,MAX(IF(LEFT($T24,7)="Passive",$R24+MAX(Cost!$B$8,ROUNDUP(Cost!$B$7*$R24,0)),$R24+Cost!$B$9),N($U24)))) -> 12 | W24: =$V24*$Q24 -> 0.072 | X24: https://www.lcsc.com/product-detail/C15849.html | Z24: ,C220,C221, | AA24: =IF($Z24="",0,LEN($Z24)-LEN(SUBSTITUTE($Z24,",",""))-1) -> 2 | AB24: =IF(OR($M24="Yes",$M24="Owner"),IF(COUNTIFS($H$4:$H24,$H24,$M$4:$M24,"Yes")+COUNTIFS($H$4:$H24,$H24,$M$4:$M24,"Owner")=1,1,0),0) -> 1 | AC24: Samsung CL | AD24: =MID($H24,FIND("CL",$H24)+5,3) -> 105 | AE24: =IF(ISNUMBER(FIND("R",$AD24)),SUBSTITUTE($AD24,"R",".")*1,LEFT($AD24,2)*10^RIGHT($AD24,1))*10^-12 -> 1e-06 | AF24: {=LEFT($E24,FIND(" ",$E24)-1)*IFERROR(INDEX({1000,1000000,0.000000000001,0.000000001,0.000001},MATCH(MID($E24,FIND(" ",$E24)+1,1),{"k","M","p","n","µ"},0)),1)} -> 1e-06 | AG24: =IF(AND(RIGHT($E24,1)="F",ABS($AF24-$AE24)<=Checks!$C$6*$AE24),"OK","CHECK") -> OK
A25: 2 USB audio bridge (CH32V307 + AGRV2K CPLD + clocks) | B25: FB202 | C25: 1 | D25: Ferrite bead 3V3D → CPLD VDD33/VDDA33 (AGM: bead-isolated feed) | E25: 600 Ω @ 100 MHz | F25: 0603 | G25: 200 mA, 0.45 Ω | H25: Sunlord GZ1608D601TF | I25: C1002 | J25: Basic | K25: JLCPCB library | L25: JLCPCB Basic | M25: Yes | O25: 2 | P25: 0 | Q25: 0.0127 | R25: =IF(OR($M25="Yes",$M25="Owner"),$C25*Cost!$B$6,0) -> 5 | S25: =$R25*$Q25 -> 0.0635 | T25: Passive: +5 %, min +2 | V25: =IF($M25="Owner",$R25,IF($M25<>"Yes",0,MAX(IF(LEFT($T25,7)="Passive",$R25+MAX(Cost!$B$8,ROUNDUP(Cost!$B$7*$R25,0)),$R25+Cost!$B$9),N($U25)))) -> 7 | W25: =$V25*$Q25 -> 0.0889 | X25: https://www.lcsc.com/product-detail/C1002.html | Y25: ≤ 40 mA CPLD budget → 18 mV drop | Z25: ,FB202, | AA25: =IF($Z25="",0,LEN($Z25)-LEN(SUBSTITUTE($Z25,",",""))-1) -> 1 | AB25: =IF(OR($M25="Yes",$M25="Owner"),IF(COUNTIFS($H$4:$H25,$H25,$M$4:$M25,"Yes")+COUNTIFS($H$4:$H25,$H25,$M$4:$M25,"Owner")=1,1,0),0) -> 1
A26: 2 USB audio bridge (CH32V307 + AGRV2K CPLD + clocks) | B26: J201 | C26: 1 | D26: Pads: MCU 2-wire SDI debug (WCH-LinkE) + BOOT0 + USART1 | E26: — | F26: 8 SMD pads | G26: — | H26: PCB pads (no component) | I26: — | J26: — | K26: PCB copper | L26: — | M26: Pads | O26: 0 | P26: 0 | Q26: 0 | R26: =IF(OR($M26="Yes",$M26="Owner"),$C26*Cost!$B$6,0) -> 0 | S26: =$R26*$Q26 -> 0 | T26: — | V26: =IF($M26="Owner",$R26,IF($M26<>"Yes",0,MAX(IF(LEFT($T26,7)="Passive",$R26+MAX(Cost!$B$8,ROUNDUP(Cost!$B$7*$R26,0)),$R26+Cost!$B$9),N($U26)))) -> 0 | W26: =$V26*$Q26 -> 0 | Y26: Copper pads only — exclude from the JLCPCB BOM/CPL; pin 1 = N2_J201_3V3 via the DNF R241 (never power the board from the probe) | Z26: ,J201, | AA26: =IF($Z26="",0,LEN($Z26)-LEN(SUBSTITUTE($Z26,",",""))-1) -> 1 | AB26: =IF(OR($M26="Yes",$M26="Owner"),IF(COUNTIFS($H$4:$H26,$H26,$M$4:$M26,"Yes")+COUNTIFS($H$4:$H26,$H26,$M$4:$M26,"Owner")=1,1,0),0) -> 0
A27: 2 USB audio bridge (CH32V307 + AGRV2K CPLD + clocks) | B27: J202 | C27: 1 | D27: Pads: CPLD 2-wire Compact-JTAG (J-Link / AGM DAP-Link) | E27: — | F27: 5 SMD pads | G27: — | H27: PCB pads (no component) | I27: — | J27: — | K27: PCB copper | L27: — | M27: Pads | O27: 0 | P27: 0 | Q27: 0 | R27: =IF(OR($M27="Yes",$M27="Owner"),$C27*Cost!$B$6,0) -> 0 | S27: =$R27*$Q27 -> 0 | T27: — | V27: =IF($M27="Owner",$R27,IF($M27<>"Yes",0,MAX(IF(LEFT($T27,7)="Passive",$R27+MAX(Cost!$B$8,ROUNDUP(Cost!$B$7*$R27,0)),$R27+Cost!$B$9),N($U27)))) -> 0 | W27: =$V27*$Q27 -> 0 | Y27: Copper pads only — exclude from the JLCPCB BOM/CPL; 3V3D sense only | Z27: ,J202, | AA27: =IF($Z27="",0,LEN($Z27)-LEN(SUBSTITUTE($Z27,",",""))-1) -> 1 | AB27: =IF(OR($M27="Yes",$M27="Owner"),IF(COUNTIFS($H$4:$H27,$H27,$M$4:$M27,"Yes")+COUNTIFS($H$4:$H27,$H27,$M$4:$M27,"Owner")=1,1,0),0) -> 0
A28: 2 USB audio bridge (CH32V307 + AGRV2K CPLD + clocks) | B28: Q207 | C28: 1 | D28: N-MOSFET, open-drain DAC_RESETB driver (on = DAC reset; gate PA8 + R240 pull-up to 3V3M) | E28: AO3400A | F28: SOT-23 | G28: 30 V, VGS ±12 V, VGS(th) 0.65-1.45 V, RDS(on) ≤ 48 mΩ at 2.5 V | H28: AOS AO3400A | I28: C20917 | J28: Basic | K28: JLCPCB library | L28: JLCPCB Basic (same part as Q502-Q506, Q616, Q617) | M28: Yes | O28: 3 | P28: 0 | Q28: 0.0524 | R28: =IF(OR($M28="Yes",$M28="Owner"),$C28*Cost!$B$6,0) -> 5 | S28: =$R28*$Q28 -> 0.262 | T28: Other: +1 | V28: =IF($M28="Owner",$R28,IF($M28<>"Yes",0,MAX(IF(LEFT($T28,7)="Passive",$R28+MAX(Cost!$B$8,ROUNDUP(Cost!$B$7*$R28,0)),$R28+Cost!$B$9),N($U28)))) -> 6 | W28: =$V28*$Q28 -> 0.3144 | X28: https://www.aosmd.com/res/datasheets/AO3400A.pdf | Y28: New; replaces R233; pins 1 G, 2 S, 3 D (as Q502–Q506) | Z28: ,Q207, | AA28: =IF($Z28="",0,LEN($Z28)-LEN(SUBSTITUTE($Z28,",",""))-1) -> 1 | AB28: =IF(OR($M28="Yes",$M28="Owner"),IF(COUNTIFS($H$4:$H28,$H28,$M$4:$M28,"Yes")+COUNTIFS($H$4:$H28,$H28,$M$4:$M28,"Owner")=1,1,0),0) -> 1
A29: 2 USB audio bridge (CH32V307 + AGRV2K CPLD + clocks) | B29: R201, R202, R207, R208, R212, R213, R216-R218, R227, R231, R232, R234, R236, R238, R239 | C29: 16 | D29: 10 k: pull-ups/downs (NRST, BOOT0, BOOT1, I²C SCL/SDA, osc enables, mux inputs, MCLK_EN, MCLK, CPLD_NRST, MCLK_PERMIT, JTMS, JTCK) and the AVCC_EN series R236 | E29: 10 kΩ | F29: 0402 | G29: 1 % | H29: UNI-ROYAL 0402WGF1002TCE | I29: C25744 | J29: Basic | K29: JLCPCB library | L29: JLCPCB Basic | M29: Yes | O29: 2 | P29: 0 | Q29: 0.002 | R29: =IF(OR($M29="Yes",$M29="Owner"),$C29*Cost!$B$6,0) -> 80 | S29: =$R29*$Q29 -> 0.16 | T29: Passive: +5 %, min +2 | V29: =IF($M29="Owner",$R29,IF($M29<>"Yes",0,MAX(IF(LEFT($T29,7)="Passive",$R29+MAX(Cost!$B$8,ROUNDUP(Cost!$B$7*$R29,0)),$R29+Cost!$B$9),N($U29)))) -> 84 | W29: =$V29*$Q29 -> 0.168 | X29: https://www.lcsc.com/product-detail/C25744.html | Y29: R212/R213/R218 changed from 2.2 k; R216/R217 now fitted; R227, R231, R232, R234, R236, R238, R239 new; R207/R208 changed to 10 k (I²C at 100 kHz) | Z29: ,R201,R202,R207,R208,R212,R213,R216,R217,R218,R227,R231,R232,R234,R236,R238,R239, | AA29: =IF($Z29="",0,LEN($Z29)-LEN(SUBSTITUTE($Z29,",",""))-1) -> 16 | AB29: =IF(OR($M29="Yes",$M29="Owner"),IF(COUNTIFS($H$4:$H29,$H29,$M$4:$M29,"Yes")+COUNTIFS($H$4:$H29,$H29,$M$4:$M29,"Owner")=1,1,0),0) -> 0 | AC29: UNI-ROYAL | AD29: =MID($H29,18,4) -> 1002 | AE29: =LEFT($AD29,3)*IF(ISNUMBER(--RIGHT($AD29,1)),10^RIGHT($AD29,1),10^(0-FIND(RIGHT($AD29,1),"JKLM"))) -> 10000 | AF29: {=LEFT($E29,FIND(" ",$E29)-1)*IFERROR(INDEX({1000,1000000,0.000000000001,0.000000001,0.000001},MATCH(MID($E29,FIND(" ",$E29)+1,1),{"k","M","p","n","µ"},0)),1)} -> 10000 | AG29: =IF(AND(RIGHT($E29,1)="Ω",ABS($AF29-$AE29)<=Checks!$C$6*$AE29),"OK","CHECK") -> OK
A30: 2 USB audio bridge (CH32V307 + AGRV2K CPLD + clocks) | B30: R203-R206, R210, R211, R215, R224, R225 | C30: 9 | D30: Series source terminations (MCLK, I²S, osc→mux, mux→CPLD, link) | E30: 33 Ω | F30: 0402 | G30: 1 %, 62.5 mW | H30: UNI-ROYAL 0402WGF330JTCE | I30: C25105 | J30: Basic | K30: JLCPCB library | L30: JLCPCB Basic | M30: Yes | O30: 2 | P30: 0 | Q30: 0.002 | R30: =IF(OR($M30="Yes",$M30="Owner"),$C30*Cost!$B$6,0) -> 45 | S30: =$R30*$Q30 -> 0.09 | T30: Passive: +5 %, min +2 | V30: =IF($M30="Owner",$R30,IF($M30<>"Yes",0,MAX(IF(LEFT($T30,7)="Passive",$R30+MAX(Cost!$B$8,ROUNDUP(Cost!$B$7*$R30,0)),$R30+Cost!$B$9),N($U30)))) -> 48 | W30: =$V30*$Q30 -> 0.096 | X30: https://www.lcsc.com/product-detail/C25105.html | Y30: R215 now fitted | Z30: ,R203,R204,R205,R206,R210,R211,R215,R224,R225, | AA30: =IF($Z30="",0,LEN($Z30)-LEN(SUBSTITUTE($Z30,",",""))-1) -> 9 | AB30: =IF(OR($M30="Yes",$M30="Owner"),IF(COUNTIFS($H$4:$H30,$H30,$M$4:$M30,"Yes")+COUNTIFS($H$4:$H30,$H30,$M$4:$M30,"Owner")=1,1,0),0) -> 1 | AC30: UNI-ROYAL | AD30: =MID($H30,18,4) -> 330J | AE30: =LEFT($AD30,3)*IF(ISNUMBER(--RIGHT($AD30,1)),10^RIGHT($AD30,1),10^(0-FIND(RIGHT($AD30,1),"JKLM"))) -> 33 | AF30: {=LEFT($E30,FIND(" ",$E30)-1)*IFERROR(INDEX({1000,1000000,0.000000000001,0.000000001,0.000001},MATCH(MID($E30,FIND(" ",$E30)+1,1),{"k","M","p","n","µ"},0)),1)} -> 33 | AG30: =IF(AND(RIGHT($E30,1)="Ω",ABS($AF30-$AE30)<=Checks!$C$6*$AE30),"OK","CHECK") -> OK
A31: 2 USB audio bridge (CH32V307 + AGRV2K CPLD + clocks) | B31: R228-R230, R242-R246 | C31: 8 | D31: 330 Ω: I²S capture taps to MCU I²S2 (CPLD side); ADC pin injection limiters PC0-PC4 | E31: 330 Ω | F31: 0402 | G31: 1 %, 62.5 mW | H31: UNI-ROYAL 0402WGF3300TCE | I31: C25104 | J31: Basic | K31: JLCPCB library | L31: JLCPCB Basic | M31: Yes | O31: 2 | P31: 0 | Q31: 0.002 | R31: =IF(OR($M31="Yes",$M31="Owner"),$C31*Cost!$B$6,0) -> 40 | S31: =$R31*$Q31 -> 0.08 | T31: Passive: +5 %, min +2 | V31: =IF($M31="Owner",$R31,IF($M31<>"Yes",0,MAX(IF(LEFT($T31,7)="Passive",$R31+MAX(Cost!$B$8,ROUNDUP(Cost!$B$7*$R31,0)),$R31+Cost!$B$9),N($U31)))) -> 42 | W31: =$V31*$Q31 -> 0.084 | X31: https://www.lcsc.com/product-detail/C25104.html | Y31: R242–R246 new (at the MCU pins); LCSC C25104, JLCPCB Basic | Z31: ,R228,R229,R230,R242,R243,R244,R245,R246, | AA31: =IF($Z31="",0,LEN($Z31)-LEN(SUBSTITUTE($Z31,",",""))-1) -> 8 | AB31: =IF(OR($M31="Yes",$M31="Owner"),IF(COUNTIFS($H$4:$H31,$H31,$M$4:$M31,"Yes")+COUNTIFS($H$4:$H31,$H31,$M$4:$M31,"Owner")=1,1,0),0) -> 1 | AC31: UNI-ROYAL | AD31: =MID($H31,18,4) -> 3300 | AE31: =LEFT($AD31,3)*IF(ISNUMBER(--RIGHT($AD31,1)),10^RIGHT($AD31,1),10^(0-FIND(RIGHT($AD31,1),"JKLM"))) -> 330 | AF31: {=LEFT($E31,FIND(" ",$E31)-1)*IFERROR(INDEX({1000,1000000,0.000000000001,0.000000001,0.000001},MATCH(MID($E31,FIND(" ",$E31)+1,1),{"k","M","p","n","µ"},0)),1)} -> 330 | AG31: =IF(AND(RIGHT($E31,1)="Ω",ABS($AF31-$AE31)<=Checks!$C$6*$AE31),"OK","CHECK") -> OK
A32: 2 USB audio bridge (CH32V307 + AGRV2K CPLD + clocks) | B32: R235, R240 | C32: 2 | D32: 100 k: pull-down at U206 Y (X201 INH / PB1 readback / Q616 gate via R645); Q207 gate pull-up to 3V3M | E32: 100 kΩ | F32: 0402 | G32: 1 % | H32: UNI-ROYAL 0402WGF1003TCE | I32: C25741 | J32: Basic | K32: JLCPCB library | L32: JLCPCB Basic | M32: Yes | O32: 2 | P32: 0 | Q32: 0.002 | R32: =IF(OR($M32="Yes",$M32="Owner"),$C32*Cost!$B$6,0) -> 10 | S32: =$R32*$Q32 -> 0.02 | T32: Passive: +5 %, min +2 | V32: =IF($M32="Owner",$R32,IF($M32<>"Yes",0,MAX(IF(LEFT($T32,7)="Passive",$R32+MAX(Cost!$B$8,ROUNDUP(Cost!$B$7*$R32,0)),$R32+Cost!$B$9),N($U32)))) -> 12 | W32: =$V32*$Q32 -> 0.024 | X32: https://www.lcsc.com/product-detail/C25741.html | Y32: R235 and R240 new; same part as R646/R648 | Z32: ,R235,R240, | AA32: =IF($Z32="",0,LEN($Z32)-LEN(SUBSTITUTE($Z32,",",""))-1) -> 2 | AB32: =IF(OR($M32="Yes",$M32="Owner"),IF(COUNTIFS($H$4:$H32,$H32,$M$4:$M32,"Yes")+COUNTIFS($H$4:$H32,$H32,$M$4:$M32,"Owner")=1,1,0),0) -> 0 | AC32: UNI-ROYAL | AD32: =MID($H32,18,4) -> 1003 | AE32: =LEFT($AD32,3)*IF(ISNUMBER(--RIGHT($AD32,1)),10^RIGHT($AD32,1),10^(0-FIND(RIGHT($AD32,1),"JKLM"))) -> 100000 | AF32: {=LEFT($E32,FIND(" ",$E32)-1)*IFERROR(INDEX({1000,1000000,0.000000000001,0.000000001,0.000001},MATCH(MID($E32,FIND(" ",$E32)+1,1),{"k","M","p","n","µ"},0)),1)} -> 100000 | AG32: =IF(AND(RIGHT($E32,1)="Ω",ABS($AF32-$AE32)<=Checks!$C$6*$AE32),"OK","CHECK") -> OK
A33: 2 USB audio bridge (CH32V307 + AGRV2K CPLD + clocks) | B33: R237 | C33: 1 | D33: AUD_EN series resistor from MCU PC10 | E33: 4.7 kΩ | F33: 0402 | G33: 1 % | H33: UNI-ROYAL 0402WGF4701TCE | I33: C25900 | J33: Basic | K33: JLCPCB library | L33: JLCPCB Basic | M33: Yes | O33: 2 | P33: 0 | Q33: 0.002 | R33: =IF(OR($M33="Yes",$M33="Owner"),$C33*Cost!$B$6,0) -> 5 | S33: =$R33*$Q33 -> 0.01 | T33: Passive: +5 %, min +2 | V33: =IF($M33="Owner",$R33,IF($M33<>"Yes",0,MAX(IF(LEFT($T33,7)="Passive",$R33+MAX(Cost!$B$8,ROUNDUP(Cost!$B$7*$R33,0)),$R33+Cost!$B$9),N($U33)))) -> 7 | W33: =$V33*$Q33 -> 0.014 | X33: https://www.lcsc.com/product-detail/C25900.html | Y33: New (lets the 3V3A-good supervisor override the MCU); LCSC number to be confirmed at order | Z33: ,R237, | AA33: =IF($Z33="",0,LEN($Z33)-LEN(SUBSTITUTE($Z33,",",""))-1) -> 1 | AB33: =IF(OR($M33="Yes",$M33="Owner"),IF(COUNTIFS($H$4:$H33,$H33,$M$4:$M33,"Yes")+COUNTIFS($H$4:$H33,$H33,$M$4:$M33,"Owner")=1,1,0),0) -> 1 | AC33: UNI-ROYAL | AD33: =MID($H33,18,4) -> 4701 | AE33: =LEFT($AD33,3)*IF(ISNUMBER(--RIGHT($AD33,1)),10^RIGHT($AD33,1),10^(0-FIND(RIGHT($AD33,1),"JKLM"))) -> 4700 | AF33: {=LEFT($E33,FIND(" ",$E33)-1)*IFERROR(INDEX({1000,1000000,0.000000000001,0.000000001,0.000001},MATCH(MID($E33,FIND(" ",$E33)+1,1),{"k","M","p","n","µ"},0)),1)} -> 4700 | AG33: =IF(AND(RIGHT($E33,1)="Ω",ABS($AF33-$AE33)<=Checks!$C$6*$AE33),"OK","CHECK") -> OK
A34: 2 USB audio bridge (CH32V307 + AGRV2K CPLD + clocks) | B34: R241 | C34: 1 | D34: J201 pin 1 link to 3V3M (DNF: WCH-LinkE 3V3 is a power output) | E34: 0 Ω | F34: 0402 | G34: jumper | H34: UNI-ROYAL 0402WGF0000TCE | I34: C17168 | J34: Basic | K34: — (DNF) | L34: JLCPCB Basic | M34: No | O34: 2 | P34: 0 | Q34: 0.002 | R34: =IF(OR($M34="Yes",$M34="Owner"),$C34*Cost!$B$6,0) -> 0 | S34: =$R34*$Q34 -> 0 | T34: — | V34: =IF($M34="Owner",$R34,IF($M34<>"Yes",0,MAX(IF(LEFT($T34,7)="Passive",$R34+MAX(Cost!$B$8,ROUNDUP(Cost!$B$7*$R34,0)),$R34+Cost!$B$9),N($U34)))) -> 0 | W34: =$V34*$Q34 -> 0 | X34: https://www.lcsc.com/product-detail/C17168.html | Y34: New DNF link; net N2_J201_3V3 | Z34: ,R241, | AA34: =IF($Z34="",0,LEN($Z34)-LEN(SUBSTITUTE($Z34,",",""))-1) -> 1 | AB34: =IF(OR($M34="Yes",$M34="Owner"),IF(COUNTIFS($H$4:$H34,$H34,$M$4:$M34,"Yes")+COUNTIFS($H$4:$H34,$H34,$M$4:$M34,"Owner")=1,1,0),0) -> 0 | AC34: UNI-ROYAL | AD34: =MID($H34,18,4) -> 0000 | AE34: =LEFT($AD34,3)*IF(ISNUMBER(--RIGHT($AD34,1)),10^RIGHT($AD34,1),10^(0-FIND(RIGHT($AD34,1),"JKLM"))) -> 0 | AF34: {=LEFT($E34,FIND(" ",$E34)-1)*IFERROR(INDEX({1000,1000000,0.000000000001,0.000000001,0.000001},MATCH(MID($E34,FIND(" ",$E34)+1,1),{"k","M","p","n","µ"},0)),1)} -> 0 | AG34: =IF(AND(RIGHT($E34,1)="Ω",ABS($AF34-$AE34)<=Checks!$C$6*$AE34),"OK","CHECK") -> OK
A35: 2 USB audio bridge (CH32V307 + AGRV2K CPLD + clocks) | B35: U201 | C35: 1 | D35: MCU, RISC-V V4F 144 MHz, USB2.0 HS PHY, own UAC2 firmware | E35: CH32V307RCT6 | F35: LQFP-64M 10 × 10 | G35: 3.3 V, -40…85 °C | H35: WCH CH32V307RCT6 | I35: C2988083 | J35: Extended | K35: JLCPCB library | L35: JLCPCB 364 / LCSC 193 (Sep 2026): thin stock, single source — pre-order 6 (5 boards + 1) | M35: Yes | O35: 64 | P35: 0 | Q35: 3.47 | R35: =IF(OR($M35="Yes",$M35="Owner"),$C35*Cost!$B$6,0) -> 5 | S35: =$R35*$Q35 -> 17.35 | T35: Other: +1 | V35: =IF($M35="Owner",$R35,IF($M35<>"Yes",0,MAX(IF(LEFT($T35,7)="Passive",$R35+MAX(Cost!$B$8,ROUNDUP(Cost!$B$7*$R35,0)),$R35+Cost!$B$9),N($U35)))) -> 6 | W35: =$V35*$Q35 -> 20.82 | X35: https://www.wch-ic.com/downloads/CH32V307DS0_PDF.html | Y35: MSL 3 (bake) | Z35: ,U201, | AA35: =IF($Z35="",0,LEN($Z35)-LEN(SUBSTITUTE($Z35,",",""))-1) -> 1 | AB35: =IF(OR($M35="Yes",$M35="Owner"),IF(COUNTIFS($H$4:$H35,$H35,$M$4:$M35,"Yes")+COUNTIFS($H$4:$H35,$H35,$M$4:$M35,"Owner")=1,1,0),0) -> 1
A36: 2 USB audio bridge (CH32V307 + AGRV2K CPLD + clocks) | B36: U202 | C36: 1 | D36: CPLD 2K LUT (AG32 silicon): SPI link, FIFO, I²S master, osc/mux/MCLK enables | E36: AGRV2KQ32 | F36: QFN-32 4 × 4, EP 2.7 | G36: 3.3 V, TJ -40…85 °C | H36: AGM AGRV2KQ32 | I36: C18208899 | J36: Extended | K36: JLCPCB library | L36: LCSC 980 (Sep 2026): thin stock, single source — pre-order 6 (5 boards + 1) | M36: Yes | N36: Yes | O36: 33 | P36: 0 | Q36: 1.6503 | R36: =IF(OR($M36="Yes",$M36="Owner"),$C36*Cost!$B$6,0) -> 5 | S36: =$R36*$Q36 -> 8.2515 | T36: Other: +1 | V36: =IF($M36="Owner",$R36,IF($M36<>"Yes",0,MAX(IF(LEFT($T36,7)="Passive",$R36+MAX(Cost!$B$8,ROUNDUP(Cost!$B$7*$R36,0)),$R36+Cost!$B$9),N($U36)))) -> 6 | W36: =$V36*$Q36 -> 9.9018 | X36: https://www.ag32mcu.com/wp-content/uploads/2026/02/AGRV2K_Rev_3_0.pdf | Y36: Programmed via J202 (J-Link / AGM DAP-Link); AGM ships AGRV2K parts marked as the AG32VF303 of the same package (order remark); exposed-pad size and net checked at gate G-3; X-ray | Z36: ,U202, | AA36: =IF($Z36="",0,LEN($Z36)-LEN(SUBSTITUTE($Z36,",",""))-1) -> 1 | AB36: =IF(OR($M36="Yes",$M36="Owner"),IF(COUNTIFS($H$4:$H36,$H36,$M$4:$M36,"Yes")+COUNTIFS($H$4:$H36,$H36,$M$4:$M36,"Owner")=1,1,0),0) -> 1
A37: 2 USB audio bridge (CH32V307 + AGRV2K CPLD + clocks) | B37: U205 | C37: 1 | D37: 2:1 clock mux (family select), now fitted | E37: 74LVC1G157 | F37: SOT-363 (TSSOP6) | G37: 1.65-5.5 V, IOFF | H37: Nexperia 74LVC1G157GW,125 | I37: C135822 | J37: Extended | K37: JLCPCB library | L37: LCSC stock | M37: Yes | O37: 6 | P37: 0 | Q37: 0.2106 | R37: =IF(OR($M37="Yes",$M37="Owner"),$C37*Cost!$B$6,0) -> 5 | S37: =$R37*$Q37 -> 1.053 | T37: Other: +1 | V37: =IF($M37="Owner",$R37,IF($M37<>"Yes",0,MAX(IF(LEFT($T37,7)="Passive",$R37+MAX(Cost!$B$8,ROUNDUP(Cost!$B$7*$R37,0)),$R37+Cost!$B$9),N($U37)))) -> 6 | W37: =$V37*$Q37 -> 1.2636 | X37: https://assets.nexperia.com/documents/data-sheet/74LVC1G157.pdf | Y37: S = OSC44_EN; S = L → I0 (X202) | Z37: ,U205, | AA37: =IF($Z37="",0,LEN($Z37)-LEN(SUBSTITUTE($Z37,",",""))-1) -> 1 | AB37: =IF(OR($M37="Yes",$M37="Owner"),IF(COUNTIFS($H$4:$H37,$H37,$M$4:$M37,"Yes")+COUNTIFS($H$4:$H37,$H37,$M$4:$M37,"Owner")=1,1,0),0) -> 1
A38: 2 USB audio bridge (CH32V307 + AGRV2K CPLD + clocks) | B38: U206 | C38: 1 | D38: 3-input AND: X201 E/D = MCLK_EN AND AVCC_EN AND MCLK_PERMIT (hardware MCLK stop) | E38: 74LVC1G11 | F38: SOT-363 (TSSOP6) | G38: 1.65-5.5 V, IOFF, inputs 5.5 V tolerant, Schmitt action, tpd ≤ 4.9 ns | H38: Nexperia 74LVC1G11GW-Q100H | I38: C548242 | J38: Extended | K38: JLCPCB library | L38: LCSC 3,690 (Sep 2026) | M38: Yes | O38: 6 | P38: 0 | Q38: 0.0768 | R38: =IF(OR($M38="Yes",$M38="Owner"),$C38*Cost!$B$6,0) -> 5 | S38: =$R38*$Q38 -> 0.384 | T38: Other: +1 | V38: =IF($M38="Owner",$R38,IF($M38<>"Yes",0,MAX(IF(LEFT($T38,7)="Passive",$R38+MAX(Cost!$B$8,ROUNDUP(Cost!$B$7*$R38,0)),$R38+Cost!$B$9),N($U38)))) -> 6 | W38: =$V38*$Q38 -> 0.4608 | X38: https://assets.nexperia.com/documents/data-sheet/74LVC1G11.pdf | Y38: Was 74LVC1G08GW (C12512, SOT353 5-pin); 6-pin SOT363-2 footprint: 1 A, 2 GND, 3 B, 4 Y, 5 VCC, 6 C; input B = N2_AVCC_EN_G; VOH ≥ VCC − 0.1 V vs Kyocera VIH 0.7 VCC; Y also feeds R645 → Q616 | Z38: ,U206, | AA38: =IF($Z38="",0,LEN($Z38)-LEN(SUBSTITUTE($Z38,",",""))-1) -> 1 | AB38: =IF(OR($M38="Yes",$M38="Owner"),IF(COUNTIFS($H$4:$H38,$H38,$M$4:$M38,"Yes")+COUNTIFS($H$4:$H38,$H38,$M$4:$M38,"Owner")=1,1,0),0) -> 1
A39: 2 USB audio bridge (CH32V307 + AGRV2K CPLD + clocks) | B39: U208 | C39: 1 | D39: Triple buffer, Ioff (partial power-down), 3V3M → 3V3D domain crossing of LINK_SCK/LINK_MOSI/LINK_FRAME, placed at U202 | E39: 74LVC3G34 | F39: VSSOP-8 0.5 mm (SOT765-1, DC) | G39: 1.65–5.5 V, Ioff ±10 µA (VCC = 0, VI/VO 5.5 V), inputs 5.5 V tolerant, tpd 1.4–4.1 ns (3.3 V ± 0.3 V, −40…85 °C), ICC ≤ 10 µA, MSL 1 260 °C | H39: TI SN74LVC3G34DCUR | I39: C130024 | J39: Extended | K39: JLCPCB library | L39: LCSC 550 (25 Sep 2026), min/multiple 5 — pre-order 10 | M39: Yes | O39: 8 | P39: 0 | Q39: 0.2012 | R39: =IF(OR($M39="Yes",$M39="Owner"),$C39*Cost!$B$6,0) -> 5 | S39: =$R39*$Q39 -> 1.006 | T39: Other: +1 | U39: 10 | V39: =IF($M39="Owner",$R39,IF($M39<>"Yes",0,MAX(IF(LEFT($T39,7)="Passive",$R39+MAX(Cost!$B$8,ROUNDUP(Cost!$B$7*$R39,0)),$R39+Cost!$B$9),N($U39)))) -> 10 | W39: =$V39*$Q39 -> 2.012 | X39: https://assets.nexperia.com/documents/data-sheet/74LVC3G34.pdf | Y39: Cost patch: replaces the Nexperia 74LVC3G34DC,125 (C548774, US$ 0.7647) — same DCU pinout 1 1A, 2 3Y, 3 2A, 4 GND, 5 2Y, 6 3A, 7 1Y, 8 VCC (TI datasheet pin table); the Nexperia part is the approved alternate | Z39: ,U208, | AA39: =IF($Z39="",0,LEN($Z39)-LEN(SUBSTITUTE($Z39,",",""))-1) -> 1 | AB39: =IF(OR($M39="Yes",$M39="Owner"),IF(COUNTIFS($H$4:$H39,$H39,$M$4:$M39,"Yes")+COUNTIFS($H$4:$H39,$H39,$M$4:$M39,"Owner")=1,1,0),0) -> 1
A40: 2 USB audio bridge (CH32V307 + AGRV2K CPLD + clocks) | B40: X201 | C40: 1 | D40: Oscillator 80 MHz CMOS SPXO (crystal), stand-by pin 1 (oscillation stop) - DAC MCLK only | E40: 80.000 MHz | F40: 2.5 × 2.0 mm 4-pad, plain 2520 land (no 3225 pads) | G40: ±50 ppm (-40…85 °C incl. initial/temp/supply/load/1-yr aging), ICC ≤ 8.0 mA loaded 15 pF (2.8-3.63 V, over temp), stand-by ≤ 5 µA, SYM 45-55 %, tr/tf ≤ 4.5 ns (10-90 %), t_dis ≤ 200 ns, enable/start-up ≤ 2 ms (spec; 3 ms catalogue), VIH ≥ 0.7 VCC, VIL ≤ 0.3 VCC, abs max 4.0 V, reflow 260 °C ×2, MSL 1 | H40: Kyocera KC2520K80.0000C1GE00 | I40: C1988889 | J40: Extended | K40: Global sourcing | L40: LCSC C1988889 not stocked → JLCPCB global sourcing: DigiKey 2,964 (Aug 2026), Mouser 1,375 (+10,000 on order) | M40: Yes | N40: Yes | O40: 4 | P40: 0 | Q40: 1.39 | R40: =IF(OR($M40="Yes",$M40="Owner"),$C40*Cost!$B$6,0) -> 5 | S40: =$R40*$Q40 -> 6.95 | T40: Other: +1 | V40: =IF($M40="Owner",$R40,IF($M40<>"Yes",0,MAX(IF(LEFT($T40,7)="Passive",$R40+MAX(Cost!$B$8,ROUNDUP(Cost!$B$7*$R40,0)),$R40+Cost!$B$9),N($U40)))) -> 6 | W40: =$V40*$Q40 -> 8.34 | X40: https://ele.kyocera.com/assets/products/crystal-device/specification/KC2520K80.0000C1GE00_e.pdf | Y40: Replaces the obsolete Epson SG-210STF 75 MHz (25 Sep 2026); conditional second source NDK NSC5338D-80M (bring-up checks of disable time and edges; 12.7 mA budget; 2520 land; no R509 change); TXC 7X-80.000MBE-T withdrawn; SCTF SX3M80 (C5179978, 3225) not approved and has no land; stand-by driven by U206 | Z40: ,X201, | AA40: =IF($Z40="",0,LEN($Z40)-LEN(SUBSTITUTE($Z40,",",""))-1) -> 1 | AB40: =IF(OR($M40="Yes",$M40="Owner"),IF(COUNTIFS($H$4:$H40,$H40,$M$4:$M40,"Yes")+COUNTIFS($H$4:$H40,$H40,$M$4:$M40,"Owner")=1,1,0),0) -> 1
A41: 2 USB audio bridge (CH32V307 + AGRV2K CPLD + clocks) | B41: X202 | C41: 1 | D41: Oscillator 49.152 MHz ultra-low phase noise, stand-by (Hi-Z, osc stops) | E41: 49.152 MHz | F41: 2.5 × 2.0 mm 4-pad, plain 2520 land | G41: ±50 ppm overall, 15 mA max, 35 µA stand-by | H41: NDK NZ2520SDA-49.152MHZ-NSC5083D | I41: — | J41: Extended | K41: Global sourcing | L41: JLCPCB global sourcing: DigiKey 644-NSC5083D-49.152M, 3,438 in stock (24 Sep 2026); JLCPCB record C9900006427 | M41: Yes | N41: Yes | O41: 4 | P41: 0 | Q41: 2 | R41: =IF(OR($M41="Yes",$M41="Owner"),$C41*Cost!$B$6,0) -> 5 | S41: =$R41*$Q41 -> 10 | T41: Other: +1 | V41: =IF($M41="Owner",$R41,IF($M41<>"Yes",0,MAX(IF(LEFT($T41,7)="Passive",$R41+MAX(Cost!$B$8,ROUNDUP(Cost!$B$7*$R41,0)),$R41+Cost!$B$9),N($U41)))) -> 6 | W41: =$V41*$Q41 -> 12 | X41: https://www.ndk.com/en/products/upload/lineup/pdf/NDKT02-00008_en.pdf | Y41: Replaces the 24.576 MHz OT3225 (C2831388); compliant second source SiT8008BI-xx-33S-49.152000 (2.5 × 2.0 mm, 4.3 µA stand-by); SCTF SX3M49.152M20F30TNN (C2901591, 3225) is a non-compliant fallback (output-disable only, both oscillators run, +25 mA: Default power targets not met) and does not fit the 2520 land | Z41: ,X202, | AA41: =IF($Z41="",0,LEN($Z41)-LEN(SUBSTITUTE($Z41,",",""))-1) -> 1 | AB41: =IF(OR($M41="Yes",$M41="Owner"),IF(COUNTIFS($H$4:$H41,$H41,$M$4:$M41,"Yes")+COUNTIFS($H$4:$H41,$H41,$M$4:$M41,"Owner")=1,1,0),0) -> 1
A42: 2 USB audio bridge (CH32V307 + AGRV2K CPLD + clocks) | B42: X203 | C42: 1 | D42: Oscillator 45.1584 MHz ultra-low phase noise, stand-by (Hi-Z, osc stops) | E42: 45.1584 MHz | F42: 2.5 × 2.0 mm 4-pad, plain 2520 land | G42: ±50 ppm overall, 15 mA max, 35 µA stand-by | H42: NDK NZ2520SDA-45.1584MHZ-NSC5083D | I42: — | J42: Extended | K42: Global sourcing | L42: JLCPCB global sourcing: DigiKey NSC5083D-45.158M 3,166 (Sep 2026), 24-week factory lead | M42: Yes | N42: Yes | O42: 4 | P42: 0 | Q42: 2 | R42: =IF(OR($M42="Yes",$M42="Owner"),$C42*Cost!$B$6,0) -> 5 | S42: =$R42*$Q42 -> 10 | T42: Other: +1 | V42: =IF($M42="Owner",$R42,IF($M42<>"Yes",0,MAX(IF(LEFT($T42,7)="Passive",$R42+MAX(Cost!$B$8,ROUNDUP(Cost!$B$7*$R42,0)),$R42+Cost!$B$9),N($U42)))) -> 6 | W42: =$V42*$Q42 -> 12 | X42: https://www.ndk.com/en/products/upload/lineup/pdf/NDKT02-00008_en.pdf | Y42: Replaces the 22.5792 MHz SX2M (C5452663); compliant second source SiT8008BI-xx-33S-45.158400; SCTF SX3M45.1584M20F30TNN (C2901589, 3225) is a non-compliant fallback (output-disable only, both oscillators run, +25 mA: Default power targets not met) and does not fit the 2520 land | Z42: ,X203, | AA42: =IF($Z42="",0,LEN($Z42)-LEN(SUBSTITUTE($Z42,",",""))-1) -> 1 | AB42: =IF(OR($M42="Yes",$M42="Owner"),IF(COUNTIFS($H$4:$H42,$H42,$M$4:$M42,"Yes")+COUNTIFS($H$4:$H42,$H42,$M$4:$M42,"Owner")=1,1,0),0) -> 1
A43: 2 USB audio bridge (CH32V307 + AGRV2K CPLD + clocks) | B43: Y201 | C43: 1 | D43: Crystal, MCU HSE (USBHS PLL ref = HSE/2 = 4 MHz) | E43: 8 MHz | F43: 5.0 × 3.2 mm 2-pad | G43: ±10 ppm, CL 20 pF | H43: YXC X50328MSB2GI | I43: C115962 | J43: Basic | K43: JLCPCB library | L43: JLCPCB Basic | M43: Yes | O43: 2 | P43: 0 | Q43: 0.2452 | R43: =IF(OR($M43="Yes",$M43="Owner"),$C43*Cost!$B$6,0) -> 5 | S43: =$R43*$Q43 -> 1.226 | T43: Other: +1 | V43: =IF($M43="Owner",$R43,IF($M43<>"Yes",0,MAX(IF(LEFT($T43,7)="Passive",$R43+MAX(Cost!$B$8,ROUNDUP(Cost!$B$7*$R43,0)),$R43+Cost!$B$9),N($U43)))) -> 6 | W43: =$V43*$Q43 -> 1.4712 | X43: https://www.lcsc.com/product-detail/C115962.html | Y43: Kept | Z43: ,Y201, | AA43: =IF($Z43="",0,LEN($Z43)-LEN(SUBSTITUTE($Z43,",",""))-1) -> 1 | AB43: =IF(OR($M43="Yes",$M43="Owner"),IF(COUNTIFS($H$4:$H43,$H43,$M$4:$M43,"Yes")+COUNTIFS($H$4:$H43,$H43,$M$4:$M43,"Owner")=1,1,0),0) -> 1
A44: 3 DAC (ES9018K2M) and its supplies | B44: C301 | C44: 1 | D44: LP5907 input (5V_SYS); ≥ 1.04 µF effective at 5.5 V | E44: 2.2 µF | F44: 0603 | G44: 16 V X5R ±10 % | H44: Samsung CL10A225KO8NNNC | I44: C23630 | J44: Basic | K44: JLCPCB library | L44: JLCPCB Basic | M44: Yes | O44: 2 | P44: 0 | Q44: 0.012 | R44: =IF(OR($M44="Yes",$M44="Owner"),$C44*Cost!$B$6,0) -> 5 | S44: =$R44*$Q44 -> 0.06 | T44: Passive: +5 %, min +2 | V44: =IF($M44="Owner",$R44,IF($M44<>"Yes",0,MAX(IF(LEFT($T44,7)="Passive",$R44+MAX(Cost!$B$8,ROUNDUP(Cost!$B$7*$R44,0)),$R44+Cost!$B$9),N($U44)))) -> 7 | W44: =$V44*$Q44 -> 0.084 | X44: https://www.lcsc.com/product-detail/C23630.html | Y44: Changed 1 µF → 2.2 µF | Z44: ,C301, | AA44: =IF($Z44="",0,LEN($Z44)-LEN(SUBSTITUTE($Z44,",",""))-1) -> 1 | AB44: =IF(OR($M44="Yes",$M44="Owner"),IF(COUNTIFS($H$4:$H44,$H44,$M$4:$M44,"Yes")+COUNTIFS($H$4:$H44,$H44,$M$4:$M44,"Owner")=1,1,0),0) -> 1 | AC44: Samsung CL | AD44: =MID($H44,FIND("CL",$H44)+5,3) -> 225 | AE44: =IF(ISNUMBER(FIND("R",$AD44)),SUBSTITUTE($AD44,"R",".")*1,LEFT($AD44,2)*10^RIGHT($AD44,1))*10^-12 -> 2.2e-06 | AF44: {=LEFT($E44,FIND(" ",$E44)-1)*IFERROR(INDEX({1000,1000000,0.000000000001,0.000000001,0.000001},MATCH(MID($E44,FIND(" ",$E44)+1,1),{"k","M","p","n","µ"},0)),1)} -> 2.2e-06 | AG44: =IF(AND(RIGHT($E44,1)="F",ABS($AF44-$AE44)<=Checks!$C$6*$AE44),"OK","CHECK") -> OK
A45: 3 DAC (ES9018K2M) and its supplies | B45: C302 | C45: 1 | D45: LP5907 output (3V3A total ≤ 7.6 µF upper bound ≤ 10 µF) | E45: 2.2 µF | F45: 0603 | G45: 16 V X5R ±10 % | H45: Samsung CL10A225KO8NNNC | I45: C23630 | J45: Basic | K45: JLCPCB library | L45: JLCPCB Basic | M45: Yes | O45: 2 | P45: 0 | Q45: 0.012 | R45: =IF(OR($M45="Yes",$M45="Owner"),$C45*Cost!$B$6,0) -> 5 | S45: =$R45*$Q45 -> 0.06 | T45: Passive: +5 %, min +2 | V45: =IF($M45="Owner",$R45,IF($M45<>"Yes",0,MAX(IF(LEFT($T45,7)="Passive",$R45+MAX(Cost!$B$8,ROUNDUP(Cost!$B$7*$R45,0)),$R45+Cost!$B$9),N($U45)))) -> 7 | W45: =$V45*$Q45 -> 0.084 | X45: https://www.lcsc.com/product-detail/C23630.html | Y45: Changed 1 µF → 2.2 µF | Z45: ,C302, | AA45: =IF($Z45="",0,LEN($Z45)-LEN(SUBSTITUTE($Z45,",",""))-1) -> 1 | AB45: =IF(OR($M45="Yes",$M45="Owner"),IF(COUNTIFS($H$4:$H45,$H45,$M$4:$M45,"Yes")+COUNTIFS($H$4:$H45,$H45,$M$4:$M45,"Owner")=1,1,0),0) -> 0 | AC45: Samsung CL | AD45: =MID($H45,FIND("CL",$H45)+5,3) -> 225 | AE45: =IF(ISNUMBER(FIND("R",$AD45)),SUBSTITUTE($AD45,"R",".")*1,LEFT($AD45,2)*10^RIGHT($AD45,1))*10^-12 -> 2.2e-06 | AF45: {=LEFT($E45,FIND(" ",$E45)-1)*IFERROR(INDEX({1000,1000000,0.000000000001,0.000000001,0.000001},MATCH(MID($E45,FIND(" ",$E45)+1,1),{"k","M","p","n","µ"},0)),1)} -> 2.2e-06 | AG45: =IF(AND(RIGHT($E45,1)="F",ABS($AF45-$AE45)<=Checks!$C$6*$AE45),"OK","CHECK") -> OK
A46: 3 DAC (ES9018K2M) and its supplies | B46: C303, C304, C310, C439, C440 | C46: 5 | D46: AVCC_L, AVCC_R and DVDD bulk at the DAC pins; C439 DVCC / C440 VCCA after FB301/FB302 | E46: 2.2 µF | F46: 0603 | G46: 16 V X5R ±10 % | H46: Samsung CL10A225KO8NNNC | I46: C23630 | J46: Basic | K46: JLCPCB library | L46: JLCPCB 3.2 M (Sep 2026) | M46: Yes | O46: 2 | P46: 0 | Q46: 0.0191 | R46: =IF(OR($M46="Yes",$M46="Owner"),$C46*Cost!$B$6,0) -> 25 | S46: =$R46*$Q46 -> 0.4775 | T46: Passive: +5 %, min +2 | V46: =IF($M46="Owner",$R46,IF($M46<>"Yes",0,MAX(IF(LEFT($T46,7)="Passive",$R46+MAX(Cost!$B$8,ROUNDUP(Cost!$B$7*$R46,0)),$R46+Cost!$B$9),N($U46)))) -> 27 | W46: =$V46*$Q46 -> 0.5157 | X46: https://www.lcsc.com/product-detail/C23630.html | Y46: C439/C440 new (damp the ferrite / 100 nF resonance) | Z46: ,C303,C304,C310,C439,C440, | AA46: =IF($Z46="",0,LEN($Z46)-LEN(SUBSTITUTE($Z46,",",""))-1) -> 5 | AB46: =IF(OR($M46="Yes",$M46="Owner"),IF(COUNTIFS($H$4:$H46,$H46,$M$4:$M46,"Yes")+COUNTIFS($H$4:$H46,$H46,$M$4:$M46,"Owner")=1,1,0),0) -> 0 | AC46: Samsung CL | AD46: =MID($H46,FIND("CL",$H46)+5,3) -> 225 | AE46: =IF(ISNUMBER(FIND("R",$AD46)),SUBSTITUTE($AD46,"R",".")*1,LEFT($AD46,2)*10^RIGHT($AD46,1))*10^-12 -> 2.2e-06 | AF46: {=LEFT($E46,FIND(" ",$E46)-1)*IFERROR(INDEX({1000,1000000,0.000000000001,0.000000001,0.000001},MATCH(MID($E46,FIND(" ",$E46)+1,1),{"k","M","p","n","µ"},0)),1)} -> 2.2e-06 | AG46: =IF(AND(RIGHT($E46,1)="F",ABS($AF46-$AE46)<=Checks!$C$6*$AE46),"OK","CHECK") -> OK
A47: 3 DAC (ES9018K2M) and its supplies | B47: C305-C309 | C47: 5 | D47: HF decoupling at AVCC_L, AVCC_R, VCCA, DVCC, DVDD pins | E47: 100 nF | F47: 0402 | G47: 16 V X7R ±10 % | H47: Samsung CL05B104KO5NNNC | I47: C1525 | J47: Basic | K47: JLCPCB library | L47: JLCPCB stock | M47: Yes | O47: 2 | P47: 0 | Q47: 0.0045 | R47: =IF(OR($M47="Yes",$M47="Owner"),$C47*Cost!$B$6,0) -> 25 | S47: =$R47*$Q47 -> 0.1125 | T47: Passive: +5 %, min +2 | V47: =IF($M47="Owner",$R47,IF($M47<>"Yes",0,MAX(IF(LEFT($T47,7)="Passive",$R47+MAX(Cost!$B$8,ROUNDUP(Cost!$B$7*$R47,0)),$R47+Cost!$B$9),N($U47)))) -> 27 | W47: =$V47*$Q47 -> 0.1215 | X47: https://www.lcsc.com/product-detail/C1525.html | Z47: ,C305,C306,C307,C308,C309, | AA47: =IF($Z47="",0,LEN($Z47)-LEN(SUBSTITUTE($Z47,",",""))-1) -> 5 | AB47: =IF(OR($M47="Yes",$M47="Owner"),IF(COUNTIFS($H$4:$H47,$H47,$M$4:$M47,"Yes")+COUNTIFS($H$4:$H47,$H47,$M$4:$M47,"Owner")=1,1,0),0) -> 0 | AC47: Samsung CL | AD47: =MID($H47,FIND("CL",$H47)+5,3) -> 104 | AE47: =IF(ISNUMBER(FIND("R",$AD47)),SUBSTITUTE($AD47,"R",".")*1,LEFT($AD47,2)*10^RIGHT($AD47,1))*10^-12 -> 1e-07 | AF47: {=LEFT($E47,FIND(" ",$E47)-1)*IFERROR(INDEX({1000,1000000,0.000000000001,0.000000001,0.000001},MATCH(MID($E47,FIND(" ",$E47)+1,1),{"k","M","p","n","µ"},0)),1)} -> 1e-07 | AG47: =IF(AND(RIGHT($E47,1)="F",ABS($AF47-$AE47)<=Checks!$C$6*$AE47),"OK","CHECK") -> OK
A48: 3 DAC (ES9018K2M) and its supplies | B48: C311 | C48: 1 | D48: TLV758P input (3V3D) | E48: 1 µF | F48: 0603 | G48: 50 V X5R ±10 % | H48: Samsung CL10A105KB8NNNC | I48: C15849 | J48: Basic | K48: JLCPCB library | L48: As in Parts List v0.6 | M48: Yes | O48: 2 | P48: 0 | Q48: 0.006 | R48: =IF(OR($M48="Yes",$M48="Owner"),$C48*Cost!$B$6,0) -> 5 | S48: =$R48*$Q48 -> 0.03 | T48: Passive: +5 %, min +2 | V48: =IF($M48="Owner",$R48,IF($M48<>"Yes",0,MAX(IF(LEFT($T48,7)="Passive",$R48+MAX(Cost!$B$8,ROUNDUP(Cost!$B$7*$R48,0)),$R48+Cost!$B$9),N($U48)))) -> 7 | W48: =$V48*$Q48 -> 0.042 | X48: https://www.lcsc.com/product-detail/C15849.html | Y48: Unchanged part | Z48: ,C311, | AA48: =IF($Z48="",0,LEN($Z48)-LEN(SUBSTITUTE($Z48,",",""))-1) -> 1 | AB48: =IF(OR($M48="Yes",$M48="Owner"),IF(COUNTIFS($H$4:$H48,$H48,$M$4:$M48,"Yes")+COUNTIFS($H$4:$H48,$H48,$M$4:$M48,"Owner")=1,1,0),0) -> 0 | AC48: Samsung CL | AD48: =MID($H48,FIND("CL",$H48)+5,3) -> 105 | AE48: =IF(ISNUMBER(FIND("R",$AD48)),SUBSTITUTE($AD48,"R",".")*1,LEFT($AD48,2)*10^RIGHT($AD48,1))*10^-12 -> 1e-06 | AF48: {=LEFT($E48,FIND(" ",$E48)-1)*IFERROR(INDEX({1000,1000000,0.000000000001,0.000000001,0.000001},MATCH(MID($E48,FIND(" ",$E48)+1,1),{"k","M","p","n","µ"},0)),1)} -> 1e-06 | AG48: =IF(AND(RIGHT($E48,1)="F",ABS($AF48-$AE48)<=Checks!$C$6*$AE48),"OK","CHECK") -> OK
A49: 3 DAC (ES9018K2M) and its supplies | B49: C312 | C49: 1 | D49: TLV758P output (1V3) | E49: 1 µF | F49: 0603 | G49: 50 V X5R ±10 % | H49: Samsung CL10A105KB8NNNC | I49: C15849 | J49: Basic | K49: JLCPCB library | L49: As in Parts List v0.6 | M49: Yes | O49: 2 | P49: 0 | Q49: 0.006 | R49: =IF(OR($M49="Yes",$M49="Owner"),$C49*Cost!$B$6,0) -> 5 | S49: =$R49*$Q49 -> 0.03 | T49: Passive: +5 %, min +2 | V49: =IF($M49="Owner",$R49,IF($M49<>"Yes",0,MAX(IF(LEFT($T49,7)="Passive",$R49+MAX(Cost!$B$8,ROUNDUP(Cost!$B$7*$R49,0)),$R49+Cost!$B$9),N($U49)))) -> 7 | W49: =$V49*$Q49 -> 0.042 | X49: https://www.lcsc.com/product-detail/C15849.html | Y49: Unchanged part | Z49: ,C312, | AA49: =IF($Z49="",0,LEN($Z49)-LEN(SUBSTITUTE($Z49,",",""))-1) -> 1 | AB49: =IF(OR($M49="Yes",$M49="Owner"),IF(COUNTIFS($H$4:$H49,$H49,$M$4:$M49,"Yes")+COUNTIFS($H$4:$H49,$H49,$M$4:$M49,"Owner")=1,1,0),0) -> 0 | AC49: Samsung CL | AD49: =MID($H49,FIND("CL",$H49)+5,3) -> 105 | AE49: =IF(ISNUMBER(FIND("R",$AD49)),SUBSTITUTE($AD49,"R",".")*1,LEFT($AD49,2)*10^RIGHT($AD49,1))*10^-12 -> 1e-06 | AF49: {=LEFT($E49,FIND(" ",$E49)-1)*IFERROR(INDEX({1000,1000000,0.000000000001,0.000000001,0.000001},MATCH(MID($E49,FIND(" ",$E49)+1,1),{"k","M","p","n","µ"},0)),1)} -> 1e-06 | AG49: =IF(AND(RIGHT($E49,1)="F",ABS($AF49-$AE49)<=Checks!$C$6*$AE49),"OK","CHECK") -> OK
A50: 3 DAC (ES9018K2M) and its supplies | B50: C441 | C50: 1 | D50: DNF 3V3A capacitor: slows a current-limited 3V3A rise for power-up pop margin | E50: 1 µF | F50: 0603 | G50: 50 V X5R ±10 % | H50: Samsung CL10A105KB8NNNC | I50: C15849 | J50: Basic | K50: — (DNF) | L50: DNF (JLCPCB stock when fitted) | M50: No | O50: 2 | P50: 0 | Q50: 0 | R50: =IF(OR($M50="Yes",$M50="Owner"),$C50*Cost!$B$6,0) -> 0 | S50: =$R50*$Q50 -> 0 | T50: — | V50: =IF($M50="Owner",$R50,IF($M50<>"Yes",0,MAX(IF(LEFT($T50,7)="Passive",$R50+MAX(Cost!$B$8,ROUNDUP(Cost!$B$7*$R50,0)),$R50+Cost!$B$9),N($U50)))) -> 0 | W50: =$V50*$Q50 -> 0 | X50: https://www.lcsc.com/product-detail/C15849.html | Y50: With C440 fitted, 3V3A stays ≤ 10 µF effective (LP5907 limit) only with DC-bias credit — confirm before fitting (fallback for the power-up pop, fitted only after the bring-up measurement) | Z50: ,C441, | AA50: =IF($Z50="",0,LEN($Z50)-LEN(SUBSTITUTE($Z50,",",""))-1) -> 1 | AB50: =IF(OR($M50="Yes",$M50="Owner"),IF(COUNTIFS($H$4:$H50,$H50,$M$4:$M50,"Yes")+COUNTIFS($H$4:$H50,$H50,$M$4:$M50,"Owner")=1,1,0),0) -> 0 | AC50: Samsung CL | AD50: =MID($H50,FIND("CL",$H50)+5,3) -> 105 | AE50: =IF(ISNUMBER(FIND("R",$AD50)),SUBSTITUTE($AD50,"R",".")*1,LEFT($AD50,2)*10^RIGHT($AD50,1))*10^-12 -> 1e-06 | AF50: {=LEFT($E50,FIND(" ",$E50)-1)*IFERROR(INDEX({1000,1000000,0.000000000001,0.000000001,0.000001},MATCH(MID($E50,FIND(" ",$E50)+1,1),{"k","M","p","n","µ"},0)),1)} -> 1e-06 | AG50: =IF(AND(RIGHT($E50,1)="F",ABS($AF50-$AE50)<=Checks!$C$6*$AE50),"OK","CHECK") -> OK
A51: 3 DAC (ES9018K2M) and its supplies | B51: FB301, FB302 | C51: 2 | D51: Ferrite beads: 3V3D → DVCC (FB301, 14.2 mA) and 3V3A → VCCA (FB302, 0.8 mA at 22 MHz, ≤ 2.9 mA at 80 MHz (assumption), XI buffer) | E51: 600 Ω @ 100 MHz | F51: 0603 | G51: 200 mA, 0.45 Ω DCR | H51: Sunlord GZ1608D601TF | I51: C1002 | J51: Basic | K51: JLCPCB library | L51: JLCPCB stock | M51: Yes | O51: 2 | P51: 0 | Q51: 0.0127 | R51: =IF(OR($M51="Yes",$M51="Owner"),$C51*Cost!$B$6,0) -> 10 | S51: =$R51*$Q51 -> 0.127 | T51: Passive: +5 %, min +2 | V51: =IF($M51="Owner",$R51,IF($M51<>"Yes",0,MAX(IF(LEFT($T51,7)="Passive",$R51+MAX(Cost!$B$8,ROUNDUP(Cost!$B$7*$R51,0)),$R51+Cost!$B$9),N($U51)))) -> 12 | W51: =$V51*$Q51 -> 0.1524 | X51: https://www.lcsc.com/product-detail/C1002.html | Y51: FB302 new (VCCA branch) | Z51: ,FB301,FB302, | AA51: =IF($Z51="",0,LEN($Z51)-LEN(SUBSTITUTE($Z51,",",""))-1) -> 2 | AB51: =IF(OR($M51="Yes",$M51="Owner"),IF(COUNTIFS($H$4:$H51,$H51,$M$4:$M51,"Yes")+COUNTIFS($H$4:$H51,$H51,$M$4:$M51,"Owner")=1,1,0),0) -> 0
A52: 3 DAC (ES9018K2M) and its supplies | B52: R301, R302 | C52: 2 | D52: AVCC_L / AVCC_R feed from 3V3A (separate branches) | E52: 2.2 Ω | F52: 0805 | G52: 1 %, 0.125 W | H52: UNI-ROYAL 0805W8F220KT5E | I52: C17521 | J52: Basic | K52: JLCPCB library | L52: JLCPCB stock | M52: Yes | O52: 2 | P52: 0 | Q52: 0.003 | R52: =IF(OR($M52="Yes",$M52="Owner"),$C52*Cost!$B$6,0) -> 10 | S52: =$R52*$Q52 -> 0.03 | T52: Passive: +5 %, min +2 | V52: =IF($M52="Owner",$R52,IF($M52<>"Yes",0,MAX(IF(LEFT($T52,7)="Passive",$R52+MAX(Cost!$B$8,ROUNDUP(Cost!$B$7*$R52,0)),$R52+Cost!$B$9),N($U52)))) -> 12 | W52: =$V52*$Q52 -> 0.036 | X52: https://www.lcsc.com/product-detail/C17521.html | Z52: ,R301,R302, | AA52: =IF($Z52="",0,LEN($Z52)-LEN(SUBSTITUTE($Z52,",",""))-1) -> 2 | AB52: =IF(OR($M52="Yes",$M52="Owner"),IF(COUNTIFS($H$4:$H52,$H52,$M$4:$M52,"Yes")+COUNTIFS($H$4:$H52,$H52,$M$4:$M52,"Owner")=1,1,0),0) -> 1 | AC52: UNI-ROYAL | AD52: =MID($H52,18,4) -> 220K | AE52: =LEFT($AD52,3)*IF(ISNUMBER(--RIGHT($AD52,1)),10^RIGHT($AD52,1),10^(0-FIND(RIGHT($AD52,1),"JKLM"))) -> 2.2 | AF52: {=LEFT($E52,FIND(" ",$E52)-1)*IFERROR(INDEX({1000,1000000,0.000000000001,0.000000001,0.000001},MATCH(MID($E52,FIND(" ",$E52)+1,1),{"k","M","p","n","µ"},0)),1)} -> 2.2 | AG52: =IF(AND(RIGHT($E52,1)="Ω",ABS($AF52-$AE52)<=Checks!$C$6*$AE52),"OK","CHECK") -> OK
A53: 3 DAC (ES9018K2M) and its supplies | B53: R303 | C53: 1 | D53: AVCC_EN pull-down (LP5907 EN and Q502 gate) | E53: 100 kΩ | F53: 0402 | G53: 1 % | H53: UNI-ROYAL 0402WGF1003TCE | I53: C25741 | J53: Basic | K53: JLCPCB library | L53: As in Parts List v0.6 | M53: Yes | O53: 2 | P53: 0 | Q53: 0.0033 | R53: =IF(OR($M53="Yes",$M53="Owner"),$C53*Cost!$B$6,0) -> 5 | S53: =$R53*$Q53 -> 0.0165 | T53: Passive: +5 %, min +2 | V53: =IF($M53="Owner",$R53,IF($M53<>"Yes",0,MAX(IF(LEFT($T53,7)="Passive",$R53+MAX(Cost!$B$8,ROUNDUP(Cost!$B$7*$R53,0)),$R53+Cost!$B$9),N($U53)))) -> 7 | W53: =$V53*$Q53 -> 0.0231 | X53: https://www.lcsc.com/product-detail/C25741.html | Y53: Unchanged; R307 deleted | Z53: ,R303, | AA53: =IF($Z53="",0,LEN($Z53)-LEN(SUBSTITUTE($Z53,",",""))-1) -> 1 | AB53: =IF(OR($M53="Yes",$M53="Owner"),IF(COUNTIFS($H$4:$H53,$H53,$M$4:$M53,"Yes")+COUNTIFS($H$4:$H53,$H53,$M$4:$M53,"Owner")=1,1,0),0) -> 0 | AC53: UNI-ROYAL | AD53: =MID($H53,18,4) -> 1003 | AE53: =LEFT($AD53,3)*IF(ISNUMBER(--RIGHT($AD53,1)),10^RIGHT($AD53,1),10^(0-FIND(RIGHT($AD53,1),"JKLM"))) -> 100000 | AF53: {=LEFT($E53,FIND(" ",$E53)-1)*IFERROR(INDEX({1000,1000000,0.000000000001,0.000000001,0.000001},MATCH(MID($E53,FIND(" ",$E53)+1,1),{"k","M","p","n","µ"},0)),1)} -> 100000 | AG53: =IF(AND(RIGHT($E53,1)="Ω",ABS($AF53-$AE53)<=Checks!$C$6*$AE53),"OK","CHECK") -> OK
A54: 3 DAC (ES9018K2M) and its supplies | B54: R305 | C54: 1 | D54: DAC RESETB pull-UP to DVCC for the Q207 open-drain driver; 0.33 mA from DVCC only while Q207 holds reset | E54: 10 kΩ | F54: 0402 | G54: 1 % | H54: UNI-ROYAL 0402WGF1002TCE | I54: C25744 | J54: Basic | K54: JLCPCB library | L54: JLCPCB stock | M54: Yes | O54: 2 | P54: 0 | Q54: 0.0033 | R54: =IF(OR($M54="Yes",$M54="Owner"),$C54*Cost!$B$6,0) -> 5 | S54: =$R54*$Q54 -> 0.0165 | T54: Passive: +5 %, min +2 | V54: =IF($M54="Owner",$R54,IF($M54<>"Yes",0,MAX(IF(LEFT($T54,7)="Passive",$R54+MAX(Cost!$B$8,ROUNDUP(Cost!$B$7*$R54,0)),$R54+Cost!$B$9),N($U54)))) -> 7 | W54: =$V54*$Q54 -> 0.0231 | X54: https://www.lcsc.com/product-detail/C25744.html | Y54: Changed from a 100 k pull-down to GND; VIH ≥ DVCC/2 + 0.4 V met with ≥ 3.0 V; VOL ≤ 7 mV with Q207; rise 0.4 µs (10–90 %) | Z54: ,R305, | AA54: =IF($Z54="",0,LEN($Z54)-LEN(SUBSTITUTE($Z54,",",""))-1) -> 1 | AB54: =IF(OR($M54="Yes",$M54="Owner"),IF(COUNTIFS($H$4:$H54,$H54,$M$4:$M54,"Yes")+COUNTIFS($H$4:$H54,$H54,$M$4:$M54,"Owner")=1,1,0),0) -> 0 | AC54: UNI-ROYAL | AD54: =MID($H54,18,4) -> 1002 | AE54: =LEFT($AD54,3)*IF(ISNUMBER(--RIGHT($AD54,1)),10^RIGHT($AD54,1),10^(0-FIND(RIGHT($AD54,1),"JKLM"))) -> 10000 | AF54: {=LEFT($E54,FIND(" ",$E54)-1)*IFERROR(INDEX({1000,1000000,0.000000000001,0.000000001,0.000001},MATCH(MID($E54,FIND(" ",$E54)+1,1),{"k","M","p","n","µ"},0)),1)} -> 10000 | AG54: =IF(AND(RIGHT($E54,1)="Ω",ABS($AF54-$AE54)<=Checks!$C$6*$AE54),"OK","CHECK") -> OK
A55: 3 DAC (ES9018K2M) and its supplies | B55: R533 | C55: 1 | D55: U303 feedback top (OUT → FB) | E55: 15.0 kΩ | F55: 0603 | G55: 0.1 %, 25 ppm/°C, thin film | H55: YAGEO RT0603BRD0715KL | I55: C326733 | J55: Extended (not verified) | K55: JLCPCB library | L55: LCSC 209,580 (25 Sep 2026) | M55: Yes | O55: 2 | P55: 0 | Q55: 0.0296 | R55: =IF(OR($M55="Yes",$M55="Owner"),$C55*Cost!$B$6,0) -> 5 | S55: =$R55*$Q55 -> 0.148 | T55: Passive: +5 %, min +2 | V55: =IF($M55="Owner",$R55,IF($M55<>"Yes",0,MAX(IF(LEFT($T55,7)="Passive",$R55+MAX(Cost!$B$8,ROUNDUP(Cost!$B$7*$R55,0)),$R55+Cost!$B$9),N($U55)))) -> 7 | W55: =$V55*$Q55 -> 0.2072 | X55: https://www.lcsc.com/product-detail/C326733.html | Y55: New | Z55: ,R533, | AA55: =IF($Z55="",0,LEN($Z55)-LEN(SUBSTITUTE($Z55,",",""))-1) -> 1 | AB55: =IF(OR($M55="Yes",$M55="Owner"),IF(COUNTIFS($H$4:$H55,$H55,$M$4:$M55,"Yes")+COUNTIFS($H$4:$H55,$H55,$M$4:$M55,"Owner")=1,1,0),0) -> 1 | AC55: YAGEO | AD55: =MID($H55,18,FIND("L",$H55,18)-18) -> 15K | AE55: =(SUBSTITUTE(SUBSTITUTE(SUBSTITUTE($AD55,"R","."),"K","."),"M",".")&"0")*IF(ISNUMBER(FIND("K",$AD55)),1000,IF(ISNUMBER(FIND("M",$AD55)),10^6,1)) -> 15000 | AF55: {=LEFT($E55,FIND(" ",$E55)-1)*IFERROR(INDEX({1000,1000000,0.000000000001,0.000000001,0.000001},MATCH(MID($E55,FIND(" ",$E55)+1,1),{"k","M","p","n","µ"},0)),1)} -> 15000 | AG55: =IF(AND(RIGHT($E55,1)="Ω",ABS($AF55-$AE55)<=Checks!$C$6*$AE55),"OK","CHECK") -> OK
A56: 3 DAC (ES9018K2M) and its supplies | B56: R534 | C56: 1 | D56: U303 feedback bottom (FB → GND) | E56: 11.0 kΩ | F56: 0603 | G56: 0.1 %, 25 ppm/°C, thin film | H56: YAGEO RT0603BRD0711KL | I56: C728581 | J56: Extended (not verified) | K56: JLCPCB library | L56: LCSC 2,260 (24 Sep 2026) | M56: Yes | O56: 2 | P56: 0 | Q56: 0.0499 | R56: =IF(OR($M56="Yes",$M56="Owner"),$C56*Cost!$B$6,0) -> 5 | S56: =$R56*$Q56 -> 0.2495 | T56: Passive: +5 %, min +2 | V56: =IF($M56="Owner",$R56,IF($M56<>"Yes",0,MAX(IF(LEFT($T56,7)="Passive",$R56+MAX(Cost!$B$8,ROUNDUP(Cost!$B$7*$R56,0)),$R56+Cost!$B$9),N($U56)))) -> 7 | W56: =$V56*$Q56 -> 0.3493 | X56: https://www.lcsc.com/product-detail/C728581.html | Y56: New | Z56: ,R534, | AA56: =IF($Z56="",0,LEN($Z56)-LEN(SUBSTITUTE($Z56,",",""))-1) -> 1 | AB56: =IF(OR($M56="Yes",$M56="Owner"),IF(COUNTIFS($H$4:$H56,$H56,$M$4:$M56,"Yes")+COUNTIFS($H$4:$H56,$H56,$M$4:$M56,"Owner")=1,1,0),0) -> 1 | AC56: YAGEO | AD56: =MID($H56,18,FIND("L",$H56,18)-18) -> 11K | AE56: =(SUBSTITUTE(SUBSTITUTE(SUBSTITUTE($AD56,"R","."),"K","."),"M",".")&"0")*IF(ISNUMBER(FIND("K",$AD56)),1000,IF(ISNUMBER(FIND("M",$AD56)),10^6,1)) -> 11000 | AF56: {=LEFT($E56,FIND(" ",$E56)-1)*IFERROR(INDEX({1000,1000000,0.000000000001,0.000000001,0.000001},MATCH(MID($E56,FIND(" ",$E56)+1,1),{"k","M","p","n","µ"},0)),1)} -> 11000 | AG56: =IF(AND(RIGHT($E56,1)="Ω",ABS($AF56-$AE56)<=Checks!$C$6*$AE56),"OK","CHECK") -> OK
A57: 3 DAC (ES9018K2M) and its supplies | B57: U301 | C57: 1 | D57: DAC, 32-bit stereo, current-mode outputs, I²C; asynchronous (DPLL) mode | E57: ES9018K2M | F57: QFN-28 5 × 5 + EP | G57: DNR 127 dB-A, THD+N -120 dB typ (current mode) | H57: ESS ES9018K2M | I57: C2688377 | J57: Extended | K57: JLCPCB library | L57: LCSC 724: thin stock, single source — pre-order 6 (5 boards + 1) | M57: Yes | N57: Yes | O57: 29 | P57: 0 | Q57: 3.4678 | R57: =IF(OR($M57="Yes",$M57="Owner"),$C57*Cost!$B$6,0) -> 5 | S57: =$R57*$Q57 -> 17.339 | T57: Other: +1 | V57: =IF($M57="Owner",$R57,IF($M57<>"Yes",0,MAX(IF(LEFT($T57,7)="Passive",$R57+MAX(Cost!$B$8,ROUNDUP(Cost!$B$7*$R57,0)),$R57+Cost!$B$9),N($U57)))) -> 6 | W57: =$V57*$Q57 -> 20.8068 | X57: https://www.esstech.com/ (ES9018K2M datasheet v3.7, 22 Apr 2021) | Y57: Exposed pad solder-mask-defined per the ESS land pattern, 5 thermal vias 0.30 mm unfilled and tented on L4 (no epoxy fill or cap), 50–70 % windowpane paste; X-ray | Z57: ,U301, | AA57: =IF($Z57="",0,LEN($Z57)-LEN(SUBSTITUTE($Z57,",",""))-1) -> 1 | AB57: =IF(OR($M57="Yes",$M57="Owner"),IF(COUNTIFS($H$4:$H57,$H57,$M$4:$M57,"Yes")+COUNTIFS($H$4:$H57,$H57,$M$4:$M57,"Owner")=1,1,0),0) -> 1
A58: 3 DAC (ES9018K2M) and its supplies | B58: U302 | C58: 1 | D58: LDO 3V3A (VCCA, AVCC_L/R, VREF, DC-sense bias), EN = AVCC_EN | E58: 3.3 V, 250 mA | F58: SOT-23-5 | G58: ±2 %, 6.5 µVrms typ | H58: TI LP5907MFX-3.3/NOPB | I58: C80670 | J58: Extended | K58: JLCPCB library | L58: As in Parts List v0.6 | M58: Yes | O58: 5 | P58: 0 | Q58: 0.2104 | R58: =IF(OR($M58="Yes",$M58="Owner"),$C58*Cost!$B$6,0) -> 5 | S58: =$R58*$Q58 -> 1.052 | T58: Other: +1 | V58: =IF($M58="Owner",$R58,IF($M58<>"Yes",0,MAX(IF(LEFT($T58,7)="Passive",$R58+MAX(Cost!$B$8,ROUNDUP(Cost!$B$7*$R58,0)),$R58+Cost!$B$9),N($U58)))) -> 6 | W58: =$V58*$Q58 -> 1.2624 | X58: https://www.ti.com/lit/ds/symlink/lp5907.pdf | Y58: Unchanged; internal 230 Ω discharge not relied on | Z58: ,U302, | AA58: =IF($Z58="",0,LEN($Z58)-LEN(SUBSTITUTE($Z58,",",""))-1) -> 1 | AB58: =IF(OR($M58="Yes",$M58="Owner"),IF(COUNTIFS($H$4:$H58,$H58,$M$4:$M58,"Yes")+COUNTIFS($H$4:$H58,$H58,$M$4:$M58,"Owner")=1,1,0),0) -> 1
A59: 3 DAC (ES9018K2M) and its supplies | B59: U303 | C59: 1 | D59: LDO 1V3 (ES9018K2M external DVDD) from 3V3D, adjustable, EN = AUD_EN, internal active discharge (95 Ω typ) | E59: 1.300 V (R533/R534) | F59: SOT-23-5 (DBV) | G59: VFB 0.55 V ±1 % (TJ ≤ 85 °C), 500 mA, VDO ≤ 400 mV | H59: TI TLV75801PDBVR | I59: C2877852 | J59: Extended | K59: JLCPCB library | L59: LCSC 113,390 (24 Sep 2026) | M59: Yes | O59: 5 | P59: 0 | Q59: 0.18 | R59: =IF(OR($M59="Yes",$M59="Owner"),$C59*Cost!$B$6,0) -> 5 | S59: =$R59*$Q59 -> 0.9 | T59: Other: +1 | V59: =IF($M59="Owner",$R59,IF($M59<>"Yes",0,MAX(IF(LEFT($T59,7)="Passive",$R59+MAX(Cost!$B$8,ROUNDUP(Cost!$B$7*$R59,0)),$R59+Cost!$B$9),N($U59)))) -> 6 | W59: =$V59*$Q59 -> 1.08 | X59: https://www.ti.com/lit/ds/symlink/tlv758p.pdf | Y59: Changed from ME6216A13; pin 1 IN, 2 GND, 3 EN, 4 FB, 5 OUT; 1.272–1.325 V incl. line/load | Z59: ,U303, | AA59: =IF($Z59="",0,LEN($Z59)-LEN(SUBSTITUTE($Z59,",",""))-1) -> 1 | AB59: =IF(OR($M59="Yes",$M59="Owner"),IF(COUNTIFS($H$4:$H59,$H59,$M$4:$M59,"Yes")+COUNTIFS($H$4:$H59,$H59,$M$4:$M59,"Owner")=1,1,0),0) -> 1
A60: 4 I/V converters and output legs | B60: C401-C408 | C60: 8 | D60: Leg lead capacitor across R2 and across R4 (phase lead; same value both sides for CMRR) | E60: 10 pF | F60: 0603 | G60: 50 V C0G ±5 % (±0.5 pF) | H60: Samsung CL10C100JB8NNNC | I60: C1634 | J60: Basic | K60: JLCPCB library | L60: JLCPCB 1.44 M | M60: Yes | O60: 2 | P60: 0 | Q60: 0.0076 | R60: =IF(OR($M60="Yes",$M60="Owner"),$C60*Cost!$B$6,0) -> 40 | S60: =$R60*$Q60 -> 0.304 | T60: Passive: +5 %, min +2 | V60: =IF($M60="Owner",$R60,IF($M60<>"Yes",0,MAX(IF(LEFT($T60,7)="Passive",$R60+MAX(Cost!$B$8,ROUNDUP(Cost!$B$7*$R60,0)),$R60+Cost!$B$9),N($U60)))) -> 42 | W60: =$V60*$Q60 -> 0.3192 | X60: https://www.lcsc.com/product-detail/C1634.html | Y60: Fallback value range 4.7–22 pF on the same footprint | Z60: ,C401,C402,C403,C404,C405,C406,C407,C408, | AA60: =IF($Z60="",0,LEN($Z60)-LEN(SUBSTITUTE($Z60,",",""))-1) -> 8 | AB60: =IF(OR($M60="Yes",$M60="Owner"),IF(COUNTIFS($H$4:$H60,$H60,$M$4:$M60,"Yes")+COUNTIFS($H$4:$H60,$H60,$M$4:$M60,"Owner")=1,1,0),0) -> 1 | AC60: Samsung CL | AD60: =MID($H60,FIND("CL",$H60)+5,3) -> 100 | AE60: =IF(ISNUMBER(FIND("R",$AD60)),SUBSTITUTE($AD60,"R",".")*1,LEFT($AD60,2)*10^RIGHT($AD60,1))*10^-12 -> 1e-11 | AF60: {=LEFT($E60,FIND(" ",$E60)-1)*IFERROR(INDEX({1000,1000000,0.000000000001,0.000000001,0.000001},MATCH(MID($E60,FIND(" ",$E60)+1,1),{"k","M","p","n","µ"},0)),1)} -> 1e-11 | AG60: =IF(AND(RIGHT($E60,1)="F",ABS($AF60-$AE60)<=Checks!$C$6*$AE60),"OK","CHECK") -> OK
A61: 4 I/V converters and output legs | B61: C409-C412 | C61: 4 | D61: OPA1622 V+ and V− decoupling | E61: 100 nF | F61: 0402 | G61: 16 V X7R ±10 % | H61: Samsung CL05B104KO5NNNC | I61: C1525 | J61: Basic | K61: JLCPCB library | L61: JLCPCB stock | M61: Yes | O61: 2 | P61: 0 | Q61: 0.0045 | R61: =IF(OR($M61="Yes",$M61="Owner"),$C61*Cost!$B$6,0) -> 20 | S61: =$R61*$Q61 -> 0.09 | T61: Passive: +5 %, min +2 | V61: =IF($M61="Owner",$R61,IF($M61<>"Yes",0,MAX(IF(LEFT($T61,7)="Passive",$R61+MAX(Cost!$B$8,ROUNDUP(Cost!$B$7*$R61,0)),$R61+Cost!$B$9),N($U61)))) -> 22 | W61: =$V61*$Q61 -> 0.099 | X61: https://www.lcsc.com/product-detail/C1525.html | Z61: ,C409,C410,C411,C412, | AA61: =IF($Z61="",0,LEN($Z61)-LEN(SUBSTITUTE($Z61,",",""))-1) -> 4 | AB61: =IF(OR($M61="Yes",$M61="Owner"),IF(COUNTIFS($H$4:$H61,$H61,$M$4:$M61,"Yes")+COUNTIFS($H$4:$H61,$H61,$M$4:$M61,"Owner")=1,1,0),0) -> 0 | AC61: Samsung CL | AD61: =MID($H61,FIND("CL",$H61)+5,3) -> 104 | AE61: =IF(ISNUMBER(FIND("R",$AD61)),SUBSTITUTE($AD61,"R",".")*1,LEFT($AD61,2)*10^RIGHT($AD61,1))*10^-12 -> 1e-07 | AF61: {=LEFT($E61,FIND(" ",$E61)-1)*IFERROR(INDEX({1000,1000000,0.000000000001,0.000000001,0.000001},MATCH(MID($E61,FIND(" ",$E61)+1,1),{"k","M","p","n","µ"},0)),1)} -> 1e-07 | AG61: =IF(AND(RIGHT($E61,1)="F",ABS($AF61-$AE61)<=Checks!$C$6*$AE61),"OK","CHECK") -> OK
A62: 4 I/V converters and output legs | B62: C413-C416 | C62: 4 | D62: OPA1622 local bulk, V+ and V− | E62: 10 µF | F62: 0805 | G62: 25 V X5R ±10 % | H62: Samsung CL21A106KAYNNNE | I62: C15850 | J62: Basic | K62: JLCPCB library | L62: JLCPCB stock | M62: Yes | O62: 2 | P62: 0 | Q62: 0.085 | R62: =IF(OR($M62="Yes",$M62="Owner"),$C62*Cost!$B$6,0) -> 20 | S62: =$R62*$Q62 -> 1.7 | T62: Passive: +5 %, min +2 | V62: =IF($M62="Owner",$R62,IF($M62<>"Yes",0,MAX(IF(LEFT($T62,7)="Passive",$R62+MAX(Cost!$B$8,ROUNDUP(Cost!$B$7*$R62,0)),$R62+Cost!$B$9),N($U62)))) -> 22 | W62: =$V62*$Q62 -> 1.87 | X62: https://www.lcsc.com/product-detail/C15850.html | Z62: ,C413,C414,C415,C416, | AA62: =IF($Z62="",0,LEN($Z62)-LEN(SUBSTITUTE($Z62,",",""))-1) -> 4 | AB62: =IF(OR($M62="Yes",$M62="Owner"),IF(COUNTIFS($H$4:$H62,$H62,$M$4:$M62,"Yes")+COUNTIFS($H$4:$H62,$H62,$M$4:$M62,"Owner")=1,1,0),0) -> 1 | AC62: Samsung CL | AD62: =MID($H62,FIND("CL",$H62)+5,3) -> 106 | AE62: =IF(ISNUMBER(FIND("R",$AD62)),SUBSTITUTE($AD62,"R",".")*1,LEFT($AD62,2)*10^RIGHT($AD62,1))*10^-12 -> 1e-05 | AF62: {=LEFT($E62,FIND(" ",$E62)-1)*IFERROR(INDEX({1000,1000000,0.000000000001,0.000000001,0.000001},MATCH(MID($E62,FIND(" ",$E62)+1,1),{"k","M","p","n","µ"},0)),1)} -> 1e-05 | AG62: =IF(AND(RIGHT($E62,1)="F",ABS($AF62-$AE62)<=Checks!$C$6*$AE62),"OK","CHECK") -> OK
A63: 4 I/V converters and output legs | B63: C417-C420 | C63: 4 | D63: I/V feedback capacitor Cf (single part, replaces 2 × 330 pF): 278 kHz with 698 Ω | E63: 820 pF | F63: 0603 | G63: 50 V C0G ±5 % | H63: KEMET C0603C821J5GACTU | I63: C2169093 | J63: Extended | K63: JLCPCB library | L63: LCSC 880; alt. Murata GRM1885C1H821JA01D | M63: Yes | O63: 2 | P63: 0 | Q63: 0.0111 | R63: =IF(OR($M63="Yes",$M63="Owner"),$C63*Cost!$B$6,0) -> 20 | S63: =$R63*$Q63 -> 0.222 | T63: Passive: +5 %, min +2 | V63: =IF($M63="Owner",$R63,IF($M63<>"Yes",0,MAX(IF(LEFT($T63,7)="Passive",$R63+MAX(Cost!$B$8,ROUNDUP(Cost!$B$7*$R63,0)),$R63+Cost!$B$9),N($U63)))) -> 22 | W63: =$V63*$Q63 -> 0.2442 | X63: https://www.lcsc.com/product-detail/C2169093.html | Z63: ,C417,C418,C419,C420, | AA63: =IF($Z63="",0,LEN($Z63)-LEN(SUBSTITUTE($Z63,",",""))-1) -> 4 | AB63: =IF(OR($M63="Yes",$M63="Owner"),IF(COUNTIFS($H$4:$H63,$H63,$M$4:$M63,"Yes")+COUNTIFS($H$4:$H63,$H63,$M$4:$M63,"Owner")=1,1,0),0) -> 1
A64: 4 I/V converters and output legs | B64: C421 | C64: 1 | D64: VREF HF decoupling (tau 0.19 µs: VREF tracks 3V3A) | E64: 33 pF | F64: 0402 | G64: 50 V C0G ±5 % | H64: FH 0402CG330J500NT | I64: C1562 | J64: Basic | K64: JLCPCB library | L64: JLCPCB stock | M64: Yes | O64: 2 | P64: 0 | Q64: 0.002 | R64: =IF(OR($M64="Yes",$M64="Owner"),$C64*Cost!$B$6,0) -> 5 | S64: =$R64*$Q64 -> 0.01 | T64: Passive: +5 %, min +2 | V64: =IF($M64="Owner",$R64,IF($M64<>"Yes",0,MAX(IF(LEFT($T64,7)="Passive",$R64+MAX(Cost!$B$8,ROUNDUP(Cost!$B$7*$R64,0)),$R64+Cost!$B$9),N($U64)))) -> 7 | W64: =$V64*$Q64 -> 0.014 | X64: https://www.lcsc.com/product-detail/C1562.html | Z64: ,C421, | AA64: =IF($Z64="",0,LEN($Z64)-LEN(SUBSTITUTE($Z64,",",""))-1) -> 1 | AB64: =IF(OR($M64="Yes",$M64="Owner"),IF(COUNTIFS($H$4:$H64,$H64,$M$4:$M64,"Yes")+COUNTIFS($H$4:$H64,$H64,$M$4:$M64,"Owner")=1,1,0),0) -> 0 | AC64: FH | AD64: =IF(ISNUMBER(FIND("CG",$H64)),MID($H64,FIND("CG",$H64)+2,3),MID($H64,FIND(" 0",$H64)+6,3)) -> 330 | AE64: =IF(ISNUMBER(FIND("R",$AD64)),SUBSTITUTE($AD64,"R",".")*1,LEFT($AD64,2)*10^RIGHT($AD64,1))*10^-12 -> 3.3e-11 | AF64: {=LEFT($E64,FIND(" ",$E64)-1)*IFERROR(INDEX({1000,1000000,0.000000000001,0.000000001,0.000001},MATCH(MID($E64,FIND(" ",$E64)+1,1),{"k","M","p","n","µ"},0)),1)} -> 3.3e-11 | AG64: =IF(AND(RIGHT($E64,1)="F",ABS($AF64-$AE64)<=Checks!$C$6*$AE64),"OK","CHECK") -> OK
A65: 4 I/V converters and output legs | B65: C423-C426 | C65: 4 | D65: OPA2210 VPOS_IV and VNEG_IV decoupling | E65: 100 nF | F65: 0402 | G65: 16 V X7R ±10 % | H65: Samsung CL05B104KO5NNNC | I65: C1525 | J65: Basic | K65: JLCPCB library | L65: JLCPCB stock | M65: Yes | O65: 2 | P65: 0 | Q65: 0.0045 | R65: =IF(OR($M65="Yes",$M65="Owner"),$C65*Cost!$B$6,0) -> 20 | S65: =$R65*$Q65 -> 0.09 | T65: Passive: +5 %, min +2 | V65: =IF($M65="Owner",$R65,IF($M65<>"Yes",0,MAX(IF(LEFT($T65,7)="Passive",$R65+MAX(Cost!$B$8,ROUNDUP(Cost!$B$7*$R65,0)),$R65+Cost!$B$9),N($U65)))) -> 22 | W65: =$V65*$Q65 -> 0.099 | X65: https://www.lcsc.com/product-detail/C1525.html | Z65: ,C423,C424,C425,C426, | AA65: =IF($Z65="",0,LEN($Z65)-LEN(SUBSTITUTE($Z65,",",""))-1) -> 4 | AB65: =IF(OR($M65="Yes",$M65="Owner"),IF(COUNTIFS($H$4:$H65,$H65,$M$4:$M65,"Yes")+COUNTIFS($H$4:$H65,$H65,$M$4:$M65,"Owner")=1,1,0),0) -> 0 | AC65: Samsung CL | AD65: =MID($H65,FIND("CL",$H65)+5,3) -> 104 | AE65: =IF(ISNUMBER(FIND("R",$AD65)),SUBSTITUTE($AD65,"R",".")*1,LEFT($AD65,2)*10^RIGHT($AD65,1))*10^-12 -> 1e-07 | AF65: {=LEFT($E65,FIND(" ",$E65)-1)*IFERROR(INDEX({1000,1000000,0.000000000001,0.000000001,0.000001},MATCH(MID($E65,FIND(" ",$E65)+1,1),{"k","M","p","n","µ"},0)),1)} -> 1e-07 | AG65: =IF(AND(RIGHT($E65,1)="F",ABS($AF65-$AE65)<=Checks!$C$6*$AE65),"OK","CHECK") -> OK
A66: 4 I/V converters and output legs | B66: C431-C438 | C66: 8 | D66: Leg T-network shunt capacitor (pole 199 kHz, HF noise gain 4 for capacitive-load stability) | E66: 1.8 nF | F66: 0603 | G66: 50 V C0G ±5 % | H66: Murata GRM1885C1H182JA01D | I66: C97878 | J66: Extended | K66: JLCPCB library | L66: LCSC 750-1,900 | M66: Yes | O66: 2 | P66: 0 | Q66: 0.0163 | R66: =IF(OR($M66="Yes",$M66="Owner"),$C66*Cost!$B$6,0) -> 40 | S66: =$R66*$Q66 -> 0.652 | T66: Passive: +5 %, min +2 | V66: =IF($M66="Owner",$R66,IF($M66<>"Yes",0,MAX(IF(LEFT($T66,7)="Passive",$R66+MAX(Cost!$B$8,ROUNDUP(Cost!$B$7*$R66,0)),$R66+Cost!$B$9),N($U66)))) -> 42 | W66: =$V66*$Q66 -> 0.6846 | X66: https://www.lcsc.com/product-detail/C97878.html | Z66: ,C431,C432,C433,C434,C435,C436,C437,C438, | AA66: =IF($Z66="",0,LEN($Z66)-LEN(SUBSTITUTE($Z66,",",""))-1) -> 8 | AB66: =IF(OR($M66="Yes",$M66="Owner"),IF(COUNTIFS($H$4:$H66,$H66,$M$4:$M66,"Yes")+COUNTIFS($H$4:$H66,$H66,$M$4:$M66,"Owner")=1,1,0),0) -> 1
A67: 4 I/V converters and output legs | B67: C442, C443 | C67: 2 | D67: I/V supply reservoirs (N4_VPOS_IV, N4_VNEG_IV), MnO2 tantalum (no DC-bias loss): 198–242 µF | E67: 220 µF | F67: 7343-31 (D) | G67: 10 V, ±10 %, ESR ≤ 0.5 Ω at 100 kHz, DCL ≤ 22 µA (0.01CV) at 25 °C (AVX TAJ rule) | H67: Kyocera AVX TAJD227K010RNJ | I67: C8024 | J67: Extended | K67: JLCPCB library | L67: LCSC 44,987 in stock (25 Sep 2026) — pre-order 12 | M67: Yes | O67: 2 | P67: 0 | Q67: 0.5257 | R67: =IF(OR($M67="Yes",$M67="Owner"),$C67*Cost!$B$6,0) -> 10 | S67: =$R67*$Q67 -> 5.257 | T67: Passive: +5 %, min +2 | V67: =IF($M67="Owner",$R67,IF($M67<>"Yes",0,MAX(IF(LEFT($T67,7)="Passive",$R67+MAX(Cost!$B$8,ROUNDUP(Cost!$B$7*$R67,0)),$R67+Cost!$B$9),N($U67)))) -> 12 | W67: =$V67*$Q67 -> 6.3084 | X67: https://www.kemet.com/ (T495 surge-robust MnO2) | Y67: Cost patch: replaces the KEMET T495D227K010ATE100 (global sourcing, 24-week lead); polarised: C442 + to N4_VPOS_IV, C443 + to GND; applied ≤ 3.9 V = 39 % of rated; reverse clamped by D413/D414; charging current limited by the LM27762 (no surge); hold-up re-checked at 176 µF with a VF + ESR drop of 0.31 V; polarity gate G-4 | Z67: ,C442,C443, | AA67: =IF($Z67="",0,LEN($Z67)-LEN(SUBSTITUTE($Z67,",",""))-1) -> 2 | AB67: =IF(OR($M67="Yes",$M67="Owner"),IF(COUNTIFS($H$4:$H67,$H67,$M$4:$M67,"Yes")+COUNTIFS($H$4:$H67,$H67,$M$4:$M67,"Owner")=1,1,0),0) -> 1
A68: 4 I/V converters and output legs | B68: D405-D408 | C68: 4 | D68: DAC-pin protection moved to the I/V outputs: dual series Schottky, common node on each OPA2210 output, lower anode to GND, upper cathode to AVCC_L (D405/D406) or AVCC_R (D407/D408); nothing on the DAC pins (virtual ground) | E68: BAT54S | F68: SOT-23 | G68: 30 V, 200 mA, IFSM 600 mA, VF ≤ 0.5 V at 30 mA, Cd ≤ 10 pF | H68: Nexperia BAT54S,215 | I68: C47546 | J68: Extended | K68: JLCPCB library | L68: JLCPCB ≈ 230 k, Economic and Standard, MSL 1 (25 Sep 2026) | M68: Yes | O68: 3 | P68: 0 | Q68: 0.0245 | R68: =IF(OR($M68="Yes",$M68="Owner"),$C68*Cost!$B$6,0) -> 20 | S68: =$R68*$Q68 -> 0.49 | T68: Other: +1 | V68: =IF($M68="Owner",$R68,IF($M68<>"Yes",0,MAX(IF(LEFT($T68,7)="Passive",$R68+MAX(Cost!$B$8,ROUNDUP(Cost!$B$7*$R68,0)),$R68+Cost!$B$9),N($U68)))) -> 21 | W68: =$V68*$Q68 -> 0.5145 | X68: https://assets.nexperia.com/documents/data-sheet/BAT54S.pdf | Y68: Pin 1 A1, pin 2 K2, pin 3 K1/A2 (Nexperia Table 2); replaces the JSMSEMI BAT54S (C916425) at the DAC pins; polarity gate G-4 | Z68: ,D405,D406,D407,D408, | AA68: =IF($Z68="",0,LEN($Z68)-LEN(SUBSTITUTE($Z68,",",""))-1) -> 4 | AB68: =IF(OR($M68="Yes",$M68="Owner"),IF(COUNTIFS($H$4:$H68,$H68,$M$4:$M68,"Yes")+COUNTIFS($H$4:$H68,$H68,$M$4:$M68,"Owner")=1,1,0),0) -> 1
A69: 4 I/V converters and output legs | B69: D411, D412 | C69: 2 | D69: I/V supply hold-up diodes: VPOS → N4_VPOS_IV (D411) and N4_VNEG_IV → VNEG (D412), low-VF Schottky | E69: PMEG2010AEH | F69: SOD-123F | G69: 20 V, 1 A; VF ≤ 253 mV at 30 mA, 25 °C (datasheet limit); ≤ 298 mV at 30 mA and ≤ 282 mV at the 17.4 mA operating maximum, 0 °C (worst-case calculation with a typical tempco of −1.5…−1.8 mV/K) vs 0.30 V used; IR 0.28–0.44 mA at 5 V, 50 °C vs 1 mA in the hold-up model | H69: Nexperia PMEG2010AEH,115 | I69: C110921 | J69: Extended | K69: JLCPCB library | L69: LCSC C110921: 7,335 in stock (25 Sep 2026); the JLCPCB-placed quantity of 11 (10 + attrition) follows JLCPCB's minimums; the LCSC minimum/multiple of 5 applies only to the owner's LCSC gate-sample order | M69: Yes | O69: 2 | P69: 0 | Q69: 0.3209 | R69: =IF(OR($M69="Yes",$M69="Owner"),$C69*Cost!$B$6,0) -> 10 | S69: =$R69*$Q69 -> 3.209 | T69: Other: +1 | V69: =IF($M69="Owner",$R69,IF($M69<>"Yes",0,MAX(IF(LEFT($T69,7)="Passive",$R69+MAX(Cost!$B$8,ROUNDUP(Cost!$B$7*$R69,0)),$R69+Cost!$B$9),N($U69)))) -> 11 | W69: =$V69*$Q69 -> 3.5299 | X69: https://assets.nexperia.com/documents/data-sheet/PMEG2010AEH.pdf | Y69: Pin 1 cathode, pin 2 anode (SOD123F); the OPA2210 stays powered and inside its common-mode range until 3V3A < 0.3 V at every hard unplug; polarity gate G-4 | Z69: ,D411,D412, | AA69: =IF($Z69="",0,LEN($Z69)-LEN(SUBSTITUTE($Z69,",",""))-1) -> 2 | AB69: =IF(OR($M69="Yes",$M69="Owner"),IF(COUNTIFS($H$4:$H69,$H69,$M$4:$M69,"Yes")+COUNTIFS($H$4:$H69,$H69,$M$4:$M69,"Owner")=1,1,0),0) -> 1
A70: 4 I/V converters and output legs | B70: D413, D414 | C70: 2 | D70: Reverse clamps across the polarised I/V reservoirs: D413 GND → N4_VPOS_IV (across C442), D414 N4_VNEG_IV → GND (across C443) | E70: BAT54 | F70: SOT-23 | G70: 30 V, 200 mA; VF ≤ 400 mV at 10 mA, ≤ 500 mV at 30 mA (25 °C); IR ≤ 2 µA at 25 V, 25 °C | H70: Nexperia BAT54,215 | I70: C85084 | J70: Extended | K70: JLCPCB library | L70: JLCPCB stock ≫ need (same part as D104/D105) | M70: Yes | O70: 3 | P70: 0 | Q70: 0.02 | R70: =IF(OR($M70="Yes",$M70="Owner"),$C70*Cost!$B$6,0) -> 10 | S70: =$R70*$Q70 -> 0.2 | T70: Other: +1 | V70: =IF($M70="Owner",$R70,IF($M70<>"Yes",0,MAX(IF(LEFT($T70,7)="Passive",$R70+MAX(Cost!$B$8,ROUNDUP(Cost!$B$7*$R70,0)),$R70+Cost!$B$9),N($U70)))) -> 11 | W70: =$V70*$Q70 -> 0.22 | X70: https://assets.nexperia.com/documents/data-sheet/BAT54_SER.pdf | Y70: Pin 1 A, pin 2 n.c. (pad only), pin 3 K; each within 3 mm of its capacitor; C442/C443 reverse ≤ 0.47 V (≤ 13 mA, 0 °C); leakage ≤ 25 µA per rail at 60 °C (assumption) | Z70: ,D413,D414, | AA70: =IF($Z70="",0,LEN($Z70)-LEN(SUBSTITUTE($Z70,",",""))-1) -> 2 | AB70: =IF(OR($M70="Yes",$M70="Owner"),IF(COUNTIFS($H$4:$H70,$H70,$M$4:$M70,"Yes")+COUNTIFS($H$4:$H70,$H70,$M$4:$M70,"Owner")=1,1,0),0) -> 1
A71: 4 I/V converters and output legs | B71: R401, R403, R405, R407, R409, R411, R413, R415 | C71: 8 | D71: Leg input T network, first half R1a/R3a (1.30 k, stocked value) | E71: 1.30 kΩ | F71: 0603 | G71: 0.1 %, 25 ppm/K, thin film, 0.1 W | H71: YAGEO RT0603BRD071K3L | I71: C705738 | J71: Extended | K71: JLCPCB library | L71: LCSC 100 in stock (25 Sep 2026, min/multiple 20): buy now 60 = 40 + attrition (order multiple) | M71: Yes | O71: 2 | P71: 0 | Q71: 0.0259 | R71: =IF(OR($M71="Yes",$M71="Owner"),$C71*Cost!$B$6,0) -> 40 | S71: =$R71*$Q71 -> 1.036 | T71: Passive: +5 %, min +2 | U71: 60 | V71: =IF($M71="Owner",$R71,IF($M71<>"Yes",0,MAX(IF(LEFT($T71,7)="Passive",$R71+MAX(Cost!$B$8,ROUNDUP(Cost!$B$7*$R71,0)),$R71+Cost!$B$9),N($U71)))) -> 60 | W71: =$V71*$Q71 -> 1.554 | X71: https://www.digikey.com/en/products/detail/susumu/RG1608N-132-W-T1/600600 | Y71: Cost patch: replaces the Susumu RG1608N-132-W-T1 0.05 %/10 ppm (global sourcing). With the mixed leg network (0.05 % 2.00 k R2/R4) the DC offset over 0–50 °C is 5.61 / 11.21 mV guaranteed from published terms and 7.73 / 15.47 mV with the unpublished DAC terms (margins 2.27 / 4.53 mV to the 10 / 20 mV limits); production screen 7.83 / 15.67 mV; per-board offset test at 0–5, 25 and 50 °C. If LCSC stock is below 60 at ordering, fit the Susumu part | Z71: ,R401,R403,R405,R407,R409,R411,R413,R415, | AA71: =IF($Z71="",0,LEN($Z71)-LEN(SUBSTITUTE($Z71,",",""))-1) -> 8 | AB71: =IF(OR($M71="Yes",$M71="Owner"),IF(COUNTIFS($H$4:$H71,$H71,$M$4:$M71,"Yes")+COUNTIFS($H$4:$H71,$H71,$M$4:$M71,"Owner")=1,1,0),0) -> 1 | AC71: YAGEO | AD71: =MID($H71,18,FIND("L",$H71,18)-18) -> 1K3 | AE71: =(SUBSTITUTE(SUBSTITUTE(SUBSTITUTE($AD71,"R","."),"K","."),"M",".")&"0")*IF(ISNUMBER(FIND("K",$AD71)),1000,IF(ISNUMBER(FIND("M",$AD71)),10^6,1)) -> 1300 | AF71: {=LEFT($E71,FIND(" ",$E71)-1)*IFERROR(INDEX({1000,1000000,0.000000000001,0.000000001,0.000001},MATCH(MID($E71,FIND(" ",$E71)+1,1),{"k","M","p","n","µ"},0)),1)} -> 1300 | AG71: =IF(AND(RIGHT($E71,1)="Ω",ABS($AF71-$AE71)<=Checks!$C$6*$AE71),"OK","CHECK") -> OK
A72: 4 I/V converters and output legs | B72: R402, R404, R406, R408, R410, R412, R414, R416 | C72: 8 | D72: Leg feedback R2 and ground-leg R4 (0.05 %, 10 ppm/K) | E72: 2.00 kΩ | F72: 0603 | G72: 0.05 %, 10 ppm/K, thin film, 0.1 W, AEC-Q200 | H72: Susumu RG1608N-202-W-T1 | I72: — | J72: Extended | K72: Global sourcing | L72: Global sourcing: DigiKey 16,746 cut tape (25 Sep 2026); alternate Panasonic ERA-3ARW202V (0.05 %/10 ppm, DigiKey 1,259); no LCSC stock (YAGEO RT0603WRB072KL C864006 out of stock) | M72: Yes | O72: 2 | P72: 0 | Q72: 0.6 | R72: =IF(OR($M72="Yes",$M72="Owner"),$C72*Cost!$B$6,0) -> 40 | S72: =$R72*$Q72 -> 24 | T72: Passive: +5 %, min +2 | V72: =IF($M72="Owner",$R72,IF($M72<>"Yes",0,MAX(IF(LEFT($T72,7)="Passive",$R72+MAX(Cost!$B$8,ROUNDUP(Cost!$B$7*$R72,0)),$R72+Cost!$B$9),N($U72)))) -> 42 | W72: =$V72*$Q72 -> 25.2 | X72: https://www.digikey.com/en/products/detail/susumu/RG1608N-202-W-T1/600604 | Y72: Mixed leg network: 0.05 % 2.00 k R2/R4 with the 0.1 % T network → DC offset over 0–50 °C guaranteed 5.61 / 11.21 mV from published terms, 7.73 / 15.47 mV with the unpublished DAC terms (tolerates 2.06 × the DAC assumption); supersedes the 0.1 % Panasonic ERA-3AEB202V of v0.7; change control as R401 | Z72: ,R402,R404,R406,R408,R410,R412,R414,R416, | AA72: =IF($Z72="",0,LEN($Z72)-LEN(SUBSTITUTE($Z72,",",""))-1) -> 8 | AB72: =IF(OR($M72="Yes",$M72="Owner"),IF(COUNTIFS($H$4:$H72,$H72,$M$4:$M72,"Yes")+COUNTIFS($H$4:$H72,$H72,$M$4:$M72,"Owner")=1,1,0),0) -> 1
A73: 4 I/V converters and output legs | B73: R417-R420 | C73: 4 | D73: DFT link per leg between the OPA1622 output pin and the leg node LEG_xx (protection sense networks, output switch K601-K604 to the jack); removed on the test board for the rail-stuck emulation | E73: 0 Ω | F73: 0402 | G73: jumper, ≤ 50 mΩ | H73: UNI-ROYAL 0402WGF0000TCE | I73: C17168 | J73: Basic | K73: JLCPCB library | L73: JLCPCB stock | M73: Yes | O73: 2 | P73: 0 | Q73: 0.002 | R73: =IF(OR($M73="Yes",$M73="Owner"),$C73*Cost!$B$6,0) -> 20 | S73: =$R73*$Q73 -> 0.04 | T73: Passive: +5 %, min +2 | V73: =IF($M73="Owner",$R73,IF($M73<>"Yes",0,MAX(IF(LEFT($T73,7)="Passive",$R73+MAX(Cost!$B$8,ROUNDUP(Cost!$B$7*$R73,0)),$R73+Cost!$B$9),N($U73)))) -> 22 | W73: =$V73*$Q73 -> 0.044 | X73: https://www.lcsc.com/product-detail/C17168.html | Y73: Kept for design-for-test (detector/energy tests); approved alternate: ferrite bead Murata BLM15PX330SN1D (0402, 33 Ω ±25 % at 100 MHz, 3 A, DCR ≤ 0.022 Ω) for ESD robustness with the switch closed — fit 0 Ω by default | Z73: ,R417,R418,R419,R420, | AA73: =IF($Z73="",0,LEN($Z73)-LEN(SUBSTITUTE($Z73,",",""))-1) -> 4 | AB73: =IF(OR($M73="Yes",$M73="Owner"),IF(COUNTIFS($H$4:$H73,$H73,$M$4:$M73,"Yes")+COUNTIFS($H$4:$H73,$H73,$M$4:$M73,"Owner")=1,1,0),0) -> 0 | AC73: UNI-ROYAL | AD73: =MID($H73,18,4) -> 0000 | AE73: =LEFT($AD73,3)*IF(ISNUMBER(--RIGHT($AD73,1)),10^RIGHT($AD73,1),10^(0-FIND(RIGHT($AD73,1),"JKLM"))) -> 0 | AF73: {=LEFT($E73,FIND(" ",$E73)-1)*IFERROR(INDEX({1000,1000000,0.000000000001,0.000000001,0.000001},MATCH(MID($E73,FIND(" ",$E73)+1,1),{"k","M","p","n","µ"},0)),1)} -> 0 | AG73: =IF(AND(RIGHT($E73,1)="Ω",ABS($AF73-$AE73)<=Checks!$C$6*$AE73),"OK","CHECK") -> OK
A74: 4 I/V converters and output legs | B74: R423-R426 | C74: 4 | D74: I/V feedback resistor Rf (single part, replaces 1 k ∥ 5.1 k) | E74: 698 Ω | F74: 0603 | G74: 0.1 %, 25 ppm/K, thin film | H74: YAGEO RT0603BRD07698RL | I74: C861525 | J74: Extended | K74: JLCPCB library | L74: LCSC 120 in stock (25 Sep 2026, min/multiple 20): pre-order 40 = 20 + attrition, no global sourcing | M74: Yes | O74: 2 | P74: 0 | Q74: 0.0254 | R74: =IF(OR($M74="Yes",$M74="Owner"),$C74*Cost!$B$6,0) -> 20 | S74: =$R74*$Q74 -> 0.508 | T74: Passive: +5 %, min +2 | U74: 40 | V74: =IF($M74="Owner",$R74,IF($M74<>"Yes",0,MAX(IF(LEFT($T74,7)="Passive",$R74+MAX(Cost!$B$8,ROUNDUP(Cost!$B$7*$R74,0)),$R74+Cost!$B$9),N($U74)))) -> 40 | W74: =$V74*$Q74 -> 1.016 | X74: https://www.lcsc.com/product-detail/C861525.html | Y74: Change control: sets the protection common-mode window — change only together with the protection design | Z74: ,R423,R424,R425,R426, | AA74: =IF($Z74="",0,LEN($Z74)-LEN(SUBSTITUTE($Z74,",",""))-1) -> 4 | AB74: =IF(OR($M74="Yes",$M74="Owner"),IF(COUNTIFS($H$4:$H74,$H74,$M$4:$M74,"Yes")+COUNTIFS($H$4:$H74,$H74,$M$4:$M74,"Owner")=1,1,0),0) -> 1 | AC74: YAGEO | AD74: =MID($H74,18,FIND("L",$H74,18)-18) -> 698R | AE74: =(SUBSTITUTE(SUBSTITUTE(SUBSTITUTE($AD74,"R","."),"K","."),"M",".")&"0")*IF(ISNUMBER(FIND("K",$AD74)),1000,IF(ISNUMBER(FIND("M",$AD74)),10^6,1)) -> 698 | AF74: {=LEFT($E74,FIND(" ",$E74)-1)*IFERROR(INDEX({1000,1000000,0.000000000001,0.000000001,0.000001},MATCH(MID($E74,FIND(" ",$E74)+1,1),{"k","M","p","n","µ"},0)),1)} -> 698 | AG74: =IF(AND(RIGHT($E74,1)="Ω",ABS($AF74-$AE74)<=Checks!$C$6*$AE74),"OK","CHECK") -> OK
A75: 4 I/V converters and output legs | B75: R431 | C75: 1 | D75: VREF divider top (from 3V3A) | E75: 9.76 kΩ | F75: 0603 | G75: 0.1 %, 25 ppm/K, thin film | H75: YAGEO RT0603BRD079K76L | I75: C861616 | J75: Extended | K75: JLCPCB library | L75: LCSC ≈ 1,860 | M75: Yes | O75: 2 | P75: 0 | Q75: 0.035 | R75: =IF(OR($M75="Yes",$M75="Owner"),$C75*Cost!$B$6,0) -> 5 | S75: =$R75*$Q75 -> 0.175 | T75: Passive: +5 %, min +2 | V75: =IF($M75="Owner",$R75,IF($M75<>"Yes",0,MAX(IF(LEFT($T75,7)="Passive",$R75+MAX(Cost!$B$8,ROUNDUP(Cost!$B$7*$R75,0)),$R75+Cost!$B$9),N($U75)))) -> 7 | W75: =$V75*$Q75 -> 0.245 | X75: https://www.lcsc.com/product-detail/C861616.html | Y75: VREF = 0.50607 × 3V3A = 1.670 V: midpoint of the ESS null range 1.65…1.702 V; change control as R423–R426 | Z75: ,R431, | AA75: =IF($Z75="",0,LEN($Z75)-LEN(SUBSTITUTE($Z75,",",""))-1) -> 1 | AB75: =IF(OR($M75="Yes",$M75="Owner"),IF(COUNTIFS($H$4:$H75,$H75,$M$4:$M75,"Yes")+COUNTIFS($H$4:$H75,$H75,$M$4:$M75,"Owner")=1,1,0),0) -> 1 | AC75: YAGEO | AD75: =MID($H75,18,FIND("L",$H75,18)-18) -> 9K76 | AE75: =(SUBSTITUTE(SUBSTITUTE(SUBSTITUTE($AD75,"R","."),"K","."),"M",".")&"0")*IF(ISNUMBER(FIND("K",$AD75)),1000,IF(ISNUMBER(FIND("M",$AD75)),10^6,1)) -> 9760 | AF75: {=LEFT($E75,FIND(" ",$E75)-1)*IFERROR(INDEX({1000,1000000,0.000000000001,0.000000001,0.000001},MATCH(MID($E75,FIND(" ",$E75)+1,1),{"k","M","p","n","µ"},0)),1)} -> 9760 | AG75: =IF(AND(RIGHT($E75,1)="Ω",ABS($AF75-$AE75)<=Checks!$C$6*$AE75),"OK","CHECK") -> OK
A76: 4 I/V converters and output legs | B76: R432 | C76: 1 | D76: VREF divider bottom | E76: 10.0 kΩ | F76: 0603 | G76: 0.1 %, 25 ppm/K, thin film | H76: YAGEO RT0603BRD0710KL | I76: C95204 | J76: Extended | K76: JLCPCB library | L76: LCSC 498,660 | M76: Yes | O76: 2 | P76: 0 | Q76: 0.0331 | R76: =IF(OR($M76="Yes",$M76="Owner"),$C76*Cost!$B$6,0) -> 5 | S76: =$R76*$Q76 -> 0.1655 | T76: Passive: +5 %, min +2 | V76: =IF($M76="Owner",$R76,IF($M76<>"Yes",0,MAX(IF(LEFT($T76,7)="Passive",$R76+MAX(Cost!$B$8,ROUNDUP(Cost!$B$7*$R76,0)),$R76+Cost!$B$9),N($U76)))) -> 7 | W76: =$V76*$Q76 -> 0.2317 | X76: https://www.lcsc.com/product-detail/C95204.html | Y76: Change control as R423–R426 | Z76: ,R432, | AA76: =IF($Z76="",0,LEN($Z76)-LEN(SUBSTITUTE($Z76,",",""))-1) -> 1 | AB76: =IF(OR($M76="Yes",$M76="Owner"),IF(COUNTIFS($H$4:$H76,$H76,$M$4:$M76,"Yes")+COUNTIFS($H$4:$H76,$H76,$M$4:$M76,"Owner")=1,1,0),0) -> 1 | AC76: YAGEO | AD76: =MID($H76,18,FIND("L",$H76,18)-18) -> 10K | AE76: =(SUBSTITUTE(SUBSTITUTE(SUBSTITUTE($AD76,"R","."),"K","."),"M",".")&"0")*IF(ISNUMBER(FIND("K",$AD76)),1000,IF(ISNUMBER(FIND("M",$AD76)),10^6,1)) -> 10000 | AF76: {=LEFT($E76,FIND(" ",$E76)-1)*IFERROR(INDEX({1000,1000000,0.000000000001,0.000000001,0.000001},MATCH(MID($E76,FIND(" ",$E76)+1,1),{"k","M","p","n","µ"},0)),1)} -> 10000 | AG76: =IF(AND(RIGHT($E76,1)="Ω",ABS($AF76-$AE76)<=Checks!$C$6*$AE76),"OK","CHECK") -> OK
A77: 4 I/V converters and output legs | B77: R438-R445 | C77: 8 | D77: Leg input T network, second half R1b/R3b (680 Ω, stocked value) | E77: 680 Ω | F77: 0603 | G77: 0.1 %, 25 ppm/K, thin film, 0.1 W | H77: YAGEO RT0603BRD07680RL | I77: C861519 | J77: Extended | K77: JLCPCB library | L77: LCSC 8,000 in stock (25 Sep 2026, min/multiple 20): pre-order 60 (order multiple) | M77: Yes | O77: 2 | P77: 0 | Q77: 0.0256 | R77: =IF(OR($M77="Yes",$M77="Owner"),$C77*Cost!$B$6,0) -> 40 | S77: =$R77*$Q77 -> 1.024 | T77: Passive: +5 %, min +2 | U77: 60 | V77: =IF($M77="Owner",$R77,IF($M77<>"Yes",0,MAX(IF(LEFT($T77,7)="Passive",$R77+MAX(Cost!$B$8,ROUNDUP(Cost!$B$7*$R77,0)),$R77+Cost!$B$9),N($U77)))) -> 60 | W77: =$V77*$Q77 -> 1.536 | X77: https://www.digikey.com/en/products/detail/susumu/RG1608N-681-W-T1/600593 | Y77: Cost patch: replaces the Susumu RG1608N-681-W-T1 0.05 %/10 ppm (global sourcing; also the rework fallback); offset: see the R401 line; change control as R401 | Z77: ,R438,R439,R440,R441,R442,R443,R444,R445, | AA77: =IF($Z77="",0,LEN($Z77)-LEN(SUBSTITUTE($Z77,",",""))-1) -> 8 | AB77: =IF(OR($M77="Yes",$M77="Owner"),IF(COUNTIFS($H$4:$H77,$H77,$M$4:$M77,"Yes")+COUNTIFS($H$4:$H77,$H77,$M$4:$M77,"Owner")=1,1,0),0) -> 1 | AC77: YAGEO | AD77: =MID($H77,18,FIND("L",$H77,18)-18) -> 680R | AE77: =(SUBSTITUTE(SUBSTITUTE(SUBSTITUTE($AD77,"R","."),"K","."),"M",".")&"0")*IF(ISNUMBER(FIND("K",$AD77)),1000,IF(ISNUMBER(FIND("M",$AD77)),10^6,1)) -> 680 | AF77: {=LEFT($E77,FIND(" ",$E77)-1)*IFERROR(INDEX({1000,1000000,0.000000000001,0.000000001,0.000001},MATCH(MID($E77,FIND(" ",$E77)+1,1),{"k","M","p","n","µ"},0)),1)} -> 680 | AG77: =IF(AND(RIGHT($E77,1)="Ω",ABS($AF77-$AE77)<=Checks!$C$6*$AE77),"OK","CHECK") -> OK
A78: 4 I/V converters and output legs | B78: R446, R447 | C78: 2 | D78: DNF VREF trim footprints: R446 parallel to R431 raises VREF, R447 parallel to R432 lowers VREF; fitted only if the 25 °C offset screen fails | E78: DNF (237 k … 2 M) | F78: 0603 | G78: 0.1 %, 25 ppm/K thin film when fitted | H78: YAGEO RT0603BRD07xxxL (value from the trim table) | I78: — | J78: Extended | K78: — (DNF) | L78: DNF | M78: No | O78: 2 | P78: 0 | Q78: 0 | R78: =IF(OR($M78="Yes",$M78="Owner"),$C78*Cost!$B$6,0) -> 0 | S78: =$R78*$Q78 -> 0 | T78: — | V78: =IF($M78="Owner",$R78,IF($M78<>"Yes",0,MAX(IF(LEFT($T78,7)="Passive",$R78+MAX(Cost!$B$8,ROUNDUP(Cost!$B$7*$R78,0)),$R78+Cost!$B$9),N($U78)))) -> 0 | W78: =$V78*$Q78 -> 0 | X78: https://yageogroup.com/ (RT series thin film) | Y78: Trim values: 237 k → VREF +2.1 %, 487 k +1.0 %, 243 k −2.1 %, 499 k −1.0 %; change control together with the protection VREF/3V3A window | Z78: ,R446,R447, | AA78: =IF($Z78="",0,LEN($Z78)-LEN(SUBSTITUTE($Z78,",",""))-1) -> 2 | AB78: =IF(OR($M78="Yes",$M78="Owner"),IF(COUNTIFS($H$4:$H78,$H78,$M$4:$M78,"Yes")+COUNTIFS($H$4:$H78,$H78,$M$4:$M78,"Owner")=1,1,0),0) -> 0
A79: 4 I/V converters and output legs | B79: U401, U402 | C79: 2 | D79: Op-amp, dual, output legs (U401 = L+/L−, U402 = R+/R−); EN tied to V+ | E79: OPA1622IDRCR | F79: VSON-10 3 × 3 + pad | G79: IQ 3.3 mA/ch max (25 °C), 4.2 mA/ch (-40…125 °C) | H79: TI OPA1622IDRCR | I79: C2876559 | J79: Extended | K79: JLCPCB library | L79: JLCPCB stock | M79: Yes | N79: Yes | O79: 11 | P79: 0 | Q79: 1.7871 | R79: =IF(OR($M79="Yes",$M79="Owner"),$C79*Cost!$B$6,0) -> 10 | S79: =$R79*$Q79 -> 17.871 | T79: Other: +1 | V79: =IF($M79="Owner",$R79,IF($M79<>"Yes",0,MAX(IF(LEFT($T79,7)="Passive",$R79+MAX(Cost!$B$8,ROUNDUP(Cost!$B$7*$R79,0)),$R79+Cost!$B$9),N($U79)))) -> 11 | W79: =$V79*$Q79 -> 19.6581 | X79: https://www.ti.com/lit/ds/symlink/opa1622.pdf (SBOS727B) | Z79: ,U401,U402, | AA79: =IF($Z79="",0,LEN($Z79)-LEN(SUBSTITUTE($Z79,",",""))-1) -> 2 | AB79: =IF(OR($M79="Yes",$M79="Owner"),IF(COUNTIFS($H$4:$H79,$H79,$M$4:$M79,"Yes")+COUNTIFS($H$4:$H79,$H79,$M$4:$M79,"Owner")=1,1,0),0) -> 1
A80: 4 I/V converters and output legs | B80: U403, U404 | C80: 2 | D80: Op-amp, dual, I/V converters (one amplifier per DAC pin) | E80: OPA2210IDR | F80: SOIC-8 | G80: Vos 35 µV, IQ 2.5 mA/ch max, CM (V-)+1.5…(V+)-1.5 V | H80: TI OPA2210IDR | I80: C1849415 | J80: Extended | K80: JLCPCB library | L80: LCSC 16 in stock (25 Sep 2026): buy now 11 (10 for 5 boards + attrition, no spares) into the JLCPCB private library; DigiKey 0 (1,626 due 14 Dec 2026), Mouser 0 (9,922 due 23 Nov 2026) | M80: Yes | O80: 8 | P80: 0 | Q80: 2.6708 | R80: =IF(OR($M80="Yes",$M80="Owner"),$C80*Cost!$B$6,0) -> 10 | S80: =$R80*$Q80 -> 26.708 | T80: Other: +1 | V80: =IF($M80="Owner",$R80,IF($M80<>"Yes",0,MAX(IF(LEFT($T80,7)="Passive",$R80+MAX(Cost!$B$8,ROUNDUP(Cost!$B$7*$R80,0)),$R80+Cost!$B$9),N($U80)))) -> 11 | W80: =$V80*$Q80 -> 29.3788 | X80: https://www.ti.com/lit/ds/symlink/opa2210.pdf (SBOS924H) | Y80: No compliant pin-compatible alternative: order before layout release; unit price US$ 2.6708 at the LCSC 10+ tier (US$ 3.1151 at 1+), corrected 25 Sep 2026 (was 1.0035); MSL 2 (bake) | Z80: ,U403,U404, | AA80: =IF($Z80="",0,LEN($Z80)-LEN(SUBSTITUTE($Z80,",",""))-1) -> 2 | AB80: =IF(OR($M80="Yes",$M80="Owner"),IF(COUNTIFS($H$4:$H80,$H80,$M$4:$M80,"Yes")+COUNTIFS($H$4:$H80,$H80,$M$4:$M80,"Owner")=1,1,0),0) -> 1
A81: 5 Power: domains, current limit, ±3.8 V rails, discharge | B81: C501 | C81: 1 | D81: TLV767 (U504) input capacitor on 5V_SYS, ≤ 3 mm from the U504 IN pin (U502 is fed from VBUS with C102 as its input capacitor) | E81: 1 µF | F81: 0603 | G81: 50 V X5R ±10 % | H81: Samsung CL10A105KB8NNNC | I81: C15849 | J81: Basic | K81: JLCPCB library | L81: As in Parts List v0.6 | M81: Yes | O81: 2 | P81: 0 | Q81: 0.006 | R81: =IF(OR($M81="Yes",$M81="Owner"),$C81*Cost!$B$6,0) -> 5 | S81: =$R81*$Q81 -> 0.03 | T81: Passive: +5 %, min +2 | V81: =IF($M81="Owner",$R81,IF($M81<>"Yes",0,MAX(IF(LEFT($T81,7)="Passive",$R81+MAX(Cost!$B$8,ROUNDUP(Cost!$B$7*$R81,0)),$R81+Cost!$B$9),N($U81)))) -> 7 | W81: =$V81*$Q81 -> 0.042 | X81: https://www.lcsc.com/product-detail/C15849.html | Y81: Unchanged part; serves U504 only (U502 now has C102 as its input capacitor) | Z81: ,C501, | AA81: =IF($Z81="",0,LEN($Z81)-LEN(SUBSTITUTE($Z81,",",""))-1) -> 1 | AB81: =IF(OR($M81="Yes",$M81="Owner"),IF(COUNTIFS($H$4:$H81,$H81,$M$4:$M81,"Yes")+COUNTIFS($H$4:$H81,$H81,$M$4:$M81,"Owner")=1,1,0),0) -> 0 | AC81: Samsung CL | AD81: =MID($H81,FIND("CL",$H81)+5,3) -> 105 | AE81: =IF(ISNUMBER(FIND("R",$AD81)),SUBSTITUTE($AD81,"R",".")*1,LEFT($AD81,2)*10^RIGHT($AD81,1))*10^-12 -> 1e-06 | AF81: {=LEFT($E81,FIND(" ",$E81)-1)*IFERROR(INDEX({1000,1000000,0.000000000001,0.000000001,0.000001},MATCH(MID($E81,FIND(" ",$E81)+1,1),{"k","M","p","n","µ"},0)),1)} -> 1e-06 | AG81: =IF(AND(RIGHT($E81,1)="F",ABS($AF81-$AE81)<=Checks!$C$6*$AE81),"OK","CHECK") -> OK
A82: 5 Power: domains, current limit, ±3.8 V rails, discharge | B82: C502 | C82: 1 | D82: TPS70933 output (3V3M); ≥ 2.2 µF required by TI | E82: 2.2 µF | F82: 0603 | G82: 16 V X5R ±10 % | H82: Samsung CL10A225KO8NNNC | I82: C23630 | J82: Basic | K82: JLCPCB library | L82: JLCPCB Basic | M82: Yes | O82: 2 | P82: 0 | Q82: 0.012 | R82: =IF(OR($M82="Yes",$M82="Owner"),$C82*Cost!$B$6,0) -> 5 | S82: =$R82*$Q82 -> 0.06 | T82: Passive: +5 %, min +2 | V82: =IF($M82="Owner",$R82,IF($M82<>"Yes",0,MAX(IF(LEFT($T82,7)="Passive",$R82+MAX(Cost!$B$8,ROUNDUP(Cost!$B$7*$R82,0)),$R82+Cost!$B$9),N($U82)))) -> 7 | W82: =$V82*$Q82 -> 0.084 | X82: https://www.lcsc.com/product-detail/C23630.html | Y82: Changed 1 µF → 2.2 µF (TPS70933 output capacitor) | Z82: ,C502, | AA82: =IF($Z82="",0,LEN($Z82)-LEN(SUBSTITUTE($Z82,",",""))-1) -> 1 | AB82: =IF(OR($M82="Yes",$M82="Owner"),IF(COUNTIFS($H$4:$H82,$H82,$M$4:$M82,"Yes")+COUNTIFS($H$4:$H82,$H82,$M$4:$M82,"Owner")=1,1,0),0) -> 0 | AC82: Samsung CL | AD82: =MID($H82,FIND("CL",$H82)+5,3) -> 225 | AE82: =IF(ISNUMBER(FIND("R",$AD82)),SUBSTITUTE($AD82,"R",".")*1,LEFT($AD82,2)*10^RIGHT($AD82,1))*10^-12 -> 2.2e-06 | AF82: {=LEFT($E82,FIND(" ",$E82)-1)*IFERROR(INDEX({1000,1000000,0.000000000001,0.000000001,0.000001},MATCH(MID($E82,FIND(" ",$E82)+1,1),{"k","M","p","n","µ"},0)),1)} -> 2.2e-06 | AG82: =IF(AND(RIGHT($E82,1)="F",ABS($AF82-$AE82)<=Checks!$C$6*$AE82),"OK","CHECK") -> OK
A83: 5 Power: domains, current limit, ±3.8 V rails, discharge | B83: C505 | C83: 1 | D83: TPS2596 input (0.1 µF recommended by TI) | E83: 100 nF | F83: 0402 | G83: 16 V X7R | H83: Samsung CL05B104KO5NNNC | I83: C1525 | J83: Basic | K83: JLCPCB library | L83: As in Parts List v0.6 | M83: Yes | O83: 2 | P83: 0 | Q83: 0.0045 | R83: =IF(OR($M83="Yes",$M83="Owner"),$C83*Cost!$B$6,0) -> 5 | S83: =$R83*$Q83 -> 0.0225 | T83: Passive: +5 %, min +2 | V83: =IF($M83="Owner",$R83,IF($M83<>"Yes",0,MAX(IF(LEFT($T83,7)="Passive",$R83+MAX(Cost!$B$8,ROUNDUP(Cost!$B$7*$R83,0)),$R83+Cost!$B$9),N($U83)))) -> 7 | W83: =$V83*$Q83 -> 0.0315 | X83: https://www.lcsc.com/product-detail/C1525.html | Y83: Unchanged part | Z83: ,C505, | AA83: =IF($Z83="",0,LEN($Z83)-LEN(SUBSTITUTE($Z83,",",""))-1) -> 1 | AB83: =IF(OR($M83="Yes",$M83="Owner"),IF(COUNTIFS($H$4:$H83,$H83,$M$4:$M83,"Yes")+COUNTIFS($H$4:$H83,$H83,$M$4:$M83,"Owner")=1,1,0),0) -> 0 | AC83: Samsung CL | AD83: =MID($H83,FIND("CL",$H83)+5,3) -> 104 | AE83: =IF(ISNUMBER(FIND("R",$AD83)),SUBSTITUTE($AD83,"R",".")*1,LEFT($AD83,2)*10^RIGHT($AD83,1))*10^-12 -> 1e-07 | AF83: {=LEFT($E83,FIND(" ",$E83)-1)*IFERROR(INDEX({1000,1000000,0.000000000001,0.000000001,0.000001},MATCH(MID($E83,FIND(" ",$E83)+1,1),{"k","M","p","n","µ"},0)),1)} -> 1e-07 | AG83: =IF(AND(RIGHT($E83,1)="F",ABS($AF83-$AE83)<=Checks!$C$6*$AE83),"OK","CHECK") -> OK
A84: 5 Power: domains, current limit, ±3.8 V rails, discharge | B84: C506 | C84: 1 | D84: TPS2596 output (5V_ANA) | E84: 1 µF | F84: 0603 | G84: 50 V X5R ±10 % | H84: Samsung CL10A105KB8NNNC | I84: C15849 | J84: Basic | K84: JLCPCB library | L84: As in Parts List v0.6 | M84: Yes | O84: 2 | P84: 0 | Q84: 0.006 | R84: =IF(OR($M84="Yes",$M84="Owner"),$C84*Cost!$B$6,0) -> 5 | S84: =$R84*$Q84 -> 0.03 | T84: Passive: +5 %, min +2 | V84: =IF($M84="Owner",$R84,IF($M84<>"Yes",0,MAX(IF(LEFT($T84,7)="Passive",$R84+MAX(Cost!$B$8,ROUNDUP(Cost!$B$7*$R84,0)),$R84+Cost!$B$9),N($U84)))) -> 7 | W84: =$V84*$Q84 -> 0.042 | X84: https://www.lcsc.com/product-detail/C15849.html | Y84: Unchanged | Z84: ,C506, | AA84: =IF($Z84="",0,LEN($Z84)-LEN(SUBSTITUTE($Z84,",",""))-1) -> 1 | AB84: =IF(OR($M84="Yes",$M84="Owner"),IF(COUNTIFS($H$4:$H84,$H84,$M$4:$M84,"Yes")+COUNTIFS($H$4:$H84,$H84,$M$4:$M84,"Owner")=1,1,0),0) -> 0 | AC84: Samsung CL | AD84: =MID($H84,FIND("CL",$H84)+5,3) -> 105 | AE84: =IF(ISNUMBER(FIND("R",$AD84)),SUBSTITUTE($AD84,"R",".")*1,LEFT($AD84,2)*10^RIGHT($AD84,1))*10^-12 -> 1e-06 | AF84: {=LEFT($E84,FIND(" ",$E84)-1)*IFERROR(INDEX({1000,1000000,0.000000000001,0.000000001,0.000001},MATCH(MID($E84,FIND(" ",$E84)+1,1),{"k","M","p","n","µ"},0)),1)} -> 1e-06 | AG84: =IF(AND(RIGHT($E84,1)="F",ABS($AF84-$AE84)<=Checks!$C$6*$AE84),"OK","CHECK") -> OK
A85: 5 Power: domains, current limit, ±3.8 V rails, discharge | B85: C507 | C85: 1 | D85: LM27762 VIN | E85: 10 µF | F85: 0805 | G85: 25 V X5R ±10 % | H85: Samsung CL21A106KAYNNNE | I85: C15850 | J85: Basic | K85: JLCPCB library | L85: As in Parts List v0.6 | M85: Yes | O85: 2 | P85: 0 | Q85: 0.085 | R85: =IF(OR($M85="Yes",$M85="Owner"),$C85*Cost!$B$6,0) -> 5 | S85: =$R85*$Q85 -> 0.425 | T85: Passive: +5 %, min +2 | V85: =IF($M85="Owner",$R85,IF($M85<>"Yes",0,MAX(IF(LEFT($T85,7)="Passive",$R85+MAX(Cost!$B$8,ROUNDUP(Cost!$B$7*$R85,0)),$R85+Cost!$B$9),N($U85)))) -> 7 | W85: =$V85*$Q85 -> 0.595 | X85: https://www.lcsc.com/product-detail/C15850.html | Y85: Unchanged | Z85: ,C507, | AA85: =IF($Z85="",0,LEN($Z85)-LEN(SUBSTITUTE($Z85,",",""))-1) -> 1 | AB85: =IF(OR($M85="Yes",$M85="Owner"),IF(COUNTIFS($H$4:$H85,$H85,$M$4:$M85,"Yes")+COUNTIFS($H$4:$H85,$H85,$M$4:$M85,"Owner")=1,1,0),0) -> 0 | AC85: Samsung CL | AD85: =MID($H85,FIND("CL",$H85)+5,3) -> 106 | AE85: =IF(ISNUMBER(FIND("R",$AD85)),SUBSTITUTE($AD85,"R",".")*1,LEFT($AD85,2)*10^RIGHT($AD85,1))*10^-12 -> 1e-05 | AF85: {=LEFT($E85,FIND(" ",$E85)-1)*IFERROR(INDEX({1000,1000000,0.000000000001,0.000000001,0.000001},MATCH(MID($E85,FIND(" ",$E85)+1,1),{"k","M","p","n","µ"},0)),1)} -> 1e-05 | AG85: =IF(AND(RIGHT($E85,1)="F",ABS($AF85-$AE85)<=Checks!$C$6*$AE85),"OK","CHECK") -> OK
A86: 5 Power: domains, current limit, ±3.8 V rails, discharge | B86: C508 | C86: 1 | D86: LM27762 flying capacitor C1 | E86: 1 µF | F86: 0603 | G86: 50 V X5R ±10 % | H86: Samsung CL10A105KB8NNNC | I86: C15849 | J86: Basic | K86: JLCPCB library | L86: As in Parts List v0.6 | M86: Yes | O86: 2 | P86: 0 | Q86: 0.006 | R86: =IF(OR($M86="Yes",$M86="Owner"),$C86*Cost!$B$6,0) -> 5 | S86: =$R86*$Q86 -> 0.03 | T86: Passive: +5 %, min +2 | V86: =IF($M86="Owner",$R86,IF($M86<>"Yes",0,MAX(IF(LEFT($T86,7)="Passive",$R86+MAX(Cost!$B$8,ROUNDUP(Cost!$B$7*$R86,0)),$R86+Cost!$B$9),N($U86)))) -> 7 | W86: =$V86*$Q86 -> 0.042 | X86: https://www.lcsc.com/product-detail/C15849.html | Y86: Unchanged | Z86: ,C508, | AA86: =IF($Z86="",0,LEN($Z86)-LEN(SUBSTITUTE($Z86,",",""))-1) -> 1 | AB86: =IF(OR($M86="Yes",$M86="Owner"),IF(COUNTIFS($H$4:$H86,$H86,$M$4:$M86,"Yes")+COUNTIFS($H$4:$H86,$H86,$M$4:$M86,"Owner")=1,1,0),0) -> 0 | AC86: Samsung CL | AD86: =MID($H86,FIND("CL",$H86)+5,3) -> 105 | AE86: =IF(ISNUMBER(FIND("R",$AD86)),SUBSTITUTE($AD86,"R",".")*1,LEFT($AD86,2)*10^RIGHT($AD86,1))*10^-12 -> 1e-06 | AF86: {=LEFT($E86,FIND(" ",$E86)-1)*IFERROR(INDEX({1000,1000000,0.000000000001,0.000000001,0.000001},MATCH(MID($E86,FIND(" ",$E86)+1,1),{"k","M","p","n","µ"},0)),1)} -> 1e-06 | AG86: =IF(AND(RIGHT($E86,1)="F",ABS($AF86-$AE86)<=Checks!$C$6*$AE86),"OK","CHECK") -> OK
A87: 5 Power: domains, current limit, ±3.8 V rails, discharge | B87: C509-C511 | C87: 3 | D87: LM27762 CP, OUT+ and OUT− capacitors | E87: 10 µF | F87: 0805 | G87: 25 V X5R ±10 % | H87: Samsung CL21A106KAYNNNE | I87: C15850 | J87: Basic | K87: JLCPCB library | L87: As in Parts List v0.6 | M87: Yes | O87: 2 | P87: 0 | Q87: 0.085 | R87: =IF(OR($M87="Yes",$M87="Owner"),$C87*Cost!$B$6,0) -> 15 | S87: =$R87*$Q87 -> 1.275 | T87: Passive: +5 %, min +2 | V87: =IF($M87="Owner",$R87,IF($M87<>"Yes",0,MAX(IF(LEFT($T87,7)="Passive",$R87+MAX(Cost!$B$8,ROUNDUP(Cost!$B$7*$R87,0)),$R87+Cost!$B$9),N($U87)))) -> 17 | W87: =$V87*$Q87 -> 1.445 | X87: https://www.lcsc.com/product-detail/C15850.html | Y87: Unchanged | Z87: ,C509,C510,C511, | AA87: =IF($Z87="",0,LEN($Z87)-LEN(SUBSTITUTE($Z87,",",""))-1) -> 3 | AB87: =IF(OR($M87="Yes",$M87="Owner"),IF(COUNTIFS($H$4:$H87,$H87,$M$4:$M87,"Yes")+COUNTIFS($H$4:$H87,$H87,$M$4:$M87,"Owner")=1,1,0),0) -> 0 | AC87: Samsung CL | AD87: =MID($H87,FIND("CL",$H87)+5,3) -> 106 | AE87: =IF(ISNUMBER(FIND("R",$AD87)),SUBSTITUTE($AD87,"R",".")*1,LEFT($AD87,2)*10^RIGHT($AD87,1))*10^-12 -> 1e-05 | AF87: {=LEFT($E87,FIND(" ",$E87)-1)*IFERROR(INDEX({1000,1000000,0.000000000001,0.000000001,0.000001},MATCH(MID($E87,FIND(" ",$E87)+1,1),{"k","M","p","n","µ"},0)),1)} -> 1e-05 | AG87: =IF(AND(RIGHT($E87,1)="F",ABS($AF87-$AE87)<=Checks!$C$6*$AE87),"OK","CHECK") -> OK
A88: 5 Power: domains, current limit, ±3.8 V rails, discharge | B88: C512 | C88: 1 | D88: TLV767 output (3V3D bulk; TLV767 needs 2.2…220 µF) | E88: 10 µF | F88: 0805 | G88: 25 V X5R ±10 % | H88: Samsung CL21A106KAYNNNE | I88: C15850 | J88: Basic | K88: JLCPCB library | L88: As in Parts List v0.6 | M88: Yes | O88: 2 | P88: 0 | Q88: 0.085 | R88: =IF(OR($M88="Yes",$M88="Owner"),$C88*Cost!$B$6,0) -> 5 | S88: =$R88*$Q88 -> 0.425 | T88: Passive: +5 %, min +2 | V88: =IF($M88="Owner",$R88,IF($M88<>"Yes",0,MAX(IF(LEFT($T88,7)="Passive",$R88+MAX(Cost!$B$8,ROUNDUP(Cost!$B$7*$R88,0)),$R88+Cost!$B$9),N($U88)))) -> 7 | W88: =$V88*$Q88 -> 0.595 | X88: https://www.lcsc.com/product-detail/C15850.html | Y88: Unchanged; C504 deleted | Z88: ,C512, | AA88: =IF($Z88="",0,LEN($Z88)-LEN(SUBSTITUTE($Z88,",",""))-1) -> 1 | AB88: =IF(OR($M88="Yes",$M88="Owner"),IF(COUNTIFS($H$4:$H88,$H88,$M$4:$M88,"Yes")+COUNTIFS($H$4:$H88,$H88,$M$4:$M88,"Owner")=1,1,0),0) -> 0 | AC88: Samsung CL | AD88: =MID($H88,FIND("CL",$H88)+5,3) -> 106 | AE88: =IF(ISNUMBER(FIND("R",$AD88)),SUBSTITUTE($AD88,"R",".")*1,LEFT($AD88,2)*10^RIGHT($AD88,1))*10^-12 -> 1e-05 | AF88: {=LEFT($E88,FIND(" ",$E88)-1)*IFERROR(INDEX({1000,1000000,0.000000000001,0.000000001,0.000001},MATCH(MID($E88,FIND(" ",$E88)+1,1),{"k","M","p","n","µ"},0)),1)} -> 1e-05 | AG88: =IF(AND(RIGHT($E88,1)="F",ABS($AF88-$AE88)<=Checks!$C$6*$AE88),"OK","CHECK") -> OK
A89: 5 Power: domains, current limit, ±3.8 V rails, discharge | B89: C513 | C89: 1 | D89: DNF: damping capacitor in series with R531 | E89: 10 µF | F89: 0805 | G89: 25 V X5R ±10 % | H89: Samsung CL21A106KAYNNNE | I89: C15850 | J89: Basic | K89: — (DNF) | L89: As in Parts List v0.6 | M89: No | O89: 2 | P89: 0 | Q89: 0.085 | R89: =IF(OR($M89="Yes",$M89="Owner"),$C89*Cost!$B$6,0) -> 0 | S89: =$R89*$Q89 -> 0 | T89: — | V89: =IF($M89="Owner",$R89,IF($M89<>"Yes",0,MAX(IF(LEFT($T89,7)="Passive",$R89+MAX(Cost!$B$8,ROUNDUP(Cost!$B$7*$R89,0)),$R89+Cost!$B$9),N($U89)))) -> 0 | W89: =$V89*$Q89 -> 0 | X89: https://www.lcsc.com/product-detail/C15850.html | Y89: New DNF fallback | Z89: ,C513, | AA89: =IF($Z89="",0,LEN($Z89)-LEN(SUBSTITUTE($Z89,",",""))-1) -> 1 | AB89: =IF(OR($M89="Yes",$M89="Owner"),IF(COUNTIFS($H$4:$H89,$H89,$M$4:$M89,"Yes")+COUNTIFS($H$4:$H89,$H89,$M$4:$M89,"Owner")=1,1,0),0) -> 0 | AC89: Samsung CL | AD89: =MID($H89,FIND("CL",$H89)+5,3) -> 106 | AE89: =IF(ISNUMBER(FIND("R",$AD89)),SUBSTITUTE($AD89,"R",".")*1,LEFT($AD89,2)*10^RIGHT($AD89,1))*10^-12 -> 1e-05 | AF89: {=LEFT($E89,FIND(" ",$E89)-1)*IFERROR(INDEX({1000,1000000,0.000000000001,0.000000001,0.000001},MATCH(MID($E89,FIND(" ",$E89)+1,1),{"k","M","p","n","µ"},0)),1)} -> 1e-05 | AG89: =IF(AND(RIGHT($E89,1)="F",ABS($AF89-$AE89)<=Checks!$C$6*$AE89),"OK","CHECK") -> OK
A90: 5 Power: domains, current limit, ±3.8 V rails, discharge | B90: C514 | C90: 1 | D90: TPS2596 dVdt capacitor: 5V_ANA ramp 0 → 5.5 V in 0.9–1.9 ms; with the I/V reservoirs, rails good ≤ 18.8 ms; firmware T_START = 40 ms | E90: 10 nF | F90: 0402 | G90: 50 V X7R ±10 % | H90: Samsung CL05B103KB5NNNC | I90: C15195 | J90: Basic | K90: JLCPCB library | L90: As in Parts List v0.6 | M90: Yes | O90: 2 | P90: 0 | Q90: 0.002 | R90: =IF(OR($M90="Yes",$M90="Owner"),$C90*Cost!$B$6,0) -> 5 | S90: =$R90*$Q90 -> 0.01 | T90: Passive: +5 %, min +2 | V90: =IF($M90="Owner",$R90,IF($M90<>"Yes",0,MAX(IF(LEFT($T90,7)="Passive",$R90+MAX(Cost!$B$8,ROUNDUP(Cost!$B$7*$R90,0)),$R90+Cost!$B$9),N($U90)))) -> 7 | W90: =$V90*$Q90 -> 0.014 | X90: https://www.lcsc.com/product-detail/C15195.html | Y90: New; 10 nF kept (the 470 nF option was reverted) | Z90: ,C514, | AA90: =IF($Z90="",0,LEN($Z90)-LEN(SUBSTITUTE($Z90,",",""))-1) -> 1 | AB90: =IF(OR($M90="Yes",$M90="Owner"),IF(COUNTIFS($H$4:$H90,$H90,$M$4:$M90,"Yes")+COUNTIFS($H$4:$H90,$H90,$M$4:$M90,"Owner")=1,1,0),0) -> 0 | AC90: Samsung CL | AD90: =MID($H90,FIND("CL",$H90)+5,3) -> 103 | AE90: =IF(ISNUMBER(FIND("R",$AD90)),SUBSTITUTE($AD90,"R",".")*1,LEFT($AD90,2)*10^RIGHT($AD90,1))*10^-12 -> 1e-08 | AF90: {=LEFT($E90,FIND(" ",$E90)-1)*IFERROR(INDEX({1000,1000000,0.000000000001,0.000000001,0.000001},MATCH(MID($E90,FIND(" ",$E90)+1,1),{"k","M","p","n","µ"},0)),1)} -> 1e-08 | AG90: =IF(AND(RIGHT($E90,1)="F",ABS($AF90-$AE90)<=Checks!$C$6*$AE90),"OK","CHECK") -> OK
A91: 5 Power: domains, current limit, ±3.8 V rails, discharge | B91: C515 | C91: 1 | D91: U505 VDD decoupling (0.1-10 µF required) | E91: 100 nF | F91: 0402 | G91: 16 V X7R | H91: Samsung CL05B104KO5NNNC | I91: C1525 | J91: Basic | K91: JLCPCB library | L91: As in Parts List v0.6 | M91: Yes | O91: 2 | P91: 0 | Q91: 0.0045 | R91: =IF(OR($M91="Yes",$M91="Owner"),$C91*Cost!$B$6,0) -> 5 | S91: =$R91*$Q91 -> 0.0225 | T91: Passive: +5 %, min +2 | V91: =IF($M91="Owner",$R91,IF($M91<>"Yes",0,MAX(IF(LEFT($T91,7)="Passive",$R91+MAX(Cost!$B$8,ROUNDUP(Cost!$B$7*$R91,0)),$R91+Cost!$B$9),N($U91)))) -> 7 | W91: =$V91*$Q91 -> 0.0315 | X91: https://www.lcsc.com/product-detail/C1525.html | Y91: New | Z91: ,C515, | AA91: =IF($Z91="",0,LEN($Z91)-LEN(SUBSTITUTE($Z91,",",""))-1) -> 1 | AB91: =IF(OR($M91="Yes",$M91="Owner"),IF(COUNTIFS($H$4:$H91,$H91,$M$4:$M91,"Yes")+COUNTIFS($H$4:$H91,$H91,$M$4:$M91,"Owner")=1,1,0),0) -> 0 | AC91: Samsung CL | AD91: =MID($H91,FIND("CL",$H91)+5,3) -> 104 | AE91: =IF(ISNUMBER(FIND("R",$AD91)),SUBSTITUTE($AD91,"R",".")*1,LEFT($AD91,2)*10^RIGHT($AD91,1))*10^-12 -> 1e-07 | AF91: {=LEFT($E91,FIND(" ",$E91)-1)*IFERROR(INDEX({1000,1000000,0.000000000001,0.000000001,0.000001},MATCH(MID($E91,FIND(" ",$E91)+1,1),{"k","M","p","n","µ"},0)),1)} -> 1e-07 | AG91: =IF(AND(RIGHT($E91,1)="F",ABS($AF91-$AE91)<=Checks!$C$6*$AE91),"OK","CHECK") -> OK
A92: 5 Power: domains, current limit, ±3.8 V rails, discharge | B92: C516 | C92: 1 | D92: ANA_SENSE ADC input capacitor at PA0 | E92: 100 pF | F92: 0402 | G92: 50 V C0G ±5 % | H92: Samsung CL05C101JB5NNNC | I92: C1546 | J92: Basic | K92: JLCPCB library | L92: JLCPCB Basic | M92: Yes | O92: 2 | P92: 0 | Q92: 0.002 | R92: =IF(OR($M92="Yes",$M92="Owner"),$C92*Cost!$B$6,0) -> 5 | S92: =$R92*$Q92 -> 0.01 | T92: Passive: +5 %, min +2 | V92: =IF($M92="Owner",$R92,IF($M92<>"Yes",0,MAX(IF(LEFT($T92,7)="Passive",$R92+MAX(Cost!$B$8,ROUNDUP(Cost!$B$7*$R92,0)),$R92+Cost!$B$9),N($U92)))) -> 7 | W92: =$V92*$Q92 -> 0.014 | X92: https://www.lcsc.com/product-detail/C1546.html | Y92: New; place at the MCU PA0 pin | Z92: ,C516, | AA92: =IF($Z92="",0,LEN($Z92)-LEN(SUBSTITUTE($Z92,",",""))-1) -> 1 | AB92: =IF(OR($M92="Yes",$M92="Owner"),IF(COUNTIFS($H$4:$H92,$H92,$M$4:$M92,"Yes")+COUNTIFS($H$4:$H92,$H92,$M$4:$M92,"Owner")=1,1,0),0) -> 0 | AC92: Samsung CL | AD92: =MID($H92,FIND("CL",$H92)+5,3) -> 101 | AE92: =IF(ISNUMBER(FIND("R",$AD92)),SUBSTITUTE($AD92,"R",".")*1,LEFT($AD92,2)*10^RIGHT($AD92,1))*10^-12 -> 1e-10 | AF92: {=LEFT($E92,FIND(" ",$E92)-1)*IFERROR(INDEX({1000,1000000,0.000000000001,0.000000001,0.000001},MATCH(MID($E92,FIND(" ",$E92)+1,1),{"k","M","p","n","µ"},0)),1)} -> 1e-10 | AG92: =IF(AND(RIGHT($E92,1)="F",ABS($AF92-$AE92)<=Checks!$C$6*$AE92),"OK","CHECK") -> OK
A93: 5 Power: domains, current limit, ±3.8 V rails, discharge | B93: D104, D105 | C93: 2 | D93: Schottky OUT → IN reverse-voltage clamps: D104 across U302 (3V3A → 5V_SYS), D105 across U503 (5V_ANA → 5V_SYS); D103 deleted (the TPS70933 blocks reverse current) | E93: — | F93: SOT-23 (pin 1 A, 2 NC, 3 K) | G93: 30 V, 200 mA, VF ≤ 0.24/0.32/0.40/0.50/0.80 V at 0.1/1/10/30/100 mA, IR ≤ 2 µA at 25 V (25 °C), Cd ≤ 10 pF | H93: Nexperia BAT54,215 | I93: C85084 | J93: Extended | K93: JLCPCB library | L93: LCSC C85084 (same part as D413/D414) | M93: Yes | O93: 3 | P93: 0 | Q93: 0.02 | R93: =IF(OR($M93="Yes",$M93="Owner"),$C93*Cost!$B$6,0) -> 10 | S93: =$R93*$Q93 -> 0.2 | T93: Other: +1 | V93: =IF($M93="Owner",$R93,IF($M93<>"Yes",0,MAX(IF(LEFT($T93,7)="Passive",$R93+MAX(Cost!$B$8,ROUNDUP(Cost!$B$7*$R93,0)),$R93+Cost!$B$9),N($U93)))) -> 11 | W93: =$V93*$Q93 -> 0.22 | X93: https://assets.nexperia.com/documents/data-sheet/BAT54_SER.pdf | Y93: Anode on the regulator OUT, cathode on its IN; each ≤ 3 mm from its regulator; D103 removed with the suspend power cut | Z93: ,D104,D105, | AA93: =IF($Z93="",0,LEN($Z93)-LEN(SUBSTITUTE($Z93,",",""))-1) -> 2 | AB93: =IF(OR($M93="Yes",$M93="Owner"),IF(COUNTIFS($H$4:$H93,$H93,$M$4:$M93,"Yes")+COUNTIFS($H$4:$H93,$H93,$M$4:$M93,"Owner")=1,1,0),0) -> 0
A94: 5 Power: domains, current limit, ±3.8 V rails, discharge | B94: FB501 | C94: 1 | D94: Ferrite 5V_ANA → 5V_ANA_F (LM27762 VIN) | E94: 120 Ω @ 100 MHz | F94: 0603 | G94: 2 A, 50 mΩ max | H94: Murata BLM18PG121SN1D | I94: C14709 | J94: Basic | K94: JLCPCB library | L94: As in Parts List v0.6 | M94: Yes | O94: 2 | P94: 0 | Q94: 0.0157 | R94: =IF(OR($M94="Yes",$M94="Owner"),$C94*Cost!$B$6,0) -> 5 | S94: =$R94*$Q94 -> 0.0785 | T94: Passive: +5 %, min +2 | V94: =IF($M94="Owner",$R94,IF($M94<>"Yes",0,MAX(IF(LEFT($T94,7)="Passive",$R94+MAX(Cost!$B$8,ROUNDUP(Cost!$B$7*$R94,0)),$R94+Cost!$B$9),N($U94)))) -> 7 | W94: =$V94*$Q94 -> 0.1099 | X94: https://www.lcsc.com/product-detail/C14709.html | Y94: Unchanged | Z94: ,FB501, | AA94: =IF($Z94="",0,LEN($Z94)-LEN(SUBSTITUTE($Z94,",",""))-1) -> 1 | AB94: =IF(OR($M94="Yes",$M94="Owner"),IF(COUNTIFS($H$4:$H94,$H94,$M$4:$M94,"Yes")+COUNTIFS($H$4:$H94,$H94,$M$4:$M94,"Owner")=1,1,0),0) -> 1
A95: 5 Power: domains, current limit, ±3.8 V rails, discharge | B95: Q502-Q506 | C95: 5 | D95: N-MOSFETs of the EN-derived discharge: Q502/Q504 inverters (gate AVCC_EN / AUD_EN), Q503/Q505/Q506 discharge 3V3A/3V3D/1V3 | E95: AO3400A | F95: SOT-23 | G95: 30 V, VGS(th) 0.65-1.45 V, Rds(on) ≤ 48 mΩ at 2.5 V | H95: AOS AO3400A | I95: C20917 | J95: Basic | K95: JLCPCB library | L95: JLCPCB 723,732 (Sep 2026) | M95: Yes | O95: 3 | P95: 0 | Q95: 0.0853 | R95: =IF(OR($M95="Yes",$M95="Owner"),$C95*Cost!$B$6,0) -> 25 | S95: =$R95*$Q95 -> 2.1325 | T95: Other: +1 | V95: =IF($M95="Owner",$R95,IF($M95<>"Yes",0,MAX(IF(LEFT($T95,7)="Passive",$R95+MAX(Cost!$B$8,ROUNDUP(Cost!$B$7*$R95,0)),$R95+Cost!$B$9),N($U95)))) -> 26 | W95: =$V95*$Q95 -> 2.2178 | X95: https://www.aosmd.com/res/datasheets/AO3400A.pdf | Y95: Q506/R530 kept (the TLV758P internal 95 Ω pull-down is typical only) | Z95: ,Q502,Q503,Q504,Q505,Q506, | AA95: =IF($Z95="",0,LEN($Z95)-LEN(SUBSTITUTE($Z95,",",""))-1) -> 5 | AB95: =IF(OR($M95="Yes",$M95="Owner"),IF(COUNTIFS($H$4:$H95,$H95,$M$4:$M95,"Yes")+COUNTIFS($H$4:$H95,$H95,$M$4:$M95,"Owner")=1,1,0),0) -> 0
A96: 5 Power: domains, current limit, ±3.8 V rails, discharge | B96: Q507 | C96: 1 | D96: NPN pulling the U102 EN low in Stop (suspend power cut): collector on N1_U102_EN, emitter to GND; the off-state leakage keeps EN ≥ 3.18 V at VBUS 4.40 V and 50 °C (+1.28 V above the 1.9 V turn-on threshold; hot leakage extrapolated from the 25 °C datasheet maximum — engineering estimate) | E96: MMBT3904 | F96: SOT-23 | G96: 40 V, 200 mA, hFE 100-300 | H96: JSCJ MMBT3904 (RANGE:100-300) | I96: C20526 | J96: Basic | K96: JLCPCB library | L96: LCSC 25,800 (same part as Q612/Q614) | M96: Yes | O96: 3 | P96: 0 | Q96: 0.0104 | R96: =IF(OR($M96="Yes",$M96="Owner"),$C96*Cost!$B$6,0) -> 5 | S96: =$R96*$Q96 -> 0.052 | T96: Other: +1 | V96: =IF($M96="Owner",$R96,IF($M96<>"Yes",0,MAX(IF(LEFT($T96,7)="Passive",$R96+MAX(Cost!$B$8,ROUNDUP(Cost!$B$7*$R96,0)),$R96+Cost!$B$9),N($U96)))) -> 6 | W96: =$V96*$Q96 -> 0.0624 | X96: https://www.lcsc.com/product-detail/C20526.html | Y96: New (suspend power cut); placed beside C104 at U102 pin 4, emitter via at the pad; R537 (series from PC14) and R538 (base–emitter) at the transistor; pin 1 B, 2 E, 3 C | Z96: ,Q507, | AA96: =IF($Z96="",0,LEN($Z96)-LEN(SUBSTITUTE($Z96,",",""))-1) -> 1 | AB96: =IF(OR($M96="Yes",$M96="Owner"),IF(COUNTIFS($H$4:$H96,$H96,$M$4:$M96,"Yes")+COUNTIFS($H$4:$H96,$H96,$M$4:$M96,"Owner")=1,1,0),0) -> 1
A97: 5 Power: domains, current limit, ±3.8 V rails, discharge | B97: R501 | C97: 1 | D97: LM27762 FB+ top, single resistor (VPOS 3.789/3.852/3.915 V with R502) | E97: 221 kΩ | F97: 0603 | G97: 0.1 %, 25 ppm/°C, thin film | H97: YAGEO RT0603BRD07221KL | I97: C705748 | J97: Extended (not verified) | K97: JLCPCB library | L97: LCSC 4,260 (Feb 2026) | M97: Yes | O97: 2 | P97: 0 | Q97: 0.0254 | R97: =IF(OR($M97="Yes",$M97="Owner"),$C97*Cost!$B$6,0) -> 5 | S97: =$R97*$Q97 -> 0.127 | T97: Passive: +5 %, min +2 | V97: =IF($M97="Owner",$R97,IF($M97<>"Yes",0,MAX(IF(LEFT($T97,7)="Passive",$R97+MAX(Cost!$B$8,ROUNDUP(Cost!$B$7*$R97,0)),$R97+Cost!$B$9),N($U97)))) -> 7 | W97: =$V97*$Q97 -> 0.1778 | X97: https://www.lcsc.com/product-detail/C705748.html | Y97: Changed (was 100k + 100k + 15k + 10k); R515/R516/R523 deleted; 215 k for a 3.78 V option; bring-up fallback 232 k (VPOS 3.919/3.984/4.049 V) — fit only together with R672 237 k → 243 k and a re-check of the protection thresholds | Z97: ,R501, | AA97: =IF($Z97="",0,LEN($Z97)-LEN(SUBSTITUTE($Z97,",",""))-1) -> 1 | AB97: =IF(OR($M97="Yes",$M97="Owner"),IF(COUNTIFS($H$4:$H97,$H97,$M$4:$M97,"Yes")+COUNTIFS($H$4:$H97,$H97,$M$4:$M97,"Owner")=1,1,0),0) -> 1 | AC97: YAGEO | AD97: =MID($H97,18,FIND("L",$H97,18)-18) -> 221K | AE97: =(SUBSTITUTE(SUBSTITUTE(SUBSTITUTE($AD97,"R","."),"K","."),"M",".")&"0")*IF(ISNUMBER(FIND("K",$AD97)),1000,IF(ISNUMBER(FIND("M",$AD97)),10^6,1)) -> 221000 | AF97: {=LEFT($E97,FIND(" ",$E97)-1)*IFERROR(INDEX({1000,1000000,0.000000000001,0.000000001,0.000001},MATCH(MID($E97,FIND(" ",$E97)+1,1),{"k","M","p","n","µ"},0)),1)} -> 221000 | AG97: =IF(AND(RIGHT($E97,1)="Ω",ABS($AF97-$AE97)<=Checks!$C$6*$AE97),"OK","CHECK") -> OK
A98: 5 Power: domains, current limit, ±3.8 V rails, discharge | B98: R502, R504 | C98: 2 | D98: LM27762 FB+ / FB- bottom (≥ 50 k per TI) | E98: 100 kΩ | F98: 0603 | G98: 0.1 %, 25 ppm/°C, thin film | H98: YAGEO RT0603BRD07100KL | I98: C122538 | J98: Extended (not verified) | K98: JLCPCB library | L98: LCSC 254,300 (Mar 2026) | M98: Yes | O98: 2 | P98: 0 | Q98: 0.0223 | R98: =IF(OR($M98="Yes",$M98="Owner"),$C98*Cost!$B$6,0) -> 10 | S98: =$R98*$Q98 -> 0.223 | T98: Passive: +5 %, min +2 | V98: =IF($M98="Owner",$R98,IF($M98<>"Yes",0,MAX(IF(LEFT($T98,7)="Passive",$R98+MAX(Cost!$B$8,ROUNDUP(Cost!$B$7*$R98,0)),$R98+Cost!$B$9),N($U98)))) -> 12 | W98: =$V98*$Q98 -> 0.2676 | X98: https://www.lcsc.com/product-detail/C122538.html | Y98: Changed to 0.1 % thin film | Z98: ,R502,R504, | AA98: =IF($Z98="",0,LEN($Z98)-LEN(SUBSTITUTE($Z98,",",""))-1) -> 2 | AB98: =IF(OR($M98="Yes",$M98="Owner"),IF(COUNTIFS($H$4:$H98,$H98,$M$4:$M98,"Yes")+COUNTIFS($H$4:$H98,$H98,$M$4:$M98,"Owner")=1,1,0),0) -> 1 | AC98: YAGEO | AD98: =MID($H98,18,FIND("L",$H98,18)-18) -> 100K | AE98: =(SUBSTITUTE(SUBSTITUTE(SUBSTITUTE($AD98,"R","."),"K","."),"M",".")&"0")*IF(ISNUMBER(FIND("K",$AD98)),1000,IF(ISNUMBER(FIND("M",$AD98)),10^6,1)) -> 100000 | AF98: {=LEFT($E98,FIND(" ",$E98)-1)*IFERROR(INDEX({1000,1000000,0.000000000001,0.000000001,0.000001},MATCH(MID($E98,FIND(" ",$E98)+1,1),{"k","M","p","n","µ"},0)),1)} -> 100000 | AG98: =IF(AND(RIGHT($E98,1)="Ω",ABS($AF98-$AE98)<=Checks!$C$6*$AE98),"OK","CHECK") -> OK
A99: 5 Power: domains, current limit, ±3.8 V rails, discharge | B99: R503 | C99: 1 | D99: LM27762 FB- top, single resistor (|VNEG| 3.661/3.721/3.781 V with R504) | E99: 205 kΩ | F99: 0603 | G99: 0.1 %, 25 ppm/°C, thin film | H99: YAGEO RT0603BRD07205KL | I99: C861217 | J99: Extended (not verified) | K99: JLCPCB library | L99: LCSC 900 (Jul 2026) — low stock: order early or JLCPCB global sourcing | M99: Yes | O99: 2 | P99: 0 | Q99: 0.0316 | R99: =IF(OR($M99="Yes",$M99="Owner"),$C99*Cost!$B$6,0) -> 5 | S99: =$R99*$Q99 -> 0.158 | T99: Passive: +5 %, min +2 | V99: =IF($M99="Owner",$R99,IF($M99<>"Yes",0,MAX(IF(LEFT($T99,7)="Passive",$R99+MAX(Cost!$B$8,ROUNDUP(Cost!$B$7*$R99,0)),$R99+Cost!$B$9),N($U99)))) -> 7 | W99: =$V99*$Q99 -> 0.2212 | X99: https://www.lcsc.com/product-detail/C861217.html | Y99: Changed (was 100k + 100k + 5.1k); R517/R518 deleted | Z99: ,R503, | AA99: =IF($Z99="",0,LEN($Z99)-LEN(SUBSTITUTE($Z99,",",""))-1) -> 1 | AB99: =IF(OR($M99="Yes",$M99="Owner"),IF(COUNTIFS($H$4:$H99,$H99,$M$4:$M99,"Yes")+COUNTIFS($H$4:$H99,$H99,$M$4:$M99,"Owner")=1,1,0),0) -> 1 | AC99: YAGEO | AD99: =MID($H99,18,FIND("L",$H99,18)-18) -> 205K | AE99: =(SUBSTITUTE(SUBSTITUTE(SUBSTITUTE($AD99,"R","."),"K","."),"M",".")&"0")*IF(ISNUMBER(FIND("K",$AD99)),1000,IF(ISNUMBER(FIND("M",$AD99)),10^6,1)) -> 205000 | AF99: {=LEFT($E99,FIND(" ",$E99)-1)*IFERROR(INDEX({1000,1000000,0.000000000001,0.000000001,0.000001},MATCH(MID($E99,FIND(" ",$E99)+1,1),{"k","M","p","n","µ"},0)),1)} -> 205000 | AG99: =IF(AND(RIGHT($E99,1)="Ω",ABS($AF99-$AE99)<=Checks!$C$6*$AE99),"OK","CHECK") -> OK
A100: 5 Power: domains, current limit, ±3.8 V rails, discharge | B100: R505 | C100: 1 | D100: PGOOD pull-up to 5V_ANA_F (LM27762 VIN, as TI specifies) | E100: 100 kΩ | F100: 0402 | G100: 1 % | H100: UNI-ROYAL 0402WGF1003TCE | I100: C25741 | J100: Basic | K100: JLCPCB library | L100: As in Parts List v0.6 | M100: Yes | O100: 2 | P100: 0 | Q100: 0.0033 | R100: =IF(OR($M100="Yes",$M100="Owner"),$C100*Cost!$B$6,0) -> 5 | S100: =$R100*$Q100 -> 0.0165 | T100: Passive: +5 %, min +2 | V100: =IF($M100="Owner",$R100,IF($M100<>"Yes",0,MAX(IF(LEFT($T100,7)="Passive",$R100+MAX(Cost!$B$8,ROUNDUP(Cost!$B$7*$R100,0)),$R100+Cost!$B$9),N($U100)))) -> 7 | W100: =$V100*$Q100 -> 0.0231 | X100: https://www.lcsc.com/product-detail/C25741.html | Y100: Changed 10 k → 100 k (no latch timing need) | Z100: ,R505, | AA100: =IF($Z100="",0,LEN($Z100)-LEN(SUBSTITUTE($Z100,",",""))-1) -> 1 | AB100: =IF(OR($M100="Yes",$M100="Owner"),IF(COUNTIFS($H$4:$H100,$H100,$M$4:$M100,"Yes")+COUNTIFS($H$4:$H100,$H100,$M$4:$M100,"Owner")=1,1,0),0) -> 0 | AC100: UNI-ROYAL | AD100: =MID($H100,18,4) -> 1003 | AE100: =LEFT($AD100,3)*IF(ISNUMBER(--RIGHT($AD100,1)),10^RIGHT($AD100,1),10^(0-FIND(RIGHT($AD100,1),"JKLM"))) -> 100000 | AF100: {=LEFT($E100,FIND(" ",$E100)-1)*IFERROR(INDEX({1000,1000000,0.000000000001,0.000000001,0.000001},MATCH(MID($E100,FIND(" ",$E100)+1,1),{"k","M","p","n","µ"},0)),1)} -> 100000 | AG100: =IF(AND(RIGHT($E100,1)="Ω",ABS($AF100-$AE100)<=Checks!$C$6*$AE100),"OK","CHECK") -> OK
...

Sheet Purchasing list
A1: Purchasing list — JLCPCB order (one line per part number) and the two owner orders
A2: JLCPCB order: quantities and costs summed from the Parts list by part number for the lines placed by JLCPCB (Fit = Yes): exact 5-board quantity plus attrition, no spares. JLCPCB-placed parts follow JLCPCB's minimums (a pre-ordered line buys at least its order quantity as costed); LCSC minimums and multiples apply only to the owner's LCSC order. Column Q checks both. Buy now = order before layout release into the JLCPCB private parts library; Pre-order = order early from LCSC stock. Owner orders: the owner-fitted parts (which double as samples for the pre-layout checks) and the other gate samples, bought by the owner from DigiKey and LCSC.
A3: Item | B3: Part type | C3: Part number (MPN) | D3: Value | E3: Package | F3: LCSC no. | G3: JLCPCB class | H3: Source | I3: Designators | J3: Qty per board | K3: Qty for 5 boards | L3: Qty to order (5 boards + attrition) | M3: Attrition | N3: Order rule | O3: LCSC minimum (input) | P3: LCSC multiple (input) | Q3: Order-rule check | R3: Unit price US$ | S3: Line cost US$ | T3: Buy now | U3: Reason / sourcing | V3: Notes
A4: 1 | B4: Capacitor | C4: Samsung CL21A225KAFNNNE | D4: 2.2 µF | E4: 0805 | F4: C87994 | G4: Extended | H4: JLCPCB library | I4: C102 | J4: =SUMIFS('Parts list'!$C$4:$C$185,'Parts list'!$H$4:$H$185,$C4,'Parts list'!$M$4:$M$185,"Yes") -> 1 | K4: =SUMIFS('Parts list'!$R$4:$R$185,'Parts list'!$H$4:$H$185,$C4,'Parts list'!$M$4:$M$185,"Yes") -> 5 | L4: =SUMIFS('Parts list'!$V$4:$V$185,'Parts list'!$H$4:$H$185,$C4,'Parts list'!$M$4:$M$185,"Yes") -> 7 | M4: =$L4-$K4 -> 2 | N4: JLCPCB stock, per piece | Q4: =IF(N($O4)=0,"per piece",IF(AND($L4>=$O4,MOD($L4,MAX(1,N($P4)))=0),"OK","CHECK")) -> per piece | R4: =IF($L4=0,0,$S4/$L4) -> 0.02 | S4: =SUMIFS('Parts list'!$W$4:$W$185,'Parts list'!$H$4:$H$185,$C4,'Parts list'!$M$4:$M$185,"Yes") -> 0.14 | U4: At PCBA order: exact quantity + attrition
A5: 2 | B5: Capacitor | C5: Samsung CL05C101JB5NNNC | D5: 100 pF | E5: 0402 | F5: C1546 | G5: Basic | H5: JLCPCB library | I5: C103, C516, C624 | J5: =SUMIFS('Parts list'!$C$4:$C$185,'Parts list'!$H$4:$H$185,$C5,'Parts list'!$M$4:$M$185,"Yes") -> 3 | K5: =SUMIFS('Parts list'!$R$4:$R$185,'Parts list'!$H$4:$H$185,$C5,'Parts list'!$M$4:$M$185,"Yes") -> 15 | L5: =SUMIFS('Parts list'!$V$4:$V$185,'Parts list'!$H$4:$H$185,$C5,'Parts list'!$M$4:$M$185,"Yes") -> 21 | M5: =$L5-$K5 -> 6 | N5: JLCPCB stock, per piece | Q5: =IF(N($O5)=0,"per piece",IF(AND($L5>=$O5,MOD($L5,MAX(1,N($P5)))=0),"OK","CHECK")) -> per piece | R5: =IF($L5=0,0,$S5/$L5) -> 0.002 | S5: =SUMIFS('Parts list'!$W$4:$W$185,'Parts list'!$H$4:$H$185,$C5,'Parts list'!$M$4:$M$185,"Yes") -> 0.042 | U5: At PCBA order: exact quantity + attrition
A6: 3 | B6: Capacitor | C6: Samsung CL05B104KO5NNNC | D6: 100 nF | E6: 0402 | F6: C1525 | G6: Basic | H6: JLCPCB library | I6: C104, C203-C210, C212-C215, C218, C219, C222-C224, C305-C309, C409-C412, C423-C426, C505, C515, C618, C619, C622, C623, C626-C628, C630, C635-C638, C655-C666 | J6: =SUMIFS('Parts list'!$C$4:$C$185,'Parts list'!$H$4:$H$185,$C6,'Parts list'!$M$4:$M$185,"Yes") -> 57 | K6: =SUMIFS('Parts list'!$R$4:$R$185,'Parts list'!$H$4:$H$185,$C6,'Parts list'!$M$4:$M$185,"Yes") -> 285 | L6: =SUMIFS('Parts list'!$V$4:$V$185,'Parts list'!$H$4:$H$185,$C6,'Parts list'!$M$4:$M$185,"Yes") -> 308 | M6: =$L6-$K6 -> 23 | N6: JLCPCB stock, per piece | Q6: =IF(N($O6)=0,"per piece",IF(AND($L6>=$O6,MOD($L6,MAX(1,N($P6)))=0),"OK","CHECK")) -> per piece | R6: =IF($L6=0,0,$S6/$L6) -> 0.0031090909 | S6: =SUMIFS('Parts list'!$W$4:$W$185,'Parts list'!$H$4:$H$185,$C6,'Parts list'!$M$4:$M$185,"Yes") -> 0.9576 | U6: At PCBA order: exact quantity + attrition | V6: Unit price differs between BOM lines (US$ 0.0011 / 0.0045); the line cost uses each line's price, the unit price shown is the average
A7: 4 | B7: Connector | C7: GCT USB4105-GF-A | D7: — | E7: SMD horizontal top mount, 0.95 mm shell stakes | F7: C3020560 | G7: Extended | H7: Global sourcing | I7: J101 | J7: =SUMIFS('Parts list'!$C$4:$C$185,'Parts list'!$H$4:$H$185,$C7,'Parts list'!$M$4:$M$185,"Yes") -> 1 | K7: =SUMIFS('Parts list'!$R$4:$R$185,'Parts list'!$H$4:$H$185,$C7,'Parts list'!$M$4:$M$185,"Yes") -> 5 | L7: =SUMIFS('Parts list'!$V$4:$V$185,'Parts list'!$H$4:$H$185,$C7,'Parts list'!$M$4:$M$185,"Yes") -> 6 | M7: =$L7-$K7 -> 1 | N7: Global sourcing via JLCPCB, per piece | Q7: =IF(N($O7)=0,"per piece",IF(AND($L7>=$O7,MOD($L7,MAX(1,N($P7)))=0),"OK","CHECK")) -> per piece | R7: =IF($L7=0,0,$S7/$L7) -> 1.09 | S7: =SUMIFS('Parts list'!$W$4:$W$185,'Parts list'!$H$4:$H$185,$C7,'Parts list'!$M$4:$M$185,"Yes") -> 6.54 | U7: Global sourcing, bought with the PCBA order
A8: 5 | B8: Resistor | C8: UNI-ROYAL 0402WGF5101TCE | D8: 5.1 kΩ | E8: 0402 | F8: C25905 | G8: Basic | H8: JLCPCB library | I8: R101, R102 | J8: =SUMIFS('Parts list'!$C$4:$C$185,'Parts list'!$H$4:$H$185,$C8,'Parts list'!$M$4:$M$185,"Yes") -> 2 | K8: =SUMIFS('Parts list'!$R$4:$R$185,'Parts list'!$H$4:$H$185,$C8,'Parts list'!$M$4:$M$185,"Yes") -> 10 | L8: =SUMIFS('Parts list'!$V$4:$V$185,'Parts list'!$H$4:$H$185,$C8,'Parts list'!$M$4:$M$185,"Yes") -> 12 | M8: =$L8-$K8 -> 2 | N8: JLCPCB stock, per piece | Q8: =IF(N($O8)=0,"per piece",IF(AND($L8>=$O8,MOD($L8,MAX(1,N($P8)))=0),"OK","CHECK")) -> per piece | R8: =IF($L8=0,0,$S8/$L8) -> 0.002 | S8: =SUMIFS('Parts list'!$W$4:$W$185,'Parts list'!$H$4:$H$185,$C8,'Parts list'!$M$4:$M$185,"Yes") -> 0.024 | U8: At PCBA order: exact quantity + attrition
A9: 6 | B9: Resistor | C9: UNI-ROYAL 0402WGF1002TCE | D9: 10 kΩ | E9: 0402 | F9: C25744 | G9: Basic | H9: JLCPCB library | I9: R103, R104, R201, R202, R207, R208, R212, R213, R216-R218, R227, R231, R232, R234, R236, R238, R239, R305, R508, R522, R951 | J9: =SUMIFS('Parts list'!$C$4:$C$185,'Parts list'!$H$4:$H$185,$C9,'Parts list'!$M$4:$M$185,"Yes") -> 22 | K9: =SUMIFS('Parts list'!$R$4:$R$185,'Parts list'!$H$4:$H$185,$C9,'Parts list'!$M$4:$M$185,"Yes") -> 110 | L9: =SUMIFS('Parts list'!$V$4:$V$185,'Parts list'!$H$4:$H$185,$C9,'Parts list'!$M$4:$M$185,"Yes") -> 124 | M9: =$L9-$K9 -> 14 | N9: JLCPCB stock, per piece | Q9: =IF(N($O9)=0,"per piece",IF(AND($L9>=$O9,MOD($L9,MAX(1,N($P9)))=0),"OK","CHECK")) -> per piece | R9: =IF($L9=0,0,$S9/$L9) -> 0.0019887097 | S9: =SUMIFS('Parts list'!$W$4:$W$185,'Parts list'!$H$4:$H$185,$C9,'Parts list'!$M$4:$M$185,"Yes") -> 0.2466 | U9: At PCBA order: exact quantity + attrition | V9: Unit price differs between BOM lines (US$ 0.0005 / 0.002 / 0.0033); the line cost uses each line's price, the unit price shown is the average
A10: 7 | B10: Resistor | C10: UNI-ROYAL 0402WGF1003TCE | D10: 100 kΩ | E10: 0402 | F10: C25741 | G10: Basic | H10: JLCPCB library | I10: R105, R108, R235, R240, R303, R505, R511, R512, R513, R535, R537, R538, R646-R648, R667, R669, R680, R687, R691, R693, R695, R696, R939, R950 | J10: =SUMIFS('Parts list'!$C$4:$C$185,'Parts list'!$H$4:$H$185,$C10,'Parts list'!$M$4:$M$185,"Yes") -> 25 | K10: =SUMIFS('Parts list'!$R$4:$R$185,'Parts list'!$H$4:$H$185,$C10,'Parts list'!$M$4:$M$185,"Yes") -> 125 | L10: =SUMIFS('Parts list'!$V$4:$V$185,'Parts list'!$H$4:$H$185,$C10,'Parts list'!$M$4:$M$185,"Yes") -> 151 | M10: =$L10-$K10 -> 26 | N10: JLCPCB stock, per piece | Q10: =IF(N($O10)=0,"per piece",IF(AND($L10>=$O10,MOD($L10,MAX(1,N($P10)))=0),"OK","CHECK")) -> per piece | R10: =IF($L10=0,0,$S10/$L10) -> 0.0019172185 | S10: =SUMIFS('Parts list'!$W$4:$W$185,'Parts list'!$H$4:$H$185,$C10,'Parts list'!$M$4:$M$185,"Yes") -> 0.2895 | U10: At PCBA order: exact quantity + attrition | V10: Unit price differs between BOM lines (US$ 0.0005 / 0.002 / 0.0033); the line cost uses each line's price, the unit price shown is the average
A11: 8 | B11: Resistor | C11: UNI-ROYAL 0402WGF4702TCE | D11: 47 kΩ | E11: 0402 | F11: C25792 | G11: Basic | H11: JLCPCB library | I11: R106, R536 | J11: =SUMIFS('Parts list'!$C$4:$C$185,'Parts list'!$H$4:$H$185,$C11,'Parts list'!$M$4:$M$185,"Yes") -> 2 | K11: =SUMIFS('Parts list'!$R$4:$R$185,'Parts list'!$H$4:$H$185,$C11,'Parts list'!$M$4:$M$185,"Yes") -> 10 | L11: =SUMIFS('Parts list'!$V$4:$V$185,'Parts list'!$H$4:$H$185,$C11,'Parts list'!$M$4:$M$185,"Yes") -> 14 | M11: =$L11-$K11 -> 4 | N11: JLCPCB stock, per piece | Q11: =IF(N($O11)=0,"per piece",IF(AND($L11>=$O11,MOD($L11,MAX(1,N($P11)))=0),"OK","CHECK")) -> per piece | R11: =IF($L11=0,0,$S11/$L11) -> 0.002 | S11: =SUMIFS('Parts list'!$W$4:$W$185,'Parts list'!$H$4:$H$185,$C11,'Parts list'!$M$4:$M$185,"Yes") -> 0.028 | U11: At PCBA order: exact quantity + attrition
A12: 9 | B12: Resistor | C12: UNI-ROYAL 0402WGF0000TCE | D12: 0 Ω | E12: 0402 | F12: C17168 | G12: Basic | H12: JLCPCB library | I12: R107, R417-R420 | J12: =SUMIFS('Parts list'!$C$4:$C$185,'Parts list'!$H$4:$H$185,$C12,'Parts list'!$M$4:$M$185,"Yes") -> 5 | K12: =SUMIFS('Parts list'!$R$4:$R$185,'Parts list'!$H$4:$H$185,$C12,'Parts list'!$M$4:$M$185,"Yes") -> 25 | L12: =SUMIFS('Parts list'!$V$4:$V$185,'Parts list'!$H$4:$H$185,$C12,'Parts list'!$M$4:$M$185,"Yes") -> 29 | M12: =$L12-$K12 -> 4 | N12: JLCPCB stock, per piece | Q12: =IF(N($O12)=0,"per piece",IF(AND($L12>=$O12,MOD($L12,MAX(1,N($P12)))=0),"OK","CHECK")) -> per piece | R12: =IF($L12=0,0,$S12/$L12) -> 0.002 | S12: =SUMIFS('Parts list'!$W$4:$W$185,'Parts list'!$H$4:$H$185,$C12,'Parts list'!$M$4:$M$185,"Yes") -> 0.058 | U12: At PCBA order: exact quantity + attrition
A13: 10 | B13: Resistor | C13: UNI-ROYAL 0402WGF4703TCE | D13: 470 kΩ | E13: 0402 | F13: C25790 | G13: Basic (not verified) | H13: JLCPCB library | I13: R109, R532, R688, R689, R935-R937 | J13: =SUMIFS('Parts list'!$C$4:$C$185,'Parts list'!$H$4:$H$185,$C13,'Parts list'!$M$4:$M$185,"Yes") -> 7 | K13: =SUMIFS('Parts list'!$R$4:$R$185,'Parts list'!$H$4:$H$185,$C13,'Parts list'!$M$4:$M$185,"Yes") -> 35 | L13: =SUMIFS('Parts list'!$V$4:$V$185,'Parts list'!$H$4:$H$185,$C13,'Parts list'!$M$4:$M$185,"Yes") -> 41 | M13: =$L13-$K13 -> 6 | N13: JLCPCB stock, per piece | Q13: =IF(N($O13)=0,"per piece",IF(AND($L13>=$O13,MOD($L13,MAX(1,N($P13)))=0),"OK","CHECK")) -> per piece | R13: =IF($L13=0,0,$S13/$L13) -> 0.0028560976 | S13: =SUMIFS('Parts list'!$W$4:$W$185,'Parts list'!$H$4:$H$185,$C13,'Parts list'!$M$4:$M$185,"Yes") -> 0.1171 | U13: At PCBA order: exact quantity + attrition | V13: Unit price differs between BOM lines (US$ 0.002 / 0.0033); the line cost uses each line's price, the unit price shown is the average
A14: 11 | B14: IC | C14: ST USBLC6-2SC6 | D14: — | E14: SOT-23-6 | F14: C7519 | G14: Extended | H14: JLCPCB library | I14: U101 | J14: =SUMIFS('Parts list'!$C$4:$C$185,'Parts list'!$H$4:$H$185,$C14,'Parts list'!$M$4:$M$185,"Yes") -> 1 | K14: =SUMIFS('Parts list'!$R$4:$R$185,'Parts list'!$H$4:$H$185,$C14,'Parts list'!$M$4:$M$185,"Yes") -> 5 | L14: =SUMIFS('Parts list'!$V$4:$V$185,'Parts list'!$H$4:$H$185,$C14,'Parts list'!$M$4:$M$185,"Yes") -> 6 | M14: =$L14-$K14 -> 1 | N14: JLCPCB stock, per piece | Q14: =IF(N($O14)=0,"per piece",IF(AND($L14>=$O14,MOD($L14,MAX(1,N($P14)))=0),"OK","CHECK")) -> per piece | R14: =IF($L14=0,0,$S14/$L14) -> 0.1844 | S14: =SUMIFS('Parts list'!$W$4:$W$185,'Parts list'!$H$4:$H$185,$C14,'Parts list'!$M$4:$M$185,"Yes") -> 1.1064 | U14: At PCBA order: exact quantity + attrition
A15: 12 | B15: IC | C15: TI TPS25200DRVR | D15: — | E15: WSON-6 2 × 2 (DRV) + pad | F15: C128401 | G15: Extended | H15: JLCPCB library | I15: U102 | J15: =SUMIFS('Parts list'!$C$4:$C$185,'Parts list'!$H$4:$H$185,$C15,'Parts list'!$M$4:$M$185,"Yes") -> 1 | K15: =SUMIFS('Parts list'!$R$4:$R$185,'Parts list'!$H$4:$H$185,$C15,'Parts list'!$M$4:$M$185,"Yes") -> 5 | L15: =SUMIFS('Parts list'!$V$4:$V$185,'Parts list'!$H$4:$H$185,$C15,'Parts list'!$M$4:$M$185,"Yes") -> 6 | M15: =$L15-$K15 -> 1 | N15: JLCPCB stock, per piece | Q15: =IF(N($O15)=0,"per piece",IF(AND($L15>=$O15,MOD($L15,MAX(1,N($P15)))=0),"OK","CHECK")) -> per piece | R15: =IF($L15=0,0,$S15/$L15) -> 0.44 | S15: =SUMIFS('Parts list'!$W$4:$W$185,'Parts list'!$H$4:$H$185,$C15,'Parts list'!$M$4:$M$185,"Yes") -> 2.64 | U15: At PCBA order: exact quantity + attrition
A16: 13 | B16: IC | C16: TI TPD2E2U06DRLR | D16: — | E16: SOT-5X3 (DRL) 5-pin | F16: C1972959 | G16: Extended (not verified) | H16: JLCPCB library | I16: U103 | J16: =SUMIFS('Parts list'!$C$4:$C$185,'Parts list'!$H$4:$H$185,$C16,'Parts list'!$M$4:$M$185,"Yes") -> 1 | K16: =SUMIFS('Parts list'!$R$4:$R$185,'Parts list'!$H$4:$H$185,$C16,'Parts list'!$M$4:$M$185,"Yes") -> 5 | L16: =SUMIFS('Parts list'!$V$4:$V$185,'Parts list'!$H$4:$H$185,$C16,'Parts list'!$M$4:$M$185,"Yes") -> 6 | M16: =$L16-$K16 -> 1 | N16: JLCPCB stock, per piece | Q16: =IF(N($O16)=0,"per piece",IF(AND($L16>=$O16,MOD($L16,MAX(1,N($P16)))=0),"OK","CHECK")) -> per piece | R16: =IF($L16=0,0,$S16/$L16) -> 0.22 | S16: =SUMIFS('Parts list'!$W$4:$W$185,'Parts list'!$H$4:$H$185,$C16,'Parts list'!$M$4:$M$185,"Yes") -> 1.32 | U16: At PCBA order: exact quantity + attrition
A17: 14 | B17: Capacitor | C17: FH 0402CG330J500NT | D17: 33 pF | E17: 0402 | F17: C1562 | G17: Basic | H17: JLCPCB library | I17: C201, C202, C421 | J17: =SUMIFS('Parts list'!$C$4:$C$185,'Parts list'!$H$4:$H$185,$C17,'Parts list'!$M$4:$M$185,"Yes") -> 3 | K17: =SUMIFS('Parts list'!$R$4:$R$185,'Parts list'!$H$4:$H$185,$C17,'Parts list'!$M$4:$M$185,"Yes") -> 15 | L17: =SUMIFS('Parts list'!$V$4:$V$185,'Parts list'!$H$4:$H$185,$C17,'Parts list'!$M$4:$M$185,"Yes") -> 19 | M17: =$L17-$K17 -> 4 | N17: JLCPCB stock, per piece | Q17: =IF(N($O17)=0,"per piece",IF(AND($L17>=$O17,MOD($L17,MAX(1,N($P17)))=0),"OK","CHECK")) -> per piece | R17: =IF($L17=0,0,$S17/$L17) -> 0.002 | S17: =SUMIFS('Parts list'!$W$4:$W$185,'Parts list'!$H$4:$H$185,$C17,'Parts list'!$M$4:$M$185,"Yes") -> 0.038 | U17: At PCBA order: exact quantity + attrition
A18: 15 | B18: Capacitor | C18: Samsung CL05A225MQ5NSNC | D18: 2.2 µF | E18: 0402 | F18: C12530 | G18: Basic | H18: JLCPCB library | I18: C211 | J18: =SUMIFS('Parts list'!$C$4:$C$185,'Parts list'!$H$4:$H$185,$C18,'Parts list'!$M$4:$M$185,"Yes") -> 1 | K18: =SUMIFS('Parts list'!$R$4:$R$185,'Parts list'!$H$4:$H$185,$C18,'Parts list'!$M$4:$M$185,"Yes") -> 5 | L18: =SUMIFS('Parts list'!$V$4:$V$185,'Parts list'!$H$4:$H$185,$C18,'Parts list'!$M$4:$M$185,"Yes") -> 7 | M18: =$L18-$K18 -> 2 | N18: JLCPCB stock, per piece | Q18: =IF(N($O18)=0,"per piece",IF(AND($L18>=$O18,MOD($L18,MAX(1,N($P18)))=0),"OK","CHECK")) -> per piece | R18: =IF($L18=0,0,$S18/$L18) -> 0.005 | S18: =SUMIFS('Parts list'!$W$4:$W$185,'Parts list'!$H$4:$H$185,$C18,'Parts list'!$M$4:$M$185,"Yes") -> 0.035 | U18: At PCBA order: exact quantity + attrition
A19: 16 | B19: Capacitor | C19: Samsung CL05B103KB5NNNC | D19: 10 nF | E19: 0402 | F19: C15195 | G19: Basic | H19: JLCPCB library | I19: C217, C514, C620, C621 | J19: =SUMIFS('Parts list'!$C$4:$C$185,'Parts list'!$H$4:$H$185,$C19,'Parts list'!$M$4:$M$185,"Yes") -> 4 | K19: =SUMIFS('Parts list'!$R$4:$R$185,'Parts list'!$H$4:$H$185,$C19,'Parts list'!$M$4:$M$185,"Yes") -> 20 | L19: =SUMIFS('Parts list'!$V$4:$V$185,'Parts list'!$H$4:$H$185,$C19,'Parts list'!$M$4:$M$185,"Yes") -> 26 | M19: =$L19-$K19 -> 6 | N19: JLCPCB stock, per piece | Q19: =IF(N($O19)=0,"per piece",IF(AND($L19>=$O19,MOD($L19,MAX(1,N($P19)))=0),"OK","CHECK")) -> per piece | R19: =IF($L19=0,0,$S19/$L19) -> 0.0015846154 | S19: =SUMIFS('Parts list'!$W$4:$W$185,'Parts list'!$H$4:$H$185,$C19,'Parts list'!$M$4:$M$185,"Yes") -> 0.0412 | U19: At PCBA order: exact quantity + attrition | V19: Unit price differs between BOM lines (US$ 0.0011 / 0.002); the line cost uses each line's price, the unit price shown is the average
A20: 17 | B20: Capacitor | C20: Samsung CL10A105KB8NNNC | D20: 1 µF | E20: 0603 | F20: C15849 | G20: Basic | H20: JLCPCB library | I20: C220, C221, C311, C312, C501, C506, C508, C617 | J20: =SUMIFS('Parts list'!$C$4:$C$185,'Parts list'!$H$4:$H$185,$C20,'Parts list'!$M$4:$M$185,"Yes") -> 8 | K20: =SUMIFS('Parts list'!$R$4:$R$185,'Parts list'!$H$4:$H$185,$C20,'Parts list'!$M$4:$M$185,"Yes") -> 40 | L20: =SUMIFS('Parts list'!$V$4:$V$185,'Parts list'!$H$4:$H$185,$C20,'Parts list'!$M$4:$M$185,"Yes") -> 54 | M20: =$L20-$K20 -> 14 | N20: JLCPCB stock, per piece | Q20: =IF(N($O20)=0,"per piece",IF(AND($L20>=$O20,MOD($L20,MAX(1,N($P20)))=0),"OK","CHECK")) -> per piece | R20: =IF($L20=0,0,$S20/$L20) -> 0.006 | S20: =SUMIFS('Parts list'!$W$4:$W$185,'Parts list'!$H$4:$H$185,$C20,'Parts list'!$M$4:$M$185,"Yes") -> 0.324 | U20: At PCBA order: exact quantity + attrition
A21: 18 | B21: Ferrite bead | C21: Sunlord GZ1608D601TF | D21: 600 Ω @ 100 MHz | E21: 0603 | F21: C1002 | G21: Basic | H21: JLCPCB library | I21: FB202, FB301, FB302 | J21: =SUMIFS('Parts list'!$C$4:$C$185,'Parts list'!$H$4:$H$185,$C21,'Parts list'!$M$4:$M$185,"Yes") -> 3 | K21: =SUMIFS('Parts list'!$R$4:$R$185,'Parts list'!$H$4:$H$185,$C21,'Parts list'!$M$4:$M$185,"Yes") -> 15 | L21: =SUMIFS('Parts list'!$V$4:$V$185,'Parts list'!$H$4:$H$185,$C21,'Parts list'!$M$4:$M$185,"Yes") -> 19 | M21: =$L21-$K21 -> 4 | N21: JLCPCB stock, per piece | Q21: =IF(N($O21)=0,"per piece",IF(AND($L21>=$O21,MOD($L21,MAX(1,N($P21)))=0),"OK","CHECK")) -> per piece | R21: =IF($L21=0,0,$S21/$L21) -> 0.0127 | S21: =SUMIFS('Parts list'!$W$4:$W$185,'Parts list'!$H$4:$H$185,$C21,'Parts list'!$M$4:$M$185,"Yes") -> 0.2413 | U21: At PCBA order: exact quantity + attrition
A22: 19 | B22: Transistor | C22: AOS AO3400A | D22: AO3400A | E22: SOT-23 | F22: C20917 | G22: Basic | H22: JLCPCB library | I22: Q207, Q502-Q506, Q616, Q617, Q619, Q620, Q622 | J22: =SUMIFS('Parts list'!$C$4:$C$185,'Parts list'!$H$4:$H$185,$C22,'Parts list'!$M$4:$M$185,"Yes") -> 11 | K22: =SUMIFS('Parts list'!$R$4:$R$185,'Parts list'!$H$4:$H$185,$C22,'Parts list'!$M$4:$M$185,"Yes") -> 55 | L22: =SUMIFS('Parts list'!$V$4:$V$185,'Parts list'!$H$4:$H$185,$C22,'Parts list'!$M$4:$M$185,"Yes") -> 58 | M22: =$L22-$K22 -> 3 | N22: JLCPCB stock, per piece | Q22: =IF(N($O22)=0,"per piece",IF(AND($L22>=$O22,MOD($L22,MAX(1,N($P22)))=0),"OK","CHECK")) -> per piece | R22: =IF($L22=0,0,$S22/$L22) -> 0.067148276 | S22: =SUMIFS('Parts list'!$W$4:$W$185,'Parts list'!$H$4:$H$185,$C22,'Parts list'!$M$4:$M$185,"Yes") -> 3.8946 | U22: At PCBA order: exact quantity + attrition | V22: Unit price differs between BOM lines (US$ 0.0524 / 0.0853); the line cost uses each line's price, the unit price shown is the average
A23: 20 | B23: Resistor | C23: UNI-ROYAL 0402WGF330JTCE | D23: 33 Ω | E23: 0402 | F23: C25105 | G23: Basic | H23: JLCPCB library | I23: R203-R206, R210, R211, R215, R224, R225 | J23: =SUMIFS('Parts list'!$C$4:$C$185,'Parts list'!$H$4:$H$185,$C23,'Parts list'!$M$4:$M$185,"Yes") -> 9 | K23: =SUMIFS('Parts list'!$R$4:$R$185,'Parts list'!$H$4:$H$185,$C23,'Parts list'!$M$4:$M$185,"Yes") -> 45 | L23: =SUMIFS('Parts list'!$V$4:$V$185,'Parts list'!$H$4:$H$185,$C23,'Parts list'!$M$4:$M$185,"Yes") -> 48 | M23: =$L23-$K23 -> 3 | N23: JLCPCB stock, per piece | Q23: =IF(N($O23)=0,"per piece",IF(AND($L23>=$O23,MOD($L23,MAX(1,N($P23)))=0),"OK","CHECK")) -> per piece | R23: =IF($L23=0,0,$S23/$L23) -> 0.002 | S23: =SUMIFS('Parts list'!$W$4:$W$185,'Parts list'!$H$4:$H$185,$C23,'Parts list'!$M$4:$M$185,"Yes") -> 0.096 | U23: At PCBA order: exact quantity + attrition
A24: 21 | B24: Resistor | C24: UNI-ROYAL 0402WGF3300TCE | D24: 330 Ω | E24: 0402 | F24: C25104 | G24: Basic | H24: JLCPCB library | I24: R228-R230, R242-R246, R665 | J24: =SUMIFS('Parts list'!$C$4:$C$185,'Parts list'!$H$4:$H$185,$C24,'Parts list'!$M$4:$M$185,"Yes") -> 9 | K24: =SUMIFS('Parts list'!$R$4:$R$185,'Parts list'!$H$4:$H$185,$C24,'Parts list'!$M$4:$M$185,"Yes") -> 45 | L24: =SUMIFS('Parts list'!$V$4:$V$185,'Parts list'!$H$4:$H$185,$C24,'Parts list'!$M$4:$M$185,"Yes") -> 49 | M24: =$L24-$K24 -> 4 | N24: JLCPCB stock, per piece | Q24: =IF(N($O24)=0,"per piece",IF(AND($L24>=$O24,MOD($L24,MAX(1,N($P24)))=0),"OK","CHECK")) -> per piece | R24: =IF($L24=0,0,$S24/$L24) -> 0.0018571429 | S24: =SUMIFS('Parts list'!$W$4:$W$185,'Parts list'!$H$4:$H$185,$C24,'Parts list'!$M$4:$M$185,"Yes") -> 0.091 | U24: At PCBA order: exact quantity + attrition | V24: Unit price differs between BOM lines (US$ 0.001 / 0.002); the line cost uses each line's price, the unit price shown is the average
A25: 22 | B25: Resistor | C25: UNI-ROYAL 0402WGF4701TCE | D25: 4.7 kΩ | E25: 0402 | F25: C25900 | G25: Basic | H25: JLCPCB library | I25: R237, R643, R644 | J25: =SUMIFS('Parts list'!$C$4:$C$185,'Parts list'!$H$4:$H$185,$C25,'Parts list'!$M$4:$M$185,"Yes") -> 3 | K25: =SUMIFS('Parts list'!$R$4:$R$185,'Parts list'!$H$4:$H$185,$C25,'Parts list'!$M$4:$M$185,"Yes") -> 15 | L25: =SUMIFS('Parts list'!$V$4:$V$185,'Parts list'!$H$4:$H$185,$C25,'Parts list'!$M$4:$M$185,"Yes") -> 19 | M25: =$L25-$K25 -> 4 | N25: JLCPCB stock, per piece | Q25: =IF(N($O25)=0,"per piece",IF(AND($L25>=$O25,MOD($L25,MAX(1,N($P25)))=0),"OK","CHECK")) -> per piece | R25: =IF($L25=0,0,$S25/$L25) -> 0.0010526316 | S25: =SUMIFS('Parts list'!$W$4:$W$185,'Parts list'!$H$4:$H$185,$C25,'Parts list'!$M$4:$M$185,"Yes") -> 0.02 | U25: At PCBA order: exact quantity + attrition | V25: Unit price differs between BOM lines (US$ 0.0005 / 0.002); the line cost uses each line's price, the unit price shown is the average
A26: 23 | B26: IC | C26: WCH CH32V307RCT6 | D26: CH32V307RCT6 | E26: LQFP-64M 10 × 10 | F26: C2988083 | G26: Extended | H26: JLCPCB library | I26: U201 | J26: =SUMIFS('Parts list'!$C$4:$C$185,'Parts list'!$H$4:$H$185,$C26,'Parts list'!$M$4:$M$185,"Yes") -> 1 | K26: =SUMIFS('Parts list'!$R$4:$R$185,'Parts list'!$H$4:$H$185,$C26,'Parts list'!$M$4:$M$185,"Yes") -> 5 | L26: =SUMIFS('Parts list'!$V$4:$V$185,'Parts list'!$H$4:$H$185,$C26,'Parts list'!$M$4:$M$185,"Yes") -> 6 | M26: =$L26-$K26 -> 1 | N26: JLCPCB stock, per piece | Q26: =IF(N($O26)=0,"per piece",IF(AND($L26>=$O26,MOD($L26,MAX(1,N($P26)))=0),"OK","CHECK")) -> per piece | R26: =IF($L26=0,0,$S26/$L26) -> 3.47 | S26: =SUMIFS('Parts list'!$W$4:$W$185,'Parts list'!$H$4:$H$185,$C26,'Parts list'!$M$4:$M$185,"Yes") -> 20.82 | T26: Pre-order | U26: Single source, thin stock (JLCPCB 364 / LCSC 193): pre-order 6
A27: 24 | B27: IC | C27: AGM AGRV2KQ32 | D27: AGRV2KQ32 | E27: QFN-32 4 × 4, EP 2.7 | F27: C18208899 | G27: Extended | H27: JLCPCB library | I27: U202 | J27: =SUMIFS('Parts list'!$C$4:$C$185,'Parts list'!$H$4:$H$185,$C27,'Parts list'!$M$4:$M$185,"Yes") -> 1 | K27: =SUMIFS('Parts list'!$R$4:$R$185,'Parts list'!$H$4:$H$185,$C27,'Parts list'!$M$4:$M$185,"Yes") -> 5 | L27: =SUMIFS('Parts list'!$V$4:$V$185,'Parts list'!$H$4:$H$185,$C27,'Parts list'!$M$4:$M$185,"Yes") -> 6 | M27: =$L27-$K27 -> 1 | N27: JLCPCB stock, per piece | Q27: =IF(N($O27)=0,"per piece",IF(AND($L27>=$O27,MOD($L27,MAX(1,N($P27)))=0),"OK","CHECK")) -> per piece | R27: =IF($L27=0,0,$S27/$L27) -> 1.6503 | S27: =SUMIFS('Parts list'!$W$4:$W$185,'Parts list'!$H$4:$H$185,$C27,'Parts list'!$M$4:$M$185,"Yes") -> 9.9018 | T27: Pre-order | U27: Single source, thin stock (LCSC 980): pre-order 6
A28: 25 | B28: IC | C28: Nexperia 74LVC1G157GW,125 | D28: 74LVC1G157 | E28: SOT-363 (TSSOP6) | F28: C135822 | G28: Extended | H28: JLCPCB library | I28: U205 | J28: =SUMIFS('Parts list'!$C$4:$C$185,'Parts list'!$H$4:$H$185,$C28,'Parts list'!$M$4:$M$185,"Yes") -> 1 | K28: =SUMIFS('Parts list'!$R$4:$R$185,'Parts list'!$H$4:$H$185,$C28,'Parts list'!$M$4:$M$185,"Yes") -> 5 | L28: =SUMIFS('Parts list'!$V$4:$V$185,'Parts list'!$H$4:$H$185,$C28,'Parts list'!$M$4:$M$185,"Yes") -> 6 | M28: =$L28-$K28 -> 1 | N28: JLCPCB stock, per piece | Q28: =IF(N($O28)=0,"per piece",IF(AND($L28>=$O28,MOD($L28,MAX(1,N($P28)))=0),"OK","CHECK")) -> per piece | R28: =IF($L28=0,0,$S28/$L28) -> 0.2106 | S28: =SUMIFS('Parts list'!$W$4:$W$185,'Parts list'!$H$4:$H$185,$C28,'Parts list'!$M$4:$M$185,"Yes") -> 1.2636 | U28: At PCBA order: exact quantity + attrition
A29: 26 | B29: IC | C29: Nexperia 74LVC1G11GW-Q100H | D29: 74LVC1G11 | E29: SOT-363 (TSSOP6) | F29: C548242 | G29: Extended | H29: JLCPCB library | I29: U206 | J29: =SUMIFS('Parts list'!$C$4:$C$185,'Parts list'!$H$4:$H$185,$C29,'Parts list'!$M$4:$M$185,"Yes") -> 1 | K29: =SUMIFS('Parts list'!$R$4:$R$185,'Parts list'!$H$4:$H$185,$C29,'Parts list'!$M$4:$M$185,"Yes") -> 5 | L29: =SUMIFS('Parts list'!$V$4:$V$185,'Parts list'!$H$4:$H$185,$C29,'Parts list'!$M$4:$M$185,"Yes") -> 6 | M29: =$L29-$K29 -> 1 | N29: JLCPCB stock, per piece | Q29: =IF(N($O29)=0,"per piece",IF(AND($L29>=$O29,MOD($L29,MAX(1,N($P29)))=0),"OK","CHECK")) -> per piece | R29: =IF($L29=0,0,$S29/$L29) -> 0.0768 | S29: =SUMIFS('Parts list'!$W$4:$W$185,'Parts list'!$H$4:$H$185,$C29,'Parts list'!$M$4:$M$185,"Yes") -> 0.4608 | U29: At PCBA order: exact quantity + attrition
A30: 27 | B30: IC | C30: TI SN74LVC3G34DCUR | D30: 74LVC3G34 | E30: VSSOP-8 0.5 mm (SOT765-1, DC) | F30: C130024 | G30: Extended | H30: JLCPCB library | I30: U208 | J30: =SUMIFS('Parts list'!$C$4:$C$185,'Parts list'!$H$4:$H$185,$C30,'Parts list'!$M$4:$M$185,"Yes") -> 1 | K30: =SUMIFS('Parts list'!$R$4:$R$185,'Parts list'!$H$4:$H$185,$C30,'Parts list'!$M$4:$M$185,"Yes") -> 5 | L30: =SUMIFS('Parts list'!$V$4:$V$185,'Parts list'!$H$4:$H$185,$C30,'Parts list'!$M$4:$M$185,"Yes") -> 10 | M30: =$L30-$K30 -> 5 | N30: Pre-order: minimum order quantity 10 (as costed) | O30: 10 | Q30: =IF(N($O30)=0,"per piece",IF(AND($L30>=$O30,MOD($L30,MAX(1,N($P30)))=0),"OK","CHECK")) -> OK | R30: =IF($L30=0,0,$S30/$L30) -> 0.2012 | S30: =SUMIFS('Parts list'!$W$4:$W$185,'Parts list'!$H$4:$H$185,$C30,'Parts list'!$M$4:$M$185,"Yes") -> 2.012 | T30: Pre-order | U30: Pre-order 10 (order quantity as costed)
A31: 28 | B31: Oscillator | C31: Kyocera KC2520K80.0000C1GE00 | D31: 80.000 MHz | E31: 2.5 × 2.0 mm 4-pad, plain 2520 land (no 3225 pads) | F31: C1988889 | G31: Extended | H31: Global sourcing | I31: X201 | J31: =SUMIFS('Parts list'!$C$4:$C$185,'Parts list'!$H$4:$H$185,$C31,'Parts list'!$M$4:$M$185,"Yes") -> 1 | K31: =SUMIFS('Parts list'!$R$4:$R$185,'Parts list'!$H$4:$H$185,$C31,'Parts list'!$M$4:$M$185,"Yes") -> 5 | L31: =SUMIFS('Parts list'!$V$4:$V$185,'Parts list'!$H$4:$H$185,$C31,'Parts list'!$M$4:$M$185,"Yes") -> 6 | M31: =$L31-$K31 -> 1 | N31: Global sourcing via JLCPCB, per piece | Q31: =IF(N($O31)=0,"per piece",IF(AND($L31>=$O31,MOD($L31,MAX(1,N($P31)))=0),"OK","CHECK")) -> per piece | R31: =IF($L31=0,0,$S31/$L31) -> 1.39 | S31: =SUMIFS('Parts list'!$W$4:$W$185,'Parts list'!$H$4:$H$185,$C31,'Parts list'!$M$4:$M$185,"Yes") -> 8.34 | T31: Yes | U31: X201: global sourcing; 32-week factory lead
A32: 29 | B32: Oscillator | C32: NDK NZ2520SDA-49.152MHZ-NSC5083D | D32: 49.152 MHz | E32: 2.5 × 2.0 mm 4-pad, plain 2520 land | F32: — | G32: Extended | H32: Global sourcing | I32: X202 | J32: =SUMIFS('Parts list'!$C$4:$C$185,'Parts list'!$H$4:$H$185,$C32,'Parts list'!$M$4:$M$185,"Yes") -> 1 | K32: =SUMIFS('Parts list'!$R$4:$R$185,'Parts list'!$H$4:$H$185,$C32,'Parts list'!$M$4:$M$185,"Yes") -> 5 | L32: =SUMIFS('Parts list'!$V$4:$V$185,'Parts list'!$H$4:$H$185,$C32,'Parts list'!$M$4:$M$185,"Yes") -> 6 | M32: =$L32-$K32 -> 1 | N32: Global sourcing via JLCPCB, per piece | Q32: =IF(N($O32)=0,"per piece",IF(AND($L32>=$O32,MOD($L32,MAX(1,N($P32)))=0),"OK","CHECK")) -> per piece | R32: =IF($L32=0,0,$S32/$L32) -> 2 | S32: =SUMIFS('Parts list'!$W$4:$W$185,'Parts list'!$H$4:$H$185,$C32,'Parts list'!$M$4:$M$185,"Yes") -> 12 | T32: Yes | U32: X202: global sourcing; 24-week factory lead
A33: 30 | B33: Oscillator | C33: NDK NZ2520SDA-45.1584MHZ-NSC5083D | D33: 45.1584 MHz | E33: 2.5 × 2.0 mm 4-pad, plain 2520 land | F33: — | G33: Extended | H33: Global sourcing | I33: X203 | J33: =SUMIFS('Parts list'!$C$4:$C$185,'Parts list'!$H$4:$H$185,$C33,'Parts list'!$M$4:$M$185,"Yes") -> 1 | K33: =SUMIFS('Parts list'!$R$4:$R$185,'Parts list'!$H$4:$H$185,$C33,'Parts list'!$M$4:$M$185,"Yes") -> 5 | L33: =SUMIFS('Parts list'!$V$4:$V$185,'Parts list'!$H$4:$H$185,$C33,'Parts list'!$M$4:$M$185,"Yes") -> 6 | M33: =$L33-$K33 -> 1 | N33: Global sourcing via JLCPCB, per piece | Q33: =IF(N($O33)=0,"per piece",IF(AND($L33>=$O33,MOD($L33,MAX(1,N($P33)))=0),"OK","CHECK")) -> per piece | R33: =IF($L33=0,0,$S33/$L33) -> 2 | S33: =SUMIFS('Parts list'!$W$4:$W$185,'Parts list'!$H$4:$H$185,$C33,'Parts list'!$M$4:$M$185,"Yes") -> 12 | T33: Yes | U33: X203: global sourcing; 24-week factory lead
A34: 31 | B34: Crystal | C34: YXC X50328MSB2GI | D34: 8 MHz | E34: 5.0 × 3.2 mm 2-pad | F34: C115962 | G34: Basic | H34: JLCPCB library | I34: Y201 | J34: =SUMIFS('Parts list'!$C$4:$C$185,'Parts list'!$H$4:$H$185,$C34,'Parts list'!$M$4:$M$185,"Yes") -> 1 | K34: =SUMIFS('Parts list'!$R$4:$R$185,'Parts list'!$H$4:$H$185,$C34,'Parts list'!$M$4:$M$185,"Yes") -> 5 | L34: =SUMIFS('Parts list'!$V$4:$V$185,'Parts list'!$H$4:$H$185,$C34,'Parts list'!$M$4:$M$185,"Yes") -> 6 | M34: =$L34-$K34 -> 1 | N34: JLCPCB stock, per piece | Q34: =IF(N($O34)=0,"per piece",IF(AND($L34>=$O34,MOD($L34,MAX(1,N($P34)))=0),"OK","CHECK")) -> per piece | R34: =IF($L34=0,0,$S34/$L34) -> 0.2452 | S34: =SUMIFS('Parts list'!$W$4:$W$185,'Parts list'!$H$4:$H$185,$C34,'Parts list'!$M$4:$M$185,"Yes") -> 1.4712 | U34: At PCBA order: exact quantity + attrition
A35: 32 | B35: Capacitor | C35: Samsung CL10A225KO8NNNC | D35: 2.2 µF | E35: 0603 | F35: C23630 | G35: Basic | H35: JLCPCB library | I35: C301, C302, C303, C304, C310, C439, C440, C502 | J35: =SUMIFS('Parts list'!$C$4:$C$185,'Parts list'!$H$4:$H$185,$C35,'Parts list'!$M$4:$M$185,"Yes") -> 8 | K35: =SUMIFS('Parts list'!$R$4:$R$185,'Parts list'!$H$4:$H$185,$C35,'Parts list'!$M$4:$M$185,"Yes") -> 40 | L35: =SUMIFS('Parts list'!$V$4:$V$185,'Parts list'!$H$4:$H$185,$C35,'Parts list'!$M$4:$M$185,"Yes") -> 48 | M35: =$L35-$K35 -> 8 | N35: JLCPCB stock, per piece | Q35: =IF(N($O35)=0,"per piece",IF(AND($L35>=$O35,MOD($L35,MAX(1,N($P35)))=0),"OK","CHECK")) -> per piece | R35: =IF($L35=0,0,$S35/$L35) -> 0.01599375 | S35: =SUMIFS('Parts list'!$W$4:$W$185,'Parts list'!$H$4:$H$185,$C35,'Parts list'!$M$4:$M$185,"Yes") -> 0.7677 | U35: At PCBA order: exact quantity + attrition | V35: Unit price differs between BOM lines (US$ 0.012 / 0.0191); the line cost uses each line's price, the unit price shown is the average
A36: 33 | B36: Resistor | C36: UNI-ROYAL 0805W8F220KT5E | D36: 2.2 Ω | E36: 0805 | F36: C17521 | G36: Basic | H36: JLCPCB library | I36: R301, R302 | J36: =SUMIFS('Parts list'!$C$4:$C$185,'Parts list'!$H$4:$H$185,$C36,'Parts list'!$M$4:$M$185,"Yes") -> 2 | K36: =SUMIFS('Parts list'!$R$4:$R$185,'Parts list'!$H$4:$H$185,$C36,'Parts list'!$M$4:$M$185,"Yes") -> 10 | L36: =SUMIFS('Parts list'!$V$4:$V$185,'Parts list'!$H$4:$H$185,$C36,'Parts list'!$M$4:$M$185,"Yes") -> 12 | M36: =$L36-$K36 -> 2 | N36: JLCPCB stock, per piece | Q36: =IF(N($O36)=0,"per piece",IF(AND($L36>=$O36,MOD($L36,MAX(1,N($P36)))=0),"OK","CHECK")) -> per piece | R36: =IF($L36=0,0,$S36/$L36) -> 0.003 | S36: =SUMIFS('Parts list'!$W$4:$W$185,'Parts list'!$H$4:$H$185,$C36,'Parts list'!$M$4:$M$185,"Yes") -> 0.036 | U36: At PCBA order: exact quantity + attrition
A37: 34 | B37: Resistor | C37: YAGEO RT0603BRD0715KL | D37: 15.0 kΩ | E37: 0603 | F37: C326733 | G37: Extended (not verified) | H37: JLCPCB library | I37: R533 | J37: =SUMIFS('Parts list'!$C$4:$C$185,'Parts list'!$H$4:$H$185,$C37,'Parts list'!$M$4:$M$185,"Yes") -> 1 | K37: =SUMIFS('Parts list'!$R$4:$R$185,'Parts list'!$H$4:$H$185,$C37,'Parts list'!$M$4:$M$185,"Yes") -> 5 | L37: =SUMIFS('Parts list'!$V$4:$V$185,'Parts list'!$H$4:$H$185,$C37,'Parts list'!$M$4:$M$185,"Yes") -> 7 | M37: =$L37-$K37 -> 2 | N37: JLCPCB stock, per piece | Q37: =IF(N($O37)=0,"per piece",IF(AND($L37>=$O37,MOD($L37,MAX(1,N($P37)))=0),"OK","CHECK")) -> per piece | R37: =IF($L37=0,0,$S37/$L37) -> 0.0296 | S37: =SUMIFS('Parts list'!$W$4:$W$185,'Parts list'!$H$4:$H$185,$C37,'Parts list'!$M$4:$M$185,"Yes") -> 0.2072 | U37: At PCBA order: exact quantity + attrition
A38: 35 | B38: Resistor | C38: YAGEO RT0603BRD0711KL | D38: 11.0 kΩ | E38: 0603 | F38: C728581 | G38: Extended (not verified) | H38: JLCPCB library | I38: R534 | J38: =SUMIFS('Parts list'!$C$4:$C$185,'Parts list'!$H$4:$H$185,$C38,'Parts list'!$M$4:$M$185,"Yes") -> 1 | K38: =SUMIFS('Parts list'!$R$4:$R$185,'Parts list'!$H$4:$H$185,$C38,'Parts list'!$M$4:$M$185,"Yes") -> 5 | L38: =SUMIFS('Parts list'!$V$4:$V$185,'Parts list'!$H$4:$H$185,$C38,'Parts list'!$M$4:$M$185,"Yes") -> 7 | M38: =$L38-$K38 -> 2 | N38: JLCPCB stock, per piece | Q38: =IF(N($O38)=0,"per piece",IF(AND($L38>=$O38,MOD($L38,MAX(1,N($P38)))=0),"OK","CHECK")) -> per piece | R38: =IF($L38=0,0,$S38/$L38) -> 0.0499 | S38: =SUMIFS('Parts list'!$W$4:$W$185,'Parts list'!$H$4:$H$185,$C38,'Parts list'!$M$4:$M$185,"Yes") -> 0.3493 | U38: At PCBA order: exact quantity + attrition
A39: 36 | B39: IC | C39: ESS ES9018K2M | D39: ES9018K2M | E39: QFN-28 5 × 5 + EP | F39: C2688377 | G39: Extended | H39: JLCPCB library | I39: U301 | J39: =SUMIFS('Parts list'!$C$4:$C$185,'Parts list'!$H$4:$H$185,$C39,'Parts list'!$M$4:$M$185,"Yes") -> 1 | K39: =SUMIFS('Parts list'!$R$4:$R$185,'Parts list'!$H$4:$H$185,$C39,'Parts list'!$M$4:$M$185,"Yes") -> 5 | L39: =SUMIFS('Parts list'!$V$4:$V$185,'Parts list'!$H$4:$H$185,$C39,'Parts list'!$M$4:$M$185,"Yes") -> 6 | M39: =$L39-$K39 -> 1 | N39: JLCPCB stock, per piece | Q39: =IF(N($O39)=0,"per piece",IF(AND($L39>=$O39,MOD($L39,MAX(1,N($P39)))=0),"OK","CHECK")) -> per piece | R39: =IF($L39=0,0,$S39/$L39) -> 3.4678 | S39: =SUMIFS('Parts list'!$W$4:$W$185,'Parts list'!$H$4:$H$185,$C39,'Parts list'!$M$4:$M$185,"Yes") -> 20.8068 | T39: Pre-order | U39: Single source, thin stock (LCSC 724): pre-order 6
A40: 37 | B40: IC | C40: TI LP5907MFX-3.3/NOPB | D40: 3.3 V, 250 mA | E40: SOT-23-5 | F40: C80670 | G40: Extended | H40: JLCPCB library | I40: U302 | J40: =SUMIFS('Parts list'!$C$4:$C$185,'Parts list'!$H$4:$H$185,$C40,'Parts list'!$M$4:$M$185,"Yes") -> 1 | K40: =SUMIFS('Parts list'!$R$4:$R$185,'Parts list'!$H$4:$H$185,$C40,'Parts list'!$M$4:$M$185,"Yes") -> 5 | L40: =SUMIFS('Parts list'!$V$4:$V$185,'Parts list'!$H$4:$H$185,$C40,'Parts list'!$M$4:$M$185,"Yes") -> 6 | M40: =$L40-$K40 -> 1 | N40: JLCPCB stock, per piece | Q40: =IF(N($O40)=0,"per piece",IF(AND($L40>=$O40,MOD($L40,MAX(1,N($P40)))=0),"OK","CHECK")) -> per piece | R40: =IF($L40=0,0,$S40/$L40) -> 0.2104 | S40: =SUMIFS('Parts list'!$W$4:$W$185,'Parts list'!$H$4:$H$185,$C40,'Parts list'!$M$4:$M$185,"Yes") -> 1.2624 | U40: At PCBA order: exact quantity + attrition
A41: 38 | B41: IC | C41: TI TLV75801PDBVR | D41: 1.300 V (R533/R534) | E41: SOT-23-5 (DBV) | F41: C2877852 | G41: Extended | H41: JLCPCB library | I41: U303 | J41: =SUMIFS('Parts list'!$C$4:$C$185,'Parts list'!$H$4:$H$185,$C41,'Parts list'!$M$4:$M$185,"Yes") -> 1 | K41: =SUMIFS('Parts list'!$R$4:$R$185,'Parts list'!$H$4:$H$185,$C41,'Parts list'!$M$4:$M$185,"Yes") -> 5 | L41: =SUMIFS('Parts list'!$V$4:$V$185,'Parts list'!$H$4:$H$185,$C41,'Parts list'!$M$4:$M$185,"Yes") -> 6 | M41: =$L41-$K41 -> 1 | N41: JLCPCB stock, per piece | Q41: =IF(N($O41)=0,"per piece",IF(AND($L41>=$O41,MOD($L41,MAX(1,N($P41)))=0),"OK","CHECK")) -> per piece | R41: =IF($L41=0,0,$S41/$L41) -> 0.18 | S41: =SUMIFS('Parts list'!$W$4:$W$185,'Parts list'!$H$4:$H$185,$C41,'Parts list'!$M$4:$M$185,"Yes") -> 1.08 | U41: At PCBA order: exact quantity + attrition
A42: 39 | B42: Capacitor | C42: Samsung CL10C100JB8NNNC | D42: 10 pF | E42: 0603 | F42: C1634 | G42: Basic | H42: JLCPCB library | I42: C401-C408 | J42: =SUMIFS('Parts list'!$C$4:$C$185,'Parts list'!$H$4:$H$185,$C42,'Parts list'!$M$4:$M$185,"Yes") -> 8 | K42: =SUMIFS('Parts list'!$R$4:$R$185,'Parts list'!$H$4:$H$185,$C42,'Parts list'!$M$4:$M$185,"Yes") -> 40 | L42: =SUMIFS('Parts list'!$V$4:$V$185,'Parts list'!$H$4:$H$185,$C42,'Parts list'!$M$4:$M$185,"Yes") -> 42 | M42: =$L42-$K42 -> 2 | N42: JLCPCB stock, per piece | Q42: =IF(N($O42)=0,"per piece",IF(AND($L42>=$O42,MOD($L42,MAX(1,N($P42)))=0),"OK","CHECK")) -> per piece | R42: =IF($L42=0,0,$S42/$L42) -> 0.0076 | S42: =SUMIFS('Parts list'!$W$4:$W$185,'Parts list'!$H$4:$H$185,$C42,'Parts list'!$M$4:$M$185,"Yes") -> 0.3192 | U42: At PCBA order: exact quantity + attrition
A43: 40 | B43: Capacitor | C43: Samsung CL21A106KAYNNNE | D43: 10 µF | E43: 0805 | F43: C15850 | G43: Basic | H43: JLCPCB library | I43: C413-C416, C507, C509-C511, C512 | J43: =SUMIFS('Parts list'!$C$4:$C$185,'Parts list'!$H$4:$H$185,$C43,'Parts list'!$M$4:$M$185,"Yes") -> 9 | K43: =SUMIFS('Parts list'!$R$4:$R$185,'Parts list'!$H$4:$H$185,$C43,'Parts list'!$M$4:$M$185,"Yes") -> 45 | L43: =SUMIFS('Parts list'!$V$4:$V$185,'Parts list'!$H$4:$H$185,$C43,'Parts list'!$M$4:$M$185,"Yes") -> 53 | M43: =$L43-$K43 -> 8 | N43: JLCPCB stock, per piece | Q43: =IF(N($O43)=0,"per piece",IF(AND($L43>=$O43,MOD($L43,MAX(1,N($P43)))=0),"OK","CHECK")) -> per piece | R43: =IF($L43=0,0,$S43/$L43) -> 0.085 | S43: =SUMIFS('Parts list'!$W$4:$W$185,'Parts list'!$H$4:$H$185,$C43,'Parts list'!$M$4:$M$185,"Yes") -> 4.505 | U43: At PCBA order: exact quantity + attrition
A44: 41 | B44: Capacitor | C44: KEMET C0603C821J5GACTU | D44: 820 pF | E44: 0603 | F44: C2169093 | G44: Extended | H44: JLCPCB library | I44: C417-C420 | J44: =SUMIFS('Parts list'!$C$4:$C$185,'Parts list'!$H$4:$H$185,$C44,'Parts list'!$M$4:$M$185,"Yes") -> 4 | K44: =SUMIFS('Parts list'!$R$4:$R$185,'Parts list'!$H$4:$H$185,$C44,'Parts list'!$M$4:$M$185,"Yes") -> 20 | L44: =SUMIFS('Parts list'!$V$4:$V$185,'Parts list'!$H$4:$H$185,$C44,'Parts list'!$M$4:$M$185,"Yes") -> 22 | M44: =$L44-$K44 -> 2 | N44: JLCPCB stock, per piece | Q44: =IF(N($O44)=0,"per piece",IF(AND($L44>=$O44,MOD($L44,MAX(1,N($P44)))=0),"OK","CHECK")) -> per piece | R44: =IF($L44=0,0,$S44/$L44) -> 0.0111 | S44: =SUMIFS('Parts list'!$W$4:$W$185,'Parts list'!$H$4:$H$185,$C44,'Parts list'!$M$4:$M$185,"Yes") -> 0.2442 | U44: At PCBA order: exact quantity + attrition
A45: 42 | B45: Capacitor | C45: Murata GRM1885C1H182JA01D | D45: 1.8 nF | E45: 0603 | F45: C97878 | G45: Extended | H45: JLCPCB library | I45: C431-C438 | J45: =SUMIFS('Parts list'!$C$4:$C$185,'Parts list'!$H$4:$H$185,$C45,'Parts list'!$M$4:$M$185,"Yes") -> 8 | K45: =SUMIFS('Parts list'!$R$4:$R$185,'Parts list'!$H$4:$H$185,$C45,'Parts list'!$M$4:$M$185,"Yes") -> 40 | L45: =SUMIFS('Parts list'!$V$4:$V$185,'Parts list'!$H$4:$H$185,$C45,'Parts list'!$M$4:$M$185,"Yes") -> 42 | M45: =$L45-$K45 -> 2 | N45: JLCPCB stock, per piece | Q45: =IF(N($O45)=0,"per piece",IF(AND($L45>=$O45,MOD($L45,MAX(1,N($P45)))=0),"OK","CHECK")) -> per piece | R45: =IF($L45=0,0,$S45/$L45) -> 0.0163 | S45: =SUMIFS('Parts list'!$W$4:$W$185,'Parts list'!$H$4:$H$185,$C45,'Parts list'!$M$4:$M$185,"Yes") -> 0.6846 | U45: At PCBA order: exact quantity + attrition
A46: 43 | B46: Capacitor | C46: Kyocera AVX TAJD227K010RNJ | D46: 220 µF | E46: 7343-31 (D) | F46: C8024 | G46: Extended | H46: JLCPCB library | I46: C442, C443 | J46: =SUMIFS('Parts list'!$C$4:$C$185,'Parts list'!$H$4:$H$185,$C46,'Parts list'!$M$4:$M$185,"Yes") -> 2 | K46: =SUMIFS('Parts list'!$R$4:$R$185,'Parts list'!$H$4:$H$185,$C46,'Parts list'!$M$4:$M$185,"Yes") -> 10 | L46: =SUMIFS('Parts list'!$V$4:$V$185,'Parts list'!$H$4:$H$185,$C46,'Parts list'!$M$4:$M$185,"Yes") -> 12 | M46: =$L46-$K46 -> 2 | N46: JLCPCB stock, per piece | Q46: =IF(N($O46)=0,"per piece",IF(AND($L46>=$O46,MOD($L46,MAX(1,N($P46)))=0),"OK","CHECK")) -> per piece | R46: =IF($L46=0,0,$S46/$L46) -> 0.5257 | S46: =SUMIFS('Parts list'!$W$4:$W$185,'Parts list'!$H$4:$H$185,$C46,'Parts list'!$M$4:$M$185,"Yes") -> 6.3084 | T46: Pre-order | U46: Pre-order from LCSC stock (C8024)
A47: 44 | B47: Diode | C47: Nexperia BAT54S,215 | D47: BAT54S | E47: SOT-23 | F47: C47546 | G47: Extended | H47: JLCPCB library | I47: D405-D408 | J47: =SUMIFS('Parts list'!$C$4:$C$185,'Parts list'!$H$4:$H$185,$C47,'Parts list'!$M$4:$M$185,"Yes") -> 4 | K47: =SUMIFS('Parts list'!$R$4:$R$185,'Parts list'!$H$4:$H$185,$C47,'Parts list'!$M$4:$M$185,"Yes") -> 20 | L47: =SUMIFS('Parts list'!$V$4:$V$185,'Parts list'!$H$4:$H$185,$C47,'Parts list'!$M$4:$M$185,"Yes") -> 21 | M47: =$L47-$K47 -> 1 | N47: JLCPCB stock, per piece | Q47: =IF(N($O47)=0,"per piece",IF(AND($L47>=$O47,MOD($L47,MAX(1,N($P47)))=0),"OK","CHECK")) -> per piece | R47: =IF($L47=0,0,$S47/$L47) -> 0.0245 | S47: =SUMIFS('Parts list'!$W$4:$W$185,'Parts list'!$H$4:$H$185,$C47,'Parts list'!$M$4:$M$185,"Yes") -> 0.5145 | U47: At PCBA order: exact quantity + attrition
A48: 45 | B48: Diode | C48: Nexperia PMEG2010AEH,115 | D48: PMEG2010AEH | E48: SOD-123F | F48: C110921 | G48: Extended | H48: JLCPCB library | I48: D411, D412 | J48: =SUMIFS('Parts list'!$C$4:$C$185,'Parts list'!$H$4:$H$185,$C48,'Parts list'!$M$4:$M$185,"Yes") -> 2 | K48: =SUMIFS('Parts list'!$R$4:$R$185,'Parts list'!$H$4:$H$185,$C48,'Parts list'!$M$4:$M$185,"Yes") -> 10 | L48: =SUMIFS('Parts list'!$V$4:$V$185,'Parts list'!$H$4:$H$185,$C48,'Parts list'!$M$4:$M$185,"Yes") -> 11 | M48: =$L48-$K48 -> 1 | N48: JLCPCB stock, per piece | Q48: =IF(N($O48)=0,"per piece",IF(AND($L48>=$O48,MOD($L48,MAX(1,N($P48)))=0),"OK","CHECK")) -> per piece | R48: =IF($L48=0,0,$S48/$L48) -> 0.3209 | S48: =SUMIFS('Parts list'!$W$4:$W$185,'Parts list'!$H$4:$H$185,$C48,'Parts list'!$M$4:$M$185,"Yes") -> 3.5299 | U48: At PCBA order: exact quantity + attrition
A49: 46 | B49: Diode | C49: Nexperia BAT54,215 | D49: BAT54 | E49: SOT-23 | F49: C85084 | G49: Extended | H49: JLCPCB library | I49: D413, D414, D104, D105 | J49: =SUMIFS('Parts list'!$C$4:$C$185,'Parts list'!$H$4:$H$185,$C49,'Parts list'!$M$4:$M$185,"Yes") -> 4 | K49: =SUMIFS('Parts list'!$R$4:$R$185,'Parts list'!$H$4:$H$185,$C49,'Parts list'!$M$4:$M$185,"Yes") -> 20 | L49: =SUMIFS('Parts list'!$V$4:$V$185,'Parts list'!$H$4:$H$185,$C49,'Parts list'!$M$4:$M$185,"Yes") -> 22 | M49: =$L49-$K49 -> 2 | N49: JLCPCB stock, per piece | Q49: =IF(N($O49)=0,"per piece",IF(AND($L49>=$O49,MOD($L49,MAX(1,N($P49)))=0),"OK","CHECK")) -> per piece | R49: =IF($L49=0,0,$S49/$L49) -> 0.02 | S49: =SUMIFS('Parts list'!$W$4:$W$185,'Parts list'!$H$4:$H$185,$C49,'Parts list'!$M$4:$M$185,"Yes") -> 0.44 | U49: At PCBA order: exact quantity + attrition
A50: 47 | B50: Resistor | C50: YAGEO RT0603BRD071K3L | D50: 1.30 kΩ | E50: 0603 | F50: C705738 | G50: Extended | H50: JLCPCB library | I50: R401, R403, R405, R407, R409, R411, R413, R415 | J50: =SUMIFS('Parts list'!$C$4:$C$185,'Parts list'!$H$4:$H$185,$C50,'Parts list'!$M$4:$M$185,"Yes") -> 8 | K50: =SUMIFS('Parts list'!$R$4:$R$185,'Parts list'!$H$4:$H$185,$C50,'Parts list'!$M$4:$M$185,"Yes") -> 40 | L50: =SUMIFS('Parts list'!$V$4:$V$185,'Parts list'!$H$4:$H$185,$C50,'Parts list'!$M$4:$M$185,"Yes") -> 60 | M50: =$L50-$K50 -> 20 | N50: Pre-order: minimum order quantity 60 (as costed) | O50: 60 | Q50: =IF(N($O50)=0,"per piece",IF(AND($L50>=$O50,MOD($L50,MAX(1,N($P50)))=0),"OK","CHECK")) -> OK | R50: =IF($L50=0,0,$S50/$L50) -> 0.0259 | S50: =SUMIFS('Parts list'!$W$4:$W$185,'Parts list'!$H$4:$H$185,$C50,'Parts list'!$M$4:$M$185,"Yes") -> 1.554 | T50: Yes | U50: Thin LCSC stock (100 in stock): buy 60 now (order quantity as costed); the Susumu 0.05 % part is the fallback
A51: 48 | B51: Resistor | C51: Susumu RG1608N-202-W-T1 | D51: 2.00 kΩ | E51: 0603 | F51: — | G51: Extended | H51: Global sourcing | I51: R402, R404, R406, R408, R410, R412, R414, R416 | J51: =SUMIFS('Parts list'!$C$4:$C$185,'Parts list'!$H$4:$H$185,$C51,'Parts list'!$M$4:$M$185,"Yes") -> 8 | K51: =SUMIFS('Parts list'!$R$4:$R$185,'Parts list'!$H$4:$H$185,$C51,'Parts list'!$M$4:$M$185,"Yes") -> 40 | L51: =SUMIFS('Parts list'!$V$4:$V$185,'Parts list'!$H$4:$H$185,$C51,'Parts list'!$M$4:$M$185,"Yes") -> 42 | M51: =$L51-$K51 -> 2 | N51: Global sourcing via JLCPCB, per piece | Q51: =IF(N($O51)=0,"per piece",IF(AND($L51>=$O51,MOD($L51,MAX(1,N($P51)))=0),"OK","CHECK")) -> per piece | R51: =IF($L51=0,0,$S51/$L51) -> 0.6 | S51: =SUMIFS('Parts list'!$W$4:$W$185,'Parts list'!$H$4:$H$185,$C51,'Parts list'!$M$4:$M$185,"Yes") -> 25.2 | U51: Global sourcing, bought with the PCBA order
A52: 49 | B52: Resistor | C52: YAGEO RT0603BRD07698RL | D52: 698 Ω | E52: 0603 | F52: C861525 | G52: Extended | H52: JLCPCB library | I52: R423-R426 | J52: =SUMIFS('Parts list'!$C$4:$C$185,'Parts list'!$H$4:$H$185,$C52,'Parts list'!$M$4:$M$185,"Yes") -> 4 | K52: =SUMIFS('Parts list'!$R$4:$R$185,'Parts list'!$H$4:$H$185,$C52,'Parts list'!$M$4:$M$185,"Yes") -> 20 | L52: =SUMIFS('Parts list'!$V$4:$V$185,'Parts list'!$H$4:$H$185,$C52,'Parts list'!$M$4:$M$185,"Yes") -> 40 | M52: =$L52-$K52 -> 20 | N52: Pre-order: minimum order quantity 40 (as costed) | O52: 40 | Q52: =IF(N($O52)=0,"per piece",IF(AND($L52>=$O52,MOD($L52,MAX(1,N($P52)))=0),"OK","CHECK")) -> OK | R52: =IF($L52=0,0,$S52/$L52) -> 0.0254 | S52: =SUMIFS('Parts list'!$W$4:$W$185,'Parts list'!$H$4:$H$185,$C52,'Parts list'!$M$4:$M$185,"Yes") -> 1.016 | T52: Pre-order | U52: Thin LCSC stock (120): pre-order 40 (order quantity as costed)
A53: 50 | B53: Resistor | C53: YAGEO RT0603BRD079K76L | D53: 9.76 kΩ | E53: 0603 | F53: C861616 | G53: Extended | H53: JLCPCB library | I53: R431 | J53: =SUMIFS('Parts list'!$C$4:$C$185,'Parts list'!$H$4:$H$185,$C53,'Parts list'!$M$4:$M$185,"Yes") -> 1 | K53: =SUMIFS('Parts list'!$R$4:$R$185,'Parts list'!$H$4:$H$185,$C53,'Parts list'!$M$4:$M$185,"Yes") -> 5 | L53: =SUMIFS('Parts list'!$V$4:$V$185,'Parts list'!$H$4:$H$185,$C53,'Parts list'!$M$4:$M$185,"Yes") -> 7 | M53: =$L53-$K53 -> 2 | N53: JLCPCB stock, per piece | Q53: =IF(N($O53)=0,"per piece",IF(AND($L53>=$O53,MOD($L53,MAX(1,N($P53)))=0),"OK","CHECK")) -> per piece | R53: =IF($L53=0,0,$S53/$L53) -> 0.035 | S53: =SUMIFS('Parts list'!$W$4:$W$185,'Parts list'!$H$4:$H$185,$C53,'Parts list'!$M$4:$M$185,"Yes") -> 0.245 | U53: At PCBA order: exact quantity + attrition
A54: 51 | B54: Resistor | C54: YAGEO RT0603BRD0710KL | D54: 10.0 kΩ | E54: 0603 | F54: C95204 | G54: Extended | H54: JLCPCB library | I54: R432 | J54: =SUMIFS('Parts list'!$C$4:$C$185,'Parts list'!$H$4:$H$185,$C54,'Parts list'!$M$4:$M$185,"Yes") -> 1 | K54: =SUMIFS('Parts list'!$R$4:$R$185,'Parts list'!$H$4:$H$185,$C54,'Parts list'!$M$4:$M$185,"Yes") -> 5 | L54: =SUMIFS('Parts list'!$V$4:$V$185,'Parts list'!$H$4:$H$185,$C54,'Parts list'!$M$4:$M$185,"Yes") -> 7 | M54: =$L54-$K54 -> 2 | N54: JLCPCB stock, per piece | Q54: =IF(N($O54)=0,"per piece",IF(AND($L54>=$O54,MOD($L54,MAX(1,N($P54)))=0),"OK","CHECK")) -> per piece | R54: =IF($L54=0,0,$S54/$L54) -> 0.0331 | S54: =SUMIFS('Parts list'!$W$4:$W$185,'Parts list'!$H$4:$H$185,$C54,'Parts list'!$M$4:$M$185,"Yes") -> 0.2317 | U54: At PCBA order: exact quantity + attrition
A55: 52 | B55: Resistor | C55: YAGEO RT0603BRD07680RL | D55: 680 Ω | E55: 0603 | F55: C861519 | G55: Extended | H55: JLCPCB library | I55: R438-R445 | J55: =SUMIFS('Parts list'!$C$4:$C$185,'Parts list'!$H$4:$H$185,$C55,'Parts list'!$M$4:$M$185,"Yes") -> 8 | K55: =SUMIFS('Parts list'!$R$4:$R$185,'Parts list'!$H$4:$H$185,$C55,'Parts list'!$M$4:$M$185,"Yes") -> 40 | L55: =SUMIFS('Parts list'!$V$4:$V$185,'Parts list'!$H$4:$H$185,$C55,'Parts list'!$M$4:$M$185,"Yes") -> 60 | M55: =$L55-$K55 -> 20 | N55: Pre-order: minimum order quantity 60 (as costed) | O55: 60 | Q55: =IF(N($O55)=0,"per piece",IF(AND($L55>=$O55,MOD($L55,MAX(1,N($P55)))=0),"OK","CHECK")) -> OK | R55: =IF($L55=0,0,$S55/$L55) -> 0.0256 | S55: =SUMIFS('Parts list'!$W$4:$W$185,'Parts list'!$H$4:$H$185,$C55,'Parts list'!$M$4:$M$185,"Yes") -> 1.536 | T55: Pre-order | U55: Pre-order 60 (order quantity as costed)
A56: 53 | B56: IC | C56: TI OPA1622IDRCR | D56: OPA1622IDRCR | E56: VSON-10 3 × 3 + pad | F56: C2876559 | G56: Extended | H56: JLCPCB library | I56: U401, U402 | J56: =SUMIFS('Parts list'!$C$4:$C$185,'Parts list'!$H$4:$H$185,$C56,'Parts list'!$M$4:$M$185,"Yes") -> 2 | K56: =SUMIFS('Parts list'!$R$4:$R$185,'Parts list'!$H$4:$H$185,$C56,'Parts list'!$M$4:$M$185,"Yes") -> 10 | L56: =SUMIFS('Parts list'!$V$4:$V$185,'Parts list'!$H$4:$H$185,$C56,'Parts list'!$M$4:$M$185,"Yes") -> 11 | M56: =$L56-$K56 -> 1 | N56: JLCPCB stock, per piece | Q56: =IF(N($O56)=0,"per piece",IF(AND($L56>=$O56,MOD($L56,MAX(1,N($P56)))=0),"OK","CHECK")) -> per piece | R56: =IF($L56=0,0,$S56/$L56) -> 1.7871 | S56: =SUMIFS('Parts list'!$W$4:$W$185,'Parts list'!$H$4:$H$185,$C56,'Parts list'!$M$4:$M$185,"Yes") -> 19.6581 | U56: At PCBA order: exact quantity + attrition
A57: 54 | B57: IC | C57: TI OPA2210IDR | D57: OPA2210IDR | E57: SOIC-8 | F57: C1849415 | G57: Extended | H57: JLCPCB library | I57: U403, U404 | J57: =SUMIFS('Parts list'!$C$4:$C$185,'Parts list'!$H$4:$H$185,$C57,'Parts list'!$M$4:$M$185,"Yes") -> 2 | K57: =SUMIFS('Parts list'!$R$4:$R$185,'Parts list'!$H$4:$H$185,$C57,'Parts list'!$M$4:$M$185,"Yes") -> 10 | L57: =SUMIFS('Parts list'!$V$4:$V$185,'Parts list'!$H$4:$H$185,$C57,'Parts list'!$M$4:$M$185,"Yes") -> 11 | M57: =$L57-$K57 -> 1 | N57: JLCPCB stock, per piece | Q57: =IF(N($O57)=0,"per piece",IF(AND($L57>=$O57,MOD($L57,MAX(1,N($P57)))=0),"OK","CHECK")) -> per piece | R57: =IF($L57=0,0,$S57/$L57) -> 2.6708 | S57: =SUMIFS('Parts list'!$W$4:$W$185,'Parts list'!$H$4:$H$185,$C57,'Parts list'!$M$4:$M$185,"Yes") -> 29.3788 | T57: Yes | U57: LCSC 16 in stock, DigiKey 0 until 14 Dec 2026; no compliant pin-compatible alternative
A58: 55 | B58: Ferrite bead | C58: Murata BLM18PG121SN1D | D58: 120 Ω @ 100 MHz | E58: 0603 | F58: C14709 | G58: Basic | H58: JLCPCB library | I58: FB501 | J58: =SUMIFS('Parts list'!$C$4:$C$185,'Parts list'!$H$4:$H$185,$C58,'Parts list'!$M$4:$M$185,"Yes") -> 1 | K58: =SUMIFS('Parts list'!$R$4:$R$185,'Parts list'!$H$4:$H$185,$C58,'Parts list'!$M$4:$M$185,"Yes") -> 5 | L58: =SUMIFS('Parts list'!$V$4:$V$185,'Parts list'!$H$4:$H$185,$C58,'Parts list'!$M$4:$M$185,"Yes") -> 7 | M58: =$L58-$K58 -> 2 | N58: JLCPCB stock, per piece | Q58: =IF(N($O58)=0,"per piece",IF(AND($L58>=$O58,MOD($L58,MAX(1,N($P58)))=0),"OK","CHECK")) -> per piece | R58: =IF($L58=0,0,$S58/$L58) -> 0.0157 | S58: =SUMIFS('Parts list'!$W$4:$W$185,'Parts list'!$H$4:$H$185,$C58,'Parts list'!$M$4:$M$185,"Yes") -> 0.1099 | U58: At PCBA order: exact quantity + attrition
A59: 56 | B59: Transistor | C59: JSCJ MMBT3904 (RANGE:100-300) | D59: MMBT3904 | E59: SOT-23 | F59: C20526 | G59: Basic | H59: JLCPCB library | I59: Q507, Q612, Q614 | J59: =SUMIFS('Parts list'!$C$4:$C$185,'Parts list'!$H$4:$H$185,$C59,'Parts list'!$M$4:$M$185,"Yes") -> 3 | K59: =SUMIFS('Parts list'!$R$4:$R$185,'Parts list'!$H$4:$H$185,$C59,'Parts list'!$M$4:$M$185,"Yes") -> 15 | L59: =SUMIFS('Parts list'!$V$4:$V$185,'Parts list'!$H$4:$H$185,$C59,'Parts list'!$M$4:$M$185,"Yes") -> 17 | M59: =$L59-$K59 -> 2 | N59: JLCPCB stock, per piece | Q59: =IF(N($O59)=0,"per piece",IF(AND($L59>=$O59,MOD($L59,MAX(1,N($P59)))=0),"OK","CHECK")) -> per piece | R59: =IF($L59=0,0,$S59/$L59) -> 0.0104 | S59: =SUMIFS('Parts list'!$W$4:$W$185,'Parts list'!$H$4:$H$185,$C59,'Parts list'!$M$4:$M$185,"Yes") -> 0.1768 | T59: Yes | U59: Q507 (suspend power cut), Q612/Q614: JLCPCB Basic, LCSC 25,800 (Q623–Q627 are onsemi MMBT3904LT1G, bought at the PCBA order)
A60: 57 | B60: Resistor | C60: YAGEO RT0603BRD07221KL | D60: 221 kΩ | E60: 0603 | F60: C705748 | G60: Extended (not verified) | H60: JLCPCB library | I60: R501 | J60: =SUMIFS('Parts list'!$C$4:$C$185,'Parts list'!$H$4:$H$185,$C60,'Parts list'!$M$4:$M$185,"Yes") -> 1 | K60: =SUMIFS('Parts list'!$R$4:$R$185,'Parts list'!$H$4:$H$185,$C60,'Parts list'!$M$4:$M$185,"Yes") -> 5 | L60: =SUMIFS('Parts list'!$V$4:$V$185,'Parts list'!$H$4:$H$185,$C60,'Parts list'!$M$4:$M$185,"Yes") -> 7 | M60: =$L60-$K60 -> 2 | N60: JLCPCB stock, per piece | Q60: =IF(N($O60)=0,"per piece",IF(AND($L60>=$O60,MOD($L60,MAX(1,N($P60)))=0),"OK","CHECK")) -> per piece | R60: =IF($L60=0,0,$S60/$L60) -> 0.0254 | S60: =SUMIFS('Parts list'!$W$4:$W$185,'Parts list'!$H$4:$H$185,$C60,'Parts list'!$M$4:$M$185,"Yes") -> 0.1778 | U60: At PCBA order: exact quantity + attrition
